Workbook
Name ___REM1: #REF!
Name ___REM2: #REF!
Name ___Val101: #REF!
Name ___Val102: #REF!
Name ___Val201: #REF!
Name ___Val202: #REF!
Name ___Val301: #REF!
Name ___Val302: #REF!
Name __REM1: #REF!
Name __REM2: #REF!
Name __Val101: #REF!
Name __Val102: #REF!
Name __Val201: #REF!
Name __Val202: #REF!
Name __Val301: #REF!
Name __Val302: #REF!
Name _REM1: #REF!
Name _REM2: #REF!
Name _Val101: #REF!
Name _Val102: #REF!
Name _Val201: #REF!
Name _Val202: #REF!
Name _Val301: #REF!
Name _Val302: #REF!
Name A: #REF!
Name a: '[2]B-3.2 EB'!#REF!
Name aa: #REF!
Name aa: #REF!
Name aaa: #REF!
Name ad: '[2]B-3.2 EB'!#REF!
Name Anton: #REF!
Name Anton: #REF!
Name as: #REF!
Name asgsdfg: #REF!
Name b: '[2]B-3.2 EB'!#REF!
Name b.two: [3]Sheet1!$E$497
Name B_10_10: '[4]Bill 3 - Site Works'!#REF!
Name B_10_11A: '[4]Bill 3 - Site Works'!#REF!
Name B_10_11B: '[4]Bill 3 - Site Works'!#REF!
Name B_10_12: '[4]Bill 3 - Site Works'!#REF!
Name B_10_13: '[4]Bill 3 - Site Works'!#REF!
Name B_10_14: '[4]Bill 3 - Site Works'!#REF!
Name B_10_2: '[4]Bill 3 - Site Works'!#REF!
Name B_10_3: '[4]Bill 3 - Site Works'!#REF!
Name B_10_4: '[4]Bill 3 - Site Works'!#REF!
Name B_10_5: '[4]Bill 3 - Site Works'!#REF!
Name B_10_6: '[4]Bill 3 - Site Works'!#REF!
Name B_10_7A: '[4]Bill 3 - Site Works'!#REF!
Name B_10_8A: '[4]Bill 3 - Site Works'!#REF!
Name B_10_9: '[4]Bill 3 - Site Works'!#REF!
Name B107A: '[4]Bill 3 - Site Works'!#REF!
Name BB: #REF!
Name bbb: #REF!
Name bhhbhj: #REF!
Name Bill: #REF!
Name bill1: #REF!
Name C_: #REF!
Name CApentry: #REF!
Name cc: #REF!
Name CoolingCapacity: '[5]Room Type'!$O$3

Sheet bar schedule-wattala
B1: BAR BENDING SCHEDULE | H1: BENDING SCHEDULE OF REINFORCEMENTS
B2: Project | C2: : | D2: Proposed 3 storied building - Wattala Mabola Urban council
B3: Consultant | C3: :
B4: Location | C4: : | D4: Wattala Mabola Urban council
B5: Item | C5: Bar mark | D5: Type&Size | E5: Members | F5: Nos per member | G5: Total nos | H5: Shape code (as per BS 4449 code) | I5: Length of a bar (m) | J5: Total length of bars (m) | K5: Lenth of Each Bar (m) | L5: Required Bar Qty | M5: A* | N5: B* | O5: C* | P5: D* | Q5: E* | R5: Total length (m) | Z5: Remarks
M6: m | N6: m | O6: m | P6: m | Q6: m | R6: R6 | S6: R8 | T6: T10 | U6: T12 | V6: T16 | W6: T20 | X6: T25 | Y6: T32
I8: =M8+N8+O8+P8+Q8 -> 0 | K8: 6 | R8: =IF(D8="R6",J8," ") | S8: =IF(D8="R8",J8," ") | T8: =IF(D8="T10",J8," ") | U8: =IF(D8="T12",J8," ") | V8: =IF(D8="T16",J8," ") | W8: =IF(D8="T20",J8," ") | X8: =IF(D8="T25",J8," ") | Y8: =IF(D8="T32",J8," ")
B9: Column Base
B10: F1 | C10: a | D10: T12 | E10: 10 | F10: 30 | G10: =F10*E10 -> 300 | I10: =M10+N10+O10+P10+Q10 -> 2.12 | J10: =G10*I10 -> 636 | K10: =K6*0.888 -> 0 | M10: 1.72 | N10: 0.2 | O10: 0.2 | R10: =IF(D10="R6",J10," ") | S10: =IF(D10="R8",J10," ") | T10: =IF(D10="T10",J10," ") | U10: =IF(D10="T12",J10," ") -> 636 | V10: =IF(D10="T16",J10," ") | W10: =IF(D10="T20",J10," ") | X10: =IF(D10="T25",J10," ") | Y10: =IF(D10="T32",J10," ")
B11: F2 | C11: a | D11: T12 | E11: 14 | F11: 22 | G11: =F11*E11 -> 308 | I11: =M11+N11+O11+P11+Q11 -> 1.82 | J11: =G11*I11 -> 560.56 | K11: =K7*0.888 -> 0 | M11: 1.42 | N11: 0.2 | O11: 0.2 | R11: =IF(D11="R6",J11," ") | S11: =IF(D11="R8",J11," ") | T11: =IF(D11="T10",J11," ") | U11: =IF(D11="T12",J11," ") -> 560.56 | V11: =IF(D11="T16",J11," ") | W11: =IF(D11="T20",J11," ") | X11: =IF(D11="T25",J11," ") | Y11: =IF(D11="T32",J11," ")
B12: F3 | C12: a | D12: T12 | E12: 4 | F12: 16 | G12: =F12*E12 -> 64 | I12: =M12+N12+O12+P12+Q12 -> 1.52 | J12: =G12*I12 -> 97.28 | K12: =K8*0.888 -> 5.328 | M12: 1.12 | N12: 0.2 | O12: 0.2 | R12: =IF(D12="R6",J12," ") | S12: =IF(D12="R8",J12," ") | T12: =IF(D12="T10",J12," ") | U12: =IF(D12="T12",J12," ") -> 97.28 | V12: =IF(D12="T16",J12," ") | W12: =IF(D12="T20",J12," ") | X12: =IF(D12="T25",J12," ") | Y12: =IF(D12="T32",J12," ")
B13: CF1 | C13: a | D13: T12 | E13: 1 | F13: 64 | G13: =F13*E13 -> 64 | I13: =M13+N13+O13+P13+Q13 -> 2.12 | J13: =G13*I13 -> 135.68 | K13: =K9*0.888 -> 0 | M13: 1.72 | N13: 0.2 | O13: 0.2 | R13: =IF(D13="R6",J13," ") | S13: =IF(D13="R8",J13," ") | T13: =IF(D13="T10",J13," ") | U13: =IF(D13="T12",J13," ") -> 135.68 | V13: =IF(D13="T16",J13," ") | W13: =IF(D13="T20",J13," ") | X13: =IF(D13="T25",J13," ") | Y13: =IF(D13="T32",J13," ")
B14: CF1 | C14: a | D14: T12 | E14: 1 | F14: 44 | G14: =F14*E14 -> 44 | I14: =M14+N14+O14+P14+Q14 -> 3.02 | J14: =G14*I14 -> 132.88 | K14: =K10*0.888 -> 0 | M14: 2.62 | N14: 0.2 | O14: 0.2 | R14: =IF(D14="R6",J14," ") | S14: =IF(D14="R8",J14," ") | T14: =IF(D14="T10",J14," ") | U14: =IF(D14="T12",J14," ") -> 132.88 | V14: =IF(D14="T16",J14," ") | W14: =IF(D14="T20",J14," ") | X14: =IF(D14="T25",J14," ") | Y14: =IF(D14="T32",J14," ")
B16: Total length (m) | R16: =SUM(R8:R15) -> 0 | S16: =SUM(S8:S15) -> 0 | T16: =SUM(T8:T15) -> 0 | U16: =SUM(U8:U15) -> 1562.4 | V16: =SUM(V8:V15) -> 0 | W16: =SUM(W8:W15) -> 0 | X16: =SUM(X8:X15) -> 0 | Y16: =SUM(Y8:Y15) -> 0
B17: Weight (Kg/m) | R17: =6*6/162.162 -> 0.22200022 | S17: =8*8/162.162 -> 0.39466706 | T17: =10*10/162.162 -> 0.61666728 | U17: =12*12/162.162 -> 0.88800089 | V17: =16*16/162.162 -> 1.5786682 | W17: =20*20/162.162 -> 2.4666691 | X17: =25*25/162.162 -> 3.8541705 | Y17: =32*32/162.162 -> 6.314673
B18: TOTAL (Kg) | R18: =+R17*R16 -> 0 | S18: =+S17*S16 -> 0 | T18: =+T17*T16 -> 0 | U18: =+U17*U16 -> 1387.4126 | V18: =+V17*V16 -> 0 | W18: =+W17*W16 -> 0 | X18: =+X17*X16 -> 0 | Y18: =+Y17*Y16 -> 0 | Z18: =Y18+X18+W18+V18+U18+T18+S18+R18 -> 1387.4126
B21: Column shaft -upto DPC
B22: C1 | C22: a | D22: T16 | E22: 32 | F22: 4 | G22: =F22*E22 -> 128 | I22: =M22+N22+O22+P22+Q22 -> 1.97 | J22: =G22*I22 -> 252.16 | K22: =K18*0.888 -> 0 | M22: 1.23 | N22: 0.74 | R22: =IF(D22="R6",J22," ") | S22: =IF(D22="R8",J22," ") | T22: =IF(D22="T10",J22," ") | U22: =IF(D22="T12",J22," ") | V22: =IF(D22="T16",J22," ") -> 252.16 | W22: =IF(D22="T20",J22," ") | X22: =IF(D22="T25",J22," ") | Y22: =IF(D22="T32",J22," ")
B23: C2 | C23: a | D23: T16 | E23: 4 | F23: 4 | G23: =F23*E23 -> 16 | I23: =M23+N23+O23+P23+Q23 -> 1.97 | J23: =G23*I23 -> 31.52 | K23: =K19*0.888 -> 0 | M23: 1.23 | N23: 0.74 | R23: =IF(D23="R6",J23," ") | S23: =IF(D23="R8",J23," ") | T23: =IF(D23="T10",J23," ") | U23: =IF(D23="T12",J23," ") | V23: =IF(D23="T16",J23," ") -> 31.52 | W23: =IF(D23="T20",J23," ") | X23: =IF(D23="T25",J23," ") | Y23: =IF(D23="T32",J23," ")
B25: Total length (m) | R25: =SUM(R20:R24) -> 0 | S25: =SUM(S20:S24) -> 0 | T25: =SUM(T20:T24) -> 0 | U25: =SUM(U20:U24) -> 0 | V25: =SUM(V20:V24) -> 283.68 | W25: =SUM(W20:W24) -> 0 | X25: =SUM(X20:X24) -> 0 | Y25: =SUM(Y20:Y24) -> 0
B26: Weight (Kg/m) | R26: =6*6/162.162 -> 0.22200022 | S26: =8*8/162.162 -> 0.39466706 | T26: =10*10/162.162 -> 0.61666728 | U26: =12*12/162.162 -> 0.88800089 | V26: =16*16/162.162 -> 1.5786682 | W26: =20*20/162.162 -> 2.4666691 | X26: =25*25/162.162 -> 3.8541705 | Y26: =32*32/162.162 -> 6.314673
B27: TOTAL (Kg) | R27: =+R26*R25 -> 0 | S27: =+S26*S25 -> 0 | T27: =+T26*T25 -> 0 | U27: =+U26*U25 -> 0 | V27: =+V26*V25 -> 447.83661 | W27: =+W26*W25 -> 0 | X27: =+X26*X25 -> 0 | Y27: =+Y26*Y25 -> 0 | Z27: =Y27+X27+W27+V27+U27+T27+S27+R27 -> 447.83661
B30: Plinth Beam
B31: pb 300X300 | C31: a | D31: T16 | E31: 1 | F31: 4 | G31: =F31*E31 -> 4 | I31: =M31+N31+O31+P31+Q31 -> 179 | J31: =G31*I31 -> 716 | K31: =K27*0.888 -> 0 | M31: 179 | R31: =IF(D31="R6",J31," ") | S31: =IF(D31="R8",J31," ") | T31: =IF(D31="T10",J31," ") | U31: =IF(D31="T12",J31," ") | V31: =IF(D31="T16",J31," ") -> 716 | W31: =IF(D31="T20",J31," ") | X31: =IF(D31="T25",J31," ") | Y31: =IF(D31="T32",J31," ")
B32: pb 225X300 | C32: a | D32: T16 | E32: 1 | F32: 4 | G32: =F32*E32 -> 4 | I32: =M32+N32+O32+P32+Q32 -> 48 | J32: =G32*I32 -> 192 | K32: =K28*0.888 -> 0 | M32: 48 | R32: =IF(D32="R6",J32," ") | S32: =IF(D32="R8",J32," ") | T32: =IF(D32="T10",J32," ") | U32: =IF(D32="T12",J32," ") | V32: =IF(D32="T16",J32," ") -> 192 | W32: =IF(D32="T20",J32," ") | X32: =IF(D32="T25",J32," ") | Y32: =IF(D32="T32",J32," ")
B34: Total length (m) | R34: =SUM(R29:R33) -> 0 | S34: =SUM(S29:S33) -> 0 | T34: =SUM(T29:T33) -> 0 | U34: =SUM(U29:U33) -> 0 | V34: =SUM(V29:V33) -> 908 | W34: =SUM(W29:W33) -> 0 | X34: =SUM(X29:X33) -> 0 | Y34: =SUM(Y29:Y33) -> 0
B35: Weight (Kg/m) | R35: =6*6/162.162 -> 0.22200022 | S35: =8*8/162.162 -> 0.39466706 | T35: =10*10/162.162 -> 0.61666728 | U35: =12*12/162.162 -> 0.88800089 | V35: =16*16/162.162 -> 1.5786682 | W35: =20*20/162.162 -> 2.4666691 | X35: =25*25/162.162 -> 3.8541705 | Y35: =32*32/162.162 -> 6.314673
B36: TOTAL (Kg) | R36: =+R35*R34 -> 0 | S36: =+S35*S34 -> 0 | T36: =+T35*T34 -> 0 | U36: =+U35*U34 -> 0 | V36: =+V35*V34 -> 1433.4308 | W36: =+W35*W34 -> 0 | X36: =+X35*X34 -> 0 | Y36: =+Y35*Y34 -> 0 | Z36: =Y36+X36+W36+V36+U36+T36+S36+R36 -> 1433.4308
B38: Column shaft -DPC -1st
B39: C1 | C39: a | D39: T16 | E39: 32 | F39: 4 | G39: =F39*E39 -> 128 | I39: =M39+N39+O39+P39+Q39 -> 4 | J39: =G39*I39 -> 512 | K39: =K35*0.888 -> 0 | M39: 4 | R39: =IF(D39="R6",J39," ") | S39: =IF(D39="R8",J39," ") | T39: =IF(D39="T10",J39," ") | U39: =IF(D39="T12",J39," ") | V39: =IF(D39="T16",J39," ") -> 512 | W39: =IF(D39="T20",J39," ") | X39: =IF(D39="T25",J39," ") | Y39: =IF(D39="T32",J39," ")
B40: C2 | C40: a | D40: T16 | E40: 4 | F40: 4 | G40: =F40*E40 -> 16 | I40: =M40+N40+O40+P40+Q40 -> 4 | J40: =G40*I40 -> 64 | K40: =K36*0.888 -> 0 | M40: 4 | R40: =IF(D40="R6",J40," ") | S40: =IF(D40="R8",J40," ") | T40: =IF(D40="T10",J40," ") | U40: =IF(D40="T12",J40," ") | V40: =IF(D40="T16",J40," ") -> 64 | W40: =IF(D40="T20",J40," ") | X40: =IF(D40="T25",J40," ") | Y40: =IF(D40="T32",J40," ")
B42: Total length (m) | R42: =SUM(R37:R41) -> 0 | S42: =SUM(S37:S41) -> 0 | T42: =SUM(T37:T41) -> 0 | U42: =SUM(U37:U41) -> 0 | V42: =SUM(V37:V41) -> 576 | W42: =SUM(W37:W41) -> 0 | X42: =SUM(X37:X41) -> 0 | Y42: =SUM(Y37:Y41) -> 0
B43: Weight (Kg/m) | R43: =6*6/162.162 -> 0.22200022 | S43: =8*8/162.162 -> 0.39466706 | T43: =10*10/162.162 -> 0.61666728 | U43: =12*12/162.162 -> 0.88800089 | V43: =16*16/162.162 -> 1.5786682 | W43: =20*20/162.162 -> 2.4666691 | X43: =25*25/162.162 -> 3.8541705 | Y43: =32*32/162.162 -> 6.314673
B44: TOTAL (Kg) | R44: =+R43*R42 -> 0 | S44: =+S43*S42 -> 0 | T44: =+T43*T42 -> 0 | U44: =+U43*U42 -> 0 | V44: =+V43*V42 -> 909.31291 | W44: =+W43*W42 -> 0 | X44: =+X43*X42 -> 0 | Y44: =+Y43*Y42 -> 0 | Z44: =Y44+X44+W44+V44+U44+T44+S44+R44 -> 909.31291
B47: G/F beam
B48: 1,7 A1-C | C48: B | D48: T16 | E48: 2 | F48: 2 | G48: =F48*E48 -> 4 | I48: =M48+N48+O48+P48+Q48 -> 12.75 | J48: =G48*I48 -> 51 | K48: =K44*0.888 -> 0 | M48: 12.75 | R48: =IF(D48="R6",J48," ") | S48: =IF(D48="R8",J48," ") | T48: =IF(D48="T10",J48," ") | U48: =IF(D48="T12",J48," ") | V48: =IF(D48="T16",J48," ") -> 51 | W48: =IF(D48="T20",J48," ") | X48: =IF(D48="T25",J48," ") | Y48: =IF(D48="T32",J48," ")
C49: T | D49: T16 | E49: 2 | F49: 2 | G49: =F49*E49 -> 4 | I49: =M49+N49+O49+P49+Q49 -> 12.75 | J49: =G49*I49 -> 51 | K49: =K45*0.888 -> 0 | M49: 12.75 | R49: =IF(D49="R6",J49," ") | S49: =IF(D49="R8",J49," ") | T49: =IF(D49="T10",J49," ") | U49: =IF(D49="T12",J49," ") | V49: =IF(D49="T16",J49," ") -> 51 | W49: =IF(D49="T20",J49," ") | X49: =IF(D49="T25",J49," ") | Y49: =IF(D49="T32",J49," ")
C50: T | D50: T16 | E50: 2 | F50: 1 | G50: =F50*E50 -> 2 | I50: =M50+N50+O50+P50+Q50 -> 1.8 | J50: =G50*I50 -> 3.6 | K50: =K46*0.888 -> 0 | M50: 1.8 | R50: =IF(D50="R6",J50," ") | S50: =IF(D50="R8",J50," ") | T50: =IF(D50="T10",J50," ") | U50: =IF(D50="T12",J50," ") | V50: =IF(D50="T16",J50," ") -> 3.6 | W50: =IF(D50="T20",J50," ") | X50: =IF(D50="T25",J50," ") | Y50: =IF(D50="T32",J50," ")
C51: T | D51: T16 | E51: 2 | F51: 2 | G51: =F51*E51 -> 4 | I51: =M51+N51+O51+P51+Q51 -> 2.95 | J51: =G51*I51 -> 11.8 | K51: =K47*0.888 -> 0 | M51: 2.95 | R51: =IF(D51="R6",J51," ") | S51: =IF(D51="R8",J51," ") | T51: =IF(D51="T10",J51," ") | U51: =IF(D51="T12",J51," ") | V51: =IF(D51="T16",J51," ") -> 11.8 | W51: =IF(D51="T20",J51," ") | X51: =IF(D51="T25",J51," ") | Y51: =IF(D51="T32",J51," ")
C52: T | D52: T16 | E52: 2 | F52: 2 | G52: =F52*E52 -> 4 | I52: =M52+N52+O52+P52+Q52 -> 2.95 | J52: =G52*I52 -> 11.8 | K52: =K48*0.888 -> 0 | M52: 2.95 | R52: =IF(D52="R6",J52," ") | S52: =IF(D52="R8",J52," ") | T52: =IF(D52="T10",J52," ") | U52: =IF(D52="T12",J52," ") | V52: =IF(D52="T16",J52," ") -> 11.8 | W52: =IF(D52="T20",J52," ") | X52: =IF(D52="T25",J52," ") | Y52: =IF(D52="T32",J52," ")
B55: Total length (m) | R55: =SUM(R46:R54) -> 0 | S55: =SUM(S46:S54) -> 0 | T55: =SUM(T46:T54) -> 0 | U55: =SUM(U46:U54) -> 0 | V55: =SUM(V46:V54) -> 129.2 | W55: =SUM(W46:W54) -> 0 | X55: =SUM(X46:X54) -> 0 | Y55: =SUM(Y46:Y54) -> 0
B56: Weight (Kg/m) | R56: =6*6/162.162 -> 0.22200022 | S56: =8*8/162.162 -> 0.39466706 | T56: =10*10/162.162 -> 0.61666728 | U56: =12*12/162.162 -> 0.88800089 | V56: =16*16/162.162 -> 1.5786682 | W56: =20*20/162.162 -> 2.4666691 | X56: =25*25/162.162 -> 3.8541705 | Y56: =32*32/162.162 -> 6.314673
B57: TOTAL (Kg) | R57: =+R56*R55 -> 0 | S57: =+S56*S55 -> 0 | T57: =+T56*T55 -> 0 | U57: =+U56*U55 -> 0 | V57: =+V56*V55 -> 203.96394 | W57: =+W56*W55 -> 0 | X57: =+X56*X55 -> 0 | Y57: =+Y56*Y55 -> 0 | Z57: =Y57+X57+W57+V57+U57+T57+S57+R57 -> 203.96394
B60: F/F Slab
C61: a | D61: T10 | E61: 1 | F61: 29 | G61: =F61*E61 -> 29 | I61: =M61+N61+O61+P61+Q61 -> 6.5 | J61: =G61*I61 -> 188.5 | K61: =K57*0.888 -> 0 | M61: 6.5 | R61: =IF(D61="R6",J61," ") | S61: =IF(D61="R8",J61," ") | T61: =IF(D61="T10",J61," ") -> 188.5 | U61: =IF(D61="T12",J61," ") | V61: =IF(D61="T16",J61," ") | W61: =IF(D61="T20",J61," ") | X61: =IF(D61="T25",J61," ") | Y61: =IF(D61="T32",J61," ")
C62: a | D62: T10 | E62: 1 | F62: 23 | G62: =F62*E62 -> 23 | I62: =M62+N62+O62+P62+Q62 -> 7.318 | J62: =G62*I62 -> 168.314 | K62: =K58*0.888 -> 0 | M62: 7.318 | R62: =IF(D62="R6",J62," ") | S62: =IF(D62="R8",J62," ") | T62: =IF(D62="T10",J62," ") -> 168.314 | U62: =IF(D62="T12",J62," ") | V62: =IF(D62="T16",J62," ") | W62: =IF(D62="T20",J62," ") | X62: =IF(D62="T25",J62," ") | Y62: =IF(D62="T32",J62," ")
C63: a | D63: T10 | E63: 1 | F63: 23 | G63: =F63*E63 -> 23 | I63: =M63+N63+O63+P63+Q63 -> 1.8 | J63: =G63*I63 -> 41.4 | K63: =K59*0.888 -> 0 | M63: 1.8 | R63: =IF(D63="R6",J63," ") | S63: =IF(D63="R8",J63," ") | T63: =IF(D63="T10",J63," ") -> 41.4 | U63: =IF(D63="T12",J63," ") | V63: =IF(D63="T16",J63," ") | W63: =IF(D63="T20",J63," ") | X63: =IF(D63="T25",J63," ") | Y63: =IF(D63="T32",J63," ")
C64: a | D64: T10 | E64: 1 | F64: 23 | G64: =F64*E64 -> 23 | I64: =M64+N64+O64+P64+Q64 -> 1.3 | J64: =G64*I64 -> 29.9 | K64: =K60*0.888 -> 0 | M64: 1.3 | R64: =IF(D64="R6",J64," ") | S64: =IF(D64="R8",J64," ") | T64: =IF(D64="T10",J64," ") -> 29.9 | U64: =IF(D64="T12",J64," ") | V64: =IF(D64="T16",J64," ") | W64: =IF(D64="T20",J64," ") | X64: =IF(D64="T25",J64," ") | Y64: =IF(D64="T32",J64," ")
B67: Total length (m) | R67: =SUM(R59:R66) -> 0 | S67: =SUM(S59:S66) -> 0 | T67: =SUM(T59:T66) -> 428.114 | U67: =SUM(U59:U66) -> 0 | V67: =SUM(V59:V66) -> 0 | W67: =SUM(W59:W66) -> 0 | X67: =SUM(X59:X66) -> 0 | Y67: =SUM(Y59:Y66) -> 0
B68: Weight (Kg/m) | R68: =6*6/162.162 -> 0.22200022 | S68: =8*8/162.162 -> 0.39466706 | T68: =10*10/162.162 -> 0.61666728 | U68: =12*12/162.162 -> 0.88800089 | V68: =16*16/162.162 -> 1.5786682 | W68: =20*20/162.162 -> 2.4666691 | X68: =25*25/162.162 -> 3.8541705 | Y68: =32*32/162.162 -> 6.314673
B69: TOTAL (Kg) | R69: =+R68*R67 -> 0 | S69: =+S68*S67 -> 0 | T69: =+T68*T67 -> 264.0039 | U69: =+U68*U67 -> 0 | V69: =+V68*V67 -> 0 | W69: =+W68*W67 -> 0 | X69: =+X68*X67 -> 0 | Y69: =+Y68*Y67 -> 0 | Z69: =Y69+X69+W69+V69+U69+T69+S69+R69 -> 264.0039
B72: Column shaft -1st - 2nd
B73: C1 | C73: a | D73: T16 | E73: 23 | F73: 4 | G73: =F73*E73 -> 92 | I73: =M73+N73+O73+P73+Q73 -> 4 | J73: =G73*I73 -> 368 | K73: =K69*0.888 -> 0 | M73: 4 | R73: =IF(D73="R6",J73," ") | S73: =IF(D73="R8",J73," ") | T73: =IF(D73="T10",J73," ") | U73: =IF(D73="T12",J73," ") | V73: =IF(D73="T16",J73," ") -> 368 | W73: =IF(D73="T20",J73," ") | X73: =IF(D73="T25",J73," ") | Y73: =IF(D73="T32",J73," ")
B74: C2 | C74: a | D74: T16 | E74: 4 | F74: 4 | G74: =F74*E74 -> 16 | I74: =M74+N74+O74+P74+Q74 -> 4 | J74: =G74*I74 -> 64 | K74: =K70*0.888 -> 0 | M74: 4 | R74: =IF(D74="R6",J74," ") | S74: =IF(D74="R8",J74," ") | T74: =IF(D74="T10",J74," ") | U74: =IF(D74="T12",J74," ") | V74: =IF(D74="T16",J74," ") -> 64 | W74: =IF(D74="T20",J74," ") | X74: =IF(D74="T25",J74," ") | Y74: =IF(D74="T32",J74," ")
B76: Total length (m) | R76: =SUM(R71:R75) -> 0 | S76: =SUM(S71:S75) -> 0 | T76: =SUM(T71:T75) -> 0 | U76: =SUM(U71:U75) -> 0 | V76: =SUM(V71:V75) -> 432 | W76: =SUM(W71:W75) -> 0 | X76: =SUM(X71:X75) -> 0 | Y76: =SUM(Y71:Y75) -> 0
B77: Weight (Kg/m) | R77: =6*6/162.162 -> 0.22200022 | S77: =8*8/162.162 -> 0.39466706 | T77: =10*10/162.162 -> 0.61666728 | U77: =12*12/162.162 -> 0.88800089 | V77: =16*16/162.162 -> 1.5786682 | W77: =20*20/162.162 -> 2.4666691 | X77: =25*25/162.162 -> 3.8541705 | Y77: =32*32/162.162 -> 6.314673
B78: TOTAL (Kg) | R78: =+R77*R76 -> 0 | S78: =+S77*S76 -> 0 | T78: =+T77*T76 -> 0 | U78: =+U77*U76 -> 0 | V78: =+V77*V76 -> 681.98468 | W78: =+W77*W76 -> 0 | X78: =+X77*X76 -> 0 | Y78: =+Y77*Y76 -> 0 | Z78: =Y78+X78+W78+V78+U78+T78+S78+R78 -> 681.98468
B80: lift
B81: base | C81: a | D81: T12 | E81: 1 | F81: 80 | G81: =F81*E81 -> 80 | I81: =M81+N81+O81+P81+Q81 -> 3.57 | J81: =G81*I81 -> 285.6 | K81: =K77*0.888 -> 0 | M81: 3.57 | R81: =IF(D81="R6",J81," ") | S81: =IF(D81="R8",J81," ") | T81: =IF(D81="T10",J81," ") | U81: =IF(D81="T12",J81," ") -> 285.6 | V81: =IF(D81="T16",J81," ") | W81: =IF(D81="T20",J81," ") | X81: =IF(D81="T25",J81," ") | Y81: =IF(D81="T32",J81," ")
B82: wall | C82: a | D82: T12 | E82: 1 | F82: 60 | G82: =F82*E82 -> 60 | I82: =M82+N82+O82+P82+Q82 -> 3 | J82: =G82*I82 -> 180 | K82: =K78*0.888 -> 0 | M82: 3 | R82: =IF(D82="R6",J82," ") | S82: =IF(D82="R8",J82," ") | T82: =IF(D82="T10",J82," ") | U82: =IF(D82="T12",J82," ") -> 180 | V82: =IF(D82="T16",J82," ") | W82: =IF(D82="T20",J82," ") | X82: =IF(D82="T25",J82," ") | Y82: =IF(D82="T32",J82," ")
B83: base | C83: a | D83: T12 | E83: 1 | F83: 15 | G83: =F83*E83 -> 15 | I83: =M83+N83+O83+P83+Q83 -> 9.2 | J83: =G83*I83 -> 138 | K83: =K79*0.888 -> 0 | M83: =2.3*4 -> 9.2 | R83: =IF(D83="R6",J83," ") | S83: =IF(D83="R8",J83," ") | T83: =IF(D83="T10",J83," ") | U83: =IF(D83="T12",J83," ") -> 138 | V83: =IF(D83="T16",J83," ") | W83: =IF(D83="T20",J83," ") | X83: =IF(D83="T25",J83," ") | Y83: =IF(D83="T32",J83," ")
B85: Total length (m) | R85: =SUM(R79:R84) -> 0 | S85: =SUM(S79:S84) -> 0 | T85: =SUM(T79:T84) -> 0 | U85: =SUM(U79:U84) -> 603.6 | V85: =SUM(V79:V84) -> 0 | W85: =SUM(W79:W84) -> 0 | X85: =SUM(X79:X84) -> 0 | Y85: =SUM(Y79:Y84) -> 0
B86: Weight (Kg/m) | R86: =6*6/162.162 -> 0.22200022 | S86: =8*8/162.162 -> 0.39466706 | T86: =10*10/162.162 -> 0.61666728 | U86: =12*12/162.162 -> 0.88800089 | V86: =16*16/162.162 -> 1.5786682 | W86: =20*20/162.162 -> 2.4666691 | X86: =25*25/162.162 -> 3.8541705 | Y86: =32*32/162.162 -> 6.314673
B87: TOTAL (Kg) | R87: =+R86*R85 -> 0 | S87: =+S86*S85 -> 0 | T87: =+T86*T85 -> 0 | U87: =+U86*U85 -> 535.99734 | V87: =+V86*V85 -> 0 | W87: =+W86*W85 -> 0 | X87: =+X86*X85 -> 0 | Y87: =+Y86*Y85 -> 0 | Z87: =Y87+X87+W87+V87+U87+T87+S87+R87 -> 535.99734
B90: MILD STEEL REINFORCEMENT
B92: Column shaft -upto DPC
B93: C1 | C93: a | D93: R6 | E93: 32 | F93: 9 | G93: =F93*E93 -> 288 | I93: =M93+N93+O93+P93+Q93 -> 1.1 | J93: =G93*I93 -> 316.8 | K93: =K89*0.888 -> 0 | M93: 1.1 | R93: =IF(D93="R6",J93," ") -> 316.8 | S93: =IF(D93="R8",J93," ") | T93: =IF(D93="T10",J93," ") | U93: =IF(D93="T12",J93," ") | V93: =IF(D93="T16",J93," ") | W93: =IF(D93="T20",J93," ") | X93: =IF(D93="T25",J93," ") | Y93: =IF(D93="T32",J93," ")
B94: C2 | C94: a | D94: R6 | E94: 4 | F94: 9 | G94: =F94*E94 -> 36 | I94: =M94+N94+O94+P94+Q94 -> 0.9 | J94: =G94*I94 -> 32.4 | K94: =K88*0.888 -> 0 | M94: 0.9 | R94: =IF(D94="R6",J94," ") -> 32.4 | S94: =IF(D94="R8",J94," ") | T94: =IF(D94="T10",J94," ") | U94: =IF(D94="T12",J94," ") | V94: =IF(D94="T16",J94," ") | W94: =IF(D94="T20",J94," ") | X94: =IF(D94="T25",J94," ") | Y94: =IF(D94="T32",J94," ")
B97: Total length (m) | R97: =SUM(R91:R96) -> 349.2 | S97: =SUM(S91:S96) -> 0 | T97: =SUM(T91:T96) -> 0 | U97: =SUM(U91:U96) -> 0 | V97: =SUM(V91:V96) -> 0 | W97: =SUM(W91:W96) -> 0 | X97: =SUM(X91:X96) -> 0 | Y97: =SUM(Y91:Y96) -> 0
B98: Weight (Kg/m) | R98: =6*6/162.162 -> 0.22200022 | S98: =8*8/162.162 -> 0.39466706 | T98: =10*10/162.162 -> 0.61666728 | U98: =12*12/162.162 -> 0.88800089 | V98: =16*16/162.162 -> 1.5786682 | W98: =20*20/162.162 -> 2.4666691 | X98: =25*25/162.162 -> 3.8541705 | Y98: =32*32/162.162 -> 6.314673
B99: TOTAL (Kg) | R99: =+R98*R97 -> 77.522478 | S99: =+S98*S97 -> 0 | T99: =+T98*T97 -> 0 | U99: =+U98*U97 -> 0 | V99: =+V98*V97 -> 0 | W99: =+W98*W97 -> 0 | X99: =+X98*X97 -> 0 | Y99: =+Y98*Y97 -> 0 | Z99: =Y99+X99+W99+V99+U99+T99+S99+R99 -> 77.522478
B102: Plinth Beam
B103: pb 300X300 | C103: a | D103: R6 | E103: 1 | F103: 1200 | G103: =F103*E103 -> 1200 | I103: =M103+N103+O103+P103+Q103 -> 1.1 | J103: =G103*I103 -> 1320 | K103: =K99*0.888 -> 0 | M103: 1.1 | R103: =IF(D103="R6",J103," ") -> 1320 | S103: =IF(D103="R8",J103," ") | T103: =IF(D103="T10",J103," ") | U103: =IF(D103="T12",J103," ") | V103: =IF(D103="T16",J103," ") | W103: =IF(D103="T20",J103," ") | X103: =IF(D103="T25",J103," ") | Y103: =IF(D103="T32",J103," ")
B104: pb 225X300 | C104: a | D104: R6 | E104: 1 | F104: 4 | G104: =F104*E104 -> 4 | I104: =M104+N104+O104+P104+Q104 -> 0.97 | J104: 320 | K104: =K100*0.888 -> 0 | M104: 0.97 | R104: =IF(D104="R6",J104," ") -> 320 | S104: =IF(D104="R8",J104," ") | T104: =IF(D104="T10",J104," ") | U104: =IF(D104="T12",J104," ") | V104: =IF(D104="T16",J104," ") | W104: =IF(D104="T20",J104," ") | X104: =IF(D104="T25",J104," ") | Y104: =IF(D104="T32",J104," ")
B106: Total length (m) | R106: =SUM(R101:R105) -> 1640 | S106: =SUM(S101:S105) -> 0 | T106: =SUM(T101:T105) -> 0 | U106: =SUM(U101:U105) -> 0 | V106: =SUM(V101:V105) -> 0 | W106: =SUM(W101:W105) -> 0 | X106: =SUM(X101:X105) -> 0 | Y106: =SUM(Y101:Y105) -> 0
B107: Weight (Kg/m) | R107: =6*6/162.162 -> 0.22200022 | S107: =8*8/162.162 -> 0.39466706 | T107: =10*10/162.162 -> 0.61666728 | U107: =12*12/162.162 -> 0.88800089 | V107: =16*16/162.162 -> 1.5786682 | W107: =20*20/162.162 -> 2.4666691 | X107: =25*25/162.162 -> 3.8541705 | Y107: =32*32/162.162 -> 6.314673
B108: TOTAL (Kg) | R108: =+R107*R106 -> 364.08036 | S108: =+S107*S106 -> 0 | T108: =+T107*T106 -> 0 | U108: =+U107*U106 -> 0 | V108: =+V107*V106 -> 0 | W108: =+W107*W106 -> 0 | X108: =+X107*X106 -> 0 | Y108: =+Y107*Y106 -> 0 | Z108: =Y108+X108+W108+V108+U108+T108+S108+R108 -> 364.08036
B110: Column shaft -DPC -1st
B111: C1 | C111: a | D111: R6 | E111: 32 | F111: 27 | G111: =F111*E111 -> 864 | I111: =M111+N111+O111+P111+Q111 -> 1.1 | J111: =G111*I111 -> 950.4 | K111: =K107*0.888 -> 0 | M111: 1.1 | R111: =IF(D111="R6",J111," ") -> 950.4 | S111: =IF(D111="R8",J111," ") | T111: =IF(D111="T10",J111," ") | U111: =IF(D111="T12",J111," ") | V111: =IF(D111="T16",J111," ") | W111: =IF(D111="T20",J111," ") | X111: =IF(D111="T25",J111," ") | Y111: =IF(D111="T32",J111," ")
B112: C2 | C112: a | D112: R6 | E112: 4 | F112: 27 | G112: =F112*E112 -> 108 | I112: =M112+N112+O112+P112+Q112 -> 0.9 | J112: =G112*I112 -> 97.2 | K112: =K108*0.888 -> 0 | M112: 0.9 | R112: =IF(D112="R6",J112," ") -> 97.2 | S112: =IF(D112="R8",J112," ") | T112: =IF(D112="T10",J112," ") | U112: =IF(D112="T12",J112," ") | V112: =IF(D112="T16",J112," ") | W112: =IF(D112="T20",J112," ") | X112: =IF(D112="T25",J112," ") | Y112: =IF(D112="T32",J112," ")
B114: Total length (m) | R114: =SUM(R109:R113) -> 1047.6 | S114: =SUM(S109:S113) -> 0 | T114: =SUM(T109:T113) -> 0 | U114: =SUM(U109:U113) -> 0 | V114: =SUM(V109:V113) -> 0 | W114: =SUM(W109:W113) -> 0 | X114: =SUM(X109:X113) -> 0 | Y114: =SUM(Y109:Y113) -> 0
B115: Weight (Kg/m) | R115: =6*6/162.162 -> 0.22200022 | S115: =8*8/162.162 -> 0.39466706 | T115: =10*10/162.162 -> 0.61666728 | U115: =12*12/162.162 -> 0.88800089 | V115: =16*16/162.162 -> 1.5786682 | W115: =20*20/162.162 -> 2.4666691 | X115: =25*25/162.162 -> 3.8541705 | Y115: =32*32/162.162 -> 6.314673
B116: TOTAL (Kg) | R116: =+R115*R114 -> 232.56743 | S116: =+S115*S114 -> 0 | T116: =+T115*T114 -> 0 | U116: =+U115*U114 -> 0 | V116: =+V115*V114 -> 0 | W116: =+W115*W114 -> 0 | X116: =+X115*X114 -> 0 | Y116: =+Y115*Y114 -> 0 | Z116: =Y116+X116+W116+V116+U116+T116+S116+R116 -> 232.56743
B118: G/F beam
B119: 1,7 A1-C | C119: B | D119: R6 | E119: 1 | F119: 85 | G119: =F119*E119 -> 85 | I119: =M119+N119+O119+P119+Q119 -> 1.4 | J119: =G119*I119 -> 119 | K119: =K115*0.888 -> 0 | L119: 12.75 | M119: 1.4 | R119: =IF(D119="R6",J119," ") -> 119 | S119: =IF(D119="R8",J119," ") | T119: =IF(D119="T10",J119," ") | U119: =IF(D119="T12",J119," ") | V119: =IF(D119="T16",J119," ") | W119: =IF(D119="T20",J119," ") | X119: =IF(D119="T25",J119," ") | Y119: =IF(D119="T32",J119," ")
B122: Total length (m) | R122: =SUM(R117:R121) -> 119 | S122: =SUM(S117:S121) -> 0 | T122: =SUM(T117:T121) -> 0 | U122: =SUM(U117:U121) -> 0 | V122: =SUM(V117:V121) -> 0 | W122: =SUM(W117:W121) -> 0 | X122: =SUM(X117:X121) -> 0 | Y122: =SUM(Y117:Y121) -> 0
B123: Weight (Kg/m) | R123: =6*6/162.162 -> 0.22200022 | S123: =8*8/162.162 -> 0.39466706 | T123: =10*10/162.162 -> 0.61666728 | U123: =12*12/162.162 -> 0.88800089 | V123: =16*16/162.162 -> 1.5786682 | W123: =20*20/162.162 -> 2.4666691 | X123: =25*25/162.162 -> 3.8541705 | Y123: =32*32/162.162 -> 6.314673
B124: TOTAL (Kg) | R124: =+R123*R122 -> 26.418026 | S124: =+S123*S122 -> 0 | T124: =+T123*T122 -> 0 | U124: =+U123*U122 -> 0 | V124: =+V123*V122 -> 0 | W124: =+W123*W122 -> 0 | X124: =+X123*X122 -> 0 | Y124: =+Y123*Y122 -> 0 | Z124: =Y124+X124+W124+V124+U124+T124+S124+R124 -> 26.418026
B126: Column shaft -1st - 2nd
B127: C1 | C127: a | D127: R6 | E127: 23 | F127: =F111 -> 27 | G127: =F127*E127 -> 621 | I127: =M127+N127+O127+P127+Q127 -> 1.1 | J127: =G127*I127 -> 683.1 | K127: =K123*0.888 -> 0 | M127: 1.1 | R127: =IF(D127="R6",J127," ") -> 683.1 | S127: =IF(D127="R8",J127," ") | T127: =IF(D127="T10",J127," ") | U127: =IF(D127="T12",J127," ") | V127: =IF(D127="T16",J127," ") | W127: =IF(D127="T20",J127," ") | X127: =IF(D127="T25",J127," ") | Y127: =IF(D127="T32",J127," ")
B128: C2 | C128: a | D128: R6 | E128: 4 | F128: =F127 -> 27 | G128: =F128*E128 -> 108 | I128: =M128+N128+O128+P128+Q128 -> 0.8 | J128: =G128*I128 -> 86.4 | K128: =K124*0.888 -> 0 | M128: 0.8 | R128: =IF(D128="R6",J128," ") -> 86.4 | S128: =IF(D128="R8",J128," ") | T128: =IF(D128="T10",J128," ") | U128: =IF(D128="T12",J128," ") | V128: =IF(D128="T16",J128," ") | W128: =IF(D128="T20",J128," ") | X128: =IF(D128="T25",J128," ") | Y128: =IF(D128="T32",J128," ")
B130: Total length (m) | R130: =SUM(R125:R129) -> 769.5 | S130: =SUM(S125:S129) -> 0 | T130: =SUM(T125:T129) -> 0 | U130: =SUM(U125:U129) -> 0 | V130: =SUM(V125:V129) -> 0 | W130: =SUM(W125:W129) -> 0 | X130: =SUM(X125:X129) -> 0 | Y130: =SUM(Y125:Y129) -> 0
B131: Weight (Kg/m) | R131: =6*6/162.162 -> 0.22200022 | S131: =8*8/162.162 -> 0.39466706 | T131: =10*10/162.162 -> 0.61666728 | U131: =12*12/162.162 -> 0.88800089 | V131: =16*16/162.162 -> 1.5786682 | W131: =20*20/162.162 -> 2.4666691 | X131: =25*25/162.162 -> 3.8541705 | Y131: =32*32/162.162 -> 6.314673
B132: TOTAL (Kg) | R132: =+R131*R130 -> 170.82917 | S132: =+S131*S130 -> 0 | T132: =+T131*T130 -> 0 | U132: =+U131*U130 -> 0 | V132: =+V131*V130 -> 0 | W132: =+W131*W130 -> 0 | X132: =+X131*X130 -> 0 | Y132: =+Y131*Y130 -> 0 | Z132: =Y132+X132+W132+V132+U132+T132+S132+R132 -> 170.82917
H150: Footing
H151: =T6 -> T10
H152: =U6 -> T12 | I152: =#REF!+#REF! -> #REF! | J152: nr | U152: =U18+V18+T18+W18 -> 1387.4126
H153: =V6 -> T16 | I153: =#REF!+#REF!+#REF!+#REF!+#REF!+#REF!+#REF!+#REF!+#REF!+#REF! -> #REF! | J153: nr
H154: =W6 -> T20 | I154: =#REF!+#REF!+#REF! -> #REF! | J154: nr | U154: =U152/1000 -> 1.3874126
H156: shaft
...

Sheet M sheet- dodangoda (2)
A1: NO | B1: DESCRIPTION | C1: NOS | F1: LENGTH | G1: WIDTH | H1: HEIGHT | I1: QTY | J1: T.QTY | O1: UNIT
K2: 1.1
K3: =$K$2 -> 1.1 | L3: =K3*J3 -> 0 | M3: =ROUND(L3,1) -> 0 | N3: =ROUNDUP(M3,0) -> 0 | P3: 1.1
B4: top soil remove | J4: 615 | K4: 1.03 | L4: =K4*J4 -> 633.45 | M4: =ROUND(L4,1) -> 633.5 | N4: =ROUNDUP(M4,0) -> 634
K5: =$K$2 -> 1.1 | L5: =K5*J5 -> 0 | M5: =ROUND(L5,1) -> 0 | N5: =ROUNDUP(M5,0) -> 0
K6: =$K$2 -> 1.1 | L6: =K6*J6 -> 0 | M6: =ROUND(L6,1) -> 0 | N6: =ROUNDUP(M6,0) -> 0
B7: anti termite | J7: 290 | K7: =$K$2 -> 1.1 | L7: =K7*J7 -> 319 | M7: =ROUND(L7,1) -> 319 | N7: =ROUNDUP(M7,0) -> 319
J8: =J7*10.76 -> 3120.4 | K8: =$K$2 -> 1.1 | L8: =K8*J8 -> 3432.44 | M8: =ROUND(L8,1) -> 3432.4 | N8: =ROUNDUP(M8,0) -> 3433
K9: =$K$2 -> 1.1 | L9: =K9*J9 -> 0 | M9: =ROUND(L9,1) -> 0 | N9: =ROUNDUP(M9,0) -> 0
K10: =$K$2 -> 1.1 | L10: =K10*J10 -> 0 | M10: =ROUND(L10,1) -> 0 | N10: =ROUNDUP(M10,0) -> 0
K11: =$K$2 -> 1.1 | L11: =K11*J11 -> 0 | M11: =ROUND(L11,1) -> 0 | N11: =ROUNDUP(M11,0) -> 0
K12: =$K$2 -> 1.1 | L12: =K12*J12 -> 0 | M12: =ROUND(L12,1) -> 0 | N12: =ROUNDUP(M12,0) -> 0
K13: =$K$2 -> 1.1 | L13: =K13*J13 -> 0 | M13: =ROUND(L13,1) -> 0 | N13: =ROUNDUP(M13,0) -> 0
K14: =$K$2 -> 1.1 | L14: =K14*J14 -> 0 | M14: =ROUND(L14,1) -> 0 | N14: =ROUNDUP(M14,0) -> 0
K15: =$K$2 -> 1.1 | L15: =K15*J15 -> 0 | M15: =ROUND(L15,1) -> 0 | N15: =ROUNDUP(M15,0) -> 0
K16: =$K$2 -> 1.1 | L16: =K16*J16 -> 0 | M16: =ROUND(L16,1) -> 0 | N16: =ROUNDUP(M16,0) -> 0
K17: =$K$2 -> 1.1 | L17: =K17*J17 -> 0 | M17: =ROUND(L17,1) -> 0 | N17: =ROUNDUP(M17,0) -> 0
K18: =$K$2 -> 1.1 | L18: =K18*J18 -> 0 | M18: =ROUND(L18,1) -> 0 | N18: =ROUNDUP(M18,0) -> 0
K19: =$K$2 -> 1.1 | L19: =K19*J19 -> 0 | M19: =ROUND(L19,1) -> 0 | N19: =ROUNDUP(M19,0) -> 0
K20: =$K$2 -> 1.1 | L20: =K20*J20 -> 0 | M20: =ROUND(L20,1) -> 0 | N20: =ROUNDUP(M20,0) -> 0
... K532: =$K$2 -> 1.1 | L532: =K532*J532 -> 0 | M532: =ROUND(L532,1) -> 0 | N532: =ROUNDUP(M532,0) -> 0
A534: 1 | B534: clearing site vegetation | F534: =60+9 -> 69 | G534: =21+6 -> 27 | I534: =G534*F534 -> 1863 | J534: =I534 -> 1863 | K534: =$K$2 -> 1.1 | L534: =K534*J534 -> 2049.3 | M534: =ROUND(L534,1) -> 2049.3 | N534: =ROUNDUP(M534,0) -> 2050 | O534: m2
J535: =J534*10.76 -> 20045.88 | K535: =$K$2 -> 1.1 | L535: =K535*J535 -> 22050.468 | M535: =ROUND(L535,1) -> 22050.5 | N535: =ROUNDUP(M535,0) -> 22051 | O535: ft2 | P535: =J534/9.29 -> 200.53821
J536: =J535/100 -> 200.4588 | K536: 1.03 | L536: =K536*J536 -> 206.47256 | M536: =ROUND(L536,1) -> 206.5 | N536: =ROUNDUP(M536,0) -> 207 | O536: sqr
K537: =$K$2 -> 1.1 | L537: =K537*J537 -> 0 | M537: =ROUND(L537,1) -> 0 | N537: =ROUNDUP(M537,0) -> 0
B538: top soil remove | F538: 60 | G538: 21 | I538: =G538*F538 -> 1260 | J538: =I538 -> 1260 | K538: =$K$2 -> 1.1 | L538: =K538*J538 -> 1386 | M538: =ROUND(L538,1) -> 1386 | N538: =ROUNDUP(M538,0) -> 1386 | O538: m2
J539: =J538*10.76 -> 13557.6 | K539: =$K$2 -> 1.1 | L539: =K539*J539 -> 14913.36 | M539: =ROUND(L539,1) -> 14913.4 | N539: =ROUNDUP(M539,0) -> 14914 | O539: ft2
J540: =J539/100 -> 135.576 | K540: 1.05 | L540: =K540*J540 -> 142.3548 | M540: =ROUND(L540,1) -> 142.4 | N540: =ROUNDUP(M540,0) -> 143 | O540: sqr | P540: =N540-J540 -> 7.424
K541: =$K$2 -> 1.1 | L541: =K541*J541 -> 0 | M541: =ROUND(L541,1) -> 0 | N541: =ROUNDUP(M541,0) -> 0
B542: approved earth piled at site | F542: =F538 -> 60 | G542: =G538 -> 21 | H542: 1.5 | I542: =H542*G542*F542 -> 1890 | J542: =I542 -> 1890 | K542: =$K$2 -> 1.1 | L542: =K542*J542 -> 2079 | M542: =ROUND(L542,1) -> 2079 | N542: =ROUNDUP(M542,0) -> 2079 | O542: m3
J543: =J542/2.83 -> 667.84452 | K543: 1.05 | L543: =K543*J543 -> 701.23675 | M543: =ROUND(L543,1) -> 701.2 | N543: =ROUNDUP(M543,0) -> 702 | O543: cube | P543: =N543-J543 -> 34.155477
K544: =$K$2 -> 1.1 | L544: =K544*J544 -> 0 | M544: =ROUND(L544,1) -> 0 | N544: =ROUNDUP(M544,0) -> 0
B545: back filling | K545: =$K$2 -> 1.1 | L545: =K545*J545 -> 0 | M545: =ROUND(L545,1) -> 0 | N545: =ROUNDUP(M545,0) -> 0
K546: =$K$2 -> 1.1 | L546: =K546*J546 -> 0 | M546: =ROUND(L546,1) -> 0 | N546: =ROUNDUP(M546,0) -> 0
K547: =$K$2 -> 1.1 | L547: =K547*J547 -> 0 | M547: =ROUND(L547,1) -> 0 | N547: =ROUNDUP(M547,0) -> 0
B548: anti termite | F548: =F542 -> 60 | G548: =G542 -> 21 | I548: =G548*F548 -> 1260 | J548: =I548 -> 1260 | K548: =$K$2 -> 1.1 | L548: =K548*J548 -> 1386 | M548: =ROUND(L548,1) -> 1386 | N548: =ROUNDUP(M548,0) -> 1386
J549: =J548*10.76 -> 13557.6 | K549: 1.01 | L549: =K549*J549 -> 13693.176 | M549: =ROUND(L549,1) -> 13693.2 | N549: =ROUNDUP(M549,0) -> 13694 | P549: =N549-J549 -> 136.4
K550: =$K$2 -> 1.1 | L550: =K550*J550 -> 0 | M550: =ROUND(L550,1) -> 0 | N550: =ROUNDUP(M550,0) -> 0
K551: =$K$2 -> 1.1 | L551: =K551*J551 -> 0 | M551: =ROUND(L551,1) -> 0 | N551: =ROUNDUP(M551,0) -> 0
B552: excvtion
B553: lift | F553: 3 | G553: 3 | H553: 2 | I553: =H553*G553*F553 -> 18
B554: stair | F554: 2 | G554: 1.5 | H554: 1 | I554: =H554*G554*F554 -> 3
J555: =SUM(I553:I554) -> 21 | K555: =$K$2 -> 1.1 | L555: =K555*J555 -> 23.1 | M555: =ROUND(L555,1) -> 23.1 | N555: =ROUNDUP(M555,0) -> 24
J556: =J555/2.83 -> 7.4204947 | K556: =$K$2 -> 1.1 | L556: =K556*J556 -> 8.1625442 | M556: =ROUND(L556,1) -> 8.2 | N556: =ROUNDUP(M556,0) -> 9
B558: earth work support
B559: lift | E559: 4 | F559: =F553 -> 3 | H559: 2 | I559: =H559*F559*E559 -> 24 | J559: =I559 -> 24 | K559: =$K$2 -> 1.1 | L559: =K559*J559 -> 26.4 | M559: =ROUND(L559,1) -> 26.4 | N559: =ROUNDUP(M559,0) -> 27
J560: =J559*10.76 -> 258.24 | K560: =$K$2 -> 1.1 | L560: =K560*J560 -> 284.064 | M560: =ROUND(L560,1) -> 284.1 | N560: =ROUNDUP(M560,0) -> 285
B562: concrte works | K562: =$K$2 -> 1.1 | L562: =K562*J562 -> 0 | M562: =ROUND(L562,1) -> 0 | N562: =ROUNDUP(M562,0) -> 0
K563: =$K$2 -> 1.1 | L563: =K563*J563 -> 0 | M563: =ROUND(L563,1) -> 0 | N563: =ROUNDUP(M563,0) -> 0
B564: screed cocnrete | K564: =$K$2 -> 1.1 | L564: =K564*J564 -> 0 | M564: =ROUND(L564,1) -> 0 | N564: =ROUNDUP(M564,0) -> 0
B565: plinth beam | K565: =$K$2 -> 1.1 | L565: =K565*J565 -> 0 | M565: =ROUND(L565,1) -> 0 | N565: =ROUNDUP(M565,0) -> 0
B566: PB1 | F566: 27.878 | G566: 0.35 | I566: =G566*F566 -> 9.7573 | K566: =$K$2 -> 1.1 | L566: =K566*J566 -> 0 | M566: =ROUND(L566,1) -> 0 | N566: =ROUNDUP(M566,0) -> 0
B567: PB2 | F567: 23.803 | G567: 0.35 | I567: =G567*F567 -> 8.33105 | K567: =$K$2 -> 1.1 | L567: =K567*J567 -> 0 | M567: =ROUND(L567,1) -> 0 | N567: =ROUNDUP(M567,0) -> 0
B568: PB2a | F568: 6.396 | G568: 0.35 | I568: =G568*F568 -> 2.2386
B569: PB3 | F569: 49 | G569: 0.35 | I569: =G569*F569 -> 17.15 | K569: =$K$2 -> 1.1 | L569: =K569*J569 -> 0 | M569: =ROUND(L569,1) -> 0 | N569: =ROUNDUP(M569,0) -> 0
B570: PB4 | F570: 8.3 | G570: 0.35 | I570: =G570*F570 -> 2.905 | K570: =$K$2 -> 1.1 | L570: =K570*J570 -> 0 | M570: =ROUND(L570,1) -> 0 | N570: =ROUNDUP(M570,0) -> 0
B571: PB5 | F571: 9.913 | G571: 0.225 | I571: =G571*F571 -> 2.230425 | K571: =$K$2 -> 1.1 | L571: =K571*J571 -> 0 | M571: =ROUND(L571,1) -> 0 | N571: =ROUNDUP(M571,0) -> 0
B572: PB6 | F572: 4.888 | G572: 0.35 | I572: =G572*F572 -> 1.7108 | K572: =$K$2 -> 1.1 | L572: =K572*J572 -> 0 | M572: =ROUND(L572,1) -> 0 | N572: =ROUNDUP(M572,0) -> 0
B573: PB7 | F573: 3.363 | G573: 0.35 | I573: =G573*F573 -> 1.17705 | K573: =$K$2 -> 1.1 | L573: =K573*J573 -> 0 | M573: =ROUND(L573,1) -> 0 | N573: =ROUNDUP(M573,0) -> 0
B574: PB8 | F574: 27.779 | G574: 0.35 | I574: =G574*F574 -> 9.72265 | K574: =$K$2 -> 1.1 | L574: =K574*J574 -> 0 | M574: =ROUND(L574,1) -> 0 | N574: =ROUNDUP(M574,0) -> 0
B575: PB9 | F575: 59.55 | G575: 0.35 | I575: =G575*F575 -> 20.8425 | K575: =$K$2 -> 1.1 | L575: =K575*J575 -> 0 | M575: =ROUND(L575,1) -> 0 | N575: =ROUNDUP(M575,0) -> 0
B576: PB10 | F576: 2.327 | G576: 0.35 | I576: =G576*F576 -> 0.81445 | K576: =$K$2 -> 1.1 | L576: =K576*J576 -> 0 | M576: =ROUND(L576,1) -> 0 | N576: =ROUNDUP(M576,0) -> 0
B577: PB11 | F577: 3.75 | G577: 0.35 | I577: =G577*F577 -> 1.3125 | K577: =$K$2 -> 1.1 | L577: =K577*J577 -> 0 | M577: =ROUND(L577,1) -> 0 | N577: =ROUNDUP(M577,0) -> 0
B578: PB12 | F578: 2 | G578: 0.35 | I578: =G578*F578 -> 0.7 | K578: =$K$2 -> 1.1 | L578: =K578*J578 -> 0 | M578: =ROUND(L578,1) -> 0 | N578: =ROUNDUP(M578,0) -> 0
B579: PB13 | F579: 27.429 | G579: 0.35 | I579: =G579*F579 -> 9.60015 | K579: =$K$2 -> 1.1 | L579: =K579*J579 -> 0 | M579: =ROUND(L579,1) -> 0 | N579: =ROUNDUP(M579,0) -> 0
B580: PB14 | F580: 7.646 | G580: 0.35 | I580: =G580*F580 -> 2.6761 | K580: =$K$2 -> 1.1 | L580: =K580*J580 -> 0 | M580: =ROUND(L580,1) -> 0 | N580: =ROUNDUP(M580,0) -> 0
... B585: PB19 | F585: 15.775 | G585: 0.35 | I585: =G585*F585 -> 5.52125 | K585: =$K$2 -> 1.1 | L585: =K585*J585 -> 0 | M585: =ROUND(L585,1) -> 0 | N585: =ROUNDUP(M585,0) -> 0
I586: =G586*F586 -> 0
B587: PB21 | F587: 19.17 | G587: 0.35 | I587: =G587*F587 -> 6.7095 | K587: =$K$2 -> 1.1 | L587: =K587*J587 -> 0 | M587: =ROUND(L587,1) -> 0 | N587: =ROUNDUP(M587,0) -> 0
B588: PB22 | F588: 19.77 | G588: 0.35 | I588: =G588*F588 -> 6.9195 | K588: =$K$2 -> 1.1 | L588: =K588*J588 -> 0 | M588: =ROUND(L588,1) -> 0 | N588: =ROUNDUP(M588,0) -> 0
B589: PB23 | F589: 14.963 | G589: 0.35 | I589: =G589*F589 -> 5.23705 | K589: =$K$2 -> 1.1 | L589: =K589*J589 -> 0 | M589: =ROUND(L589,1) -> 0 | N589: =ROUNDUP(M589,0) -> 0
B590: PB24 | F590: 3.933 | G590: 0.35 | I590: =G590*F590 -> 1.37655 | K590: =$K$2 -> 1.1 | L590: =K590*J590 -> 0 | M590: =ROUND(L590,1) -> 0 | N590: =ROUNDUP(M590,0) -> 0
B591: PB25 | F591: 5.687 | G591: 0.225 | I591: =G591*F591 -> 1.279575 | K591: =$K$2 -> 1.1 | L591: =K591*J591 -> 0 | M591: =ROUND(L591,1) -> 0 | N591: =ROUNDUP(M591,0) -> 0
B592: PB26 | F592: 1.596 | G592: 0.35 | I592: =G592*F592 -> 0.5586 | K592: =$K$2 -> 1.1 | L592: =K592*J592 -> 0 | M592: =ROUND(L592,1) -> 0 | N592: =ROUNDUP(M592,0) -> 0
B593: PB27 | F593: 12.475 | G593: 0.35 | I593: =G593*F593 -> 4.36625 | K593: =$K$2 -> 1.1 | L593: =K593*J593 -> 0 | M593: =ROUND(L593,1) -> 0 | N593: =ROUNDUP(M593,0) -> 0
B594: PB28 | F594: 8.55 | G594: 0.35 | I594: =G594*F594 -> 2.9925 | K594: =$K$2 -> 1.1 | L594: =K594*J594 -> 0 | M594: =ROUND(L594,1) -> 0 | N594: =ROUNDUP(M594,0) -> 0
B595: PB29 | F595: 2.987 | G595: 0.35 | I595: =G595*F595 -> 1.04545 | K595: =$K$2 -> 1.1 | L595: =K595*J595 -> 0 | M595: =ROUND(L595,1) -> 0 | N595: =ROUNDUP(M595,0) -> 0
B596: PB30 | F596: 6.35 | G596: 0.35 | I596: =G596*F596 -> 2.2225 | K596: =$K$2 -> 1.1 | L596: =K596*J596 -> 0 | M596: =ROUND(L596,1) -> 0 | N596: =ROUNDUP(M596,0) -> 0
B597: PB31 | F597: 6.187 | G597: 0.35 | I597: =G597*F597 -> 2.16545 | K597: =$K$2 -> 1.1 | L597: =K597*J597 -> 0 | M597: =ROUND(L597,1) -> 0 | N597: =ROUNDUP(M597,0) -> 0
B598: PB32 | F598: 1.788 | G598: 0.35 | I598: =G598*F598 -> 0.6258 | K598: =$K$2 -> 1.1 | L598: =K598*J598 -> 0 | M598: =ROUND(L598,1) -> 0 | N598: =ROUNDUP(M598,0) -> 0
... B615: PB49 | F615: 19 | G615: 0.35 | I615: =G615*F615 -> 6.65 | K615: =$K$2 -> 1.1 | L615: =K615*J615 -> 0 | M615: =ROUND(L615,1) -> 0 | N615: =ROUNDUP(M615,0) -> 0
J616: =SUM(I566:I615) -> 222.06025 | K616: =$K$2 -> 1.1 | L616: =K616*J616 -> 244.26628 | M616: =ROUND(L616,1) -> 244.3 | N616: =ROUNDUP(M616,0) -> 245 | O616: m2
J617: =J616*10.76 -> 2389.3683 | K617: =$K$2 -> 1.1 | L617: =K617*J617 -> 2628.3051 | M617: =ROUND(L617,1) -> 2628.3 | N617: =ROUNDUP(M617,0) -> 2629 | O617: ft2
J618: =J617/100 -> 23.893683 | K618: =$K$2 -> 1.1 | L618: =K618*J618 -> 26.283051 | M618: =ROUND(L618,1) -> 26.3 | N618: =ROUNDUP(M618,0) -> 27 | O618: sqr
K619: =$K$2 -> 1.1 | L619: =K619*J619 -> 0 | M619: =ROUND(L619,1) -> 0 | N619: =ROUNDUP(M619,0) -> 0
B620: plinth beam cocnrete | K620: =$K$2 -> 1.1 | L620: =K620*J620 -> 0 | M620: =ROUND(L620,1) -> 0 | N620: =ROUNDUP(M620,0) -> 0
B621: PB1 | F621: 27.878 | G621: 0.35 | H621: 0.75 | I621: =H621*G621*F621 -> 7.317975 | K621: =$K$2 -> 1.1 | L621: =K621*J621 -> 0 | M621: =ROUND(L621,1) -> 0 | N621: =ROUNDUP(M621,0) -> 0
B622: PB2 | F622: 23.803 | G622: 0.35 | H622: 0.75 | I622: =H622*G622*F622 -> 6.2482875 | K622: =$K$2 -> 1.1 | L622: =K622*J622 -> 0 | M622: =ROUND(L622,1) -> 0 | N622: =ROUNDUP(M622,0) -> 0
B623: PB2a | F623: 6.515 | G623: 0.35 | H623: 0.5 | I623: =H623*G623*F623 -> 1.140125
B624: PB3 | F624: 49 | G624: 0.35 | H624: 0.5 | I624: =H624*G624*F624 -> 8.575 | K624: =$K$2 -> 1.1 | L624: =K624*J624 -> 0 | M624: =ROUND(L624,1) -> 0 | N624: =ROUNDUP(M624,0) -> 0
B625: PB4 | F625: 8.3 | G625: 0.35 | H625: 0.5 | I625: =H625*G625*F625 -> 1.4525 | K625: =$K$2 -> 1.1 | L625: =K625*J625 -> 0 | M625: =ROUND(L625,1) -> 0 | N625: =ROUNDUP(M625,0) -> 0
B626: PB5 | F626: 9.913 | G626: 0.225 | H626: 0.5 | I626: =H626*G626*F626 -> 1.1152125 | K626: =$K$2 -> 1.1 | L626: =K626*J626 -> 0 | M626: =ROUND(L626,1) -> 0 | N626: =ROUNDUP(M626,0) -> 0
B627: PB6 | F627: 4.888 | G627: 0.35 | H627: 0.5 | I627: =H627*G627*F627 -> 0.8554 | K627: =$K$2 -> 1.1 | L627: =K627*J627 -> 0 | M627: =ROUND(L627,1) -> 0 | N627: =ROUNDUP(M627,0) -> 0
B628: PB7 | F628: 3.363 | G628: 0.35 | H628: 0.5 | I628: =H628*G628*F628 -> 0.588525 | K628: =$K$2 -> 1.1 | L628: =K628*J628 -> 0 | M628: =ROUND(L628,1) -> 0 | N628: =ROUNDUP(M628,0) -> 0
B629: PB8 | F629: 27.779 | G629: 0.35 | H629: 0.5 | I629: =H629*G629*F629 -> 4.861325 | K629: =$K$2 -> 1.1 | L629: =K629*J629 -> 0 | M629: =ROUND(L629,1) -> 0 | N629: =ROUNDUP(M629,0) -> 0
B630: PB9 | F630: 59.55 | G630: 0.35 | H630: 0.5 | I630: =H630*G630*F630 -> 10.42125 | K630: =$K$2 -> 1.1 | L630: =K630*J630 -> 0 | M630: =ROUND(L630,1) -> 0 | N630: =ROUNDUP(M630,0) -> 0
B631: PB10 | F631: 2.327 | G631: 0.35 | H631: 0.5 | I631: =H631*G631*F631 -> 0.407225 | K631: =$K$2 -> 1.1 | L631: =K631*J631 -> 0 | M631: =ROUND(L631,1) -> 0 | N631: =ROUNDUP(M631,0) -> 0
B632: PB11 | F632: 3.75 | G632: 0.35 | H632: 0.5 | I632: =H632*G632*F632 -> 0.65625 | K632: =$K$2 -> 1.1 | L632: =K632*J632 -> 0 | M632: =ROUND(L632,1) -> 0 | N632: =ROUNDUP(M632,0) -> 0
B633: PB12 | F633: 2 | G633: 0.35 | H633: 0.5 | I633: =H633*G633*F633 -> 0.35 | K633: =$K$2 -> 1.1 | L633: =K633*J633 -> 0 | M633: =ROUND(L633,1) -> 0 | N633: =ROUNDUP(M633,0) -> 0
B634: PB13 | F634: 27.429 | G634: 0.35 | H634: 0.5 | I634: =H634*G634*F634 -> 4.800075 | K634: =$K$2 -> 1.1 | L634: =K634*J634 -> 0 | M634: =ROUND(L634,1) -> 0 | N634: =ROUNDUP(M634,0) -> 0
...

Sheet front
J6: =450*4 -> 1800
A10: BILLS OF QUANTITIES
A12: CONSTRUCTION OF PROPOSED RESIDENT PROJECT FOR MR.ROLF AT HIKKADUWA. | N12: =#REF!*45 -> #REF! | O12: =310 -> 310 | P12: =N12-O12 -> #REF! | S12: =19.5*2 -> 39
S13: =S12*5 -> 195
O15: =O12/45 -> 6.8888889
O16: =O15*338 -> 2328.4444 | S16: =S13/45 -> 4.3333333
S17: =S16*338 -> 1464.6667
S18: =S17*5 -> 7323.3333
B61: 180000
B62: =B61*12 -> 2160000
B63: =B62/300 -> 7200
B65: 100000
B66: =B65*12 -> 1200000
B67: =B66/300 -> 4000
B70: =B62-B66 -> 960000

Sheet grnd summry- tender
A1: CONSTRUCTION OF PROPOSED RESIDENT PROJECT FOR MR.ROLF AT HIKKADUWA. | M1: =1850+2500 -> 4350 | N1: =M1*1.25 -> 5437.5
A2: MAIN SUMMARY | D2: 200000000 | E2: 100000000
A3: BILL NO | B3: DESCRIPTION | C3: AMOUNT (Rs.) | H3: =C7+#REF! -> #REF! | K3: =C9/9 -> 5274321.5
D4: =D2*0.2 -> 40000000
A5: Bill No. 01 | B5: PRELIMINARIES | C5: =+prelims!I135 -> 318750 | D5: =D2*0.05 -> 10000000 | E5: =C5/C7*100 -> 0.67603188 | G5: =C5/C7 -> 0.0067603188 | H5: =C7+C15+#REF! -> #REF! | I5: =C5/H5*100 -> #REF! | J5: =C5/H3*100 -> #REF!
A7: Bill No. 02 | B7: MAIN BUILDING | C7: =+summary!C19 -> 47150143 | D7: =SUM(D4:D5) -> 50000000 | E7: =C5/E2*100 -> 0.31875 | H7: =60000000-C5 -> 59681250 | I7: =SUM(C7:C15) -> 1.4358793e+08 | M7: =1850/10.76 -> 171.93309
K8: =#REF!*8500 -> #REF! | M8: =4399 -> 4399
B9: SUB TOTAL-I | C9: =SUM(C4:C7) -> 47468893 | D9: =C5+C7 -> 47468893 | I9: =C9-summary!#REF!-'grnd summry- tender'!#REF! -> #REF! | K9: =C9*0.95 -> 45095449 | L9: =C9/9000 -> 5274.3215
E10: =52*3.9*0.3 -> 60.84
B11: Less : Discount (If any) | E11: =E10*21500 -> 1308060
G12: =1650/350 -> 4.7142857
B13: SUB TOTAL-II-CARRIED TO FORM OF BID | C13: =SUM(C9) -> 47468893 | D13: 2.0491928e+08 | E13: =59*3.9*2 -> 460.2
D14: =C13-D13 -> -1.5745038e+08 | E14: =E13*1450 -> 667290
A15: Bill No. 03 | B15: PROVISIONAL SUM | C15: =Ps!H9 -> 1500000 | H15: =SUM(C5:C7) -> 47468893 | I15: =SUM(C9:C15) -> 96437786 | J15: =C13/9000 -> 5274.3215 | K15: =9000*9100 -> 81900000
E16: =E10*95 -> 5779.8
B17: SUB TOTAL III | C17: =SUM(C13:C15) -> 48968893 | D17: ='[19]grnd summry- tender'!$C$13 -> 52997390 | E17: =E16*282 -> 1629903.6
G18: =2022-18 -> 2004
A19: Bill No. 05 | B19: ADD- CONTINGENCIES- 10% | D19: =D17+C17 -> 1.0196628e+08 | E19: =E17+E14+E11+#REF! -> #REF! | H19: =SUM(C7:C8) -> 47150143 | I19: =SUM(C9:C19) -> 1.4540668e+08 | J19: =C15/9000 -> 166.66667 | K19: =9000*9100 -> 81900000
B21: SUB TOTAL IV | C21: =+C17 -> 48968893 | I21: =C5/C7*100 -> 0.67603188 | J21: =H7*3% -> 1790437.5 | K21: =C5/H7*100 -> 0.53408734 | M21: =H7*0.0486 -> 2900508.8 | N21: =C21-#REF! -> #REF!
A23: NOTE: - price exclude to excavation (excavation, dry earth filling, back filing) work, random rubble masonry work and concrete ( concrete, formwork,reinforcement)work
B25: ADD 15% VAT | C25: =C21*0.15 -> 7345334 | D25: =D19*1.08 -> 1.1012359e+08 | E25: =C9/24 -> 1977870.6 | L25: =10000*2*12 -> 240000
I26: =C7+C5 -> 47468893 | N26: =#REF!/187 -> #REF!
B27: TOTAL PROJECT COST WITH VAT | C27: =C21+C25 -> 56314227 | L27: =SUM(L25:L26) -> 240000
F28: =34+6 -> 40 | I28: =I26/9000 -> 5274.3215
A29: Total Bid Sum to be taken in to Form of Bid in words Rupees : …………………………………….
A30: …………………………………………………………………………………..…………………..Only
E31: ='[20]grnd summry- tender'!$C$19 -> 2.6071837e+08 | K31: =C13-C73 -> -12531107
A33: Bidder's VAT Registration No: ………………………………...………………
E34: =C17-E31 -> -2.1174948e+08 | I34: 90875054
K35: =K31*1.44% -> -180447.94
A36: ……………………….
A37: Signature of Bidder: Date: ……………………………….
G38: 2600000
G39: =G38*0.2 -> 520000
A40: Name and Address of Bidder:
A41: ………………………………………………………………….……….
A42: ……………………………………………….………………………….
A43: ………………………………………………………………….……….
A46: ……………………………. ……………………………….
A47: Signature of Witness: (1) Signature of Witness: (2) | E47: =6000*13500 -> 81000000 | F47: 40000000
A48: Name and Address of Witness: (1) Name and Address of Witness: (2)
A49: ……………………………………….... …...……………………………………. | F49: =F47/10000 -> 4000
A50: ……………………………………….... …...…………………………………….
A51: ……………………………………….... …...…………………………………….
A52: Date: ………………………….. Date: ………………………………
B54: ground floor | C54: =97.7*10.76 -> 1051.252
B55: first floor | C55: =95*10.76 -> 1022.2
B56: second floor | C56: =95*10.76 -> 1022.2
B57: 3rd | C57: =95*10.76 -> 1022.2
B60: total floor area | C60: =SUM(C54:C57) -> 4117.852
B62: rate per sqft | C62: =C7/C60 -> 11450.179 | D62: =D9/C60 -> 11527.586
F67: =600 -> 600
F68: 350
F69: =F68*F67 -> 210000
F71: =F69/1000 -> 210
A73: 60000000 | B73: 60000000 | C73: 60000000 | H73: =#REF!-A73 -> #REF!
B74: v bvbnbvnbn | C74: =A73*0.0144 -> 864000 | I74: =H73*1.44% -> #REF!
C75: =C13*1.44% -> 683552.06
B78: Prepare Schemetic design and detail drawings | C78: 0.23 | H78: =C78*C75 -> 157216.97 | I78: =C78*C74 -> 198720 | J78: =I78-H78 -> 41503.026 | K78: =#REF!/9000 -> #REF!
B79: Prepare Building services detail drawings | C79: 0.18 | H79: =C79*C75 -> 123039.37 | I79: =C79*C74 -> 155520 | J79: =I79-H79 -> 32480.629
B80: Prepare Structural detail drawings | C80: 0.22 | H80: =C80*C75 -> 150381.45 | I80: =C80*C74 -> 190080 | J80: =I80-H80 -> 39698.546
B81: Prepare Cost Estimate | C81: 0.1 | H81: =C81*C75 -> 68355.206 | I81: =C81*C74 -> 86400 | J81: =I81-H81 -> 18044.794 | K81: =SUM(I78:I81) -> 630720 | L81: =J81-175000 -> -156955.21 | M81: =K81-175000 -> 455720
B82: Bidding document and procurement stage | C82: 0.12 | H82: =C82*C75 -> 82026.248 | I82: =C82*C74 -> 103680 | J82: =I82-H82 -> 21653.752
B83: Bill checking | C83: 0.15 | E83: 8300 | H83: =C83*C75 -> 102532.81 | I83: =C83*C74 -> 129600 | J83: =I83-H83 -> 27067.191
H85: =SUM(H78:H84) -> 683552.06 | I85: =SUM(I78:I84) -> 864000
B86: site supervision | H86: =12*80500 -> 966000 | I86: =H86 -> 966000 | J86: =SUM(J78:J83) -> 180447.94 | M86: =SUM(H78:H81) -> 498993.01
B87: site visit | H87: =24*10000 -> 240000 | I87: =H87 -> 240000
C89: 100000 | H89: =SUM(H85:H87) -> 1889552.1 | I89: =SUM(I85:I87) -> 2070000 | J89: =H89-I89 -> -180447.94
C96: =400000 -> 400000
C115: 7200000 | G115: 1000000000
C119: =C115/450 -> 16000
G120: =G115*0.015 -> 15000000

Sheet prelims
A1: Nos | B1: Description | C1: Mode of payment catogary | D1: Qty | E1: Unit | F1: Cost | G1: OH & P% | H1: Rate ( Rs.) | I1: Amount | J1: 0.8
B2: BILL NO. 01
A3: 1/PR | B3: A - PRELIMINARIES
B5: This Bill Provides for the typical general items complimentary to the works wich are required to be provided by the Contractor in compliance with the Conditions of Contract and Contract Data in the execution of the works according to the Contract.
B7: If the Engineer is of the opinion that any item in this section has not been provided fully by the Contractor the Engineer may adjust the amounts quoted by the Contractor for the items concerned
B9: Reimbursement of actual cost on submission of the relevant document acceptable to the Engineer plus 5% of the actual cost of obtaining the insurance policies and securities
B11: Mode of Payment Category
B12: Reimbursement of actual cost on submission of A
B13: the relavent document acceptable to the
B14: engineering plus 5% of the actaul cost of obtaining
B15: the insurance policies and securities
B17: To be paid on signal of the format contract B
B18: agreement
B20: 60% on completion of temporary building or C
B21: structures. 30% in equl installments over the
... B36: The Bidder is fully responsible for identiflying the limitataions, restrictions and difficulties imposed due to the locally of the site and its environs and should include in his prices for all contingencies that may arise as a result
A38: 1 | B38: Insurance and Securities
A40: =A38+0.01 -> 1.01 | B40: Allow sum for providing performance security | C40: A | D40: 1 | E40: Item | I40: N/A
A42: =A40+0.01 -> 1.02 | B42: Allow sum for providing advance payment security | C42: A | D42: 1 | E42: Item | I42: N/A
A44: =A42+0.01 -> 1.03 | B44: Allow Sum for insurance of Works, Machinery & Equipment, Plant, Materials, Third party persons & property and Eimployer's personal & property at site per the Contract | C44: A | D44: 1 | E44: Item | I44: N/A
B46: The minimim insurance.cover shall be:
B48: The minimum cover for insurance of the Works and Plant and Materials is 110% of the Initial Controct Price.
B50: The maximum deductible for insurance uf the Works and of Plant and Materials is 5% of the Initial Contract Price.
B52: The minimunm cover for loss or damage to Equipment is the replacement cost
B54: The maximum deductible for insurance of Equipment is 5% of minimun cover for equipment.
B56: The minimum cover for insurance of (orher propert other than the site) is Ra. 2Million per event and totul limit of indemnity shall be Rs 10 Million
B58: The mininum cover for insurance of personal injury or death.
B60: For third party and employees of the Employer and other persons engaged by the Employer in the Works is Rs.5,000,000/- per event
B62: Injury or damage to persons including employer and consultant and their employees and other consultants employed by the employer shall be covered by the personnel accident insurance cover for Rs 2 million per event effective from the date of commencement of contract until end of the defects liability period (total number of persons insured are not exceeding 10 nrs)
A64: =A44+0.01 -> 1.04 | B64: Allow Sum for insurance against accidents and injury to Contractor's personnel as per the Contract. | C64: A | D64: 1 | E64: Item | I64: N/A
B66: The iminimum cover for personal injury or death
B67: For the Contractor's workmen is Rs. 500,000/= per event
B68: Contractor s employees other than workmen is Rs.5.000.000/= per event
A70: 2 | B70: Engineer's Facilities
A72: =A70+0.01 -> 2.01 | B72: Allow lump sum for constructing, maintaining, dismantling and removal on completion of the Works, a temporary air conditioned TFU for Engineer's office with toilet,elecricity facility in conformity with the plans provided for Engineer's requirements, including furniture and fittings, furnishing, sanitary facilities necessary and other facilities. | C72: C | D72: 1 | E72: Item
B73: The follwing facilities shall be provided
B74: (1) 2-0"x4-0" Table with drawers for Engineer's representative with medium back chair
B75: (2) Chair for Engineer's Representative( two nr of low back chair)
B76: (3) lockable Cupboard for storage of drawings, documents and stationery
B77: (4) Pedestal fan
B78: (5) 30 Gb monthly data package( WIFI Router),contractor should paid data package monthly
B79: (6) 1200mm X 1200mm white board
B80: (7) I5 computer with printer
B81: (8) Adequate Size Meeting table and 6 nr of chair
A83: 2 | B83: Contractor's Facilities
A85: =A83+0.01 -> 2.01 | B85: Allow lump sum for constructing, maintaining, dismantling and removal on completion of the Works, a temporary office,stores and workshop with toilet,elecricity facility in conformity with the plans provided for Engineer's requirements, including furniture and fittings, furnishing, sanitary facilities necessary and other facilities. | C85: C | D85: 1 | E85: Item | F85: 190000 | G85: =+$J$1 -> 0.8 | H85: =ROUNDUP(F85/G85,-1) -> 237500 | I85: =D85*H85 -> 237500
A87: =#REF!+0.01 -> #REF! | B87: Allow lump sum for providing Accommodation, including all sanitory facility for Contractor's staff and workmen | C87: C | D87: 1 | E87: Item
A88: 3 | B88: Construction Managment and Supervision
A90: =A88+0.01 -> 3.01 | B90: Allow sum for employing suitable qualified and axperienced technical personnal on full time for construction maragement services at the site. | C90: E | D90: 1 | E90: Item
B91: Site Engineer( Full Time)
B92: Project Manager ( C.Eng with 10 year experience- part time)
B93: MEP Engineer( Building Service Eng with 10 year experience- part time)
B94: ( Site Engineer BSc.Eng with 5 years or NDT-Civil with 10 years experience- Full Time )
B95: (CV to be submitted with the bid)
A97: 3 | B97: Setting Out
A99: =A97+0.01 -> 3.01 | B99: Allow sum for emplyoing a licensed land surveyor to define the building site work etc., check levels and carry out such other surveys as may be necessary to establish accrately the placing of forms and pouring of concrete and all other setting out in both vertical and horizontal plane. | C99: G | D99: 1 | E99: Item | F99: 65000 | G99: =+$J$1 -> 0.8 | H99: =ROUNDUP(F99/G99,-1) -> 81250 | I99: =D99*H99 -> 81250
A101: 4 | B101: Quality, Standards and Progress
A103: =A101+0.01 -> 4.01 | B103: Allow lump sum for provision of progress reports including photograplic records and other schedules included in the CIDA publication Guidelines for Effective Construction Managenent. (CIDA/CM/01), relevant administration as directed by the Engineer. | C103: E | D103: 1 | E103: Item
A105: =A103+0.01 -> 4.02 | B105: Allow lunp sum for all cost in connection with preparing samples for testing, making arrangements for testing of Materials, Goods etc, submission of shop drawings as stipalated in the specification, obtaining test reports and submitting the same to the Engineer, | C105: F | D105: 1 | E105: Item
A107: =A101+0.01 -> 4.01 | B107: Allow lunp sum for preparing As built drawings of following services. All drawings shall be produced in triplicate to a scale (3 set of binded hard copy) and one electronic copy in Auto CAD format | C107: E | D107: 1 | E107: Item | I107: N/A
B108: 1.Architectural
B109: 2.Electricle
B110: 3.Water Supply,Sewarage and Waste Water lines
A112: 5 | B112: Health Safety and Environment
A114: =A112+0.01 -> 5.01 | B114: Allow lump sum for providing all necessary safety measures barigated etc... to workmen at site safety regulations and as directed by the Engineer | C114: E | D114: 1 | E114: Item
A116: =A114+0.01 -> 5.02 | B116: Allow lump sum for maintaining the site in a clean and orderly manner at all times and during the entire contract period. | C116: E | D116: 1 | E116: Item | I116: N/A
A118: =A116+0.01 -> 5.03 | B118: Allow lump sum for demobilization, removal of all rubbish & debris and clearing up site on completion, leaving all-in good order and handing over. | C118: G | D118: 1 | E118: Item | I118: N/A
A119: =A118+0.01 -> 5.04 | B119: Allow sum for removeing of surface water and ground water | C119: G | D119: 1 | E119: Item
A121: =A118+0.01 -> 5.04 | B121: The Contractor shall protect and maintain the approaches to the site, clear of mud and debris including providing a water pressure gun with all connected services. The contractor also shall make good any damage attributable to the works at his own expense or pay all costs, charges in connection therewith. | C121: E | D121: 1 | E121: Item
A123: 6 | B123: Security and Protection
A125: =A123+0.01 -> 6.01 | B125: Allow lump sum for providing and maintaining necessary hoarding and gates for safeguarding the Works, Materials and Plant, as directed by the Engineer. Corrugated sheet/Zn allow wall sheet GI gramed hoarding height 8ft and to necessary perimetor area | C125: E | D125: 1 | E125: Item | O125: =#REF!*10.76 -> #REF! | P125: =O125*250 -> #REF!
A127: 6 | B127: Services and Facilities
A129: =A127+0.01 -> 6.01 | B129: Allow lump sum for supply of water for the Works and paying all charges and other expenses in connection with the supply from water mains or any other alternative method of water supply, storage and reticulation | C129: E | D129: 1 | E129: Item | I129: Provide by Client
A131: =A129+0.01 -> 6.02 | B131: Allow lump sum for supplying temporary electricity for the works including connection, distribution system for the Works, internal arrangements and all payments to be authorities for consumption | C131: E | D131: 1 | E131: Item | I131: Provide by Client
A133: =A131+0.01 -> 6.03 | B133: Allow lump sum for erecting and maintaining scaffolding and/ self climbing platforms around the construction building wall area. Such scaffolding etc. shall be removed on completion and all Works disturbed shall be made good.rate to include to safety dust coverd green net for total building perimeter building height area | C133: F | D133: 1 | E133: Item | I133: Provide by Client
B135: A - PRELIMINARIES CARRIED TO GRAND SUMMARY | I135: =SUM(I26:I134) -> 318750

Sheet summary
A2: COLLECTION BILL NO.02 - MAIN BUILDING
A4: Nos | B4: Description | C4: Amount
A7: B | B7: =exca!B2 -> B - EXCAVATION & EARTH WORK | C7: =+exca!H57 -> 733800 | D7: 0.75
A8: F | B8: =masnry!B2 -> F - MASONRY WORKS | C8: =+masnry!H44 -> 5928300 | D8: 0.75
A9: G | B9: =flooring!B2 -> J - FLOORING WORK | C9: =+flooring!H11 -> 201660 | D9: 0.75
A10: H | B10: =waterprof!B2 -> E - WATER PROOFING WORK | C10: =+waterprof!H50 -> 947610 | D10: 0.8
A11: J | B11: =plastering!B2 -> K - PLASTERING WORK | C11: =+plastering!H62 -> 4495240 | D11: 0.75
A12: K | B12: =tile!B2 -> L - TILING WORK | C12: =+tile!H278 -> 8817580 | D12: 0.85
A13: L | B13: =paint!B2 -> M - COLOUR WASHING, PAINTING & POLISHING | C13: =+paint!H25 -> 2418543.2 | D13: 0.75
A14: Q | B14: =plumbing!B2 -> S - PLUMBING AND DRAINAGE WORK | C14: =+plumbing!H235 -> 2545670 | D14: 0.85
A15: S | B15: =electicle!B2 -> V - ELECTRICAL INSTALLATION. | C15: =+'electicle '!H302 -> 6307830 | D15: 0.8
A16: T | B16: =metal!B2 -> W - METAL WORK | C16: =+metal!H160 -> 10787630 | D16: 0.9
A17: U | B17: =roof!B2 -> Q - ROOFING AND CEILING | C17: =+roof!H4 -> 3966280 | D17: 0.85
B19: TOTAL CARRIED TO GRAND SUMMARY | C19: =SUM(C6:C17) -> 47150143
B36: bank washroom partition extend to wall | C36: 690 | E36: =C6+C7+#REF!+C8+C9+C10+C11+C12+C13+#REF!+C14+C15+C16+#REF!+#REF! -> #REF!
B37: hall dooe change to glazed to timber | C37: 1360
B38: second floor slab canteliver | C38: 1360
B39: first floor shops to civerd material? 20/9 | C39: 650
C42: =SUM(C36:C41) -> 4060
C45: =C19/C42 -> 11613.336

Sheet exca
A1: Nos | B1: Description | C1: Qty | D1: Unit | E1: Cost | F1: OH & P % | G1: Rate | H1: Amount | I1: =+summary!D7 -> 0.75
B2: B - EXCAVATION & EARTH WORK
B3: SITE PREPERATION
B4: Note :
B5: For the full description of materials
B6: and workmanship refer "Specification
B7: of works", "Pricing Preambles" and
B8: "Drawings".
A10: B 01 | B10: Clearing site vegetation manually including removal of bushes, shurb removing rubbish. | C10: 300 | D10: Sqm | E10: 1000 | F10: =+I1 -> 0.75 | G10: =ROUNDUP(E10/F10,-1) -> 1340 | H10: =C10*G10 -> 402000 | J10: =+C10*10.76 -> 3228
A12: B 02 | B12: Removing top soil including mud, machinery to a nessasary depth and removing all debris away from site, location decided by client withing 3 km | C12: 300 | D12: Sqm | E12: =+[21]RBD!$F$95 -> 278 | F12: =+$I$1 -> 0.75 | G12: =ROUNDUP(E12/F12,-1) -> 380 | H12: =C12*G12 -> 114000
B14: EXCAVATION
B16: Note:
B17: All excavations are measured net. No allowance made for working space.
B19: Excavations as follows in any materials met with except in rock requiring blasting.
B21: Excavation for foundation commencing from formed ground level.
A22: B 03 | B22: Excavation for column, wall, staircase foundations in any material (except rock requiring blasting) up to depth (as per the drawings), part return fill in and ram and surplus depositted within site as directed. | D22: m3
B24: Earth Work Supports
A25: B 04 | B25: Temporary earth work supports, in open planking in trenches total depth up todepth (as per the drawings) | D25: Sqm
B27: Filling & Compaction
B28: Note:-
B29: Approved earth shall mean filling materials that comply to the following :
A30: ( a ) | B30: The earth shall be free of vegetation, roots, boulders, easily decomposable materials, chemicals, industrial waste, plastic etc.
A31: ( b ) | B31: The maximum size of particle shall not exceed 75mm.
A32: ( c ) | B32: The earth shall be well graded and the silt and clay (fines) content shall not be more than 25%
A33: ( d ) | B33: The Standerd proctor density shall be grater than 1.70g/cm3
B35: Dry Earth Filling
A36: B 05 | B36: Supplying and compaction of Approved earth,compaction of earth including watering and compaction in 225mm thick layers with proctor density, using machine rammer/roller vibrator, rate to include to compaction maching charges and other nessasary related work | D36: m3
B38: Qurry Dust Filling
B39: Supplying and compaction of qurry dust compaction of earth including watering and compaction in 225mm thick layers with proctor density, using machine rammer/roller vibrator, rate to include to compaction maching charges and other nessasary related work | D39: m3
B45: Back Filling
A46: B 06 | B46: Supplying and compaction of Approved earth,compaction of earth including watering and compaction in 225mm thick layers with proctor density, using machine rammer or roller vibrator, rate to include to compaction maching charges and other nessasary related work | D46: m3
B48: Antitermite -Tretement
A49: B 07 | B49: Antitermite-treatement for the new construction with applying Biflexthrine 10Tc (Biflex ) or approved equivelant , Dialuted chemicals 1:200 ratio with water after supplying the sealed bottle with lables to the site and should be followed the manufacture standards of application including horizontal & vertical barriers. It should be 10 years warranty on application. | C49: 180 | D49: Sqm | E49: =+[21]RBD!$F$146 -> 904 | F49: =+$I$1 -> 0.75 | G49: =ROUNDUP(E49/F49,-1) -> 1210 | H49: =C49*G49 -> 217800
B51: Transport
A52: B 09 | B52: Transport of any Material / Debris by any means in bulk including loading | D52: Item
B54: Water Disposal
A55: B 10 | B55: Disposal of Ground Water and Surface Water | D55: Item
B57: EXCAVATION & EARTH WORK CARRIED TO COLLECTION | H57: =SUM(H9:H56) -> 733800
D89: =600/10.76 -> 55.762082 | I89: =1000/50 -> 20
D90: =D89*0.05 -> 2.7881041 | I90: =50/1000 -> 0.05 | K90: =D90/2.83 -> 0.98519579
C93: cemnt | D93: =13*K90 -> 12.807545
C94: sand | D94: =0.53*K90 -> 0.52215377
C95: metal | D95: =0.92*K90 -> 0.90638013

Sheet masnry
A1: Nos | B1: Description | C1: Qty | D1: Unit | E1: Cost | F1: OH & P% | G1: Rate ( Rs.) | H1: Amount | I1: =+summary!D8 -> 0.75
B2: F - MASONRY WORKS | J2: =2890/338 -> 8.5502959 | P2: =#REF!*100 -> #REF! | Q2: =P2/9.29 -> #REF! | R2: =Q2*0.225 -> #REF! | S2: =R2/2.83 -> #REF! | T2: =S2*N3 -> #REF! | U2: =T2/#REF! -> #REF!
A3: 1 | B3: BRICK MASONRY | N3: 81297 | O3: =N3/12*9 -> 60972.75
B4: Note : | N4: 85362 | O4: =N4/12*9 -> 64021.5 | S4: =#REF!*2.83 -> #REF! | T4: =S4/300*225 -> #REF!
B5: For the full description of materials | N5: 86988 | O5: =N5/12*9 -> 65241 | U5: =#REF!/T4 -> #REF! | W5: 3099 | X5: =W5*#REF! -> #REF!
B6: and workmanship refer "Specification | N6: =N7/10.76 -> #REF! | O6: =#REF!/0.3*0.225 -> #REF! | P6: =O6/9.29 -> #REF! | R6: =#REF!*100 -> #REF!
B7: of works", "Pricing Preambles" and | N7: ='m shet rolf'!#REF! -> #REF! | O7: =#REF!*0.225 -> #REF! | R7: =R6/35.29 -> #REF! | S7: =#REF!*2.83 -> #REF!
B8: "Drawings". | N8: =N7*P6 -> #REF! | U8: =9/12 -> 0.75
B10: Vertical solid walls, 225mm thick. | P10: 27881
A11: =A3+0.01 -> 1.01 | B11: Brick work in cement and sand 1:5 in super Structure in ground floor. ( 9" thick brick work) | C11: ='m shet rolf'!N28 -> 244 | D11: Sqm | E11: =+'Rate Breakdowns'!G592 -> 5802.9333 | F11: =+I1 -> 0.75 | G11: =ROUNDUP(E11/F11,-1) -> 7740 | H11: =C11*G11 -> 1888560 | N11: =G11/4*9 -> 17415 | P11: =P10/4.5*9 -> 55762 | Q11: =P11-#REF! -> #REF! | S11: =+C11*10.76/100 -> 26.2544 | T11: 9.779764 | V11: =G13-G11 -> 40 | W11: 387.4
N12: =N11/9.29 -> 1874.5963 | Q12: =#REF!-#REF! -> #REF! | Y12: =27881 -> 27881
A13: =A11+0.01 -> 1.02 | B13: Brick work in cement and sand 1:5 in First floor level.(9" thick brick work) | C13: ='m shet rolf'!N50 -> 182 | D13: Sqm | E13: =+E11*1.005 -> 5831.9479 | F13: =+$I$1 -> 0.75 | G13: =ROUNDUP(E13/F13,-1) -> 7780 | H13: =C13*G13 -> 1415960 | O13: =G11*1.12 -> 8668.8 | Q13: =G11+Q12 -> #REF! | S13: =+C13*10.76/100 -> 19.5832 | T13: 13.927744 | V13: =G15-G13 -> 40 | W13: 581.1 | Y13: =Y12/4.5*9 -> 55762
Y14: =#REF!/12*9 -> #REF!
A15: =A13+0.01 -> 1.03 | B15: Brick work in cement and sand 1:5 in Second floor level.(9" thick brick work) | C15: ='m shet rolf'!N73 -> 261 | D15: Sqm | E15: =+E11*1.01 -> 5860.9626 | F15: =+$I$1 -> 0.75 | G15: =ROUNDUP(E15/F15,-1) -> 7820 | H15: =C15*G15 -> 2041020 | P15: =#REF!*100 -> #REF! | S15: =+C15*10.76/100 -> 28.0836 | T15: 14.462516 | V15: =#REF!-G15 -> #REF! | W15: 968.5 | Y15: =Y14*#REF! -> #REF!
A17: =A15+0.01 -> 1.04 | B17: Brick work in cement and sand 1:8 in Water tank floor level.(9" thick brick work) | C17: ='m shet rolf'!N75 -> 60 | D17: Sqm | E17: =+E11*1.015 -> 5889.9773 | F17: =+$I$1 -> 0.75 | G17: =ROUNDUP(E17/F17,-1) -> 7860 | H17: =C17*G17 -> 471600
B19: Vertical solid walls, 112.5mm thick.
A21: =A17+0.01 -> 1.05 | B21: Brick work in cement and sand 1:5 in super Structure in ground floor. ( 4 1/2"" thick brick work) | D21: Sqm | N21: =G21/4*9 -> 0 | P21: =P20/4.5*9 -> 0 | Q21: =P21-#REF! -> #REF! | S21: =+C21*10.76/100 -> 0 | T21: 9.779764 | V21: =G23-G21 -> 3960 | W21: 387.4
N22: =N21/9.29 -> 0 | Q22: =#REF!-#REF! -> #REF! | Y22: =27881 -> 27881
A23: =A21+0.01 -> 1.06 | B23: Brick work in cement and sand 1:5 in First floor level( 4 1/2"" thick brick work) | C23: ='m shet rolf'!N81 -> 14 | D23: Sqm | E23: =+'Rate Breakdowns'!G645 -> 2963.6175 | F23: =+$I$1 -> 0.75 | G23: =ROUNDUP(E23/F23,-1) -> 3960 | H23: =C23*G23 -> 55440 | O23: =G21*1.12 -> 0 | Q23: =G21+Q22 -> #REF! | S23: =+C23*10.76/100 -> 1.5064 | T23: 13.927744 | V23: =G25-G23 -> 20 | W23: 581.1 | Y23: =Y22/4.5*9 -> 55762
Y24: =#REF!/12*9 -> #REF!
A25: =A23+0.01 -> 1.07 | B25: Brick work in cement and sand 1:5 in Second floor level.(( 4 1/2"" thick brick work) | C25: =C23 -> 14 | D25: Sqm | E25: =+E23*1.005 -> 2978.4356 | F25: =+$I$1 -> 0.75 | G25: =ROUNDUP(E25/F25,-1) -> 3980 | H25: =C25*G25 -> 55720 | P25: =#REF!*100 -> #REF! | S25: =+C25*10.76/100 -> 1.5064 | T25: 14.462516 | V25: =#REF!-G25 -> #REF! | W25: 968.5 | Y25: =Y24*#REF! -> #REF!
A27: =A25+0.01 -> 1.08 | B27: Brick work in cement and sand 1:8 in Roof floor level.( 4 1/2"" thick brick work) | D27: Sqm
A29: G1.1 | B29: 6" thick cement sand Cellular block wall (blocks confirming to S.L.S. 855 and subject to the approval of sample blocks) in cement and sand mortar 1:5 in ground floor. | D29: Sqm
A31: G1.2 | B31: 6" thick cement sand Cellular block wall (blocks confirming to S.L.S. 855 and subject to the approval of sample blocks) in cement and sand mortar 1:5 in first floor. | D31: Sqm
A33: G1.3 | B33: 4" thick cement sand Cellular block wall (blocks confirming to S.L.S. 855 and subject to the approval of sample blocks) in cement and sand mortar 1:5 in Second FLoor. | D33: Sqm
A35: G1.4 | B35: 4" thick cement sand Cellular block wall (blocks confirming to S.L.S. 855 and subject to the approval of sample blocks) in cement and sand mortar 1:5 in roof FLoor. | D35: Sqm
A36: G1.5 | B36: 4" thick cement sand Cellular block wall (blocks confirming to S.L.S. 855 and subject to the approval of sample blocks) in cement and sand mortar 1:5 in Roof FLoor. | D36: Sqm
A38: G1.5 | B38: 4" thick cement sand Cellular block wall (blocks confirming to S.L.S. 855 and subject to the approval of sample blocks) in cement and sand mortar 1:5 in Fourth FLoor. | D38: Sqm
A40: G1.5 | B40: 4" thick cement sand Cellular block wall (blocks confirming to S.L.S. 855 and subject to the approval of sample blocks) in cement and sand mortar 1:5 in Roof FLoor. | D40: Sqm
B41: H - RUBBLE MASONRY | P41: =#REF!*100 -> #REF!
A42: H 01 | B42: Random rubble (6"-9") masonry in cement mortar 1:5 in wall foundation. | D42: m3 | N42: =27+27+12+12 -> 78 | O42: =N42*1.05 -> 81.9 | P42: =O42/9.29 -> 8.8159311 | S42: =14.36/2.83 -> 5.0742049
B44: MASONRY WORKS CARRIED TO COLLECTION | H44: =SUM(H11:H43) -> 5928300

Sheet flooring
A1: Nos | B1: Description | C1: Qty | D1: Unit | E1: Cost | F1: OH & P% | G1: Rate ( Rs.) | H1: Amount | I1: =+summary!D9 -> 0.75
B2: J - FLOORING WORK
A4: J 01 | B4: 3/4" thick D.P.C. in cement sand 1:3 finished with 2 coats of D.P.C. tar and blinded with sand. | C4: 50 | D4: Sqm | E4: =+'Rate Breakdowns'!G854 -> 1403.0281 | F4: =+$I$1 -> 0.75 | G4: =ROUNDUP(E4/F4,-1) -> 1880 | H4: =C4*G4 -> 94000
A6: J 02 | B6: Gauge 750 polythene damp proof membrane with 6" laps laid under floors. | C6: ='m shet rolf'!N83 -> 222 | D6: Sqm | E6: =+'Rate Breakdowns'!G112 -> 255.65124 | F6: =+$I$1 -> 0.75 | G6: =ROUNDUP(E6/F6,-1) -> 350 | H6: =C6*G6 -> 77700
A8: J 03 | B8: Rendering 1/2" thick in cement sand 1:3 finished smooth with cement slurry without colour pigment and expansion joints filled with construction expansion joint sealent including the cost for cleaning the joints prior application of construction expansion joint sealent by M/s Bitumix or approved equivalent.
B9: Water tank slab/Roof Slab | C9: ='m shet rolf'!N86 -> 14 | D9: Sqm | E9: 1600 | F9: =+$I$1 -> 0.75 | G9: =ROUNDUP(E9/F9,-1) -> 2140 | H9: =C9*G9 -> 29960
B11: FLOORING WORK CARRIED TO COLLECTION | H11: =SUM(H3:H10) -> 201660
C15: =5*8 -> 40
C16: =C15/10.76 -> 3.7174721

Sheet waterprof
A1: Nos | B1: Description | C1: Qty | D1: Unit | E1: Cost | F1: OH & P% | G1: Rate ( Rs.) | H1: Amount | I1: =+summary!D10 -> 0.8
B2: E - WATER PROOFING WORK
B4: The rates for Items are strictly applicable, subject to the fulfillment of the following conditions.
B6: The water proofing material shall conform to relevant British, Euro or ASTM specifications
B8: Recommended Distributors/Agents who are marketing water proofing material/product are 1. M/s Finco Ltd. 2. M/s HE Engineering 3. M/s Ranki International 4. M/s Solico Engineering 5. M/s Sika Lanka
B9: The contractor shall submmit;
B11: (a) A written certificate stating that all material and workmanship are in conformity with the specifications and the manufactures requirements.
B13: (b) The contractor shall jointly with manufacture/supplier of the waterproofing materials shall furnish a warranty to the Employer valid for a period of 10 years after handing over of the work against dampness and/or moisture penetration through treated surfaces due to defective materials and/or workmanship
B15: payments for items shall be made on receipt of above certificate
B17: The rates for items include the cost of surface preparation, ande the cost of protective masonry screed. Appropriate B.S.R. item rate shall be used for protective layer. The approving authority for products shall be the Engineer.
A29: E. 01 | B29: Internal Wet Areas without Exposure to Sunlight Sq.ft. (Cementitious water proofing using Barralastic or approved equivalnt)
B31: Application of cementitious water proofing using Barralastic or approved equivalnt for internal wet areas such as toilet floors and walls (Walls Up to 1.50m) where the surfaces are not directly exposed to sunlight and weathering. Rate shall include to cleaning the substrate and 1:3 cement sand bedding and all other work as per manufacturer's specifications on application and shall include ponding test for a 300mm water height kept for a period of 48 hours for horizontal surfaces.
A32: E. 01.1 | B32: Ground Floor | C32: ='m shet rolf'!N94 -> 19 | D32: S.qm | E32: =+'Rate Breakdowns'!G539 -> 3634.1032 | F32: =+I1 -> 0.8 | G32: =ROUNDUP(E32/F32,-1) -> 4550 | H32: =C32*G32 -> 86450
A33: E. 01.2 | B33: First Floor | C33: ='m shet rolf'!N116 -> 54 | D33: S.qm | E33: =+E32*1.005 -> 3652.2737 | F33: =+$I$1 -> 0.8 | G33: =ROUNDUP(E33/F33,-1) -> 4570 | H33: =C33*G33 -> 246780
A34: E. 01.3 | B34: Second Floor | C34: ='m shet rolf'!N139 -> 36 | D34: S.qm | E34: =+E32*1.01 -> 3670.4443 | F34: =+$I$1 -> 0.8 | G34: =ROUNDUP(E34/F34,-1) -> 4590 | H34: =C34*G34 -> 165240
A35: E. 01.4 | B35: Roof Floor | D35: S.qm
A37: E. 02 | B37: Areas exposed to sunlight (Balconies, Sun-Shades Concrete Gutters etc) (Elastomeric water proofing using thoroseal or approved equivalent.)
B39: Application of two coats of elastomeric water proofing material using thoroseal or approved equivalnt capable to withstand temperature variation for wet areas exposed to sunlight and weathering. ( balconies, sun-shades, concrete gutters etc.) rate shall include for cleaning the substrate and all other work as per manufacturer's specifications on application and shall include ponding test for a 300mm water height kept for a period of 48 hours for horizontal surfaces and cement sand finished with neat finish smooth rendering
A40: E. 02.1 | B40: Ground Floor | D40: S.qm
A41: E. 02.2 | B41: First Floor | C41: ='m shet rolf'!N157 -> 55 | D41: S.qm | E41: =+E33 -> 3652.2737 | F41: =+$I$1 -> 0.8 | G41: =ROUNDUP(E41/F41,-1) -> 4570 | H41: =C41*G41 -> 251350
A42: E. 02.3 | B42: Second Floor | C42: ='m shet rolf'!N162 -> 29 | D42: S.qm | E42: =+E34 -> 3670.4443 | F42: =+$I$1 -> 0.8 | G42: =ROUNDUP(E42/F42,-1) -> 4590 | H42: =C42*G42 -> 133110
A43: E. 02.4 | B43: Roof Floor | C43: =flooring!C9 -> 14 | D43: S.qm | E43: =+E32*1.015 -> 3688.6148 | F43: =+$I$1 -> 0.8 | G43: =ROUNDUP(E43/F43,-1) -> 4620 | H43: =C43*G43 -> 64680
A44: E. 02.5 | B44: Water Tank Floor | D44: S.qm
A45: E 03 | B45: laying of Topseal 3mm thick,Torch-on membrane or any othere quivalent product marketed /installed by a specialist contractor registered at ICTAD under waterproofing category including 1:3 cement,sand protective screed laid to slope.Rate shall include the formation of edges,torch welding and fixing metal stripon vertical walls at termination edges.
A46: E.03.01 | B46: Fourth Floor | D46: S.qm
A47: E.03.02 | B47: Roof Slab | D47: S.qm
A48: E.03.03 | B48: Water Tank/Lift Room Slab | D48: S.qm
B50: WATER PROOFING WORK CARRIED TO COLLECTION | H50: =SUM(H32:H49) -> 947610
H56: =#REF!+H41+H46 -> #REF!

Sheet plastering
A1: Nos | B1: Description | C1: Qty | D1: Unit | E1: Cost | F1: OH & P% | G1: Rate ( Rs.) | H1: Amount | I1: =+summary!D11 -> 0.75
B2: K - PLASTERING WORK
B3: Note:
B4: 1. The rate for plastering items includes the cost of "Febmix"as a workability enhancer.
B6: 2. For coarse textured plaster ( identified as "semi-rough") all the sand should pass through 4.0mm sieve.
P7: =O7*0.6 -> 0 | Q7: =P7*10.76 -> 0
B8: External Plaster | P8: =P7/9.29 -> 0
A9: K 01 | B9: 5/8" thick plastering to plinth wall in cement sand 1:3 including finishing with cement slurry floating. Rate includes cost of "Febmix" as a workability enhancer. | C9: 52 | D9: S.qm | E9: =+'Rate Breakdowns'!G703 -> 1874.5358 | F9: =+$I$1 -> 0.75 | G9: =ROUNDUP(E9/F9,-1) -> 2500 | H9: =C9*G9 -> 130000
A11: K 02 | B11: Plastering 5/8" thick to walls in cement and sand 1:5 finished semi-rough. Rate includes cost of "Febmix"as a workability enhancer.
A12: K2.1 | B12: In Ground floor | C12: ='m shet rolf'!N178 -> 133 | D12: S.qm | E12: =+'Rate Breakdowns'!G767 -> 1871.1632 | F12: =+$I$1 -> 0.75 | G12: =ROUNDUP(E12/F12,-1) -> 2500 | H12: =C12*G12 -> 332500
A13: K2.2 | B13: In First floor | C13: ='m shet rolf'!N204 -> 182 | D13: S.qm | E13: =+E12*1.01 -> 1889.8748 | F13: =+$I$1 -> 0.75 | G13: =ROUNDUP(E13/F13,-1) -> 2520 | H13: =C13*G13 -> 458640
A14: K2.3 | B14: In Second Floor | C14: ='m shet rolf'!N227 -> 152 | D14: S.qm | E14: =+E12*1.02 -> 1908.5865 | F14: =+$I$1 -> 0.75 | G14: =ROUNDUP(E14/F14,-1) -> 2550 | H14: =C14*G14 -> 387600
A15: K2.4 | B15: In Water Tank Floor | C15: ='m shet rolf'!N240 -> 52 | D15: S.qm | E15: =+E12*1.03 -> 1927.2981 | F15: =+$I$1 -> 0.75 | G15: =ROUNDUP(E15/F15,-1) -> 2570 | H15: =C15*G15 -> 133640
A17: K 03 | B17: External revels
A18: K 03.1 | B18: Plastering 5/8" thick to reveals in ground floor in cement and sand 1:5 finished semi-rough. Rate includes cost of "Febmix"as a workability enhancer. | C18: ='m shet rolf'!N191 -> 116 | D18: L.m | E18: 600 | F18: =+$I$1 -> 0.75 | G18: =ROUNDUP(E18/F18,-1) -> 800 | H18: =C18*G18 -> 92800
A20: K 03.2 | B20: Plastering 5/8" thick to reveals in first floor in cement and sand 1:5 finished semi-rough in first floor. Rate includes cost of "Febmix"as a workability enhancer. | C20: ='m shet rolf'!N215 -> 110 | D20: L.m | E20: 630 | F20: =+$I$1 -> 0.75 | G20: =ROUNDUP(E20/F20,-1) -> 840 | H20: =C20*G20 -> 92400
A22: K 03.3 | B22: Plastering 5/8" thick to reveals in second floor in cement and sand 1:5 finished semi-rough in Second floor. Rate includes cost of "Febmix"as a workability enhancer. | C22: ='m shet rolf'!N238 -> 115 | D22: L.m | E22: 660 | F22: =+$I$1 -> 0.75 | G22: =ROUNDUP(E22/F22,-1) -> 880 | H22: =C22*G22 -> 101200
A24: K 03.4 | B24: Plastering 5/8" thick to reveals in third floor in cement and sand 1:5 finished semi-rough in third floor. Rate includes cost of "Febmix"as a workability enhancer. | D24: L.m
A26: K 03.5 | B26: Plastering 5/8" thick to reveals in roof floor in cement and sand 1:5 finished semi-rough in Fourth floor. Rate includes cost of "Febmix"as a workability enhancer. | D26: L.m
B35: Internal Plaster
A36: K 04 | B36: Plastering 5/8" thick to walls,columns in cement and sand 1:5 finished smooth with two coats of skim coat.
A37: K4.1 | B37: In Ground floor | C37: ='m shet rolf'!N259 -> 258 | D37: S.qm | E37: =+'Rate Breakdowns'!G739 -> 1531.5225 | F37: =+$I$1 -> 0.75 | G37: =ROUNDUP(E37/F37,-1) -> 2050 | H37: =C37*G37 -> 528900
A38: K4.2 | B38: In First floor | C38: ='m shet rolf'!N289 -> 298 | D38: S.qm | E38: =+E37*1.005 -> 1539.1801 | F38: =+$I$1 -> 0.75 | G38: =ROUNDUP(E38/F38,-1) -> 2060 | H38: =C38*G38 -> 613880
A39: K4.3 | B39: in Second Floor | C39: ='m shet rolf'!N314 -> 333 | D39: S.qm | E39: =+E37*1.01 -> 1546.8377 | F39: =+$I$1 -> 0.75 | G39: =ROUNDUP(E39/F39,-1) -> 2070 | H39: =C39*G39 -> 689310
A40: K4.4 | B40: In Third Floor | D40: S.qm
A42: K 05 | B42: Internal Revels
A43: K 05.1 | B43: Plastering 5/8" thick to reveals in ground floor in cement andsand 1:5 finished smooth with two coats of skim coat in ground floor.Rate includes cost of "Febmix"as a workability enhancer. | C43: ='m shet rolf'!N276 -> 163 | D43: =D20 -> L.m | E43: 600 | F43: =+$I$1 -> 0.75 | G43: =ROUNDUP(E43/F43,-1) -> 800 | H43: =C43*G43 -> 130400
A45: K 05.2 | B45: Plastering 5/8" thick to reveals in first floor in cement and sand 1:5 finished smooth with two coats of skim coat in first floor. Rate includes cost of "Febmix"as a workability enhancer. | C45: ='m shet rolf'!N301 -> 169 | D45: =D43 -> L.m | E45: 600 | F45: =+$I$1 -> 0.75 | G45: =ROUNDUP(E45/F45,-1) -> 800 | H45: =C45*G45 -> 135200
A47: K 05.3 | B47: Plastering 5/8" thick to reveals in second floor in cement and sand 1:5 finished smooth with two coats of skim coat in Second floor. Rate includes cost of "Febmix"as a workability enhancer. | C47: ='m shet rolf'!N326 -> 188 | D47: =D45 -> L.m | E47: 600 | F47: =+$I$1 -> 0.75 | G47: =ROUNDUP(E47/F47,-1) -> 800 | H47: =C47*G47 -> 150400
A49: K 05.4 | B49: Plastering 5/8" thick to reveals in third floor in cement and sand 1:5 finished smooth with two coats of skim coat in Third floor. Rate includes cost of "Febmix"as a workability enhancer. | D49: =D47 -> L.m
A51: K 06 | B51: Applying two coats of skim coat ( Not exceeding 3 mm thick) to soffit of slab,beams sunshade & stair cases Inc. preparation surface.
A52: K6.1 | B52: In Ground floor | C52: ='m shet rolf'!N329+concrete!C224 -> 245 | D52: S.qm | E52: 830 | F52: =+$I$1 -> 0.75 | G52: =ROUNDUP(E52/F52,-1) -> 1110 | H52: =C52*G52 -> 271950
A53: K6.2 | B53: In First floor | C53: ='m shet rolf'!N331+concrete!C225 -> 208 | D53: S.qm | E53: 830 | F53: =+$I$1 -> 0.75 | G53: =ROUNDUP(E53/F53,-1) -> 1110 | H53: =C53*G53 -> 230880
A54: K6.3 | B54: in Water Tank level | C54: ='m shet rolf'!N333+concrete!C226 -> 14 | D54: S.qm | E54: 830 | F54: =+$I$1 -> 0.75 | G54: =ROUNDUP(E54/F54,-1) -> 1110 | H54: =C54*G54 -> 15540
A55: K6.4 | B55: Water Tank Slab | D55: S.qm
A57: K 07 | B57: Drip Edge
B58: Forming drip for sunshade edge cement & sand 1: 3 finished semi rough in ground floor. Rate includes cost of "Febmix"as a workability enhancer.
A59: K 07.01 | B59: In Ground floor | D59: =D45 -> L.m
A60: K 07.02 | B60: In First floor | D60: =D59 -> L.m
A61: K 07.03 | B61: in Second Floor | D61: =D47 -> L.m
B62: PLASTERING WORK CARRIED TO COLLECTION | H62: =SUM(H4:H61) -> 4495240
H71: =#REF!+#REF!+#REF!+#REF!+#REF! -> #REF!

Sheet tile
A1: Nos | B1: Description | C1: Qty | D1: Unit | E1: Cost | F1: OH & P% | G1: Rate ( Rs.) | H1: Amount | I1: =+summary!D12 -> 0.85
B2: L - TILING WORK
B3: Note:
B5: Ceramic Tiles should comply to SLS 1181:2019 "specification and shall comply to relevant abrasion resistant class.
B7: Copy of the first grade tile purchase bill should be produced at the time of payment.
B9: Tiles should comply with European standard specification CEN 177.
B11: Rates include the cost of 1:3 cement:sand motar leveling bed and adhesives
B13: For tile item Should be tile range manufractured by Lanka Floor, Wall Tile or approved equivalant.
A15: 1 | B15: Wall Tiling
B16: Glazed wall tiling of size 300mm x 600mm approved colour, supplying and fixing to walls on a 1:3 cement sand mortar layer, and pointed with tile grout to match the tile. (Prime Cost of tile Rs.600.00 per sqft)
A17: =A15+0.01 -> 1.01 | B17: Ground Floor | C17: ='m shet rolf'!N103 -> 32 | D17: Sqm | E17: =+'Rate Breakdowns'!G972 -> 9167.6904 | F17: =+$I$1 -> 0.85 | G17: =ROUNDUP(E17/F17,-1) -> 10790 | H17: =C17*G17 -> 345280
A18: =A17+0.01 -> 1.02 | B18: First Floor | C18: ='m shet rolf'!N128 -> 92 | D18: Sqm | E18: =+E17*1.01 -> 9259.3673 | F18: =+$I$1 -> 0.85 | G18: =ROUNDUP(E18/F18,-1) -> 10900 | H18: =C18*G18 -> 1002800
A19: =A18+0.01 -> 1.03 | B19: Second floor | C19: ='m shet rolf'!N151 -> 61 | D19: Sqm | E19: =+E17*1.02 -> 9351.0442 | F19: =+$I$1 -> 0.85 | G19: =ROUNDUP(E19/F19,-1) -> 11010 | H19: =C19*G19 -> 671610
A20: =A19+0.01 -> 1.04 | B20: Third floor | D20: Sqm | F20: =+$I$1 -> 0.85 | G20: =ROUNDUP(E20/F20,-1) -> 0 | H20: =C20*G20 -> 0
B22: Floor Tiling
B23: Note :
B24: Tile Shall be Homogenous, porcelain floor tiles of industrial grade floor tile range manufactured by Rocell , Lanka Wall Tile or approved equivalent.
B25: Rates include the cost of 1:3 cement:sand motar leveling bed and adhesives and matching grout
B27: Copy of the first grade tile purchase bill should be produced at the time of payment.
A29: 2 | B29: Ground Floor
A30: =A29+0.01 -> 2.01 | B30: Supplying of 300mm X300mm temples stone work with masory work
B31: In Ground floor | C31: ='m shet rolf'!N351 -> 33 | D31: Sqm | E31: 1450 | F31: =+$I$1 -> 0.85 | G31: =ROUNDUP(E31/F31,-1) -> 1710 | H31: =C31*G31 -> 56430 | P31: =E31-#REF! -> #REF!
A34: =A30+0.01 -> 2.02 | B34: FF2- Homogeneous Porcelain glazed non slip ceramic gloss floor tile 600mm x 1200mm non slip floor tie paving on 1:3 cement & sand bedding with suitable adhesives and pointed with tile grout to match the tile. (Prime Cost of tile Rs.600.00 per sqft)
B35: In Ground floor | C35: ='m shet rolf'!N340 -> 105 | D35: Sqm | E35: =+'Rate Breakdowns'!G972*1.03 -> 9442.7211 | F35: =+$I$1 -> 0.85 | G35: =ROUNDUP(E35/F35,-1) -> 11110 | H35: =C35*G35 -> 1166550
A37: =A34+0.01 -> 2.03 | B37: Supply and laying of 4" high skirting including tile grout to match the tile of tiling
B38: In Ground floor | C38: ='m shet rolf'!N342 -> 56 | D38: L.m | E38: =+'Rate Breakdowns'!G1029 -> 1560.6098 | F38: =+$I$1 -> 0.85 | G38: =ROUNDUP(E38/F38,-1) -> 1840 | H38: =C38*G38 -> 103040
A40: =A37+0.01 -> 2.04 | B40: FF3- Homogeneous Porcelain glazed floor tile 600mm x 600mm paving on 1:3 cement & sand bedding with suitable adhesives and pointed with tile grout to match the tile. (Prime Cost of tile Rs.600.00 per sqft) | P40: =4*2 -> 8 | Q40: =P40*P41 -> 1282
B41: In Ground Floor | C41: ='m shet rolf'!N345 -> 32 | D41: Sqm | E41: =+'Rate Breakdowns'!G972 -> 9167.6904 | F41: =+$I$1 -> 0.85 | G41: =ROUNDUP(E41/F41,-1) -> 10790 | H41: =C41*G41 -> 345280 | P41: =1282/8 -> 160.25
A43: =A40+0.01 -> 2.05 | B43: Supply and laying of 4" high skirting including tile grout to match the tile of tiling
B44: In Ground Floor area | C44: ='m shet rolf'!N349 -> 33 | D44: L.m | E44: =+'Rate Breakdowns'!G1029 -> 1560.6098 | F44: =+$I$1 -> 0.85 | G44: =ROUNDUP(E44/F44,-1) -> 1840 | H44: =C44*G44 -> 60720
A46: =A43+0.01 -> 2.06 | B46: FF4- Homogeneous semi rough floor tile 600mm x 1600mm non slip floor tie paving on 1:3 cement & sand bedding with suitable adhesives and pointed with tile grout to match the tile. (Prime Cost of tile Rs.600.00 per sqft)
B47: In Ground Floor | C47: ='m shet rolf'!N356 -> 12 | D47: Sqm | E47: =+'Rate Breakdowns'!G972*1.15 -> 10542.844 | F47: =+$I$1 -> 0.85 | G47: =ROUNDUP(E47/F47,-1) -> 12410 | H47: =C47*G47 -> 148920
A49: =A46+0.01 -> 2.07 | B49: Supply and laying of 4" high skirting including tile grout to match the tile of tiling
B50: In Ground Floor area | C50: ='m shet rolf'!N357 -> 14 | D50: L.m | E50: =+'Rate Breakdowns'!G1029 -> 1560.6098 | F50: =+$I$1 -> 0.85 | G50: =ROUNDUP(E50/F50,-1) -> 1840 | H50: =C50*G50 -> 25760
A52: =A49+0.01 -> 2.08 | B52: FF5- Homogeneous floor tile 600mm x 600mm paving on 1:3 cement & sand bedding with suitable adhesives and pointed with tile grout to match the tile. (Prime Cost of tile Rs.600.00 per sqft)
B53: In Ground Floor area | C53: ='m shet rolf'!N353 -> 6 | D53: Sqm | E53: =+E41 -> 9167.6904 | F53: =+$I$1 -> 0.85 | G53: =ROUNDUP(E53/F53,-1) -> 10790 | H53: =C53*G53 -> 64740
A55: =A52+0.01 -> 2.09 | B55: Supply and laying of 4" high skirting including tile grout to match the tile of tiling
B56: In Ground Floor area | C56: ='m shet rolf'!N354 -> 10 | D56: L.m | E56: =+E50 -> 1560.6098 | F56: =+$I$1 -> 0.85 | G56: =ROUNDUP(E56/F56,-1) -> 1840 | H56: =C56*G56 -> 18400
A58: =A55+0.01 -> 2.1 | B58: FF6- Homogeneous Porcelain semi - glazed/matt wash room floor tile 300mm x 600mm paving on 1:3 cement & sand bedding and pointed with tile grout to match the tile.(Prime Cost of tile Rs.600.00 per sqft)
B59: In Ground floor | C59: ='m shet rolf'!N97 -> 6 | D59: Sqm | E59: =+E41 -> 9167.6904 | F59: =+$I$1 -> 0.85 | G59: =ROUNDUP(E59/F59,-1) -> 10790 | H59: =C59*G59 -> 64740
A61: =A58+0.01 -> 2.11 | B61: Homogeneous matt floor tile 150mm x 900mm paving on 1:3 cement & sand bedding with suitable adhesives and pointed with tile grout to match the tile. (Prime Cost of tile Rs.600.00 per sqft) for staircase
B62: Ground Floor to First Floor | D62: Sqm
A65: =A61+0.01 -> 2.12 | B65: Supply and laying of 4" high skirting including tile grout to match the tile of tiling
B66: Ground Floor to First Floor | D66: Sqm
A67: =A58+0.01 -> 2.11 | B67: Supplying and applying of vinyl flooring, rate to include to necessasry leveling screed
B68: In Ground floor | D68: Sqm
A70: =A67+0.01 -> 2.12 | B70: Supply and laying of 4" high timber skirting including
B71: In Ground floor | D71: L.m
A72: =A58+0.01 -> 2.11 | B72: FF7- Homogeneous Porcelain rough floor tile 600mm x 600mm paving on 1:3 cement & sand bedding and pointed with tile grout to match the tile.(Prime Cost of tile Rs.600.00 per sqft)
B73: In Ground floor | C73: ='m shet rolf'!N361 -> 32 | D73: Sqm | E73: =+E53 -> 9167.6904 | F73: =+$I$1 -> 0.85 | G73: =ROUNDUP(E73/F73,-1) -> 10790 | H73: =C73*G73 -> 345280
A75: =A72+0.01 -> 2.12 | B75: Supply and laying of 4" high skirting including tile grout to match the tile of tiling
B76: In Ground Floor area | C76: ='m shet rolf'!N364 -> 27 | D76: L.m | E76: =+E56 -> 1560.6098 | F76: =+$I$1 -> 0.85 | G76: =ROUNDUP(E76/F76,-1) -> 1840 | H76: =C76*G76 -> 49680
A78: =A70+0.01 -> 2.13 | B78: Supplying and laying of Trated Timber Kumbuk flooring for pool deck area, rate to include to necessasry leveling screed and raised fllor if necessasry
B79: In Ground floor | D79: Sqm
A81: =A78+0.01 -> 2.14 | B81: Supply and laying of 4" high timber skirting including
B82: In Ground floor | D82: L.m
A84: =A70+0.01 -> 2.13 | B84: Supplying of turfing as per the design | D84: Sqm
A86: 3 | B86: First Floor
A88: =A86+0.01 -> 3.01 | B88: FF2- Homogeneous Porcelain glazed non slip ceramic gloss floor tile 600mm x 1200mm non slip floor tie paving on 1:3 cement & sand bedding with suitable adhesives and pointed with tile grout to match the tile. (Prime Cost of tile Rs.600.00 per sqft)
B89: In First floor | C89: ='m shet rolf'!N367 -> 36 | D89: Sqm | E89: =+E35*1.05 -> 9914.8572 | F89: =+$I$1 -> 0.85 | G89: =ROUNDUP(E89/F89,-1) -> 11670 | H89: =C89*G89 -> 420120
A91: =A88+0.01 -> 3.02 | B91: Supply and laying of 4" high skirting including tile grout to match the tile of tiling
B92: In First floor | C92: ='m shet rolf'!N368 -> 36 | D92: L.m | E92: =+E44*1.05 -> 1638.6402 | F92: =+$I$1 -> 0.85 | G92: =ROUNDUP(E92/F92,-1) -> 1930 | H92: =C92*G92 -> 69480
A94: =A91+0.01 -> 3.03 | B94: FF3- Homogeneous Porcelain glazed floor tile 600mm x 600mm paving on 1:3 cement & sand bedding with suitable adhesives and pointed with tile grout to match the tile. (Prime Cost of tile Rs.600.00 per sqft)
B95: In First floor | C95: ='m shet rolf'!N372 -> 44 | D95: Sqm | E95: =+E53*1.05 -> 9626.0749 | F95: =+$I$1 -> 0.85 | G95: =ROUNDUP(E95/F95,-1) -> 11330 | H95: =C95*G95 -> 498520
A96: =A94+0.01 -> 3.04 | B96: Supply and laying of 4" high skirting including tile grout to match the tile of tiling
B97: In First floor | C97: ='m shet rolf'!N375 -> 46 | D97: L.m | E97: =+E92 -> 1638.6402 | F97: =+$I$1 -> 0.85 | G97: =ROUNDUP(E97/F97,-1) -> 1930 | H97: =C97*G97 -> 88780
A99: =A96+0.01 -> 3.05 | B99: FF7- Homogeneous Porcelain rough floor tile 600mm x 600mm paving on 1:3 cement & sand bedding and pointed with tile grout to match the tile.(Prime Cost of tile Rs.600.00 per sqft)
B100: In First floor | C100: ='m shet rolf'!N379 -> 57 | D100: Sqm | E100: =+E73*1.05 -> 9626.0749 | F100: =+$I$1 -> 0.85 | G100: =ROUNDUP(E100/F100,-1) -> 11330 | H100: =C100*G100 -> 645810
A102: =A99+0.01 -> 3.06 | B102: Supply and laying of 4" high skirting including tile grout to match the tile of tiling
B103: In First floor | C103: ='m shet rolf'!N383 -> 43 | D103: L.m | E103: =+E97 -> 1638.6402 | F103: =+$I$1 -> 0.85 | G103: =ROUNDUP(E103/F103,-1) -> 1930 | H103: =C103*G103 -> 82990
A106: =A102+0.01 -> 3.07 | B106: FF8- Supplying and laying of 25mm thk teak timber flooring for master bedroom area, rate to include to necessasry leveling screed and finished as specified
B107: In First floor | C107: ='m shet rolf'!N385 -> 39 | D107: Sqm | E107: 12350 | F107: =+$I$1 -> 0.85 | G107: =ROUNDUP(E107/F107,-1) -> 14530 | H107: =C107*G107 -> 566670
B109: Supply and laying of 4" high timber skirting including
B110: In First Floor | C110: ='m shet rolf'!N386 -> 31 | D110: L.m | E110: =+E107/10 -> 1235 | F110: =+$I$1 -> 0.85 | G110: =ROUNDUP(E110/F110,-1) -> 1460 | H110: =C110*G110 -> 45260
A112: =A86+0.01 -> 3.01 | B112: Supplying and applying of Titanium flooring, rate to include to necessasry leveling screed
B113: In First Floor | D113: Sqm
A115: =A112+0.01 -> 3.02 | B115: Supply and laying of 4" high timber skirting including
B116: In First Floor | D116: L.m
A118: =A86+0.01 -> 3.01 | B118: Homogeneous matt floor tile 150mm x 900mm paving on 1:3 cement & sand bedding with suitable adhesives and pointed with tile grout to match the tile. (Prime Cost of tile Rs.600.00 per sqft) for staircase
B119: First Floor to Second Floor | D119: Sqm
A120: =A118+0.01 -> 3.02 | B120: Supply and laying of 4" high skirting including tile grout to match the tile of tiling
B121: First Floor to Second Floor | D121: L.m
A123: =A120+0.01 -> 3.03 | B123: Homogeneous matt floor tile 150mm x 1200mm paving on 1:3 cement & sand bedding with suitable adhesives and pointed with tile grout to match the tile. (Prime Cost of tile Rs.600.00 per sqft)
B124: In First Floor | D124: Sqm
A126: =A123+0.01 -> 3.04 | B126: Supply and laying of 4" high skirting including tile grout to match the tile of tiling
B127: In First Floor | D127: L.m
A130: =A126+0.01 -> 3.05 | B130: Homogeneous Porcelain glazed floor tile 900mm x 900mm paving on 1:3 cement & sand bedding with suitable adhesives and pointed with tile grout to match the tile. (Prime Cost of tile Rs.600.00 per sqft)
B131: In First Floor | D131: Sqm
A133: =A130+0.01 -> 3.06 | B133: Supply and laying of 4" high skirting including tile grout to match the tile of tiling
B134: In First Floor | D134: L.m
A136: =A133+0.01 -> 3.07 | B136: Supplying of gravel
B137: In First Floor | D137: Item
A138: =A136+0.01 -> 3.08 | B138: Supply and laying of 4" high skirting including tile grout to match the tile of tiling
B139: In First Floor | D139: L.m
A141: =A106+0.01 -> 3.08 | B141: FF6- Homogeneous Porcelain semi - glazed/matt wash room floor tile 300mm x 600mm paving on 1:3 cement & sand bedding and pointed with tile grout to match the tile.(Prime Cost of tile Rs.600.00 per sqft)
B142: In First Floor | C142: ='m shet rolf'!N120 -> 16 | D142: Sqm | E142: =+E59*1.05 -> 9626.0749 | F142: =+$I$1 -> 0.85 | G142: =ROUNDUP(E142/F142,-1) -> 11330 | H142: =C142*G142 -> 181280
B144: Homogeneous Porcelain glazed non slip floor tile 600mm x 600mm(Balcony or Terrace) paving on 1:3 cement & sand bedding with suitable adhesives and pointed with tile grout to match the tile. (Prime Cost of tile Rs.600.00 per sqft)
B145: In First Floor | D145: Sqm
B147: Supply and laying of 4" high skirting including tile grout to match the tile of tiling
B148: In First Floor | D148: L.m
...

Sheet paint
A1: Nos | B1: Description | C1: Qty | D1: Unit | E1: Cost | F1: OH & P% | G1: Rate ( Rs.) | H1: Amount | I1: =+summary!D13 -> 0.75
B2: M - COLOUR WASHING, PAINTING & POLISHING
B3: Method of application is accordiong to the manufacturer's method specifications
B5: Internal Emultion Paint
A6: M 01 | B6: Painting walls, columns, Revels with one coat of wall primer and two coats of emulsion paint including preparing surface.
A7: M1.1 | B7: In Ground floor | C7: =plastering!C37+(plastering!C43*0.225) -> 294.675 | D7: Sqm | E7: =+'Rate Breakdowns'!G1104 -> 649.65554 | F7: =+$I$1 -> 0.75 | G7: =ROUNDUP(E7/F7,-1) -> 870 | H7: =C7*G7 -> 256367.25 | N7: =+K7*10.76/100 -> 0 | O7: =+L7*10.76/100 -> 0 | P7: =+M7-O7 -> 0 | R7: =+N7+P7 -> 0 | T7: =SUM(M7:N7) -> 0
A8: M1.2 | B8: In First floor | C8: =plastering!C38+(plastering!C45*0.225) -> 336.025 | D8: Sqm | E8: =+E7*1.005 -> 652.90382 | F8: =+$I$1 -> 0.75 | G8: =ROUNDUP(E8/F8,-1) -> 880 | H8: =C8*G8 -> 295702 | N8: =+K8*10.76/100 -> 0 | O8: =+L8*10.76/100 -> 0 | P8: =+M8-O8 -> 0 | R8: =+N8+P8 -> 0 | T8: =SUM(M8:N8) -> 0
A9: M1.3 | B9: In Second Floor | C9: =plastering!C39+(plastering!C47*0.225) -> 375.3 | D9: Sqm | E9: =+E7*1.01 -> 656.1521 | F9: =+$I$1 -> 0.75 | G9: =ROUNDUP(E9/F9,-1) -> 880 | H9: =C9*G9 -> 330264
A10: M1.4 | B10: In Third Floor | D10: Sqm
A12: M 03 | B12: Painting soffit & Beams with one coat of wall primer and two coats of emulsion paint including preparing surface.
A13: M3.1 | B13: In Ground floor | C13: =plastering!C52 -> 245 | D13: Sqm | E13: =+'Rate Breakdowns'!G1129 -> 762.6803 | F13: =+$I$1 -> 0.75 | G13: =ROUNDUP(E13/F13,-1) -> 1020 | H13: =C13*G13 -> 249900
A14: M3.2 | B14: In First floor | C14: =plastering!C53 -> 208 | D14: Sqm | E14: =+E13*1.005 -> 766.4937 | F14: =+$I$1 -> 0.75 | G14: =ROUNDUP(E14/F14,-1) -> 1030 | H14: =C14*G14 -> 214240
A15: M3.3 | B15: in Water Tank level | C15: =plastering!C54 -> 14 | D15: Sqm | E15: =+E13*1.01 -> 770.3071 | F15: =+$I$1 -> 0.75 | G15: =ROUNDUP(E15/F15,-1) -> 1030 | H15: =C15*G15 -> 14420
A16: M3.4 | B16: In Third Floor | D16: Sqm
B18: Exterior Emultion Paint
A19: M 04 | B19: Painting walls,slab and revels with one coat of Exterior wall primer and two coats of weathershield weatherproof acrylic exterior emultion paint including preparing surface. including preparing surface for exterior application before applicatin of emulsion paint.
A20: M4.1 | B20: In Ground floor | C20: =plastering!C12+(plastering!C18*0.1) -> 144.6 | D20: Sqm | E20: =+'Rate Breakdowns'!G1155 -> 1419.591 | F20: =+$I$1 -> 0.75 | G20: =ROUNDUP(E20/F20,-1) -> 1900 | H20: =C20*G20 -> 274740
A21: M4.2 | B21: In First floor | C21: =plastering!C13+(plastering!C20*0.1) -> 193 | D21: Sqm | E21: =+E20*1.005 -> 1426.6889 | F21: =+$I$1 -> 0.75 | G21: =ROUNDUP(E21/F21,-1) -> 1910 | H21: =C21*G21 -> 368630
A22: M4.3 | B22: In Second Floor | C22: =plastering!C14+(plastering!C22*0.1) -> 163.5 | D22: Sqm | E22: =+E20*1.01 -> 1433.7869 | F22: =+$I$1 -> 0.75 | G22: =ROUNDUP(E22/F22,-1) -> 1920 | H22: =C22*G22 -> 313920
A23: M4.4 | B23: in Water Tank level | C23: =plastering!C15 -> 52 | D23: Sqm | E23: =+E20*1.015 -> 1440.8848 | F23: =+$I$1 -> 0.75 | G23: =ROUNDUP(E23/F23,-1) -> 1930 | H23: =C23*G23 -> 100360
B25: COLOUR WASHING, PAINTING & POLISHING WORK CARRIED TO COLLECTION | H25: =SUM(H3:H24) -> 2418543.2
H33: =#REF!+#REF!+#REF!+#REF!+#REF! -> #REF!

Sheet plumbing
A1: Nos | B1: Description | C1: Qty | D1: Unit | E1: Cost | F1: OH & P% | G1: Rate ( Rs.) | H1: Amount | I1: =+summary!D14 -> 0.85
B2: S - PLUMBING AND DRAINAGE WORK
B3: S - SANITARY FITTINGS
B4: Note :
B5: In view of the variety of sanitary ware and fittings available in the market, it has become necessary to prescribe the exact quality requirements in terms of performance and durability aspects. The "Rocell , American Standard, Lanka Tiles - coloma " brands and respective model numbers have been chosen as a bench mark to establish the said requirements.
B7: The brand name and model number appearing in the respective BSR items are purely meant to describe the performance standard of the said fitting/item and does not imply in any way that only the "Rocell ,American Standard, Lanka Tiles - coloma " brands are recommended or considered to be restricted to the "Rocell & American Standard" brands.
B9: Any other make/brand that has equivalent performance characteristics are considered as equivalent provided such fittings meet with the following criteria.
B10: (a). Has an authorized local agent in Sri Lanka
B11: (b). The local agent has been in the trade of the offered make for not less than 5 years.
B12: (c).The cistern mechanism shall have an assurance for the availability of spares for the next 3 years.
B13: (d). The fittings are manufactured in conformity to BS, JIS, A.S.T.M., A.S. or S.L.S. standards.
B14: (e).The dimensions and performance characteristics are in par with the stated model.
B15: (f).Contractor should submit the purchasing bill and the required warranty for all "Rocell , American Standard, Lanka Tiles - coloma " products
... B26: Disable Fittings & Accessories
A27: S 01 | B27: Supply and fix ceramic wall hung wash basin for disabled of "Vitra" brand, Model No.6147 with Plush Lock waste & overflow & Bottle Trap Chrome plated or approved equivalent.(Prime cost of the wash basin is Rs.45,000.00) | D27: Nr
A29: S 02 | B29: Supply and fix Disable Water Closet "Vitra" brand-Model No.6927 with seat cover & water tank or approved equivalent complete to working order.(Prime cost of is Rs.65,000.00) | D29: Nr
A31: S 03 | B31: Supply and fix Chromium plated single level wash basin mixer tap without pop-up waste with connection flex of "cobra" brand or approved equivalent with 5 year written warranty from the authorized agent.(Prime cost of is Rs.25,000.00) | D31: Nr
A33: S 04 | B33: Supply and fix Heavy duty Straight grab bar for disabled of "J&T" brand,model "GB029" or approved equivalent.(Prime cost of is Rs.10,000.00) | D33: Nr
A36: S 01 | B36: Supply and fix white vitreous china (vc) floor standing wash basin and pedestal with overflow hole and single tap hole in center of "Rocell" brand or approved equivalent complete to working order inclusive of the 1 1/4" chromium plated waste outlet of "Rocell" brand or approved equivalent and 1 1/4" chromium plated siphon cleanable bottle trap of "Rocell" brand or approved equivalent. (Prime cost of the floor standing wash basin and pedestal is Rs.20,185.00) for servant bathroom
B37: Ground Floor | D37: Nr
A39: S 02 | B39: Supply and fix white vitreous china (vc) floor standing Vanity wash basin with overflow hole and single tap hole in center of "Rocell" brand or approved equivalent complete to working order inclusive of the 1 1/4" chromium plated waste outlet of "Rocell" brand or approved equivalent and 1 1/4" chromium plated siphon cleanable bottle trap of "Rocell" brand or approved equivalent. (Prime cost of the floor standing wash basin is Rs.50,000.00)
B40: Ground Floor | C40: 1 | D40: Nr | E40: =50000+5500 -> 55500 | F40: =+$I$1 -> 0.85 | G40: =ROUNDUP(E40/F40,-1) -> 65300 | H40: =C40*G40 -> 65300
B41: First Floor | C41: 3 | D41: Nr | E41: =50000+5700 -> 55700 | F41: =+$I$1 -> 0.85 | G41: =ROUNDUP(E41/F41,-1) -> 65530 | H41: =C41*G41 -> 196590
B42: Second Floor | C42: 2 | D42: Nr | E42: =50000+5900 -> 55900 | F42: =+$I$1 -> 0.85 | G42: =ROUNDUP(E42/F42,-1) -> 65770 | H42: =C42*G42 -> 131540
B44: Supply and fix white vitreous china (vc) floor standing close coupled semi . back to wall water closet suite with wash down flushing with 6/3 liters dual flushing has horizontal outlet with vario drain bend and two lateral holes for bottom water connection , P trap, cistern with water inlet from rear of "Rocell" brand or approved equivalent complete to working order inclusive of universal bend of "Rocell" brand. (Prime cost of the water closet, tank and seat cover is Rs.30,000.00) for Servant bathroom
B45: Ground Floor | D45: Nr
A47: S 03 | B47: Supply and fix white vitreous china (vc) floor standing close coupled semi . back to wall water closet suite with wash down flushing with 6/3 liters dual flushing has horizontal outlet with vario drain bend and two lateral holes for bottom water connection , P trap, cistern with water inlet from rear of "Rocell" brand or approved equivalent complete to working order inclusive of universal bend of "Rocell" brand. (Prime cost of the water closet, tank and seat cover is Rs.65,000.00)
B48: Ground Floor | C48: 1 | D48: Nr | E48: =65000+5500 -> 70500 | F48: =+$I$1 -> 0.85 | G48: =ROUNDUP(E48/F48,-1) -> 82950 | H48: =C48*G48 -> 82950
B49: First Floor | C49: 3 | D49: Nr | E49: =65000+5700 -> 70700 | F49: =+$I$1 -> 0.85 | G49: =ROUNDUP(E49/F49,-1) -> 83180 | H49: =C49*G49 -> 249540
B50: Second Floor | C50: 2 | D50: Nr | E50: =65000+5900 -> 70900 | F50: =+$I$1 -> 0.85 | G50: =ROUNDUP(E50/F50,-1) -> 83420 | H50: =C50*G50 -> 166840
A52: S 07 | B52: Supply and fix Chromium plated 1/2" dia. angle valve of "Rocell" brand . model or approved equivalent. (Prime cost of the Chromium plated 1/2" dia. angle valve is Rs. 2,500.00)
B53: Ground Floor | C53: =C48*3 -> 3 | D53: Nr | E53: =2500+350 -> 2850 | F53: =+$I$1 -> 0.85 | G53: =ROUNDUP(E53/F53,-1) -> 3360 | H53: =C53*G53 -> 10080
B54: First Floor | C54: =C49*3 -> 9 | D54: Nr | E54: =2500+350 -> 2850 | F54: =+$I$1 -> 0.85 | G54: =ROUNDUP(E54/F54,-1) -> 3360 | H54: =C54*G54 -> 30240
B55: Second Floor | C55: =C50*3 -> 6 | D55: Nr | E55: =2500+350 -> 2850 | F55: =+$I$1 -> 0.85 | G55: =ROUNDUP(E55/F55,-1) -> 3360 | H55: =C55*G55 -> 20160
A60: S 08 | B60: Supply and fix Chromium plated 1 1/4" chromium plated push type waste outlet of "Rocell" brand or approved equivalent. (Prime cost of the Chromium plated 1 1/4" chromium plated waste outlet is Rs. 2,500.00)
B61: Ground Floor | C61: 1 | D61: Nr | E61: =2500+300 -> 2800 | F61: =+$I$1 -> 0.85 | G61: =ROUNDUP(E61/F61,-1) -> 3300 | H61: =C61*G61 -> 3300
B62: First Floor | C62: 3 | D62: Nr | E62: =2500+300 -> 2800 | F62: =+$I$1 -> 0.85 | G62: =ROUNDUP(E62/F62,-1) -> 3300 | H62: =C62*G62 -> 9900
B63: Second Floor | C63: 2 | D63: Nr | E63: =2500+300 -> 2800 | F63: =+$I$1 -> 0.85 | G63: =ROUNDUP(E63/F63,-1) -> 3300 | H63: =C63*G63 -> 6600
A65: S 09 | B65: Supply and fix Chromium plated 1/2" dia. 36" long flexible horse of "Rocell" brand or approved equivalent. (Prime cost of the Chromium plated 1/2" dia. 18" long flexible horse is Rs. 3,000.00)
B66: Ground Floor | C66: 1 | D66: Nr | E66: =3000+450 -> 3450 | F66: =+$I$1 -> 0.85 | G66: =ROUNDUP(E66/F66,-1) -> 4060 | H66: =C66*G66 -> 4060
B67: First Floor | C67: 3 | D67: Nr | E67: =3000+450 -> 3450 | F67: =+$I$1 -> 0.85 | G67: =ROUNDUP(E67/F67,-1) -> 4060 | H67: =C67*G67 -> 12180
B68: Second Floor | C68: 2 | D68: Nr | E68: =3000+450 -> 3450 | F68: =+$I$1 -> 0.85 | G68: =ROUNDUP(E68/F68,-1) -> 4060 | H68: =C68*G68 -> 8120
A70: S 09 | B70: Supply and fix Chromium plated 1/2" dia. 12" long flexible horse of "Rocell" brand or approved equivalent. (Prime cost of the Chromium plated 1/2" dia. 12" long flexible horse is Rs. 2,500.00)
B71: Ground Floor | C71: 1 | D71: Nr | E71: =2500+450 -> 2950 | F71: =+$I$1 -> 0.85 | G71: =ROUNDUP(E71/F71,-1) -> 3480 | H71: =C71*G71 -> 3480
B72: First Floor | C72: 3 | D72: Nr | E72: =2500+450 -> 2950 | F72: =+$I$1 -> 0.85 | G72: =ROUNDUP(E72/F72,-1) -> 3480 | H72: =C72*G72 -> 10440
B73: Second Floor | C73: 2 | D73: Nr | E73: =2500+450 -> 2950 | F73: =+$I$1 -> 0.85 | G73: =ROUNDUP(E73/F73,-1) -> 3480 | H73: =C73*G73 -> 6960
B74: Supply and fix chromium plated Bidet Spray of "Rocell" brand or . approved equivalent. (Prime cost of the chromium plated Bidet Spray is Rs. 3,000.00)
B75: Ground Floor | D75: Nr
A77: S 11 | B77: Supply and fix chromium plated Bidet Spray of "Rocell" brand or . approved equivalent. (Prime cost of the chromium plated Bidet Spray is Rs. 5,000.00)
B78: Ground Floor | C78: 1 | D78: Nr | E78: =5000+300 -> 5300 | F78: =+$I$1 -> 0.85 | G78: =ROUNDUP(E78/F78,-1) -> 6240 | H78: =C78*G78 -> 6240
B79: First Floor | C79: 3 | D79: Nr | E79: =5000+300 -> 5300 | F79: =+$I$1 -> 0.85 | G79: =ROUNDUP(E79/F79,-1) -> 6240 | H79: =C79*G79 -> 18720
B80: Second Floor | C80: 2 | D80: Nr | E80: =5000+300 -> 5300 | F80: =+$I$1 -> 0.85 | G80: =ROUNDUP(E80/F80,-1) -> 6240 | H80: =C80*G80 -> 12480
A82: S 12 | B82: Supply and fix 5mm thick mirror of size 18" x 24" double coated with pencil edge back strecher. (Prime cost of the 5mm thick mirror of size 18" x 24" is Rs. 4,000.00)
B83: Ground Floor | D83: Nr
B84: First Floor | D84: Nr
B85: Third Floor | D85: Nr
B86: Fourth Floor | D86: Nr
A88: S 13 | B88: Supply and fix Chromium plated pillar tap (cold water) for wash basin of "Rocell" brand or approved equivalent. (Prime cost of the Chromium plated pillar tap (cold water) for wash basin is Rs. 6,000.00)
B89: Ground Floor | C89: 1 | D89: Nr | E89: =6000+400 -> 6400 | F89: =+$I$1 -> 0.85 | G89: =ROUNDUP(E89/F89,-1) -> 7530 | H89: =C89*G89 -> 7530
B90: First Floor | C90: 3 | D90: Nr | E90: =6000+400 -> 6400 | F90: =+$I$1 -> 0.85 | G90: =ROUNDUP(E90/F90,-1) -> 7530 | H90: =C90*G90 -> 22590
B91: Second Floor | C91: 2 | D91: Nr | E91: =6000+400 -> 6400 | F91: =+$I$1 -> 0.85 | G91: =ROUNDUP(E91/F91,-1) -> 7530 | H91: =C91*G91 -> 15060
A93: S 14 | B93: Supply and fix Chromium plated Bip tap of of "Rocell" brand or approved equivalent. (Prime cost of the Chromium plated Bip tap is Rs. 5,000.00)
B94: Ground Floor | C94: 1 | D94: Nr | E94: =5000+400 -> 5400 | F94: =+$I$1 -> 0.85 | G94: =ROUNDUP(E94/F94,-1) -> 6360 | H94: =C94*G94 -> 6360
B95: First Floor | C95: 3 | D95: Nr | E95: =5000+400 -> 5400 | F95: =+$I$1 -> 0.85 | G95: =ROUNDUP(E95/F95,-1) -> 6360 | H95: =C95*G95 -> 19080
B96: Second Floor | C96: 2 | D96: Nr | E96: =5000+400 -> 5400 | F96: =+$I$1 -> 0.85 | G96: =ROUNDUP(E96/F96,-1) -> 6360 | H96: =C96*G96 -> 12720
B101: Bathroom Accessories
A102: S 15 | B102: Supply and fix chromium plated Soap holder of "Rocell" brand or . approved equivalent. (Prime cost of the chromium plated Soap holder is Rs. 3,500.00)
B103: Ground Floor | C103: 1 | D103: Nr | E103: =3500+500 -> 4000 | F103: =+$I$1 -> 0.85 | G103: =ROUNDUP(E103/F103,-1) -> 4710 | H103: =C103*G103 -> 4710
B104: First Floor | C104: 3 | D104: Nr | E104: =3500+500 -> 4000 | F104: =+$I$1 -> 0.85 | G104: =ROUNDUP(E104/F104,-1) -> 4710 | H104: =C104*G104 -> 14130
B105: Second Floor | C105: 2 | D105: Nr | E105: =3500+500 -> 4000 | F105: =+$I$1 -> 0.85 | G105: =ROUNDUP(E105/F105,-1) -> 4710 | H105: =C105*G105 -> 9420
A107: S 15 | B107: Supply and fix chromium plated Towel Ring of "Rocell" brand or . approved equivalent. (Prime cost of the chromium plated Towel Ring is Rs. 3,500.00)
B108: Ground Floor | C108: 1 | D108: Nr | E108: =3500+550 -> 4050 | F108: =+$I$1 -> 0.85 | G108: =ROUNDUP(E108/F108,-1) -> 4770 | H108: =C108*G108 -> 4770
B109: First Floor | C109: 3 | D109: Nr | E109: =3500+550 -> 4050 | F109: =+$I$1 -> 0.85 | G109: =ROUNDUP(E109/F109,-1) -> 4770 | H109: =C109*G109 -> 14310
B110: Second Floor | C110: 2 | D110: Nr | E110: =3500+550 -> 4050 | F110: =+$I$1 -> 0.85 | G110: =ROUNDUP(E110/F110,-1) -> 4770 | H110: =C110*G110 -> 9540
A112: S 17 | B112: Supply and fix chromium plated Toilet Paper Holder of "Rocell" brand or . approved equivalent. (Prime cost of the chromium plated Toilet Paper Holder is Rs. 3,500.00)
B113: Ground Floor | C113: 1 | D113: Nr | E113: =3500+500 -> 4000 | F113: =+$I$1 -> 0.85 | G113: =ROUNDUP(E113/F113,-1) -> 4710 | H113: =C113*G113 -> 4710
B114: First Floor | C114: 3 | D114: Nr | E114: =3500+500 -> 4000 | F114: =+$I$1 -> 0.85 | G114: =ROUNDUP(E114/F114,-1) -> 4710 | H114: =C114*G114 -> 14130
B115: Second Floor | C115: 2 | D115: Nr | E115: =3500+500 -> 4000 | F115: =+$I$1 -> 0.85 | G115: =ROUNDUP(E115/F115,-1) -> 4710 | H115: =C115*G115 -> 9420
A117: S 18 | B117: Supply and fix Chromium plated bathroom floor gully cover square type of "Lanka Tiles Coloma " brand or approved equivalent. (Prime cost of the Chromium plated bathroom floor gully cover square type is Rs. 8,000.00)
B118: Ground Floor | C118: 1 | D118: Nr | E118: =8000+650 -> 8650 | F118: =+$I$1 -> 0.85 | G118: =ROUNDUP(E118/F118,-1) -> 10180 | H118: =C118*G118 -> 10180
B119: First Floor | C119: 3 | D119: Nr | E119: =8000+650 -> 8650 | F119: =+$I$1 -> 0.85 | G119: =ROUNDUP(E119/F119,-1) -> 10180 | H119: =C119*G119 -> 30540
B120: Second Floor | C120: 2 | D120: Nr | E120: =8000+650 -> 8650 | F120: =+$I$1 -> 0.85 | G120: =ROUNDUP(E120/F120,-1) -> 10180 | H120: =C120*G120 -> 20360
A122: S 19 | B122: Supply and fix chromium plated Toilet Brush Holder of "Lanka Tiles Coloma - Angelo " brand or approved equivalent. (Prime cost of the chromium plated Toilet Brush Holder is Rs. 3,000.00)
B123: Ground Floor | C123: 1 | D123: Nr | E123: =3000+550 -> 3550 | F123: =+$I$1 -> 0.85 | G123: =ROUNDUP(E123/F123,-1) -> 4180 | H123: =C123*G123 -> 4180
B124: First Floor | C124: 3 | D124: Nr | E124: =3000+550 -> 3550 | F124: =+$I$1 -> 0.85 | G124: =ROUNDUP(E124/F124,-1) -> 4180 | H124: =C124*G124 -> 12540
B125: Second Floor | C125: 2 | D125: Nr | E125: =3000+550 -> 3550 | F125: =+$I$1 -> 0.85 | G125: =ROUNDUP(E125/F125,-1) -> 4180 | H125: =C125*G125 -> 8360
B126: Kitchen Sink
A127: S 20 | B127: Supply and fix stainless steel 36"X 18"0.6mm thick shiny finish kitchen sink with double bowl of "Seal core" by mascons or approved equivalent with 5 year written warranty from the authorized agent. including PVC bottle trap and water connection with flexible hose, all complete to working order. ( Swan neck tap paid separately.) | D127: Nr
A129: S 21 | B129: Supply and fix Chromium plated Sink tap (Swan neck type) of "Rocell" . brand or approved equivalent. (Prime cost of the Chromium plated Sink tap (Swan neck type) is Rs. 3,047.00) | D129: Nr
B131: T - PLUMBING
B132: ACCESSORIES
A133: S 22 | B133: Supply and fixing 1" dia PVC Compact Ball valve. | D133: Nr
A135: S 23 | B135: Supply and fixing 1 1/2" dia PVC Compact Ball valve. | D135: Nr
B137: Foot Valve
A138: S 24 | B138: Supply and fixing 1" dia PVC Foot valve. | D138: Nr
B147: Water Tanks
B148: Water tank should combined with three layers of high density polyethylene except 5000 Ltr. Water tank.
B150: The inner and outer layers made of 100% FDA approved virgin raw materials , ensuring non-contamination.
B152: Contractor should submit the purchasing bill and the required warranty for water tanks (10 year warranty) manufactured by "Anton , Arpico" to the Divisional Engineer.
A154: S 25 | B154: Supplying and installing of water tank 2000 ltr. Capacity rate to including the cost of transport. Hoisting in position and specials,rate to include to necessary ball valve and other related fixtures and accessories | C154: 1 | D154: Nr
...

Sheet electicle 
A1: Nos | B1: Description | C1: Qty | D1: Unit | E1: Cost | F1: OH & P% | G1: Rate ( Rs.) | H1: Amount | I1: =+summary!D15 -> 0.8
B2: V - ELECTRICAL INSTALLATION.
B3: Note:
B4: Work shall be done in accordance with specifications for electrical and mechanical works - ICTAD Publication No.SCA/8 of Aug.2000(2nd Edition -Revised)
B6: Internal light wiring shall comply with the drawings and shall be in 230/440 volt PVC insulated copper cables
B8: All switches and socket outlets shall be plated type make"Clipsal", " Orange X5", "Krypton" or any other approved equivalent complying to SLS1000:1993 for switches & SLS 1998 : 1991 for soket outlets .
B10: Rate to include switch boxes, Rowl plugs, square pin plug base, Chromium plated M.S. chains, brass hooks, ceiling roses, holders and any other item necessary.
B12: All distribution boards should be incorporated with multi 9, Orange Industrial, Merlin Gerin, , Hager, LS, Moeller/EATON, clipsal,SIEMENS make MCB's (Miniature circuit Breaker ) and cabtree, Clipsal ,Orange Industrial 10 kA, LS , Merlin Gerin,Schinieider make R.C.C.B.'s (Residual Current circuit Breaker) and Schinieider, Merlin Gerin, LS, Dormans Smith ,Orange Industrial (10K), Biticano , Clockner moeller make M.C.C.B.'s (Moulded Case Circuit Breakers)
B14: The whole installation shall be carried out according to CEB/IEE wiring regulations.
B16: All the M.C.C.B.'s, MCB's and RCCB's for the distribution boards should be purchased from the following authorized agents or from heir dealers and a certificate or invoice along with their Company seal and Part No., numbers and warranty should be produced at the time of payment.
B17: a). All MCB, RCCB, shall have 20 Years warranty and hence products which comes with 20 years warranty are permitted.
B18: b). All MCCB shall have 2 Years warranty and hence products which comes with 2 years warranty are permitted.
B19: e). All socket and switches shall have 20 Years warranty and hence products which comes with 20 years warranty are permitted.
... B54: Inspection and testing
A56: V01.02 | B56: Testing of the electrical installation and submission of certificate from a chartered Electrical Engineer registered at CEB. | C56: 1 | D56: Item | E56: 25000 | F56: =+$I$1 -> 0.8 | G56: =ROUNDUP(E56/F56,-1) -> 31250 | H56: =C56*G56 -> 31250
A58: V01.03 | B58: Charges for verifying the wiring done with meggar test & continuity test before commensing installation of Distribution Board & Electrical Fittings | C58: 1 | D58: Item | E58: 42000 | F58: =+$I$1 -> 0.8 | G58: =ROUNDUP(E58/F58,-1) -> 52500 | H58: =C58*G58 -> 52500
A60: V02 | B60: Main Cabling System
B62: All the Cables quoted below shall be on measure and pay basis.
B64: Rates should include for all necessary cable accessories such as cable ties, Cable Lugs, Glands, identification tags, and all accessories for complete installation
B66: Rate shall include for supply and installation of following cables including cable trays, ladders and trunking, conduits,Underground Installments incuding sand beddings ,concrete tiles warning tapes etc. including termination.
B68: All horizontal and vertical Cable trays , trunking , conduits & ladders should be adequately sized to provide 25% spare space. Installation method shall be according to BS 7671
B70: Contractor shall investigate the site conditions and include all the cost involved in point rates given below.
B72: All wiring shall be in securely fixed conduits /trunkig above the ceiling
B74: Main cables for sub distribution boards of each floor shall be tapped from the bus bar riser
A76: V02.01 | B76: Supply, installation & termination of main cable from CEB supply to MDB | C76: 1 | D76: Item | E76: 60000 | F76: =+$I$1 -> 0.8 | G76: =ROUNDUP(E76/F76,-1) -> 75000 | H76: =C76*G76 -> 75000
A78: V02.03 | B78: Supply, installation & termination of from MDB to each DBs. | C78: 1 | D78: Item | E78: 25000 | F78: =+$I$1 -> 0.8 | G78: =ROUNDUP(E78/F78,-1) -> 31250 | H78: =C78*G78 -> 31250
A80: V03 | B80: Main Distribution Board and SUB Distribution Boards and Isolators
B82: All the Distribution Boards shall be surface/flush mounted type Distribution Boards complete with powder coated steel enclosure with lockable doors.
B84: The panel board should have wire numbering and a laminated circuit diagram pasted on the inside surface of the door.
B86: Distribution Boards shall be completed with necessary protection
B88: Make of MCCBs and MCBs, etc shall be Schnider / ABB / Terasaki or equivalent make, approved by the Consultant.
B89: Manufactures shop drawings should be submitted and approved by the Consultant before fabrication
B91: All switches and socket outlets shall be plated type make"Clipsal", " Orange X5", "Krypton" or any other approved equivalent complying to SLS1000:1993 for switches & SLS 1998 : 1991 for soket outlets .
B93: Rate to include switch boxes, Rowl plugs, square pin plug base, Chromium plated M.S. chains, brass hooks, ceiling roses, holders and any other item necessary.
B95: All distribution boards should be incorporated with multi 9, Orange Industrial, Merlin Gerin, , Hager, LS, Moeller/EATON, clipsal, SIEMENS make MCB's (Miniature circuit Breaker ) and cabtree, Clipsal ,Orange Industrial 10 kA, LS , Merlin Gerin,Schinieider make R.C.C.B.'s (Residual Current circuit Breaker) and Schinieider, Merlin Gerin, LS, Dormans Smith ,Orange Industrial (10K), Biticano , Clockner moeller make M.C.C.B.'s (Moulded Case Circuit Breakers)
B97: The whole installation shall be carried out according to CEB/IEE wiring regulations.
B99: All the M.C.C.B.'s, MCB's and RCCB's for the distribution boards should be purchased from the following authorized agents or from their dealers and a certificate or invoice along with their Company seal and Part No., numbers and warranty should be produced at the time of payment.
B101: a). All MCB, RCCB, shall have 20 Years warranty and hence products which comes with 20 years warranty are permitted.
B103: b). All MCCB shall have 2 Years warranty and hence products which comes with 2 years warranty are permitted.
... B120: Supply and Installation of Power Distribution Panels
A121: V03.01 | B121: MDB/DB
B122: 02 Nos 4P 63A MCCB /(10kA), 04 Nos 2P 32A MCB /(10kA),01 Nos 125A 4P Automatic Chainge over,01 Nos 40A 4P MCCB, 07 Nos 40A 4P MCCB, 07 Nos 40A 4P 30mA RCCB, 01 Nos 40A 2P 30mA RCCB,and nessasary bus bar and protective system and Cables Lugs and other suppotive meterials | C122: 1 | D122: P.S | E122: 400000
B123: 1 set of LED Phase indicator lamps c/w 3 x 2A fuse
B124: Supply and mounted (LED Phase indicator lamps ) Wall/Surface mounted Powder Coated Steel Enclosure with lockable doors ,cover plate & internal wiring c/w bus bars and Accessories.(Rate to include necessary MCCB,MCB,RCCB,and other necessary fixturesand Other required supportive materials should include ) The contractor shoud take advise an electricle engineer before undataking the work and
B125: Surface mounted Powder Coated Steel Enclosure with lockable doors ,cover plate & internal wiring c/w bus bars and Accessories.
A127: V03.02 | B127: DB
B128: Ground Floor,First Floor,Second Floor, Third Floor
B129: 01 No. 4P 63A MCCB (16kA Breaking capacity), 01 No. 4P 40A MCCB (16kA Breaking capacity),01 No. 2P 32A, MCB (16kA Breaking capacity),02 Nos. 1P 10A MCB (6kA Breaking capacity),02 Nos. 1P 20A MCB (6kA Breaking capacity),01 No. 2P 40A, 30mA RCCB, and nessasary bus bar and protective system and Cables Lugs and other suppotive meterials1 | D129: P.S
B130: Supply and mounted LED phase indicator lamps powder coated steel encloser with lockble door, Wall mounted distribution board (3 nr of DB) & internal wiring c/w bus bars and Accessories.(Rate to include necessary MCCB,MCB,RCCB,and other necessary fixturesand Other required supportive materials should include ) The contractor shoud take advise an electricle engineer before undataking the work
B131: Surface mounted Powder Coated Steel Enclosure with lockable doors ,cover plate & internal wiring c/w bus bars and Accessories.
A132: V03.03 | B132: DB- For Lift
B133: Supply and mounted LED phase indicator lamps powder coated steel encloser with lockble door, Wall mounted distribution board & internal wiring c/w bus bars and Accessories.(Rate to include necessary MCCB,MCB,RCCB,and other necessary fixturesand Other required supportive materials should include ) The contractor shoud take advise an electricle engineer before undataking the work | D133: P.S
B134: Surface mounted Powder Coated Steel Enclosure c/w bus bars and Accessories.
A136: V03.04 | B136: DB- For bank- 4 nr of DB
B137: Supply and mounted LED phase indicator lamps powder coated steel encloser with lockble door, Wall mounted distribution board (4 nr of DB) & internal wiring c/w bus bars and Accessories.(Rate to include necessary MCCB,MCB,RCCB,and other necessary fixturesand Other required supportive materials should include ) The contractor shoud take advise an electricle engineer before undataking the work | D137: P.S
B138: Surface mounted Powder Coated Steel Enclosure with lockable doors ,cover plate & internal wiring c/w bus bars and Accessories.
A140: V03.04 | B140: DBs For Shop
B141: Supply and mounted Wall mounted distribution board( 42 nr) & internal wiring c/w bus bars and Accessories.(Rate to include necessary MCCB,MCB,RCCB,and other necessary fixturesand Other required supportive materials should include ) The contractor shoud take advise an electricle engineer before undataking the work | D141: P.S
B142: Surface mounted Powder Coated Steel Enclosure with lockable doors ,cover plate & internal wiring c/w bus bars and Accessories.
A152: V03.05 | B152: DBs For Banks
A153: V04 | B153: Wiring for light points, ceiling fans, socket outlets
B155: Rate for point wiring shall include for all the cables trays/ladders,conduits, conduit fittings, casings,surface cable trunks, fixing material, switches, wiring and terminations, holders for light fittings and socket outlets for power points. Contractor shall obtain approvals from the Consultant/CEE for above items
B157: As a standard of quality for switches and socket outlets, the contractor may use 'ML/Legrand /ACL or approved equal'.
B159: Light fittings / Fans
B161: The light fittings supplied and installed under this contract shall be in every respect suitable for the intended purpose.
B163: Each fitting shall include bulbs, internal wiring, hanging and fixing material and be complete without any additional item/material being required to make it so.
B164: The contractor shall obtain consultants and clients approval for the fittings before fixing the fittings in the site
B166: As a standard of quality for Light fittings, the contractor may use 'Philips/Osram or approved equal'.
B168: Rate for items shall include the cost of fixing,adapter,connecting 2core 1mm2 . And any other related cost
B170: Lamp fitting shall include the cost of fitting and bulb & shall be given a two year Warranty and one year warranty for bulb
B172: Lamp fitting with given a two year Warranty for fitting
B174: Light Fittings
B175: Rate for items shall include the cost of adapter, connecting 2core 1mm 2 cable o ,galvanized hanging chain.
... B188: GROUND FLOOR
B190: Point wiring for socket outlets 13A - ( 16A Circuits) Supply, Installation & wiring of 13A power Socket Outlet, by using 2x1C 2.5mm^2 Cu /PVC/PVC Cable + 1C 2.5 mm^2 Cu/PVC Earth Cable (in radial circuit) through slab & wall in PVC conduits including PVC conduits, sunk box, junction box, outlet and complete with all other relevant accessories. | C190: 22 | D190: nr | E190: 10000 | F190: =+$I$1 -> 0.8 | G190: =ROUNDUP(E190/F190,-1) -> 12500 | H190: =C190*G190 -> 275000
B192: Light Point Wiring (10A Circuits)-indoor/outdoor Supply & Installation of light Point Wiring, by using 2x1C 1.5mm^2 Cu/PVC/PVC Cable + 1C 1.5 mm^2 Cu/PVC Earth Cable through slab & wall in PVC conduits including PVC conduits, sunk box, junction box, 10A PVC Switch and complete with all other relevant accessories. | C192: 70 | D192: nr | E192: 8500 | F192: =+$I$1 -> 0.8 | G192: =ROUNDUP(E192/F192,-1) -> 10630 | H192: =C192*G192 -> 744100
B194: Two way light Point Wiring (10A Circuits) Supply & Installation of 2way light Point Wiring, by using 2x1C 1.5mm^2 Cu/PVC/PVC Cable + 1C 1.5 mm^2 Cu/PVC Earth Cable through slab & wall in PVC conduits including PVC conduits, sunk box, junction box, 10A PVC 2 way Switches and complete with all other relevant accessories. | C194: 2 | D194: nr | E194: 9000 | F194: =+$I$1 -> 0.8 | G194: =ROUNDUP(E194/F194,-1) -> 11250 | H194: =C194*G194 -> 22500
B195: Fan Point Wiring - (10A Circuits ) Supply & installation of Fan Point wiring, by using 2X1C 1.5mm^2 Cu/PVC /PVC Cable + 1C 1.5 mm^2 Cu/PVC earth Cable through slab & wall in PVC conduits including PVC conduits, junction boxes, sunk boxes, 10A PVC Switch, and complete with all other relevant accessories. | D195: nr
B197: Supply & Installation of ceiling fans- Brand - KDK (model need to be finalized with architect) Supply & Installation of ceiling fan (Diameter-56") and speed regulator with roll plugs, screws, metal hooks (Fan hook need to be passed through the slab and properly connected) and complete with all other relevant accessories. | D197: nr
B199: Light Fittings
B201: Installation of light fittings-indoor/outdoor Installation of light fittings including roll plugs, screws and complete with all other relevant accessories. | C201: =C208+C210+C213+C217+C219+C221+C223 -> 71 | D201: nr | E201: 1350 | F201: =+$I$1 -> 0.8 | G201: =ROUNDUP(E201/F201,-1) -> 1690 | H201: =C201*G201 -> 119990
B203: Supplying of pendent light fittings Type 01-(Prime cost is Rs.35,000.00) | D203: nr
B205: Supplying of pendent light fittings Type 02-(Prime cost is Rs.35,000.00) | D205: nr
B207: Supplying of pendent light fittings Type 03-(Prime cost is Rs.35,000.00) | D207: nr
B208: Supplying of Wall Bracket light fittings -(Prime cost is Rs.6,500.00) | C208: 6 | D208: nr | E208: =6500+750 -> 7250 | F208: =+$I$1 -> 0.8 | G208: =ROUNDUP(E208/F208,-1) -> 9070 | H208: =C208*G208 -> 54420
B210: Inner diameter of 150mm dia Ceiling/slab mounted down light complete with 18w LED lamp. (Prime cost is Rs.6,000.00) | C210: 49 | D210: Nr. | E210: =6000+750 -> 6750 | F210: =+$I$1 -> 0.8 | G210: =ROUNDUP(E210/F210,-1) -> 8440 | H210: =C210*G210 -> 413560
B212: 150mmX150mm Ceiling/slab mounted down light complete with 18w LED lamp. (Prime cost is Rs.6,000.00) | D212: Nr.
B213: LED 6w Mirror lamp fitting.- (Prime cost is Rs.5,500.00) | C213: 1 | D213: Nr | E213: =5500+750 -> 6250 | F213: =+$I$1 -> 0.8 | G213: =ROUNDUP(E213/F213,-1) -> 7820 | H213: =C213*G213 -> 7820
B215: Supplying and installation of ceiling fan KDK with all fittings (Pc sum is Rs. 50,000.00) | C215: 4 | D215: nr | E215: =50000+3000 -> 53000 | F215: =+$I$1 -> 0.8 | G215: =ROUNDUP(E215/F215,-1) -> 66250 | H215: =C215*G215 -> 265000
B217: Supplying of pendent light fittings Type 01-(Prime cost is Rs.55,000.00) | C217: 3 | D217: nr | E217: =55000+1700 -> 56700 | F217: =+$I$1 -> 0.8 | G217: =ROUNDUP(E217/F217,-1) -> 70880 | H217: =C217*G217 -> 212640
B219: Supplying of pendent light fittings Type 02-(Prime cost is Rs.45,000.00) | C219: 3 | D219: nr | E219: =45000+1500 -> 46500 | F219: =+$I$1 -> 0.8 | G219: =ROUNDUP(E219/F219,-1) -> 58130 | H219: =C219*G219 -> 174390
B221: Supplying of pendent light fittings Type 03-(Prime cost is Rs.35,000.00) | C221: 1 | D221: nr | E221: =35000+1200 -> 36200 | F221: =+$I$1 -> 0.8 | G221: =ROUNDUP(E221/F221,-1) -> 45250 | H221: =C221*G221 -> 45250
B223: Supplying of Wall mounted outdoor light fittings -(Prime cost is Rs.6,500.00) | C223: 8 | D223: nr | E223: =6500+750 -> 7250 | F223: =+$I$1 -> 0.8 | G223: =ROUNDUP(E223/F223,-1) -> 9070 | H223: =C223*G223 -> 72560
B225: Supplying of floor light fittings -(Prime cost is Rs.6,500.00) | D225: nr
B226: FIRST FLOOR
B228: Point wiring for socket outlets 13A - ( 16A Circuits) Supply, Installation & wiring of 13A power Socket Outlet, by using 2x1C 2.5mm^2 Cu /PVC/PVC Cable + 1C 2.5 mm^2 Cu/PVC Earth Cable (in radial circuit) through slab & wall in PVC conduits including PVC conduits, sunk box, junction box, outlet and complete with all other relevant accessories. | C228: 33 | D228: nr | E228: 10000 | F228: =+$I$1 -> 0.8 | G228: =ROUNDUP(E228/F228,-1) -> 12500 | H228: =C228*G228 -> 412500
B230: Light Point Wiring (10A Circuits)-indoor/outdoor Supply & Installation of light Point Wiring, by using 2x1C 1.5mm^2 Cu/PVC/PVC Cable + 1C 1.5 mm^2 Cu/PVC Earth Cable through slab & wall in PVC conduits including PVC conduits, sunk box, junction box, 10A PVC Switch and complete with all other relevant accessories. | C230: 60 | D230: nr | E230: 8500 | F230: =+$I$1 -> 0.8 | G230: =ROUNDUP(E230/F230,-1) -> 10630 | H230: =C230*G230 -> 637800
B232: Two way light Point Wiring (10A Circuits) Supply & Installation of 2way light Point Wiring, by using 2x1C 1.5mm^2 Cu/PVC/PVC Cable + 1C 1.5 mm^2 Cu/PVC Earth Cable through slab & wall in PVC conduits including PVC conduits, sunk box, junction box, 10A PVC 2 way Switches and complete with all other relevant accessories. | C232: 4 | D232: nr | E232: 9000 | F232: =+$I$1 -> 0.8 | G232: =ROUNDUP(E232/F232,-1) -> 11250 | H232: =C232*G232 -> 45000
B234: Light Fittings
B236: Installation of light fittings-indoor/outdoor Installation of light fittings including roll plugs, screws and complete with all other relevant accessories. | C236: =C246+C248+C251+C253+C255+C257 -> 63 | D236: nr | E236: =+E201 -> 1350 | F236: =+$I$1 -> 0.8 | G236: =ROUNDUP(E236/F236,-1) -> 1690 | H236: =C236*G236 -> 106470
...

Sheet metal
A1: Nos | B1: Description | C1: Qty | D1: Unit | E1: Cost | F1: OH & P% | G1: Rate ( Rs.) | H1: Amount | I1: =+summary!D16 -> 0.9
B2: W - METAL WORK
B3: Note:
B4: Aluminium doors, windows and partitions shall confirm to the following requirements:
B6: 1. Aluminium alloy should confirm to- ISO - 9001:2008, SLS 1410:2011 / SLS 1411:2011
B8: 2. Anodized coating thickness should be 25 ± 5 microns
B10: 3.Aluminium extrusions available in the Local Market are being either manufactured in Sri Lanka or imported material. Due to the continuous change of the extrusion profiles and thicknesses from time to time, it has become very difficult to specify standard section sizes that are to be used for door /window frames and sash members. Hence the rates given herein are based on the recommended minimum sizes and thicknesses of profiles published by leading Aluminium profile manufacturers (Alumex Plc, Swisstek Aluminium Limited) as at present for the doors, windows, fanlights and partitions.
B12: before the fabrication contractor must submitt the following information.
B13: 1. The specifications and thickness of Aluminium extrusions proposes to use on the works.
B14: 2. Full size cross sections of profiles.
B15: 3. Documentary evidence from the Profile Manufacture to the effect that the proposed profile will serve for the intended purpose.
B16: 4. A Manufacturer's test certificate be produced as evidence that the powder coating is of required thickness.
B18: 5. Physical properties :-
... B30: The rates shall include Neoprene gasket, pop rivets, Rawl plugs,Screws,Aluminium cleats etc.
A33: 1 | B33: Metal Ceiling
A34: =A33+0.01 -> 1.01 | B34: Supplying & Installing of 600mmx 600mm non perforated white metal sheet ceiling, supported by concealed type furring suspended system installed in a flat horizontal manner using furing bars clipped on to inter locking hot dipped GI main tees with clips, ciling to be susppended using GI 04mm thick hanger rods (Prime cost of 2'-0" x 2'-0" sheet is Rs.2,640.00)
B35: Ground Floor- banak area | D35: Sqr.
B37: Aluminium Panel Ceiling
A38: =A33+0.01 -> 1.01 | B38: Supplying & installing of suspended Aluminium Panel Ceiling in 600mm x 600 grid size reveal / bevel type using hot dipped GI pre –engineered inter - locking main tees (38mm x 14mm) and cross tees (25mm x 14mm) and wall angles expose areas finished with white baked enamel finish and suspended on 4 mm dia. adjustable hanger rods with spring clips. Ceiling panels will be Compton aluminium tiles 600mm x 600mm x 0.7mm (thickness) and complete to working order as per manufacture's specifications..
B39: Ground Floor- | D39: Sqm
A41: 1 | B41: Hand Rail
B42: G.I Tube Hand Rail
A43: =A41+0.01 -> 1.01 | B43: Staircase handr/Balcony rail as per the design | C43: 1 | D43: P.S | E43: =50*8960 -> 448000 | F43: =+$I$1 -> 0.9 | G43: =ROUNDUP(E43/F43,-1) -> 497780 | H43: =C43*G43 -> 497780
A45: =A43+0.01 -> 1.02 | B45: Powder coated perforated mesh Hand Rail
B46: Supplying, fabricating & fixing of perforated mesh hand rail upto 1.2m height 50mm dia 2.3mm thick G.I round bar upright @ 3000mm c/c as vertical members fixed bottom end to steps with the 150mm dia 8mm thick M.S. plate connecting with 4 nos of 8mm dia.anchor bolts and work complete in order. Rate Shall include for applying one coat of etch primer (50% of etch primer base and 50% etch primer activator),one coat of anti-corrosive primer with two coats of enamel paint. (Prime cost is Rs, 1,250.00 per sqft) | O46: =1250*4 -> 5000
A48: 3 | B48: Partitions
A50: =A48+0.01 -> 3.01 | B50: Tempored Glass Partition
B51: P1 in 37.5mm x 25mm x 1.4mm thick hairline finished stainless steel 'U' channel framed work and 12mm thick tempered glass with printed PVC stickering fixed with silicon joints as per the detailed drawing and finishes as specified as per the drawings | D51: Sqr.
A53: =A50+0.01 -> 3.02 | B53: HPL Partition
B55: First Floor | D55: Sqm
A57: =A53+0.01 -> 3.03 | B57: Tempored fixed Glass
B58: 37.5mm x 25mm x 1.4mm thick hairline finished stainless steel 'U' channel framed work and 12mm thick tempered glass with printed PVC stickering fixed with silicon joints as per the detailed drawing and finishes as specified as per the drawings
B59: Second Floor | D59: Sqr.
A61: 2 | B61: Doors & Windows
B62: Doors
A64: =A61+0.01 -> 2.01 | B64: Door type D1 size 1500mm x 2700mm class I teak timber solid door per the detail drawings with all necessary iron mongaries
B65: In Ground Floor | C65: 1 | D65: nr | E65: =5*9*6150 -> 276750 | F65: =+$I$1 -> 0.9 | G65: =ROUNDUP(E65/F65,-1) -> 307500 | H65: =C65*G65 -> 307500
A67: =A64+0.01 -> 2.02 | B67: Door type D2 size 1000mm x 2700mm class I teak timber solid door per the detail drawings with all necessary iron mongaries
B68: In Ground Floor | C68: 1 | D68: nr | E68: =+(1+2.7)*10.76*6150 -> 244843.8 | F68: =+$I$1 -> 0.9 | G68: =ROUNDUP(E68/F68,-1) -> 272050 | H68: =C68*G68 -> 272050
A70: =A67+0.01 -> 2.03 | B70: Door type D3 size 900mm x 2700mm class I teak timber solid door per the detail drawings with all necessary iron mongaries
B71: In Ground Floor | C71: 2 | D71: nr | E71: =3*9*6150 -> 166050 | F71: =+$I$1 -> 0.9 | G71: =ROUNDUP(E71/F71,-1) -> 184500 | H71: =C71*G71 -> 369000
A73: =A70+0.01 -> 2.04 | B73: Door type D4 size 1000mm x 2700mm class I teak timber solid door per the detail drawings with all necessary iron mongaries
B74: In Ground Floor | C74: 1 | D74: nr | E74: =30*6150 -> 184500 | F74: =+$I$1 -> 0.9 | G74: =ROUNDUP(E74/F74,-1) -> 205000 | H74: =C74*G74 -> 205000
B75: In First floor | C75: 3 | D75: nr | E75: =30*6150 -> 184500 | F75: =+$I$1 -> 0.9 | G75: =ROUNDUP(E75/F75,-1) -> 205000 | H75: =C75*G75 -> 615000
B76: In Second Floor | C76: 3 | D76: nr | E76: =30*6150 -> 184500 | F76: =+$I$1 -> 0.9 | G76: =ROUNDUP(E76/F76,-1) -> 205000 | H76: =C76*G76 -> 615000
A78: =A73+0.01 -> 2.05 | B78: Door type D5 size 800mm x 2400mm class I teak timber solid door per the detail drawings with all necessary iron mongaries
B79: In Ground Floor | C79: 2 | D79: nr | E79: =21*6150 -> 129150 | F79: =+$I$1 -> 0.9 | G79: =ROUNDUP(E79/F79,-1) -> 143500 | H79: =C79*G79 -> 287000
B80: In First floor | C80: 3 | D80: nr | E80: =21*6150 -> 129150 | F80: =+$I$1 -> 0.9 | G80: =ROUNDUP(E80/F80,-1) -> 143500 | H80: =C80*G80 -> 430500
B81: In Second Floor | C81: 2 | D81: nr | E81: =21*6150 -> 129150 | F81: =+$I$1 -> 0.9 | G81: =ROUNDUP(E81/F81,-1) -> 143500 | H81: =C81*G81 -> 287000
A83: =A78+0.01 -> 2.06 | B83: Door type D6 size 2200mm x 2700mm class I teak timber solid door per the detail drawings with all necessary iron mongaries
B84: In Ground Floor | C84: 1 | D84: nr | E84: =64*6150 -> 393600 | F84: =+$I$1 -> 0.9 | G84: =ROUNDUP(E84/F84,-1) -> 437340 | H84: =C84*G84 -> 437340
B85: In First floor | C85: 1 | D85: nr | E85: =64*6150 -> 393600 | F85: =+$I$1 -> 0.9 | G85: =ROUNDUP(E85/F85,-1) -> 437340 | H85: =C85*G85 -> 437340
B86: In Second Floor | C86: 1 | D86: nr | E86: =64*6150 -> 393600 | F86: =+$I$1 -> 0.9 | G86: =ROUNDUP(E86/F86,-1) -> 437340 | H86: =C86*G86 -> 437340
A88: =A83+0.01 -> 2.07 | B88: Door type FD1 size 2200mm x 2700mm class I teak timber solid folding door per the detail drawings with all necessary iron mongaries
B89: In First floor | C89: 1 | D89: nr | E89: =64*6150 -> 393600 | F89: =+$I$1 -> 0.9 | G89: =ROUNDUP(E89/F89,-1) -> 437340 | H89: =C89*G89 -> 437340
A91: =A88+0.01 -> 2.08 | B91: Door type FD2 size 4300mm x 2700mm class I teak timber solid folding door per the detail drawings with all necessary iron mongaries
B92: In Second Floor | C92: 1 | D92: nr | E92: =125*6150 -> 768750 | F92: =+$I$1 -> 0.9 | G92: =ROUNDUP(E92/F92,-1) -> 854170 | H92: =C92*G92 -> 854170
A94: 3 | B94: Windows
A96: =A94+0.01 -> 3.01 | B96: Window type W1 size 1650mm x 1800mm class I teak timber Framed Glazed window per the detail drawings with all necessary iron mongaries
B97: In Ground Floor | C97: 2 | D97: nr | E97: =32*2150 -> 68800 | F97: =+$I$1 -> 0.9 | G97: =ROUNDUP(E97/F97,-1) -> 76450 | H97: =C97*G97 -> 152900
A100: =A96+0.01 -> 3.02 | B100: Window type FG1 , size 1775mmX2700mm class I teak timber framed tempored fixed glaed complete with all necessary ironmongeries and complete as per thedetail drawings.
B101: In Ground Floor | C101: 2 | D101: nr | E101: =52*2150 -> 111800 | F101: =+$I$1 -> 0.9 | G101: =ROUNDUP(E101/F101,-1) -> 124230 | H101: =C101*G101 -> 248460
A102: =A100+0.01 -> 3.03 | B102: Window type FG2 , size 3300mmX2700mm class I teak timber framed tempored fixed glaed complete with all necessary ironmongeries and complete as per thedetail drawings.
B103: In Ground Floor | C103: 1 | D103: nr | E103: =96*2150 -> 206400 | F103: =+$I$1 -> 0.9 | G103: =ROUNDUP(E103/F103,-1) -> 229340 | H103: =C103*G103 -> 229340
A105: =A102+0.01 -> 3.04 | B105: Window type FG3 , size 4040mmX2700mm class I teak timber framed tempored fixed glaed complete with all necessary ironmongeries and complete as per thedetail drawings.
B106: In First floor | C106: 2 | D106: nr | E106: =96*2150 -> 206400 | F106: =+$I$1 -> 0.9 | G106: =ROUNDUP(E106/F106,-1) -> 229340 | H106: =C106*G106 -> 458680
B107: In Second Floor | C107: 2 | D107: nr | E107: =96*2150 -> 206400 | F107: =+$I$1 -> 0.9 | G107: =ROUNDUP(E107/F107,-1) -> 229340 | H107: =C107*G107 -> 458680
A109: =A105+0.01 -> 3.05 | B109: Window type FG4 , size 2000mmX2700mm class I teak timber framed tempored fixed glaed complete with all necessary ironmongeries and complete as per thedetail drawings.
B110: In First floor | C110: 1 | D110: nr | E110: =58*2150 -> 124700 | F110: =+$I$1 -> 0.9 | G110: =ROUNDUP(E110/F110,-1) -> 138560 | H110: =C110*G110 -> 138560
B111: In Second Floor | C111: 1 | D111: nr | E111: =58*2150 -> 124700 | F111: =+$I$1 -> 0.9 | G111: =ROUNDUP(E111/F111,-1) -> 138560 | H111: =C111*G111 -> 138560
A113: =A109+0.01 -> 3.06 | B113: Window type FG5 , size 2925mmX2400mm tempored fixed glaed complete with all necessary ironmongeries and complete as per thedetail drawings.
B114: In Second Floor | D114: nr
A116: =A113+0.01 -> 3.07 | B116: Window type FG6 , size 2175mmX2400mm tempored fixed glaed complete with all necessary ironmongeries and complete as per thedetail drawings.
B117: In Second Floor | D117: nr
A119: =A116+0.01 -> 3.08 | B119: Window type FG7 , size 3800mmX2400mm tempored fixed glaed complete with all necessary ironmongeries and complete as per thedetail drawings.
B120: In Ground Floor | D120: nr
B121: In First floor | D121: nr
A123: =A109+0.01 -> 3.06 | B123: Window type FG5 , size 800mmX2700mm class I teak timber framed tempored fixed glaed complete with all necessary ironmongeries and complete as per thedetail drawings.
B124: In First floor | C124: 1 | D124: nr | E124: =23.2*2150 -> 49880 | F124: =+$I$1 -> 0.9 | G124: =ROUNDUP(E124/F124,-1) -> 55430 | H124: =C124*G124 -> 55430
A126: =A123+0.01 -> 3.07 | B126: Window type SL1 , size 2900mmX2700mm class I teak timber framed glazed sliding window complete with all necessary ironmongeries and complete as per thedetail drawings.
B127: In Ground Floor | C127: 1 | D127: nr | E127: =84*2150 -> 180600 | F127: =+$I$1 -> 0.9 | G127: =ROUNDUP(E127/F127,-1) -> 200670 | H127: =C127*G127 -> 200670
A129: =A126+0.01 -> 3.08 | B129: Window type SL2 , size 4400mmX2700mm class I teak timber framed glazed sliding window complete with all necessary ironmongeries and complete as per thedetail drawings.
B130: In First floor | C130: 1 | D130: nr | E130: =130*2150 -> 279500 | F130: =+$I$1 -> 0.9 | G130: =ROUNDUP(E130/F130,-1) -> 310560 | H130: =C130*G130 -> 310560
A132: =A129+0.01 -> 3.09 | B132: Window type SL3 , size 4875mmX2700mm class I teak timber framed glazed sliding window complete with all necessary ironmongeries and complete as per thedetail drawings.
B133: In Second Floor | C133: 1 | D133: nr | E133: =141*2150 -> 303150 | F133: =+$I$1 -> 0.9 | G133: =ROUNDUP(E133/F133,-1) -> 336840 | H133: =C133*G133 -> 336840
A135: =A132+0.01 -> 3.1 | B135: Window type SL4 , size 4100mmX2700mm class I teak timber framed glazed sliding window complete with all necessary ironmongeries and complete as per thedetail drawings.
B136: In Ground Floor | C136: 1 | D136: nr | E136: =120*2150 -> 258000 | F136: =+$I$1 -> 0.9 | G136: =ROUNDUP(E136/F136,-1) -> 286670 | H136: =C136*G136 -> 286670
A138: =A135+0.01 -> 3.11 | B138: Window type SL5 , size 2000mmX2700mm class I teak timber framed glazed sliding window complete with all necessary ironmongeries and complete as per thedetail drawings.
B139: In First floor | C139: 1 | D139: nr | E139: =58*2150 -> 124700 | F139: =+$I$1 -> 0.9 | G139: =ROUNDUP(E139/F139,-1) -> 138560 | H139: =C139*G139 -> 138560
B140: In Second Floor | C140: 1 | D140: nr | E140: =58*2150 -> 124700 | F140: =+$I$1 -> 0.9 | G140: =ROUNDUP(E140/F140,-1) -> 138560 | H140: =C140*G140 -> 138560
A142: =A138+0.01 -> 3.12 | B142: Window type SL6 , size 3375mmX2700mm class I teak timber framed glazed sliding window complete with all necessary ironmongeries and complete as per thedetail drawings.
B143: In Second Floor | C143: 2 | D143: nr | E143: =98*2150 -> 210700 | F143: =+$I$1 -> 0.9 | G143: =ROUNDUP(E143/F143,-1) -> 234120 | H143: =C143*G143 -> 468240
A145: =A142+0.01 -> 3.13 | B145: Window type SL7 , size 1700mmX2700mm class I teak timber framed glazed sliding window complete with all necessary ironmongeries and complete as per thedetail drawings.
B146: In Ground Floor | C146: 1 | D146: nr | E146: =50*2150 -> 107500 | F146: =+$I$1 -> 0.9 | G146: =ROUNDUP(E146/F146,-1) -> 119450 | H146: =C146*G146 -> 119450
A148: =A142+0.01 -> 3.13 | B148: Fanlight type FL1 , size 1500mmX1500mm high overall size class I teak timber framed glased anlight, complete with all necessary ironmongeries.
B149: In Ground Floor | C149: 2 | D149: nr | E149: =25*2150 -> 53750 | F149: =+$I$1 -> 0.9 | G149: =ROUNDUP(E149/F149,-1) -> 59730 | H149: =C149*G149 -> 119460
B150: In First floor | C150: 3 | D150: nr | E150: =25*2150 -> 53750 | F150: =+$I$1 -> 0.9 | G150: =ROUNDUP(E150/F150,-1) -> 59730 | H150: =C150*G150 -> 179190
B151: In Second Floor | C151: 2 | D151: nr | E151: =25*2150 -> 53750 | F151: =+$I$1 -> 0.9 | G151: =ROUNDUP(E151/F151,-1) -> 59730 | H151: =C151*G151 -> 119460
A152: =#REF!+0.01 -> #REF! | B152: RD- Supplying and fixing of Roller door with Mortor, size is 3900mmx2800mm
B153: In Ground Floor | D153: nr
...

Sheet roof
A1: Item | B1: Description | C1: Qty | D1: Unit | E1: Cost | F1: OH & P% | G1: Rate ( Rs.) | H1: Amount ( Rs.) | I1: =+summary!D17 -> 0.85
A2: 1 | B2: Q - ROOFING AND CEILING
A4: =A2+0.01 -> 1.01 | B4: Supplying fabrication and erection of roof, rate to include to roof structure, roof plumbing work and roof covering work and finished as per the detail drawings and design | C4: ='m shet rolf'!N337 -> 229 | D4: Sqm | E4: =+[21]RBD!$F$196 -> 14720 | F4: =+I1 -> 0.85 | G4: =ROUNDUP(E4/F4,-1) -> 17320 | H4: =C4*G4 -> 3966280
B7: ROOFING AND CEILING WORK CARRIED TO COLLECTION | H7: =SUM(H4:H6) -> 3966280

Sheet Ps
A1: Nos | B1: Description | C1: Qty | D1: Unit | E1: Cost | F1: OH & P% | G1: Rate ( Rs.) | H1: Amount
B2: BILL NO. 03
A3: 1 | B3: O - PROVISIONAL SUM
B4: Note:
B5: Figurs will be changed as per the MEP Engineers Specifications and Final Drawings
A7: =A3+0.01 -> 1.01 | B7: Allow Sum for Steel Staircases | D7: Pro. Sum | E7: 1500000 | H7: =E7 -> 1500000
B9: V - PROVISIONAL SUM CARRIED TO GRAND SUMMARY | H9: =SUM(H6:H8) -> 1500000
N11: =#REF!*1.1 -> #REF! | O11: 165000
H16: =100*272 -> 27200 | O16: =SUM(O10:O15) -> 165000
H17: =H16*0.6 -> 16320
H18: =H17*2 -> 32640
H19: =H18*18500 -> 603840000
H20: =H19*1.15 -> 694416000 | O20: =O16*1.1 -> 181500 | Q20: =O20-O16 -> 16500
Q21: =#REF!-O16 -> #REF!

Sheet Material
A2: BUILDING SCHEDULE OF RATES
A4: PRICES OF MATERIAL & TOOLS
K5: 719041540
A6: Item | B6: Description | C6: Unit | D6: Rate without Transport | E6: Rate with Transport | F6: Remarks | G6: Transporting Price
B8: Materials | L8: Lanwa | M8: 2100 | N8: 1920
L9: Ultratech | M9: 2200 | N9: 2050
B10: Cement ( 50 Kg ) | C10: Bags | D10: 2170 | G10: =E10-D10 -> -2170 | L10: tokyo santha | M10: 2200 | N10: 2050
G11: =E11-D11 -> 0
B12: Sand
B13: River Sand | C13: Cube | E13: 23000 | G13: =E13-D13 -> 23000 | H13: 1080 | I13: 800 | L13: 10mm | M13: 1274
B14: Sea Sand | C14: Cube | G14: =E14-D14 -> 0
B15: Wash Sand | C15: Cube | G15: =E15-D15 -> 0
M16: 6mm | N16: 10mm | O16: 12mm | P16: 16mm | Q16: 20mm | S16: =16*16 -> 256 | T16: =S16/162.162 -> 1.5786682
B17: 3/4" Metal | C17: Cube | E17: 13500 | N17: 1274 | O17: 1879 | P17: 3370
B18: 1" Metal | C18: Cube
B20: 6" x 9" Rubble | C20: Cube | E20: 14500 | L20: Binding wire | M20: 380
B21: 6" x 4" Rubble | C21: Cube
M22: 150 | N22: 17400
B23: Imported Soil | C23: Cube | E23: 7500
B24: Quarry Dust | C24: Cube
B25: ABC | C25: Cube
B28: Reinforcement | S28: =20*20 -> 400 | T28: =S28/162.162 -> 2.4666691
B29: Tor Steel | L29: Lanwa | N29: 1285 | O29: 1895 | P29: 3397 | Q29: 5374
B30: Lanwa | C30: Ton | D30: 365000 | K30: =363059.05*1.15 -> 417517.91 | L30: 363059.05
B31: Melwa | C31: Ton
B32: GTB | C32: Ton | N32: 0.617 | O32: 0.888 | P32: 1.579 | Q32: 2.467
B33: RS | C33: Ton | N33: =N32*6 -> 3.702 | O33: =O32*6 -> 5.328 | P33: =P32*6 -> 9.474 | Q33: =Q32*6 -> 14.802
N35: =N29/N33 -> 347.10967 | O35: =O29/O33 -> 355.66817 | P35: =P29/P33 -> 358.56027 | Q35: =Q29/Q33 -> 363.05905
B36: 16 BWG Binding Wire | C36: Lbs | D36: 380
B39: Water Proofing | C39: Gals | E39: 10
B40: Bitumix ( 20L ) | C40: Ltr | E40: 650
B41: Finex Motar Plus (Plasticiser) | C41: Ltr | E41: =300*1.15 -> 345 | L41: 10 Litre - Rs.2350 +VAT | M41: =2350*1.15 -> 2702.5
M42: =M41/10 -> 270.25
B44: BRICKS
B46: Engineering Brick 200mm x 100mm x 50mm
B47: Engineering Brick 200mm x 150mm x 75mm (6") thk.
B50: BLOCKS
B51: Solid Block 390 x 190 x 100mm | C51: nr
B52: Solid Block 390 x 190 x 150mm | C52: nr
B53: Solid Block 390 x 190 x 120mm | C53: nr
B55: Hollow Block 390 x 190 x 100mm | C55: nr
B56: Hollow Block 390 x 190 x 150mm | C56: nr
B57: Hollow Block 390 x 190 x 120mm | C57: nr
B59: Skim Coat
B60: Sand Papers
B61: Chiken mesh ( 1 x 3.33 ) | C61: L.ft | E61: 230 | L61: =12*7 -> 84
B62: 50 x 50 GI Mesh | C62: ft²
B63: Gauge 1000 polythene | C63: Kg | E63: 750
B65: BRC mesh (12'x7')
B66: 2"x2" | C66: item | D66: 6500 | E66: 7500 | K66: 84ft2
B67: 6"x6" | C67: item | D67: 10500 | E67: 11500
B68: 8"x8" | C68: item | D68: 8500 | E68: 9500
M69: Supreme Readymix | N69: Tokyo | O69: Prema
B70: Redy Mix Concrete | L70: G.15
L71: G.20
B72: G15
B73: G20
B74: G25 | L74: G.25
B75: Pump Car (25m3) Additional 1m3 - Rs.1500 | L75: G.30
E77: 45000 | F77: 15000
B78: Plywood Board
B79: 15mm thk 8'x4' non-coated Plywood board | C79: Nrs | E79: 4500
B80: 15mm thk 8'x4' coated Plywood board | C80: Nrs
B81: 16mm thk 8'x4' coated Plywood board | C81: Nrs | E81: 5500
B83: Mould oil | C83: Ltrs | E83: 100
B85: Class I timber
B86: 1" Class I timber planks | C86: Sq.ft | E86: 172
B87: 1" timber base plate to props | C87: Sq.ft | E87: 150
B88: 1 1/2" Class I planks | C88: Sq.ft
B89: 1" Class II timber | C89: Sq.ft | E89: 140
B90: 6"x3/4" Lunumidella Ceiling planks | C90: Sq.ft
B91: 2"x1" Class I reepers | C91: L.ft
B92: 2"x2" Class I timber | C92: L.ft | E92: 55
B93: 4"x2" Class I timber | C93: L.ft | E93: 85
B94: 4"x3" Class I timber | C94: L.ft
B95: 2"x2" Class II timber in yokes | C95: L.ft | E95: 50
B96: 2"x1" Class II timber batterns | C96: L.ft | E96: 30
B97: 2"x2" Class II Ledges | C97: L.ft | E97: 50
B98: 4"x2" Class II bearers | C98: L.ft | E98: 85
B99: 4"x2" Class II timber props | C99: L.ft | E99: 85
B100: 2"x2" Halmilla cove moulding | C100: L.ft
B101: 1 1/2"x1 1/2" Halmilla beading | C101: L.ft
B102: Props | C102: Nrs | E102: 200
B104: Brick
B106: Wirecut Bricks | C106: Nrs
B107: Brick Size 212.5mm x 100mm x 50mm ( 9" ) | C107: Nrs | E107: 18 | F107: Hashan (Wellawaya Brick Supplier) | K107: 13
B108: Brick Size 212.5mm x 150mm x 75mm ( 6" ) | C108: Nrs | E108: 30 | K108: 30
G109: =E109-D109 -> 0 | T109: with loading & unloading (AMTRAD limited prices)
B110: Bloock | G110: =E110-D110 -> 0 | L110: Size | N110: Amtrad | O110: Wapco | P110: Sachindra
B111: 390x190x100mm Solid block | C111: Nr | G111: =E111-D111 -> 0 | L111: 390x190x100mm Solid block | N111: 156
B112: 390x190x150mm Solid block | C112: Nr | G112: =E112-D112 -> 0 | L112: 390x190x150mm Solid block | N112: 240
B113: 390x190x150mm Solid block | C113: Nr | G113: =E113-D113 -> 0 | L113: 390x190x150mm Solid block | N113: 305
L114: 390x190x150mm Hollow block
B115: 390x190x150mm Hollow block | C115: Nr
B116: 390x190x150mm Hollow block | C116: Nr | G116: =E116-D116 -> 0 | L116: 390x190x150mm Hollow block
B117: 390x190x150mm Hollow block | C117: Nr | G117: =E117-D117 -> 0 | L117: 390x190x150mm Hollow block
B119: Tile
B120: 2x2 Glazed Floor tile | C120: Nrs
B121: 3x3 Glazed Floor tile | C121: Nrs
B122: 4x4 Glazed Floor tile | C122: Nrs
...

Sheet Rate Breakdowns
A2: EXCAVATION & EARTH WORK
A4: Site Clearing & Removing top soil
A5: Per 1 Sqr
B6: Decription | C6: Unit | D6: Qty | E6: Rate | F6: Amount | G6: Total
B8: Labour | F8: =D8*E8 -> 0
B9: Un/Skilled | C9: Sqr | D9: 10 | E9: 2500 | F9: =D9*E9 -> 25000
B11: Total Labour Cost | F11: =D11*E11 -> 0 | G11: =SUM(F9:F11) -> 25000
A15: Basic Cost per 10 Sqr | G15: =G11 -> 25000
A16: Basic Cost per 1 sqr | G16: =G15/10 -> 2500
A17: Basic Cost per 1m2 | G17: =G16/9.29 -> 269.10657
A20: Excavation for foundations depth not exceeding 1.5m (Manual Excavation)
A21: Per 1 Cube
B22: Decription | C22: Unit | D22: Qty | E22: Rate | F22: Amount | G22: Total
B24: Labour | F24: =D24*E24 -> 0
B25: Sub Contractor's Rate | C25: Cube | D25: 1 | E25: 6000 | F25: =D25*E25 -> 6000
B27: Total Labour Cost | F27: =D27*E27 -> 0 | G27: =SUM(F25:F27) -> 6000
A31: Basic Cost per 1 Cube | G31: =G27 -> 6000
A32: Basic Cost per 1 m3 | G32: =G31/2.83 -> 2120.1413
A35: Earth Filling (Excavated material)
A36: Per 1 Cube
B37: Decription | C37: Unit | D37: Qty | E37: Rate | F37: Amount | G37: Total
B38: Consider 12 Cubes
B40: Material
F41: =D41*E41 -> 0
F42: =D42*E42 -> 0
B43: Total Material Cost | F43: =D43*E43 -> 0 | G43: =SUM(F40:F43) -> 0
B44: Labour
B45: Un/Skilled Labour for levelling & Compaction | C45: Days | D45: 4 | E45: 2500
B46: Sub contractor's rate for earth filling | C46: Cube | D46: 1 | E46: 4500 | F46: =D46*E46 -> 4500
B48: Total Labour Cost | F48: =D48*E48 -> 0 | G48: =SUM(F45:F48) -> 4500
B49: Plant & Machinery
B51: Jumping Compactor | C51: hr | D51: 24 | E51: 625 | F51: =D51*E51 -> 15000
B53: Total Plant & Machinery Cost | F53: =D53*E53 -> 0 | G53: =SUM(F50:F53) -> 15000
A56: Basic Cost per 12 Cube | G56: =G43+G48+G53 -> 19500
A57: Basic Cost per 1 Cube | G57: =G56/12 -> 1625
A58: Basic Cost per 1 m3 | G58: =G57/2.83 -> 574.20495
A64: Imported Soil Filling
A65: Per 1 Cube
B66: Decription | C66: Unit | D66: Qty | E66: Rate | F66: Amount | G66: Total
B67: Consider 12 Cubes
B69: Material
B70: Cost of Imported Soil Transport to Site | C70: Cube | D70: 12 | E70: =Material!E23 -> 7500 | F70: =D70*E70 -> 90000
B71: 35% of Additional Soil for Compaction | F71: =F70*35% -> 31500
F72: =D72*E72 -> 0
F73: =D73*E73 -> 0
B74: Total Material Cost | F74: =D74*E74 -> 0 | G74: =SUM(F69:F74) -> 121500
B75: Labour | F75: =D75*E75 -> 0
B76: Un/Skilled Labour for levelling & Compaction | C76: Days | D76: 3 | E76: 2500
F77: =D77*E77 -> 0
B78: Sub contractor's rate for earth filling | C78: Cube | D78: 1 | E78: 4500 | F78: =D78*E78 -> 4500
B80: Total Labour Cost | F80: =D80*E80 -> 0 | G80: =SUM(F76:F80) -> 4500
B81: Plant & Machinery
B83: JCB with Operator | C83: hr | D83: 3 | E83: 7000 | F83: =D83*E83 -> 21000
B84: Jumping Compactor | C84: hr | D84: 24 | E84: 625 | F84: =D84*E84 -> 15000
B86: Total Plant & Machinery Cost | F86: =D86*E86 -> 0 | G86: =SUM(F82:F86) -> 36000
A89: Basic Cost per 12 Cube | G89: =G74+G80+G86 -> 162000
A90: Basic Cost per 1 Cube | G90: =G89/12 -> 13500
A91: Basic Cost per 1 m3 | G91: =G90/2.83 -> 4770.318
A95: Dam Proof Membrane ; Gauge 1000 Polythene
A96: Per 1 Sqr
B97: Decription | C97: Unit | D97: Qty | E97: Rate | F97: Amount | G97: Total
B99: Material
B100: Gauge 1000 polythene | C100: Kg | D100: 2.5 | E100: =Material!E63 -> 750 | F100: =D100*E100 -> 1875
F103: =D103*E103 -> 0
B104: Total Material Cost | F104: =D104*E104 -> 0 | G104: =SUM(F99:F104) -> 1875
B105: Labour | F105: =D105*E105 -> 0
B106: Laying | C106: ft2 | D106: 100 | E106: 5 | F106: =D106*E106 -> 500
B108: Total Labour Cost | F108: =D108*E108 -> 0 | G108: =SUM(F106:F108) -> 500
A111: Basic Cost per 1 Sqr | G111: =G104+G108 -> 2375
A112: Basic Cost per 1 m2 | G112: =G111/9.29 -> 255.65124
A113: Basic Cost per 1 ft2 | G113: =G112/10.76 -> 23.759409
A117: CONCRETE WORKS
A121: Cement Bag cost delivered to Site
B122: Decription | C122: Unit | D122: Qty | E122: Rate | F122: Amount
B124: Cement Bag (50kg) | C124: Bag | D124: 50 | E124: =Material!D10 -> 2170 | F124: =D124*E124 -> 108500
B125: Loading & Unloading Cost (1hr Un/Sk Labour per 1 Ton) | C125: hr | D125: 2.5 | E125: 312.5 | F125: =D125*E125 -> 781.25
B126: Transport Cost (Miximum 20km range) | C126: Turn | D126: 1 | E126: 5000 | F126: =D126*E126 -> 5000
A130: Total Cost per 50 Cement bags | F130: =SUM(F124:F129) -> 114281.25
A131: Total Cost per 1nr Cement bag delivered to Site | F131: =F130/50 -> 2285.625
A135: Grade 15 Insitu Concrete 1: 3 : 6
A136: Per 1 Cube
B137: Decription | C137: Unit | D137: Qty | E137: Rate | F137: Amount | G137: Total
B139: Material
B140: Cement Bag (50kg) | C140: Bag | D140: 13 | E140: =F131 -> 2285.625 | F140: =D140*E140 -> 29713.125
B141: Sand | C141: Cube | D141: 0.53 | E141: =Material!E13 -> 23000 | F141: =D141*E141 -> 12190
B142: 3/4"Metal | C142: Cube | D142: 0.92 | E142: =Material!E17 -> 13500 | F142: =D142*E142 -> 12420
F143: =D143*E143 -> 0
B144: Total Material Cost | F144: =D144*E144 -> 0 | G144: =SUM(F139:F144) -> 54323.125
B145: Labour | F145: =D145*E145 -> 0
B146: Sub Contractor's Rate | C146: Cube | D146: 1 | E146: 15000 | F146: =D146*E146 -> 15000
B148: Total Labour Cost | F148: =D148*E148 -> 0 | G148: =SUM(F146:F148) -> 15000
B149: Plant & Machinery
B151: Concrete Mixer | C151: Days | D151: 0.33 | E151: 5000 | F151: =D151*E151 -> 1650
B152: Poker Vibrator | C152: Days | D152: 0.33 | E152: 2000 | F152: =D152*E152 -> 660
B154: Total Plant & Machinery Cost | F154: =D154*E154 -> 0 | G154: =SUM(F150:F154) -> 2310
A157: Basic Cost per 1 Cube | G157: =G144+G148+G154 -> 71633.125
A158: Basic Cost per 1 m3 | G158: =G157/2.83 -> 25312.058
A163: Grade 20 Insitu Concrete 1: 2 : 4
A164: Per 1 Cube
B165: Decription | C165: Unit | D165: Qty | E165: Rate | F165: Amount | G165: Total
...

Sheet grnd summry- sign
A1: CONSTRUCTION OF PROPOSED SHOPPING COMPLEX WITH MULTI FUNCTIOANL HALL FOR DODANGODA PRADESHIYA SABHAWA
A2: MAIN SUMMARY
A3: BILL NO | B3: DESCRIPTION | C3: AMOUNT (Rs.) | D3: =C7+C9 -> 47150143
A5: Bill No. 01 | B5: PRELIMINARIES | C5: =prelims!I135 -> 318750 | D5: =C7+#REF!+#REF! -> #REF! | E5: =C5/D5*100 -> #REF! | F5: =C5/D3*100 -> 0.67603188
A7: Bill No. 02 | B7: MAIN BUILDING | C7: =summary!C19 -> 47150143 | D7: =60000000-C5 -> 59681250 | E7: =SUM(C7:C15) -> 1.4508793e+08
G8: =#REF!*8500 -> #REF!
A9: Bill No. 03 | B9: LABOUR WASHROOM | C9: =L.toilet!F236 -> 0 | D9: =C7-summary!#REF! -> #REF! | E9: =D9+C5 -> #REF!
B10: TOTAL PROJECT COST-CARRIED TO FORM OF BID | C10: ='grnd summry- tender'!C17 -> 48968893 | E10: =C10-summary!#REF!-'grnd summry- sign'!C9 -> #REF! | G10: =C10*0.95 -> 46520449 | H10: =C10/9000 -> 5440.9881
B12: Less : Discount (If any)
B14: SUB TOTAL-II | C14: =C10-C12 -> 48968893
B16: ADD- CONTINGENCIES- 10% | C16: ='grnd summry- tender'!C19 -> 0 | D16: =SUM(C7:C9) -> 47150143 | E16: =SUM(C10:C16) -> 97937786 | F16: =#REF!/9000 -> #REF! | G16: =9000*9100 -> 81900000
B17: SUB TOTAL II | C17: =#REF!+C10 -> #REF! | E17: =C5/C7*100 -> 0.67603188 | F17: =D7*3% -> 1790437.5 | G17: =C5/D7*100 -> 0.53408734 | I17: =D7*0.0486 -> 2900508.8 | J17: =C17-#REF! -> #REF!
B19: ADD 8% VAT | C19: ='grnd summry- tender'!C25 -> 7345334 | H19: =10000*2*12 -> 240000
E20: =C7+C5 -> 47468893 | J20: =#REF!/187 -> #REF!
B21: ='grnd summry- tender'!B27 -> TOTAL PROJECT COST WITH VAT | C21: ='grnd summry- tender'!C27 -> 56314227 | H21: =SUM(H19:H20) -> 240000
E22: =E20/9000 -> 5274.3215
D24: =C10+#REF!+C16+C19 -> #REF!
A28: ………………………….. ………………………….
A29: Quantitty Surveyor, Project Manager/Architect,
A30: C Plus Design (Pvt) Ltd. C Plus Design (Pvt) Ltd. | E30: =C10*3% -> 1469066.8
A39: ………………………….. ………………………….
A40: Technical Officer, Superintondon of Works,
A41: Dodangoda Pradeshiya Sabhawa. Dodangoda Pradeshiya Sabhawa.
A49: ………………………….. ………………………….
A50: Secretary, Chairman,
A51: Dodangoda Pradeshiya Sabhawa. Dodangoda Pradeshiya Sabhawa.
A60: …………………………..
A61: District Engineer.
A62: 60000000 | B62: 60000000 | C62: 60000000 | D62: =#REF!-A62 -> #REF!
B63: v bvbnbvnbn | C63: =A62*0.0144 -> 864000 | E63: =D62*1.44% -> #REF!
C64: =C10*1.44% -> 705152.06
B67: Prepare Schemetic design and detail drawings | C67: 0.23 | D67: =C67*C64 -> 162184.97 | E67: =C67*C63 -> 198720 | G67: =#REF!/9000 -> #REF!
B68: Prepare Building services detail drawings | C68: 0.18 | D68: =C68*C64 -> 126927.37 | E68: =C68*C63 -> 155520
B69: Prepare Structural detail drawings | C69: 0.22 | D69: =C69*C64 -> 155133.45 | E69: =C69*C63 -> 190080
B70: Prepare Cost Estimate | C70: 0.1 | D70: =C70*C64 -> 70515.206 | E70: =C70*C63 -> 86400 | F70: =SUM(D67:D70) -> 514761.01 | G70: =SUM(E67:E70) -> 630720 | H70: =F70-175000 -> 339761.01 | I70: =G70-175000 -> 455720
B71: Bidding document and procurement stage | C71: 0.12 | D71: =C71*C64 -> 84618.248 | E71: =C71*C63 -> 103680
B72: Bill checking | C72: 0.15 | D72: =C72*C64 -> 105772.81 | E72: =C72*C63 -> 129600
B75: site supervision | D75: =12*80500 -> 966000 | E75: =D75 -> 966000
B76: site visit | D76: =24*10000 -> 240000 | E76: =D76 -> 240000
D78: =SUM(D67:D76) -> 1911152.1 | E78: =SUM(E67:E76) -> 2070000

Sheet demolition
A1: Nos | B1: Description | C1: Qty | D1: Unit | E1: Rate | F1: Amount | G1: msheet
B2: 2A - DEMOLITIONS
B4: Valuble material arising from demolitions shall be the properly of the employer and shall be stacked in a place within the site premises as directed by the consultant or client and handed over with a proper way | C4: Note
B6: Debries from demolitions shall be cleared away from the site premises and cost for same should distribute among their rates. | C6: Note
B8: Rate shall include for necessary precaution for spreading dust to the adjoining building while demolition in progress | C8: Note
A10: 2A-1 | B10: Demolition of existing building. Rate to include removeing of total existing building with foundation and related work | C10: 1 | D10: Item | E10: 200000 | F10: =E10*C10 -> 200000
B12: DEMOLITIONS WORK CARRIED TO COLLECTION | F12: =SUM(F4:F11) -> 200000
D44: =600/10.76 -> 55.762082 | G44: =1000/50 -> 20
D45: =D44*0.05 -> 2.7881041 | G45: =50/1000 -> 0.05 | I45: =D45/2.83 -> 0.98519579
C48: cemnt | D48: =13*I45 -> 12.807545
C49: sand | D49: =0.53*I45 -> 0.52215377
C50: metal | D50: =0.92*I45 -> 0.90638013

Sheet concrete
A1: Nos | B1: Description | C1: Qty | D1: Unit | E1: Rate | F1: Amount
B2: C - CONCRETE
B3: Note:
B4: Rates for concrete are grouped under following categories
B6: 1. In-situ plain concrete (mixed at site either manually or with machine)
B8: 2. Reinforced concrete of Grade 20 &25 (mixed at site with a concrete mixer )
B10: These items are meant for Footings, Columns, Plinth beams, Floor beams, Tie-beams & Stair case. i.e. load bearing members. | O10: =F76+F246 -> #REF!
B12: 3. Ready mixed concrete of Grade 20 ,Grade 25 . Grade 30
B14: 4. Site produced concrete of Grade 20 - (machine mix or in case of small quantities manually mixed)
B16: These items are meant for pre-cast lintols, stiffeners, copings,concrete drains, etc.
B18: 5. Curing for In situ plain concrete, In situ reinforced concrete, Site produced concrete of Grade 20 & Ready mix concrete
B20: In - Situ Plain Concrete (mixed at site either manually or with machine)
B21: The Quality of the concrete should confirm to the relevant B.S., S.L.S. and ICTAD specification for Building works.
B22: UP TO DPC LEVEL
B23: In - Situ Plain Concrete (mixed at site either manually or with machine)
A25: C 01 | B25: Cement concrete 1:3:6 (1") laid to a thickness of 2" in wall foundations, under column/stair footings,plinth beams including placing in position,compacting and curing. | D25: Sqm | E25: =#REF! -> #REF! | F25: =+C25*E25 -> #REF!
B27: IN - SITU REINFORCED CONCRETE
B29: In - Situ Reinforced Concrete Of Grade 25 &30 (mixed at site with a concrete mixer )
B31: Grade 25 concrete shall be used for footings, columns, beams,staircases, tie-beams of reinforced concrete elements in multi-storied building (excluding lintols, stiffener columns, copings, non-structural columns and Drains).
B32: Constituent material shall comply to following;
B34: (i) Cement of strength class 42.5N and shall comply with SLS 107 (Ordinary Portland Cement) & SLS 1253 (Portland Limestone Cement) , that has been stored under proper conditions and has manufactured within 90 days at the time of concreting.
B36: (iii) Clean river sand without impurities and clay particles of grain distribution falling within the prescribed grading limit in BS 882:1992.
B38: iv) Well graded coarse aggregate free of impurities with maximum aggregate size being 20mm. grain distribution falling within the prescribed grading limit in BS 882:1992.
B40: (v) Clean portable water
B42: Volume batching of constituent material (a) The equivalent nominal mix suggest for volume batching the Grade 25 & 30 concrete is given in table 4.4 of ICTAD specification for Building Work SCA/4/I of July 2004 for a 50kg cement bag and measuring boxes is reproduced below.
B44: Coarse aggregate to be proportioned for the volume batching using the measurement boxes as indicated in the Clause 4.3.1 ICTAD/SCA/4/I. The internal dimensions of the boxes are 400 x 350 x 250mm (which is 0.035m3 and corresponds to the volume of 1 bag of cement weighing 50 kg). The proportioning of sand shall be on the basis of its dry volume and in the case of damp sand allowance for bulkage shall be made as given in Appendix 4C of ICTAD specification.
B46: Water:Cement ratio shall not exceed 0.45. Based on this Water:Cement ratio, volume of water required (either weight or converted volume of water) shall be decided for a given cement content. Required water content shall then be added by measuring the volume from a calibrated measuring Jar.
B48: Cement shall be added in bag form.
... B71: (b).Quality assurance report signed by the contractor’s technical officer or agent, Divisional Engineer’s technical officer who has witnessed the concreting along with senior technical officer in charge of the site.
A75: C 02 | B75: Volume Batched Grade 25 concrete prepared at site using mixer and vibrator in ground floor.Rate shall include the cost of curing continously for 7 days. Upto DPC
A76: C2.1 | B76: In column/strip footing | D76: m3 | E76: =#REF! -> #REF! | F76: =C76*E76 -> #REF! | K76: =+C76/2.83 -> 0 | L76: 4.8975265
A77: C2.2 | B77: In column shaft | D77: m3 | E77: =E76 -> #REF! | F77: =C77*E77 -> #REF! | K77: =+C77/2.83 -> 0 | L77: 0.6254417
A78: C2.3 | B78: In plinth Beams | D78: m3 | E78: =E77 -> #REF! | F78: =C78*E78 -> #REF! | K78: =+C78/2.83 -> 0 | L78: 6.229682
A79: C2.4 | B79: In staircases | D79: m3 | E79: =E78 -> #REF! | F79: =C79*E79 -> #REF! | K79: =+C79/2.83 -> 0 | L79: 0.37809187
A80: C2.5 | B80: In Lift base and lift wall | D80: m3 | E80: =E79 -> #REF! | F80: =C80*E80 -> #REF!
A82: C 03 | B82: Volume Batched Grade 20/ready mix reinforced concrete floors laid on ground. Rate shall include the cost of curing continously for 10 days. ( rate include to transport from batching plant. Rate shall inclue for placing, levelling, vibrating & curing the concrete & pump car cost) | K82: =18.76/2.83 -> 6.6289753
A83: C3.1 | B83: Ground floor concrete(75mm thick) | D83: m3 | E83: =#REF! -> #REF! | F83: =+C83*E83 -> #REF! | K83: 2.5 | L83: =+K83/2.83 -> 0.88339223 | M83: =E83/2.83 -> #REF! | N83: =17435*2.83+1100+384 -> 50825.05
B85: SUPER STRUCTURE
A87: C3.5 | B87: Volume Batched Grade 20 concrete prepared at site using mixer and vibrator for reinforced cast in situ lintols, copings, stiffeners and drains and pantry slab, kitchen vanity slab
A88: C3.5.1 | B88: Ground Floor | D88: m3 | E88: =E83 -> #REF! | F88: =E88*C88 -> #REF!
A89: C3.5.2 | B89: First Floor | D89: m3 | E89: =E88*1.05 -> #REF! | F89: =E89*C89 -> #REF!
A90: C3.5.3 | B90: Second Floor | D90: m3 | E90: =E89*1.05 -> #REF! | F90: =E90*C90 -> #REF!
A91: C3.5.4 | B91: Third Floor | D91: m3 | E91: =E90*1.05 -> #REF! | F91: =E91*C91 -> #REF!
A92: C3.5.5 | B92: Fouth Floor | D92: m3 | E92: =E91*1.05 -> #REF! | F92: =E92*C92 -> #REF!
A94: C 04 | B94: Volume Batched Grade 25 concrete prepared at site using mixer or Grade 25 ready mix( rate include to transport from batching plant. Rate shall inclue for placing, levelling, vibrating & curing the concrete & pump car cost) and vibrator in ground floor. Rate shall include the cost of curing continously for 7 days.
A95: C4.1 | B95: In column shaft from ground floor level to First floor level | D95: m3 | E95: =E80 -> #REF! | F95: =C95*E95 -> #REF! | K95: =E97-E95 -> #REF! | M95: =6*1.1*0.3 -> 1.98
A97: C4.2 | B97: In column shaft from First floor level to Second floor level | D97: m3 | E97: =E95*1.05 -> #REF! | F97: =C97*E97 -> #REF! | K97: =E99-E97 -> #REF!
A99: C4.3 | B99: In column shaft from Second floor level to third floor level | D99: m3 | E99: =E97*1.05 -> #REF! | F99: =C99*E99 -> #REF! | Q99: =24*0.225*0.225*3 -> 3.645
A100: C4.3 | B100: In column shaft from third floor level to fouth floor level | D100: m3 | E100: =E99*1.05 -> #REF! | F100: =C100*E100 -> #REF!
A102: C4.4 | B102: In staircase from ground floor level to First floor level | D102: m3 | E102: =E95 -> #REF!
A103: C4.5 | B103: In staircase First floor level to Second floor level | D103: m3 | E103: =E97 -> #REF!
A104: C4.5 | B104: In staircase Second floor level to third floor level | D104: m3 | E104: =E99 -> #REF!
A105: C4.5 | B105: In staircase fouth floor level to roof floor level | D105: m3 | E105: =#REF! -> #REF!
A108: C4.6 | B108: In Lift wall from ground floor level to First floor level | D108: m3 | E108: =E95 -> #REF!
A109: C4.7 | B109: In Lift wall from First floor level to Second floor level | D109: m3 | E109: =E97 -> #REF!
A110: C4.8 | B110: In Lift wall From Second floor level to roof level | D110: m3 | E110: =E99 -> #REF!
B112: READY MIX CONCRETE
B113: Requirement for Ready mixed concrete
B114: (i) Ready mix concrete is confirming to SLS 1144-1997.
B115: (ii) Minimum cement content shall be 300 kg/m3
B116: (iii) Nominal maximum size of aggregate shall be 20mm.
B117: (iv) Slump shall be as per the mix design.
B118: (v) Maximum temperature 30 Celsius
B119: (vi) Maximum free water / cement ratio to be 0.5
B120: (vii) Coarse and Fine aggregate used shall confirm to BS 882 latest version. Seive analysis reports within 6 months should be submitted for approval .
B121: (viii) Concrete grade shall be as specified.
B122: (ix) Concrete mix design shall be approved by the Engineer
B123: (x) The Ready mix supplier's plant should have been calibrated in the recent past.
... B127: Rate to include the transport from batching plant.
A129: C 05 | B129: Ready mix concrete of grade 25(25 N/mm2) confirming to SLS 1144- 1997, rate include to transport from batching plant. Rate shall inclue for placing, levelling, vibrating & curing the concrete & pump car cost | K129: 15675 | L129: 346 | M129: 898 | O129: =32294/30 -> 1076.4667
A130: C5.3 | B130: In Reinforced beam at First floor level | D130: Cu.m | E130: =#REF! -> #REF! | F130: =C130*E130 -> #REF! | K130: =+C130+C136+#REF! -> #REF! | L130: =+K130*E129+K130*500+21750+725*20.44 -> #REF! | M130: =236.65*5.25 -> 1242.4125 | N130: =SUM(L130:M130) -> #REF! | O130: =+N130/K130 -> #REF!
A131: C5.4 | B131: In Reinforced beam at second floor level | D131: Cu.m | E131: =E130*1.03 -> #REF! | F131: =C131*E131 -> #REF! | K131: =+C131+C137+#REF! -> #REF! | L131: =+K131*E129+K131*500+21750+725*18.94 -> #REF! | M131: =236.65*5.25 -> 1242.4125 | N131: =SUM(L131:M131) -> #REF! | O131: =+N131/K131 -> #REF! | P131: =10.7+5.9 -> 16.6 | Q131: =P131*0.55*0.3 -> 2.739
A132: C5.5 | B132: In Reinforced beam at Third floor level | D132: Cu.m | E132: =E131*1.03 -> #REF! | F132: =C132*E132 -> #REF! | G132: ='m shet rolf'!F1022 -> 158
A133: C5.6 | B133: In Reinforced beam at roof floor level | D133: Cu.m | E133: =E132*1.03 -> #REF! | F133: =C133*E133 -> #REF! | G133: =C130/G132*60 -> 0
A134: C5.8 | B134: In Reinforced beam at water tank level | D134: Cu.m | E134: =#REF!*1.03 -> #REF!
A136: C5.6 | B136: In Reinforced slab at First floor level | D136: Cu.m | E136: =E130 -> #REF! | F136: =C136*E136 -> #REF! | K136: =SUM(K130:K131) -> #REF!
A137: C5.7 | B137: In Reinforced Slab at second floor level | D137: Cu.m | E137: =E131 -> #REF! | F137: =C137*E137 -> #REF!
A138: C5.8 | B138: In Reinforced slab at Third floor level | D138: Cu.m | E138: =E132 -> #REF! | F138: =C138*E138 -> #REF! | M138: =C136/170*92 -> 0
A139: C5.9 | B139: In Reinforced slab at Water tank floor level | D139: Cu.m | E139: =E133 -> #REF! | F139: =C139*E139 -> #REF!
A140: C5.11 | B140: In Reinforced slab at water tank level | D140: Cu.m | E140: =E134 -> #REF! | L140: =SUM(C130:C140) -> 0
L141: =L140/5 -> 0
A142: C5.9 | B142: Curing of Concrete slabs with ponding water or covering with polythene sheets and continuous wetting for 14 days.
B143: First Floor Slab | D143: Sq.ft | F143: =C143*E143 -> 0
B144: Second Floor Slab | D144: Sq.ft | F144: =C144*E144 -> 0
B145: Roof Slab | D145: Sq.ft | F145: =C145*E145 -> 0
A147: C6 | B147: Concrete Lintols
B149: 225mmX150mm Lintol
A150: C6.01 | B150: Lintols size 9" x 6" deep in Grade 20 concrete, reinforced with 2 nos of 10mm dia. tor steel bars and 6mm mild steel stirrups @ 6" c/c including necessary formwork in ground floor. | D150: L.ft | F150: =E150*C150 -> 0
A152: C6.02 | B152: Lintols size 9" x 6" deep in Grade 20 concrete, reinforced with 2 nos of 10mm dia. tor steel bars and 6mm mild steel stirrups @ 6" c/c including necessary formwork in first floor. | D152: L.ft | F152: =E152*C152 -> 0
A154: C6.03 | B154: Lintols size 9" x 6" deep in Grade 20 concrete, reinforced with 2 os of 10mm dia. tor steel bars and 6mm mild steel stirrups @ 6" c/c including necessary formwork in second floor. | D154: L.ft | F154: =E154*C154 -> 0
B156: 100mmX150mm Lintols
A157: C6.04 | B157: Lintols size 4 1/2" x 6" deep in Grade 20 concrete, reinforced with 2 nos of 10mm dia. tor steel bars and 6mm mild steel stirrups @ 6" c/c including necessary formwork in ground floor. | D157: L.ft | F157: =E157*C157 -> 0
A159: C6.05 | B159: Lintols size 4 1/2" x 6" deep in Grade 20 concrete, reinforced with 2 nos of 10mm dia. tor steel bars and 6mm mild steel stirrups @ 6" c/c including necessary formwork in first floor. | D159: L.ft. | F159: =E159*C159 -> 0
A161: C6.06 | B161: Lintols size 4 1/2" x 6" deep in Grade 20 concrete, reinforced with 2 nos of 10mm dia. tor steel bars and 6mm mild steel stirrups @ 6" c/c including necessary formwork in second floor. | D161: L.ft | F161: =E161*C161 -> 0
A163: C7 | B163: Window Sill
B165: 225mmX150mm
A166: C7.01 | B166: Sill size 9" x 6" deep in Grade 20 concrete, reinforced with 2 nos of 10mm dia. tor steel bars and 6mm mild steel stirrups @ 6" c/c including necessary formwork in ground floor. | D166: L.ft | F166: =E166*C166 -> 0
A168: C7.02 | B168: Sill size 9" x 6" deep in Grade 20 concrete, reinforced with 2 nos of 10mm dia. tor steel bars and 6mm mild steel stirrups @ 6" c/c including necessary formwork in first floor. | D168: L.ft | F168: =E168*C168 -> 0
A170: C7.03 | B170: Sill size 9" x 6" deep in Grade 20 concrete, reinforced with 2 nos of 10mm dia. tor steel bars and 6mm mild steel stirrups @ 6" c/c including necessary formwork in second floor. | D170: L.ft | F170: =E170*C170 -> 0
B174: D - FORM WORK
...

Sheet formwrk
A1: PROPSED THREE STORY LIBREARY BUILDING FOR MINUWANGODA URBAN COUNCIL MINUWANGODA.
A3: Nos | B3: Description | C3: Qty | D3: Unit | E3: Rate | F3: Amount
B4: D - FORM WORK
B5: Note:
A6: (a) | B6: The rates given for items D 02, D 03 to D 08 herein are applicable for plywood sheets of 15 mm thick. Hence the rate is valid only if the shuttering / formwork for footing , column , beams , lintel, walls, slabs are of 15 mm thick ply boards.
A7: (b) | B7: Any deviation from the specified materials, specified thickness and the arrangement of formwork given in this document should require the written approval of the Divisional Engineer. Rate for such deviation from the item description will be decided by the D(B/SW)
A8: (c) | B8: For ordinary plywood of 15 mm thick boarding as shuttering, (Even for WBP sheets the same rate shall be applicable).
A9: D 01 | B9: Shuttering for sides of foundation with 1" thick rubber planking including dismantling | H9: =35.04*10.76 -> 377.0304
A10: D 1.1 | B10: In column footing | D10: Sqr. | E10: 3725 | F10: =C10*E10 -> 0
A11: D 1.2 | B11: steps at ground floor entrance area | D11: Sqr. | E11: 3725 | F11: =C11*E11 -> 0 | H11: =+C11*10.76 -> 0
A12: D 1.3 | B12: Ramp at rentrance | D12: Sqr. | E12: 3725 | F12: =C12*E12 -> 0 | H12: =+C12*10.76 -> 0
A14: D 02 | B14: Shuttering for sides and bottom of plinth beams, ground beams including dismantling in 15mm thick plywood board. | D14: Sqr. | E14: 13385 | F14: =C14*E14 -> 0 | H14: =105.5*10.76 -> 1135.18
A16: D 03 | B16: Shuttering for columns including dismantling in 15mm thick Plywood board.
B17: Up to DPC level | D17: Sqr. | E17: 15850 | F17: =C17*E17 -> 0 | H17: =24.47*10.76 -> 263.2972
A18: D 3.1 | B18: In column shaft from ground floor level to First floor level | D18: Sqr. | E18: =+E17*1.03 -> 16325.5 | F18: =C18*E18 -> 0 | H18: =+C18*10.76 -> 0 | I18: 1005.522
A19: D 3.2 | B19: In column shaft from First floor level to Second floor level | D19: Sqr. | E19: =+E17*1.05 -> 16642.5 | F19: =C19*E19 -> 0 | H19: =+C19*10.76 -> 0 | I19: 741.1488
A20: D 3.3 | B20: In column shaft from Second floor level to Lift machinary level | D20: Sqr. | E20: =+E17*1.07 -> 16959.5 | F20: =C20*E20 -> 0 | H20: =+C20*10.76 -> 0 | I20: 529.392
A21: D 3.4 | B21: In column shaft from Lift machinary level to water tank level | D21: Sqr. | E21: =+E17*1.1 -> 17435 | F21: =C21*E21 -> 0 | H21: =+C21*10.76 -> 0 | I21: 324.0912
A23: D 04 | B23: Shuttering for floor slab including dismantling in 15mm thick Plywood board or steel boarding support by steel jack up to 13'-0". | D23: Sqr.
A24: D 4.1 | B24: In Reinforced slab at First floor level | D24: Sqr. | E24: 13600 | F24: =C24*E24 -> 0 | H24: =+C24*10.76 -> 0 | I24: 25.46
A25: D 4.2 | B25: In Reinforced Slab at second floor level | D25: Sqr. | E25: =+E24*1.03 -> 14008 | F25: =C25*E25 -> 0 | H25: =+C25*10.76 -> 0 | I25: 25.46
A26: D 4.3 | B26: In Reinforced slab at lift machinary level | D26: Sqr. | E26: =+E24*1.05 -> 14280 | F26: =C26*E26 -> 0 | H26: =+C26*10.76 -> 0 | I26: 3.13
A27: D 4.4 | B27: In Reinforced Slab at water tank level | D27: Sqr. | E27: =+E24*1.07 -> 14552 | F27: =C27*E27 -> 0 | H27: =+C27*10.76 -> 0 | I27: 3.13
A30: D 05 | B30: Shuttering for floor Beams including dismantling in 15mm thick plywood board up to 12'-0" soffit height supported by timber props or steel jacks.
A31: D 5.1 | B31: In Reinforced beam at First floor level | D31: Sqr. | E31: 18735 | F31: =C31*E31 -> 0 | H31: =+C31*10.76 -> 0 | I31: 1535.5596
A32: D 5.2 | B32: In Reinforced beam at second floor level | D32: Sqr. | E32: =+E31*1.03 -> 19297.05 | F32: =C32*E32 -> 0 | H32: =+C32*10.76 -> 0 | I32: 1321.328
A33: D 5.3 | B33: In Reinforced beam at roof & lift machinary level | D33: Sqr. | E33: =+E31*1.05 -> 19671.75 | F33: =C33*E33 -> 0 | H33: =+C33*10.76 -> 0 | I33: 724.7936
A34: D 5.4 | B34: In Reinforced beam at water tank level | D34: Sqr. | E34: =+E31*1.07 -> 20046.45 | F34: =C34*E34 -> 0 | H34: =+C34*10.76 -> 0 | I34: 262.9744
B36: Note:
B37: The rates given in Items D09, D10, D11 herein are applicable for Rubber planks. The rubber planks are allowed only for minor works and should be used with the written approval of the D.E.
A38: D 06 | B38: Shuttering for R.C.C. copings in top of balcony , stair and boundary walls and pre - cast lintel sides
A39: D 6.1 | B39: In staircase Up to DPC level | D39: Sqr. | E39: 3700 | F39: =C39*E39 -> 0
A40: D 6.2 | B40: In staircase from ground floor level to First floor level | D40: Sqr. | E40: =+E39*1.03 -> 3811 | F40: =C40*E40 -> 0 | H40: =+#REF!*10.76 -> #REF! | I40: 399.5188
A41: D 6.3 | B41: In staircase from First floor level to Second floor level | D41: Sqr. | E41: =+E39*1.05 -> 3885 | F41: =C41*E41 -> 0 | H41: =+#REF!*10.76 -> #REF! | I41: 399.5188
B46: TOTAL CARRIED TO COLLECTION | F46: =SUM(F9:F44) -> 0

Sheet Sheet4

Sheet Sheet5

Sheet rf
A1: PROPSED THREE STORY LIBREARY BUILDING FOR MINUWANGODA URBAN COUNCIL MINUWANGODA.
A3: Nos | B3: Description | C3: Qty | D3: Unit | E3: Rate | F3: Amount
B4: E - REINFORCEMENT
A5: E 01 | B5: Mild steel reinforcement to slabs, beams, lintols, columns, footings & etc.. bent to shape, laid in position and tied with 16 B.W.G. Aneal binding wire up to Dpc .
A6: E1.1 | B6: In column shaft | D6: Kg | E6: 192 | F6: =+C6*E6 -> 0
A7: E1.2 | B7: In Tie Beams | D7: Kg | E7: 192 | F7: =+C7*E7 -> 0
A9: E 02 | B9: Mild steel reinforcement to slabs, beams, lintols, columns, footings & etc.. bent to shape, laid in position and tied with 16 B.W.G. Aneal binding wire in Ground floor .
A10: E2.1 | B10: In column shaft | D10: Kg | E10: 192 | F10: =+C10*E10 -> 0
A11: E2.2 | B11: In Beams | D11: Kg | E11: 192 | F11: =+C11*E11 -> 0
A13: E 03 | B13: Mild steel reinforcement to slabs, beams, lintols, columns, footings & etc.. bent to shape, laid in position and tied with 16 B.W.G. Aneal binding wire in first floor .
A14: E3.1 | B14: In column shaft | D14: Kg | E14: 198 | F14: =+C14*E14 -> 0
A15: E3.2 | B15: In Beams | D15: Kg | E15: 198 | F15: =+C15*E15 -> 0
A17: E 04 | B17: Mild steel reinforcement to slabs, beams, lintols, columns, footings & etc.. bent to shape, laid in position and tied with 16 B.W.G. Aneal binding wire in second floor .
A18: E4.1 | B18: In column shaft | D18: Kg | E18: 202 | F18: =+C18*E18 -> 0
A19: E4.2 | B19: In Beams | D19: Kg | E19: 202 | F19: =+C19*E19 -> 0
A21: E 05 | B21: Mild steel reinforcement to slabs, beams, lintols, columns, footings & etc.. bent to shape, laid in position and tied with 16 B.W.G. Aneal binding wire in Third floor .
A22: E5.1 | B22: In column shaft | D22: Kg | E22: 208 | F22: =+C22*E22 -> 0
A23: E5.2 | B23: In Beams | D23: Kg | E23: 208 | F23: =+C23*E23 -> 0
A25: E 06 | B25: Tor steel reinforcement to slabs, beams, lintols, columns, footings & etc.. bent to shape, laid in position and tied with 16 B.W.G. Aneal binding wire up to Dpc . | D25: Kg | E25: 164
A26: E6.1 | B26: In column footing | D26: Kg | E26: 204 | F26: =+C26*E26 -> 0
A27: E6.2 | B27: In column shaft | D27: Kg | E27: 204 | F27: =+C27*E27 -> 0
A28: E6.3 | B28: In Tie Beams | D28: Kg | E28: 204 | F28: =+C28*E28 -> 0
A29: E6.4 | B29: In staircases | D29: Kg | E29: 204 | F29: =+C29*E29 -> 0
A31: E 07 | B31: Tor steel reinforcement to slabs, beams, lintols, columns, footings & etc.. bent to shape, laid in position and tied with 16 B.W.G. Aneal binding wire in Ground floor.
A32: E7.1 | B32: In column shaft | D32: Kg | E32: 204 | F32: =+C32*E32 -> 0
A33: E7.2 | B33: In Beams | D33: Kg | E33: 204 | F33: =+C33*E33 -> 0
A34: E7.3 | B34: In Slab | D34: Kg | E34: 204 | F34: =+C34*E34 -> 0
A35: E7.4 | B35: In Staircase | D35: Kg | E35: 204 | F35: =+C35*E35 -> 0
A37: E 08 | B37: Tor steel reinforcement to slabs, beams, lintols, columns, footings & etc.. bent to shape, laid in position and tied with 16 B.W.G. Aneal binding wire in first floor.
A38: E8.1 | B38: In column shaft | D38: Kg | E38: 210 | F38: =+C38*E38 -> 0
A39: E8.2 | B39: In Beams | D39: Kg | E39: 210 | F39: =+C39*E39 -> 0
A40: E8.3 | B40: In Slab | D40: Kg | E40: 210 | F40: =+C40*E40 -> 0
A41: E8.4 | B41: In Staircase | D41: Kg | E41: 210 | F41: =+C41*E41 -> 0
A43: E 09 | B43: Tor steel reinforcement to slabs, beams, lintols, columns, footings & etc.. bent to shape, laid in position and tied with 16 B.W.G. Aneal binding wire in second floor.
A44: E9.1 | B44: In column shaft | D44: Kg | E44: 210 | F44: =+C44*E44 -> 0
A45: E9.2 | B45: In Beams | D45: Kg | E45: 210 | F45: =+C45*E45 -> 0
A46: E9.3 | B46: In Slab | D46: Kg | E46: 210 | F46: =+C46*E46 -> 0
A48: E 10 | B48: Tor steel reinforcement to slabs, beams, lintols, columns, footings & etc.. bent to shape, laid in position and tied with 16 B.W.G. Aneal binding wire in Third floor.
A49: E10.1 | B49: In column shaft | D49: Kg | E49: 216 | F49: =+C49*E49 -> 0
A50: E10.2 | B50: In Beams | D50: Kg | E50: 216 | F50: =+C50*E50 -> 0
A51: E10.3 | B51: In Slab | D51: Kg | E51: 216 | F51: =+C51*E51 -> 0
B55: TOTAL CARRIED TO COLLECTION | F55: =SUM(F5:F53) -> 0

Sheet m shet rolf
A1: NO | B1: DESCRIPTION | C1: NOS | F1: LENGTH | G1: WIDTH | H1: HEIGHT | I1: QTY | J1: T.QTY | O1: UNIT
K2: 1.05
B3: 225mm brick wall | K3: =$K$2 -> 1.05 | L3: =K3*J3 -> 0 | M3: =ROUND(L3,1) -> 0 | N3: =ROUNDUP(M3,0) -> 0 | P3: 1.1
B4: gf | F4: 61.4 | H4: 3.3 | I4: =H4*F4 -> 202.62 | K4: =$K$2 -> 1.05 | L4: =K4*J4 -> 0 | M4: =ROUND(L4,1) -> 0 | N4: =ROUNDUP(M4,0) -> 0
F5: 8.178 | H5: 3.3 | I5: =H5*F5 -> 26.9874 | K5: =$K$2 -> 1.05 | L5: =K5*J5 -> 0 | M5: =ROUND(L5,1) -> 0 | N5: =ROUNDUP(M5,0) -> 0
F6: 6.293 | H6: 3.3 | I6: =H6*F6 -> 20.7669 | K6: =$K$2 -> 1.05 | L6: =K6*J6 -> 0 | M6: =ROUND(L6,1) -> 0 | N6: =ROUNDUP(M6,0) -> 0
F7: 3.225 | H7: 3.3 | I7: =H7*F7 -> 10.6425 | K7: =$K$2 -> 1.05 | L7: =K7*J7 -> 0 | M7: =ROUND(L7,1) -> 0 | N7: =ROUNDUP(M7,0) -> 0
F8: 3.75 | H8: 3.3 | I8: =H8*F8 -> 12.375 | K8: =$K$2 -> 1.05 | L8: =K8*J8 -> 0 | M8: =ROUND(L8,1) -> 0 | N8: =ROUNDUP(M8,0) -> 0
F9: 3.6 | H9: 3.3 | I9: =H9*F9 -> 11.88 | K9: =$K$2 -> 1.05 | L9: =K9*J9 -> 0 | M9: =ROUND(L9,1) -> 0 | N9: =ROUNDUP(M9,0) -> 0
F10: 3.6 | H10: 3.3 | I10: =H10*F10 -> 11.88 | K10: =$K$2 -> 1.05 | L10: =K10*J10 -> 0 | M10: =ROUND(L10,1) -> 0 | N10: =ROUNDUP(M10,0) -> 0
F11: 3.3 | H11: 3.3 | I11: =H11*F11 -> 10.89 | K11: =$K$2 -> 1.05 | L11: =K11*J11 -> 0 | M11: =ROUND(L11,1) -> 0 | N11: =ROUNDUP(M11,0) -> 0
B12: less | K12: =$K$2 -> 1.05 | L12: =K12*J12 -> 0 | M12: =ROUND(L12,1) -> 0 | N12: =ROUNDUP(M12,0) -> 0
B13: d6 | E13: 1 | F13: 2.2 | H13: 2.7 | I13: =-H13*F13*E13 -> -5.94 | K13: =$K$2 -> 1.05 | L13: =K13*J13 -> 0 | M13: =ROUND(L13,1) -> 0 | N13: =ROUNDUP(M13,0) -> 0 | R13: =14*300 -> 4200
B14: fl1 | E14: 2 | F14: 1.5 | H14: 1.5 | I14: =-H14*F14*E14 -> -4.5 | K14: =$K$2 -> 1.05 | L14: =K14*J14 -> 0 | M14: =ROUND(L14,1) -> 0 | N14: =ROUNDUP(M14,0) -> 0
B15: w1 | E15: 1 | F15: 1.65 | H15: 1.8 | I15: =-H15*F15*E15 -> -2.97 | K15: =$K$2 -> 1.05 | L15: =K15*J15 -> 0 | M15: =ROUND(L15,1) -> 0 | N15: =ROUNDUP(M15,0) -> 0
B16: d3 | E16: 1 | F16: 0.9 | H16: 2.7 | I16: =-H16*F16*E16 -> -2.43 | K16: =$K$2 -> 1.05 | L16: =K16*J16 -> 0 | M16: =ROUND(L16,1) -> 0 | N16: =ROUNDUP(M16,0) -> 0
B17: d5 | E17: 2 | F17: 0.8 | H17: 2.4 | I17: =-H17*F17*E17 -> -3.84 | K17: =$K$2 -> 1.05 | L17: =K17*J17 -> 0 | M17: =ROUND(L17,1) -> 0 | N17: =ROUNDUP(M17,0) -> 0
B18: d4 | E18: 1 | F18: 1 | H18: 2.7 | I18: =-H18*F18*E18 -> -2.7
B19: d3 | E19: 1 | F19: 0.9 | H19: 2.7 | I19: =-H19*F19*E19 -> -2.43 | K19: =$K$2 -> 1.05 | L19: =K19*J19 -> 0 | M19: =ROUND(L19,1) -> 0 | N19: =ROUNDUP(M19,0) -> 0
B20: w1 | E20: 1 | F20: 1.65 | H20: 1.8 | I20: =-H20*F20*E20 -> -2.97 | K20: =$K$2 -> 1.05 | L20: =K20*J20 -> 0 | M20: =ROUND(L20,1) -> 0 | N20: =ROUNDUP(M20,0) -> 0
B21: sl4 | E21: 1 | F21: 4.1 | H21: 2.7 | I21: =-H21*F21*E21 -> -11.07 | K21: =$K$2 -> 1.05 | L21: =K21*J21 -> 0 | M21: =ROUND(L21,1) -> 0 | N21: =ROUNDUP(M21,0) -> 0 | Q21: =I21/100 -> -0.1107
B22: fg2 | E22: 1 | F22: 3.3 | H22: 2.7 | I22: =-H22*F22*E22 -> -8.91
B23: sl7 | E23: 1 | F23: 1.7 | H23: 2.7 | I23: =-H23*F23*E23 -> -4.59 | K23: =$K$2 -> 1.05 | L23: =K23*J23 -> 0 | M23: =ROUND(L23,1) -> 0 | N23: =ROUNDUP(M23,0) -> 0 | Q23: =Q21*2.83 -> -0.313281
B24: d1 | E24: 1 | F24: 1.5 | H24: 2.7 | I24: =-H24*F24*E24 -> -4.05 | K24: =$K$2 -> 1.05 | L24: =K24*J24 -> 0 | M24: =ROUND(L24,1) -> 0 | N24: =ROUNDUP(M24,0) -> 0
B25: fg1 | E25: 2 | F25: 1.775 | H25: 2.7 | I25: =-H25*F25*E25 -> -9.585 | K25: =$K$2 -> 1.05 | L25: =K25*J25 -> 0 | M25: =ROUND(L25,1) -> 0 | N25: =ROUNDUP(M25,0) -> 0
B26: d2 | E26: 1 | F26: 1 | H26: 2.7 | I26: =-H26*F26*E26 -> -2.7 | K26: =$K$2 -> 1.05 | L26: =K26*J26 -> 0 | M26: =ROUND(L26,1) -> 0 | N26: =ROUNDUP(M26,0) -> 0
B27: sl1 | E27: 1 | F27: 2.9 | H27: 2.7 | I27: =-H27*F27*E27 -> -7.83 | K27: =$K$2 -> 1.05 | L27: =K27*J27 -> 0 | M27: =ROUND(L27,1) -> 0 | N27: =ROUNDUP(M27,0) -> 0
J28: =SUM(I4:I27) -> 231.5268 | K28: =$K$2 -> 1.05 | L28: =K28*J28 -> 243.10314 | M28: =ROUND(L28,1) -> 243.1 | N28: =ROUNDUP(M28,0) -> 244
K29: =$K$2 -> 1.05 | L29: =K29*J29 -> 0 | M29: =ROUND(L29,1) -> 0 | N29: =ROUNDUP(M29,0) -> 0
B30: ff | F30: 24.339 | H30: 3.3 | I30: =H30*F30 -> 80.3187 | K30: =$K$2 -> 1.05 | L30: =K30*J30 -> 0 | M30: =ROUND(L30,1) -> 0 | N30: =ROUNDUP(M30,0) -> 0 | Q30: =12*300 -> 3600
F31: 5.125 | H31: 3.3 | I31: =H31*F31 -> 16.9125 | K31: =$K$2 -> 1.05 | L31: =K31*J31 -> 0 | M31: =ROUND(L31,1) -> 0 | N31: =ROUNDUP(M31,0) -> 0
F32: 8.054 | H32: 3.3 | I32: =H32*F32 -> 26.5782 | K32: =$K$2 -> 1.05 | L32: =K32*J32 -> 0 | M32: =ROUND(L32,1) -> 0 | N32: =ROUNDUP(M32,0) -> 0
F33: 7.041 | H33: 3.3 | I33: =H33*F33 -> 23.2353 | K33: =$K$2 -> 1.05 | L33: =K33*J33 -> 0 | M33: =ROUND(L33,1) -> 0 | N33: =ROUNDUP(M33,0) -> 0
F34: 7.405 | H34: 3.3 | I34: =H34*F34 -> 24.4365 | K34: =$K$2 -> 1.05 | L34: =K34*J34 -> 0 | M34: =ROUND(L34,1) -> 0 | N34: =ROUNDUP(M34,0) -> 0
F35: 9.9 | H35: 3.3 | I35: =H35*F35 -> 32.67 | K35: =$K$2 -> 1.05 | L35: =K35*J35 -> 0 | M35: =ROUND(L35,1) -> 0 | N35: =ROUNDUP(M35,0) -> 0 | Q35: =H36-H39 -> 3.3
F36: 4.87 | H36: 3.3 | I36: =H36*F36 -> 16.071 | K36: =$K$2 -> 1.05 | L36: =K36*J36 -> 0 | M36: =ROUND(L36,1) -> 0 | N36: =ROUNDUP(M36,0) -> 0
E37: 2 | F37: 1.08 | H37: 3.3 | I37: =H37*F37*E37 -> 7.128 | K37: =$K$2 -> 1.05 | L37: =K37*J37 -> 0 | M37: =ROUND(L37,1) -> 0 | N37: =ROUNDUP(M37,0) -> 0
F38: 19.2 | H38: 1.2 | I38: =H38*F38 -> 23.04
B39: less | K39: =$K$2 -> 1.05 | L39: =K39*J39 -> 0 | M39: =ROUND(L39,1) -> 0 | N39: =ROUNDUP(M39,0) -> 0
B40: fd1 | E40: 1 | F40: 2.2 | H40: 2.7 | I40: =-H40*F40*E40 -> -5.94 | K40: =$K$2 -> 1.05 | L40: =K40*J40 -> 0 | M40: =ROUND(L40,1) -> 0 | N40: =ROUNDUP(M40,0) -> 0
B41: fl1 | E41: 3 | F41: 1.5 | H41: 1.5 | I41: =-H41*F41*E41 -> -6.75 | K41: =$K$2 -> 1.05 | L41: =K41*J41 -> 0 | M41: =ROUND(L41,1) -> 0 | N41: =ROUNDUP(M41,0) -> 0
B42: sl2 | E42: 1 | F42: 4.4 | H42: 2.7 | I42: =-H42*F42*E42 -> -11.88 | K42: =$K$2 -> 1.05 | L42: =K42*J42 -> 0 | M42: =ROUND(L42,1) -> 0 | N42: =ROUNDUP(M42,0) -> 0
B43: d5 | E43: 2 | F43: 0.8 | H43: 2.4 | I43: =-H43*F43*E43 -> -3.84 | K43: =$K$2 -> 1.05 | L43: =K43*J43 -> 0 | M43: =ROUND(L43,1) -> 0 | N43: =ROUNDUP(M43,0) -> 0
B44: d4 | E44: 3 | F44: 1 | H44: 2.7 | I44: =-H44*F44*E44 -> -8.1 | K44: =$K$2 -> 1.05 | L44: =K44*J44 -> 0 | M44: =ROUND(L44,1) -> 0 | N44: =ROUNDUP(M44,0) -> 0
B45: fg5 | E45: 1 | F45: 0.8 | H45: 2.7 | I45: =-H45*F45*E45 -> -2.16 | K45: =$K$2 -> 1.05 | L45: =K45*J45 -> 0 | M45: =ROUND(L45,1) -> 0 | N45: =ROUNDUP(M45,0) -> 0
B46: fg4 | E46: 1 | F46: 2 | H46: 2.7 | I46: =-H46*F46*E46 -> -5.4 | K46: =$K$2 -> 1.05 | L46: =K46*J46 -> 0 | M46: =ROUND(L46,1) -> 0 | N46: =ROUNDUP(M46,0) -> 0
B47: fg3 | E47: 2 | F47: 4.04 | H47: 2.7 | I47: =-H47*F47*E47 -> -21.816 | K47: =$K$2 -> 1.05 | L47: =K47*J47 -> 0 | M47: =ROUND(L47,1) -> 0 | N47: =ROUNDUP(M47,0) -> 0
B48: sl5 | E48: 1 | F48: 2 | H48: 2.7 | I48: =-H48*F48*E48 -> -5.4 | K48: =$K$2 -> 1.05 | L48: =K48*J48 -> 0 | M48: =ROUND(L48,1) -> 0 | N48: =ROUNDUP(M48,0) -> 0
B49: d6 | E49: 1 | F49: 2.2 | H49: 2.7 | I49: =-H49*F49*E49 -> -5.94 | K49: =$K$2 -> 1.05 | L49: =K49*J49 -> 0 | M49: =ROUND(L49,1) -> 0 | N49: =ROUNDUP(M49,0) -> 0
J50: =SUM(I30:I49) -> 173.1642 | K50: =$K$2 -> 1.05 | L50: =K50*J50 -> 181.82241 | M50: =ROUND(L50,1) -> 181.8 | N50: =ROUNDUP(M50,0) -> 182
K51: =$K$2 -> 1.05 | L51: =K51*J51 -> 0 | M51: =ROUND(L51,1) -> 0 | N51: =ROUNDUP(M51,0) -> 0
B52: sf | F52: 55.46 | H52: 3.3 | I52: =H52*F52 -> 183.018 | K52: =$K$2 -> 1.05 | L52: =K52*J52 -> 0 | M52: =ROUND(L52,1) -> 0 | N52: =ROUNDUP(M52,0) -> 0
F53: 9.79 | H53: 3.3 | I53: =H53*F53 -> 32.307 | K53: =$K$2 -> 1.05 | L53: =K53*J53 -> 0 | M53: =ROUND(L53,1) -> 0 | N53: =ROUNDUP(M53,0) -> 0
F54: 4.4 | H54: 3.3 | I54: =H54*F54 -> 14.52 | K54: =$K$2 -> 1.05 | L54: =K54*J54 -> 0 | M54: =ROUND(L54,1) -> 0 | N54: =ROUNDUP(M54,0) -> 0
F55: 5.122 | H55: 3.3 | I55: =H55*F55 -> 16.9026 | K55: =$K$2 -> 1.05 | L55: =K55*J55 -> 0 | M55: =ROUND(L55,1) -> 0 | N55: =ROUNDUP(M55,0) -> 0
F56: 3.59 | H56: 3.3 | I56: =H56*F56 -> 11.847 | K56: =$K$2 -> 1.05 | L56: =K56*J56 -> 0 | M56: =ROUND(L56,1) -> 0 | N56: =ROUNDUP(M56,0) -> 0
F57: 4.89 | H57: 3.3 | I57: =H57*F57 -> 16.137 | K57: =$K$2 -> 1.05 | L57: =K57*J57 -> 0 | M57: =ROUND(L57,1) -> 0 | N57: =ROUNDUP(M57,0) -> 0
F58: 11.1 | H58: 3.3 | I58: =H58*F58 -> 36.63 | K58: =$K$2 -> 1.05 | L58: =K58*J58 -> 0 | M58: =ROUND(L58,1) -> 0 | N58: =ROUNDUP(M58,0) -> 0
F59: 4.664 | H59: 3.3 | I59: =H59*F59 -> 15.3912 | K59: =$K$2 -> 1.05 | L59: =K59*J59 -> 0 | M59: =ROUND(L59,1) -> 0 | N59: =ROUNDUP(M59,0) -> 0 | R59: =1500-710-690 -> 100
E60: 2 | F60: 1.2 | H60: 3.3 | I60: =H60*F60*E60 -> 7.92 | K60: =$K$2 -> 1.05 | L60: =K60*J60 -> 0 | M60: =ROUND(L60,1) -> 0 | N60: =ROUNDUP(M60,0) -> 0
F61: 2 | H61: 3.3 | I61: =H61*F61 -> 6.6 | K61: =$K$2 -> 1.05 | L61: =K61*J61 -> 0 | M61: =ROUND(L61,1) -> 0 | N61: =ROUNDUP(M61,0) -> 0
B62: less | K62: =$K$2 -> 1.05 | L62: =K62*J62 -> 0 | M62: =ROUND(L62,1) -> 0 | N62: =ROUNDUP(M62,0) -> 0
B63: fd2 | E63: 1 | F63: 4.3 | H63: 2.7 | I63: =-H63*F63*E63 -> -11.61 | K63: =$K$2 -> 1.05 | L63: =K63*J63 -> 0 | M63: =ROUND(L63,1) -> 0 | N63: =ROUNDUP(M63,0) -> 0
B64: fl1 | E64: 2 | F64: 1.5 | H64: 0.5 | I64: =-H64*F64*E64 -> -1.5 | K64: =$K$2 -> 1.05 | L64: =K64*J64 -> 0 | M64: =ROUND(L64,1) -> 0 | N64: =ROUNDUP(M64,0) -> 0
B65: sl3 | E65: 1 | F65: 4.875 | H65: 2.7 | I65: =-H65*F65*E65 -> -13.1625 | K65: =$K$2 -> 1.05 | L65: =K65*J65 -> 0 | M65: =ROUND(L65,1) -> 0 | N65: =ROUNDUP(M65,0) -> 0
B66: d4 | E66: 3 | F66: 1 | H66: 2.7 | I66: =-H66*F66*E66 -> -8.1 | K66: =$K$2 -> 1.05 | L66: =K66*J66 -> 0 | M66: =ROUND(L66,1) -> 0 | N66: =ROUNDUP(M66,0) -> 0
B67: d5 | E67: 1 | F67: 0.8 | H67: 2.4 | I67: =-H67*F67*E67 -> -1.92 | K67: =$K$2 -> 1.05 | L67: =K67*J67 -> 0 | M67: =ROUND(L67,1) -> 0 | N67: =ROUNDUP(M67,0) -> 0 | Q67: =I67/100 -> -0.0192
B68: sl6 | E68: 2 | F68: 3.375 | H68: 2.7 | I68: =-H68*F68*E68 -> -18.225 | K68: =$K$2 -> 1.05 | L68: =K68*J68 -> 0 | M68: =ROUND(L68,1) -> 0 | N68: =ROUNDUP(M68,0) -> 0 | Q68: =Q67*9.29 -> -0.178368
B69: fg4 | E69: 1 | F69: 2 | H69: 2.7 | I69: =-H69*F69*E69 -> -5.4 | K69: =$K$2 -> 1.05 | L69: =K69*J69 -> 0 | M69: =ROUND(L69,1) -> 0 | N69: =ROUNDUP(M69,0) -> 0
B70: fg3 | E70: 2 | F70: 4.04 | H70: 2.7 | I70: =-H70*F70*E70 -> -21.816 | K70: =$K$2 -> 1.05 | L70: =K70*J70 -> 0 | M70: =ROUND(L70,1) -> 0 | N70: =ROUNDUP(M70,0) -> 0
B71: d6 | E71: 1 | F71: 2.2 | H71: 2.7 | I71: =-H71*F71*E71 -> -5.94 | K71: =$K$2 -> 1.05 | L71: =K71*J71 -> 0 | M71: =ROUND(L71,1) -> 0 | N71: =ROUNDUP(M71,0) -> 0
B72: sl5 | E72: 1 | F72: 2 | H72: 2.7 | I72: =-H72*F72*E72 -> -5.4 | K72: =$K$2 -> 1.05 | L72: =K72*J72 -> 0 | M72: =ROUND(L72,1) -> 0 | N72: =ROUNDUP(M72,0) -> 0
J73: =SUM(I52:I72) -> 248.1993 | K73: =$K$2 -> 1.05 | L73: =K73*J73 -> 260.60926 | M73: =ROUND(L73,1) -> 260.6 | N73: =ROUNDUP(M73,0) -> 261 | Q73: =SUM(I62:I65) -> -26.2725
K74: =$K$2 -> 1.05 | L74: =K74*J74 -> 0 | M74: =ROUND(L74,1) -> 0 | N74: =ROUNDUP(M74,0) -> 0 | Q74: =SUM(I67:I76) -> -54.901
B75: water tank level | F75: 14.9 | I75: 3.8 | J75: =I75*F75 -> 56.62 | K75: =$K$2 -> 1.05 | L75: =K75*J75 -> 59.451 | M75: =ROUND(L75,1) -> 59.5 | N75: =ROUNDUP(M75,0) -> 60 | Q75: =Q73+Q74 -> -81.1735
K76: =$K$2 -> 1.05 | L76: =K76*J76 -> 0 | M76: =ROUND(L76,1) -> 0 | N76: =ROUNDUP(M76,0) -> 0
B77: 112.5mm brick wall | F77: 1.85 | H77: 3.3 | I77: =H77*F77 -> 6.105 | K77: =$K$2 -> 1.05 | L77: =K77*J77 -> 0 | M77: =ROUND(L77,1) -> 0 | N77: =ROUNDUP(M77,0) -> 0
F78: 2.7 | H78: 3.3 | I78: =H78*F78 -> 8.91 | K78: =$K$2 -> 1.05 | L78: =K78*J78 -> 0 | M78: =ROUND(L78,1) -> 0 | N78: =ROUNDUP(M78,0) -> 0
B79: less | K79: =$K$2 -> 1.05 | L79: =K79*J79 -> 0 | M79: =ROUND(L79,1) -> 0 | N79: =ROUNDUP(M79,0) -> 0
B80: d5 | E80: 1 | F80: 0.8 | H80: 2.4 | I80: =-H80*F80*E80 -> -1.92 | K80: =$K$2 -> 1.05 | L80: =K80*J80 -> 0 | M80: =ROUND(L80,1) -> 0 | N80: =ROUNDUP(M80,0) -> 0
J81: =SUM(I77:I80) -> 13.095 | K81: =$K$2 -> 1.05 | L81: =K81*J81 -> 13.74975 | M81: =ROUND(L81,1) -> 13.7 | N81: =ROUNDUP(M81,0) -> 14
K82: =$K$2 -> 1.05 | L82: =K82*J82 -> 0 | M82: =ROUND(L82,1) -> 0 | N82: =ROUNDUP(M82,0) -> 0
B83: polythene | J83: 211 | K83: =$K$2 -> 1.05 | L83: =K83*J83 -> 221.55 | M83: =ROUND(L83,1) -> 221.6 | N83: =ROUNDUP(M83,0) -> 222
K84: =$K$2 -> 1.05 | L84: =K84*J84 -> 0 | M84: =ROUND(L84,1) -> 0 | N84: =ROUNDUP(M84,0) -> 0
K85: =$K$2 -> 1.05 | L85: =K85*J85 -> 0 | M85: =ROUND(L85,1) -> 0 | N85: =ROUNDUP(M85,0) -> 0
B86: water tank rendering | F86: 5.1 | G86: 2.45 | J86: =G86*F86 -> 12.495 | K86: =$K$2 -> 1.05 | L86: =K86*J86 -> 13.11975 | M86: =ROUND(L86,1) -> 13.1 | N86: =ROUNDUP(M86,0) -> 14
K87: =$K$2 -> 1.05 | L87: =K87*J87 -> 0 | M87: =ROUND(L87,1) -> 0 | N87: =ROUNDUP(M87,0) -> 0
K88: =$K$2 -> 1.05 | L88: =K88*J88 -> 0 | M88: =ROUND(L88,1) -> 0 | N88: =ROUNDUP(M88,0) -> 0
B89: WATER PROOF | K89: =$K$2 -> 1.05 | L89: =K89*J89 -> 0 | M89: =ROUND(L89,1) -> 0 | N89: =ROUNDUP(M89,0) -> 0
B90: gf | E90: 1 | F90: 1.5 | G90: 3.3 | I90: =G90*F90*E90 -> 4.95
E91: 2 | F91: =F90 -> 1.5 | H91: 1.5 | I91: =H91*F91*E91 -> 4.5 | K91: =$K$2 -> 1.05 | L91: =K91*J91 -> 0 | M91: =ROUND(L91,1) -> 0 | N91: =ROUNDUP(M91,0) -> 0
E92: 2 | F92: =G90 -> 3.3 | H92: 1.5 | I92: =H92*F92*E92 -> 9.9 | K92: =$K$2 -> 1.05 | L92: =K92*J92 -> 0 | M92: =ROUND(L92,1) -> 0 | N92: =ROUNDUP(M92,0) -> 0
B93: less | K93: =$K$2 -> 1.05 | L93: =K93*J93 -> 0 | M93: =ROUND(L93,1) -> 0 | N93: =ROUNDUP(M93,0) -> 0
B94: d5 | E94: 1 | F94: 0.8 | H94: 2.4 | I94: =-H94*F94*E94 -> -1.92 | J94: =SUM(I90:I94) -> 17.43 | K94: =$K$2 -> 1.05 | L94: =K94*J94 -> 18.3015 | M94: =ROUND(L94,1) -> 18.3 | N94: =ROUNDUP(M94,0) -> 19
K95: =$K$2 -> 1.05 | L95: =K95*J95 -> 0 | M95: =ROUND(L95,1) -> 0 | N95: =ROUNDUP(M95,0) -> 0
K96: =$K$2 -> 1.05 | L96: =K96*J96 -> 0 | M96: =ROUND(L96,1) -> 0 | N96: =ROUNDUP(M96,0) -> 0
B97: floor tile | E97: 1 | F97: 1.5 | G97: 3.3 | I97: =G97*F97*E97 -> 4.95 | J97: =I97 -> 4.95 | K97: =$K$2 -> 1.05 | L97: =K97*J97 -> 5.1975 | M97: =ROUND(L97,1) -> 5.2 | N97: =ROUNDUP(M97,0) -> 6
K98: =$K$2 -> 1.05 | L98: =K98*J98 -> 0 | M98: =ROUND(L98,1) -> 0 | N98: =ROUNDUP(M98,0) -> 0
B99: wal tile | K99: =$K$2 -> 1.05 | L99: =K99*J99 -> 0 | M99: =ROUND(L99,1) -> 0 | N99: =ROUNDUP(M99,0) -> 0
E100: 2 | F100: =F97 -> 1.5 | H100: 3.3 | I100: =H100*F100*E100 -> 9.9 | K100: =$K$2 -> 1.05 | L100: =K100*J100 -> 0 | M100: =ROUND(L100,1) -> 0 | N100: =ROUNDUP(M100,0) -> 0
...

Sheet Minuwangoda Final
A1: PROPSED THREE STORY LIBREARY BUILDING FOR MINUWANGODA URBAN COUNCIL MINUWANGODA.
A3: Nos | B3: Description | C3: Qty | D3: Unit | E3: Rate | F3: Amount
B4: BILL NO. 01
A5: 1/PR | B5: PRELIMINARIES
B7: Please refer Specifications & Priceing reambles
B8: This Bill Provides for the typical general items complimentary to the works wich are required to be provided by the Contractor in compliance with the Conditions of Contract and Contract Data in the execution of the works according to the Contract.
A10: 1/PR.1 | B10: Allow lump sum for providing Securtiy Bonds and Guarantees. | C10: 1 | D10: Item | E10: 685000 | F10: =C10*E10 -> 685000
A12: 1/PR.2 | B12: Allow lump sum for mobilization to site | C12: 1 | D12: Item | E12: 20000 | F12: =C12*E12 -> 20000
A14: 1/PR.3 | B14: Allow lump sum for insurance of works, plant & machinery,materials, third pary and workmen (All the insurances should be submitted for the end of defect liability period.) | C14: 1 | D14: Item | E14: 810000 | F14: =C14*E14 -> 810000
A16: 1/PR.4 | B16: Provide lump sum to construct, maintain and removal at end of contract temporary buildings for protection & storage of materials & plant and for workshops. | C16: 1 | D16: Item | E16: 30000 | F16: =C16*E16 -> 30000
