Workbook
Name ___REM1: #REF!
Name ___REM1: #REF!
Name ___REM2: #REF!
Name ___REM2: #REF!
Name ___Val101: #REF!
Name ___Val101: #REF!
Name ___Val102: #REF!
Name ___Val102: #REF!
Name ___Val201: #REF!
Name ___Val201: #REF!
Name ___Val202: #REF!
Name ___Val202: #REF!
Name ___Val301: #REF!
Name ___Val301: #REF!
Name ___Val302: #REF!
Name ___Val302: #REF!
Name __REM1: #REF!
Name __REM1: #REF!
Name __REM2: #REF!
Name __REM2: #REF!
Name __Val101: #REF!
Name __Val101: #REF!
Name __Val102: #REF!
Name __Val102: #REF!
Name __Val201: #REF!
Name __Val201: #REF!
Name __Val202: #REF!
Name __Val202: #REF!
Name __Val301: #REF!
Name __Val301: #REF!
Name __Val302: #REF!
Name __Val302: #REF!
Name _REM1: #REF!
Name _REM1: #REF!
Name _REM2: #REF!
Name _REM2: #REF!
Name _Val101: #REF!
Name _Val101: #REF!
Name _Val102: #REF!
Name _Val102: #REF!
Name _Val201: #REF!
Name _Val201: #REF!
Name _Val202: #REF!
Name _Val202: #REF!
Name _Val301: #REF!
Name _Val301: #REF!
Name _Val302: #REF!
Name _Val302: #REF!
Name a: '[2]B-3.2 EB'!#REF!
Name aa: #REF!
Name aa: #REF!
Name aaa: #REF!
Name aaa: #REF!
Name ad: '[2]B-3.2 EB'!#REF!
Name Anton: #REF!
Name Anton: #REF!
Name as: #REF!
Name as: #REF!
Name asgsdfg: #REF!
Name asgsdfg: #REF!

Sheet front
A5: BILLS OF QUANTITIES
A9: PROPOSED HOUSE DESIGN FOR MR.RATHEESHAN AT JAFFNA.

Sheet summary
A2: COLLECTION BILL NO.02 - MAIN BUILDING
A4: Nos | B4: Description | C4: Amount
A6: A | B6: A - PRELIMINARIES | C6: =+prelims!I120 -> 405000
A7: B | B7: =exca!B2 -> B - EXCAVATION & EARTH WORK | C7: =exca!H44 -> 1396040 | D7: 0.75
A8: C | B8: =concrete!B2 -> C - CONCRETE | C8: =concrete!H187 -> 27693390 | D8: 0.75
A9: F | B9: =masnry!B2 -> F - MASONRY WORKS | C9: =masnry!H30 -> 7755790 | D9: 0.75
A10: G | B10: =floring!B2 -> J - FLOORING WORK | C10: =floring!H11 -> 273380 | D10: 0.75
A11: H | B11: =waterprof!B2 -> E - WATER PROOFING WORK | C11: =+waterprof!H38 -> 1519290 | D11: 0.75
A12: J | B12: =plastering!B2 -> K - PLASTERING WORK | C12: =plastering!H39 -> 3622140 | D12: 0.75
A13: K | B13: =tile!B2 -> L -TILING WORK | C13: =+tile!H115 -> 16408650 | D13: 0.85
A14: L | B14: =paint!B2 -> M - COLOUR WASHING, PAINTING & POLISHING | C14: =paint!H26 -> 2793270 | D14: 0.75
A15: Q | B15: =plumbing!B2 -> S - PLUMBING AND DRAINAGE WORK | C15: =plumbing!H129 -> 4426560 | D15: 0.75
A16: V | B16: ='electicle '!B2 -> V - ELECTRICAL INSTALLATION. | C16: ='electicle '!H236 -> 5143870 | D16: 0.75
A17: T | B17: =metal!B2 -> W - METAL WORK | C17: =metal!H131 -> 17065250 | D17: 0.85
B20: TOTAL CARRIED TO GRAND SUMMARY | C20: =SUM(C6:C19) -> 88502630
C21: =SUM(C7:C17) -> 88097630
C22: =+C21/5560 -> 15844.897

Sheet prelims
A1: Nos | B1: Description | C1: Mode of payment catogary | D1: Qty | E1: Unit | F1: COST | G1: OHP% | H1: Rate | I1: Amount | J1: 1
B2: BILL NO. 01
A3: 1/PR | B3: A - PRELIMINARIES
B5: This Bill Provides for the typical general items complimentary to the works wich are required to be provided by the Contractor in compliance with the Conditions of Contract and Contract Data in the execution of the works according to the Contract.
B7: If the Engineer is of the opinion that any item in this section has not been provided fully by the Contractor the Engineer may adjust the amounts quoted by the Contractor for the items concerned
B9: Reimbursement of actual cost on submission of the relevant document acceptable to the Engineer plus 5% of the actual cost of obtaining the insurance policies and securities
B11: Mode of Payment Category
B12: Reimbursement of actual cost on submission of A
B13: the relavent document acceptable to the
B14: engineering plus 5% of the actaul cost of obtaining
B15: the insurance policies and securities
B17: To be paid on signal of the format contract B
B18: agreement
B20: 60% on completion of temporary building or C
B21: structures. 30% in equl installments over the
... B36: The Bidder is fully responsible for identiflying the limitataions, restrictions and difficulties imposed due to the locally of the site and its environs and should include in his prices for all contingencies that may arise as a result
A38: 1 | B38: Insurance and Securities
A40: =A38+0.01 -> 1.01 | B40: Allow sum for providing performance security | C40: A | D40: 1 | E40: Item | I40: N/A
A42: =A40+0.01 -> 1.02 | B42: Allow sum for providing advance payment security | C42: A | D42: 1 | E42: Item | I42: N/A
A44: =A42+0.01 -> 1.03 | B44: Allow Sum for insurance of Works, Machinery & Equipment, Plant, Materials, Third party persons & property and Eimployer's personal & property at site per the Contract | C44: A | D44: 1 | E44: Item | I44: N/A
B46: The minimim insurance.cover shall be:
B48: The minimum cover for insurance of the Works and Plant and Materials is 110% of the Initial Controct Price.
B50: The maximum deductible for insurance uf the Works and of Plant and Materials is 5% of the Initial Contract Price.
B52: The minimunm cover for loss or damage to Equipment is the replacement cost
B54: The maximum deductible for insurance of Equipment is 5% of minimun cover for equipment.
B56: The minimum cover for insurance of (orher propert other than the site) is Ra. 2Million per event and totul limit of indemnity shall be Rs 10 Million
B58: The mininum cover for insurance of personal injury or death.
B60: For third party and employees of the Employer and other persons engaged by the Employer in the Works is Rs.5,000,000/- per event
B62: Injury or damage to persons including employer and consultant and their employees and other consultants employed by the employer shall be covered by the personnel accident insurance cover for Rs 2 million per event effective from the date of commencement of contract until end of the defects liability period (total number of persons insured are not exceeding 10 nrs)
A64: =A44+0.01 -> 1.04 | B64: Allow Sum for insurance against accidents and injury to Contractor's personnel as per the Contract. | C64: A | D64: 1 | E64: Item | I64: N/A
B66: The iminimum cover for personal injury or death
B67: For the Contractor's workmen is Rs. 500,000/= per event
B68: Contractor s employees other than workmen is Rs.5.000.000/= per event
A70: 2 | B70: Engineer's Facilities
A72: =A70+0.01 -> 2.01 | B72: Allow lump sum for constructing, maintaining, dismantling and removal on completion of the Works, a temporary air conditioned TFU for Engineer's office with toilet,elecricity facility in conformity with the plans provided for Engineer's requirements, including furniture and fittings, furnishing, sanitary facilities necessary and other facilities. | C72: C | D72: 1 | E72: Item
B73: The follwing facilities shall be provided
B74: (1) 2-0"x4-0" Table with drawers for Engineer's representative with medium back chair
B75: (2) Chair for Engineer's Representative( two nr of low back chair)
B76: (3) lockable Cupboard for storage of drawings, documents and stationery
B77: (4) Pedestal fan
B78: (5) 30 Gb monthly data package( WIFI Router),contractor should paid data package monthly
B79: (6) 1200mm X 1200mm white board
B80: (7) I5 computer with printer
B81: (8) Adequate Size Meeting table and 6 nr of chair
A83: 2 | B83: Contractor's Facilities
A85: =A83+0.01 -> 2.01 | B85: Allow lump sum for constructing, maintaining, dismantling and removal on completion of the Works, a temporary office,stores and workshop with toilet,elecricity facility in conformity with the plans provided for Engineer's requirements, including furniture and fittings, furnishing, sanitary facilities necessary and other facilities. | C85: C | D85: 1 | E85: Item | F85: 180000 | G85: =+$J$1 -> 1 | H85: =ROUNDUP(F85/G85,-1) -> 180000 | I85: =+H85*D85 -> 180000
A88: =#REF!+0.01 -> #REF! | B88: Allow lump sum for providing Accommodation, including all sanitory facility for Contractor's staff and workmen | C88: C | D88: 1 | E88: Item
A89: 3 | B89: Construction Managment and Supervision
A91: =A89+0.01 -> 3.01 | B91: Allow sum for employing suitable qualified and axperienced technical personnal on full time for construction maragement services at the site. | C91: E | D91: 1 | E91: Item
B92: Site Engineer( Full Time)
B93: Project Manager ( C.Eng with 10 year experience- part time)
B94: MEP Engineer( Building Service Eng with 10 year experience- part time)
B95: ( Site Engineer BSc.Eng with 5 years or NDT-Civil with 10 years experience- Full Time )
B96: (CV to be submitted with the bid)
A98: 3 | B98: Setting Out
A100: =A98+0.01 -> 3.01 | B100: Allow sum for emplyoing a licensed land surveyor to define the building site work etc., check levels and carry out such other surveys as may be necessary to establish accrately the placing of forms and pouring of concrete and all other setting out in both vertical and horizontal plane. | C100: G | D100: 1 | E100: Item | F100: 75000 | G100: =+$J$1 -> 1 | H100: =ROUNDUP(F100/G100,-1) -> 75000 | I100: =+H100*D100 -> 75000
A102: 4 | B102: Quality, Standards and Progress
A104: =A102+0.01 -> 4.01 | B104: Allow lunp sum for preparing As built drawings of following services. All drawings shall be produced in triplicate to a scale (3 set of binded hard copy) and one electronic copy in Auto CAD format | C104: E | D104: 1 | E104: Item | I104: N/A
B105: 1.Architectural
B106: 2.Electricle
B107: 3.Water Supply,Sewarage and Waste Water lines
A109: 5 | B109: Health Safety and Environment
A111: =A109+0.01 -> 5.01 | B111: Allow lump sum for maintaining the site in a clean and orderly manner at all times and during the entire contract period. | C111: E | D111: 1 | E111: Item | F111: 150000 | G111: =+$J$1 -> 1 | H111: =ROUNDUP(F111/G111,-1) -> 150000 | I111: =+H111*D111 -> 150000
A112: 6 | B112: Services and Facilities
A114: =A112+0.01 -> 6.01 | B114: Allow lump sum for supply of water for the Works and paying all charges and other expenses in connection with the supply from water mains or any other alternative method of water supply, storage and reticulation | C114: E | D114: 1 | E114: Item | I114: Provide by Client
A116: =A114+0.01 -> 6.02 | B116: Allow lump sum for supplying temporary electricity for the works including connection, distribution system for the Works, internal arrangements and all payments to be authorities for consumption | C116: E | D116: 1 | E116: Item | I116: Provide by Client
A118: =A116+0.01 -> 6.03 | B118: Allow lump sum for erecting and maintaining scaffolding and/ self climbing platforms around the construction building wall area. Such scaffolding etc. shall be removed on completion and all Works disturbed shall be made good.rate to include to safety dust coverd green net for total building perimeter building height area | C118: F | D118: 1 | E118: Item | I118: Provide by Client
B120: A - PRELIMINARIES CARRIED TO GRAND SUMMARY | I120: =SUM(I3:I119) -> 405000

Sheet waterprof
A1: Nos | B1: Description | C1: Qty | D1: Unit | E1: COST | F1: OHP% | G1: Rate | H1: Amount | I1: =+summary!D11 -> 0.75
B2: E - WATER PROOFING WORK
B4: The rates for Items are strictly applicable, subject to the fulfillment of the following conditions.
B6: The water proofing material shall conform to relevant British, Euro or ASTM specifications
B8: Recommended Distributors/Agents who are marketing water proofing material/product are 1. M/s Finco Ltd. 2. M/s HE Engineering 3. M/s Ranki International 4. M/s Solico Engineering 5. M/s Sika Lanka
B9: The contractor shall submmit;
B11: (a) A written certificate stating that all material and workmanship are in conformity with the specifications and the manufactures requirements.
B13: (b) The contractor shall jointly with manufacture/supplier of the waterproofing materials shall furnish a warranty to the Employer valid for a period of 10 years after handing over of the work against dampness and/or moisture penetration through treated surfaces due to defective materials and/or workmanship
B15: payments for items shall be made on receipt of above certificate
B17: The rates for items include the cost of surface preparation, ande the cost of protective masonry screed. Appropriate B.S.R. item rate shall be used for protective layer. The approving authority for products shall be the Engineer.
A19: E. 01 | B19: Internal Wet Areas without Exposure to Sunlight Sq.ft. (Cementitious water proofing using Barralastic or approved equivalnt)
B20: Application of cementitious water proofing using Barralastic or approved equivalnt for internal wet areas such as toilet floors and walls (Walls Up to 1.50m) where the surfaces are not directly exposed to sunlight and weathering. Rate shall include to cleaning the substrate and 1:3 cement sand bedding and all other work as per manufacturer's specifications on application and shall include ponding test for a 300mm water height kept for a period of 48 hours for horizontal surfaces.
A21: E. 01.1 | B21: Ground Floor | C21: ='m shet Mr Ratheshon'!N103 -> 32 | D21: S.qm | E21: =+RBD!F943 -> 3467.043 | F21: =+$I$1 -> 0.75 | G21: =ROUNDUP(E21/F21,-1) -> 4630 | H21: =+G21*C21 -> 148160
A22: E. 01.2 | B22: First Floor | C22: ='m shet Mr Ratheshon'!N106 -> 38 | D22: S.qm | E22: =+E21*1.02 -> 3536.3839 | F22: =+$I$1 -> 0.75 | G22: =ROUNDUP(E22/F22,-1) -> 4720 | H22: =+G22*C22 -> 179360
A23: E. 01.3 | B23: Roof top Floor | C23: ='m shet Mr Ratheshon'!N112 -> 25 | D23: S.qm | E23: =+'RBD Material'!H38*10.76 -> 4788.2 | F23: =+$I$1 -> 0.75 | G23: =ROUNDUP(E23/F23,-1) -> 6390 | H23: =+G23*C23 -> 159750
A24: E. 01.4 | B24: Roof Floor | D24: S.qm
A26: E. 02 | B26: Areas exposed to sunlight (Balconies, Sun-Shades Concrete Gutters etc) (Elastomeric water proofing using thoroseal or approved equivalent.)
B28: Application of two coats of elastomeric water proofing material using thoroseal or approved equivalnt capable to withstand temperature variation for wet areas exposed to sunlight and weathering. ( balconies, sun-shades, concrete gutters etc.) rate shall include for cleaning the substrate and all other work as per manufacturer's specifications on application and shall include ponding test for a 300mm water height kept for a period of 48 hours for horizontal surfaces and cement sand finished with neat finish smooth rendering.
A29: E. 02.1 | B29: Ground Floor | C29: ='m shet Mr Ratheshon'!N116 -> 11 | D29: S.qm | E29: =+E21 -> 3467.043 | F29: =+$I$1 -> 0.75 | G29: =ROUNDUP(E29/F29,-1) -> 4630 | H29: =+G29*C29 -> 50930
A30: E. 02.2 | B30: First Floor | C30: ='m shet Mr Ratheshon'!N123 -> 63 | D30: S.qm | E30: =+E29*1.02 -> 3536.3839 | F30: =+$I$1 -> 0.75 | G30: =ROUNDUP(E30/F30,-1) -> 4720 | H30: =+G30*C30 -> 297360
A31: E. 02.3 | B31: Roof level Floor | C31: ='m shet Mr Ratheshon'!N127 -> 107 | D31: S.qm | E31: =+E23 -> 4788.2 | F31: =+$I$1 -> 0.75 | G31: =ROUNDUP(E31/F31,-1) -> 6390 | H31: =+G31*C31 -> 683730
A32: E. 02.4 | B32: Water Tank Floor | C32: ='m shet Mr Ratheshon'!N454 -> 0 | D32: S.qm
A33: E. 02.5 | B33: laying of Topseal 3mm thick,Torch-on membrane or any othere quivalent product marketed /installed by a specialist contractor registered at ICTAD under waterproofing category including 1:3 cement,sand protective screed laid to slope.Rate shall include the formation of edges,torch welding and fixing metal stripon vertical walls at termination edges.
A34: E. 02.6 | B34: Fourth Floor | D34: S.qm
A35: E. 02.7 | B35: Roof Slab | D35: S.qm
A36: E. 02.8 | B36: Water Tank/Lift Room Slab | C36: ='m shet Mr Ratheshon'!N585 -> 0 | D36: S.qm
B38: WATER PROOFING WORK CARRIED TO COLLECTION | H38: =SUM(H19:H37) -> 1519290

Sheet concrete
A1: Nos | B1: Description | C1: Qty | D1: Unit | E1: COST | F1: OHP% | G1: Rate | H1: Amount | I1: =+summary!D8 -> 0.75
B2: C - CONCRETE
B3: Note:
B4: Rates for concrete are grouped under following categories
B6: 1. In-situ plain concrete (mixed at site either manually or with machine)
B8: 2. Reinforced concrete of Grade 20 &25 (mixed at site with a concrete mixer )
B10: These items are meant for Footings, Columns, Plinth beams, Floor beams, Tie-beams & Stair case. i.e. load bearing members. | Q10: =H74+H169 -> 936220
B12: 3. Ready mixed concrete of Grade 20 ,Grade 25 . Grade 30
B14: 4. Site produced concrete of Grade 20 - (machine mix or in case of small quantities manually mixed)
B16: These items are meant for pre-cast lintols, stiffeners, copings,concrete drains, etc.
B18: 5. Curing for In situ plain concrete, In situ reinforced concrete, Site produced concrete of Grade 20 & Ready mix concrete
B20: In - Situ Plain Concrete (mixed at site either manually or with machine)
B21: The Quality of the concrete should confirm to the relevant B.S., S.L.S. and ICTAD specification for Building works.
B22: UP TO DPC LEVEL
B23: In - Situ Plain Concrete (mixed at site either manually or with machine)
A25: C 01 | B25: Cement concrete 1:3:6 (1") laid to a thickness of 2" in wall foundations, under column/stair footings,plinth beams including placing in position,compacting and curing. | C25: 147 | D25: Sqm | E25: =+RBD!H116 -> 1331.7386 | F25: =+$I$1 -> 0.75 | G25: =ROUNDUP(E25/F25,-1) -> 1780 | H25: =+G25*C25 -> 261660
B27: IN - SITU REINFORCED CONCRETE
B29: In - Situ Reinforced Concrete Of Grade 25 &30 (mixed at site with a concrete mixer )
B31: Grade 25 concrete shall be used for footings, columns, beams,staircases, tie-beams of reinforced concrete elements in multi-storied building (excluding lintols, stiffener columns, copings, non-structural columns and Drains).
B32: Constituent material shall comply to following;
B34: (i) Cement of strength class 42.5N and shall comply with SLS 107 (Ordinary Portland Cement) & SLS 1253 (Portland Limestone Cement) , that has been stored under proper conditions and has manufactured within 90 days at the time of concreting.
B36: (iii) Clean river sand without impurities and clay particles of grain distribution falling within the prescribed grading limit in BS 882:1992.
B38: iv) Well graded coarse aggregate free of impurities with maximum aggregate size being 20mm. grain distribution falling within the prescribed grading limit in BS 882:1992.
B40: (v) Clean portable water
B42: Volume batching of constituent material (a) The equivalent nominal mix suggest for volume batching the Grade 25 & 30 concrete is given in table 4.4 of ICTAD specification for Building Work SCA/4/I of July 2004 for a 50kg cement bag and measuring boxes is reproduced below.
B44: Coarse aggregate to be proportioned for the volume batching using the measurement boxes as indicated in the Clause 4.3.1 ICTAD/SCA/4/I. The internal dimensions of the boxes are 400 x 350 x 250mm (which is 0.035m3 and corresponds to the volume of 1 bag of cement weighing 50 kg). The proportioning of sand shall be on the basis of its dry volume and in the case of damp sand allowance for bulkage shall be made as given in Appendix 4C of ICTAD specification.
B46: Water:Cement ratio shall not exceed 0.45. Based on this Water:Cement ratio, volume of water required (either weight or converted volume of water) shall be decided for a given cement content. Required water content shall then be added by measuring the volume from a calibrated measuring Jar.
B48: Cement shall be added in bag form.
... B71: (b).Quality assurance report signed by the contractor’s technical officer or agent, Divisional Engineer’s technical officer who has witnessed the concreting along with senior technical officer in charge of the site.
A73: C 02 | B73: Volume Batched Grade 25 concrete prepared at site using mixer and vibrator in ground floor.Rate shall include the cost of curing continously for 7 days. Upto DPC
A74: C2.1 | B74: In column/strip footing | C74: 16 | D74: m3 | E74: =+RBD!F204 -> 33871.94 | F74: =+$I$1 -> 0.75 | G74: =ROUNDUP(E74/F74,-1) -> 45170 | H74: =+G74*C74 -> 722720
A75: C2.2 | B75: In column shaft | C75: 2 | D75: m3 | E75: =+E74*1.1 -> 37259.134 | F75: =+$I$1 -> 0.75 | G75: =ROUNDUP(E75/F75,-1) -> 49680 | H75: =+G75*C75 -> 99360
A76: C2.3 | B76: In plinth Beams | C76: 13 | D76: m3 | E76: =+E74 -> 33871.94 | F76: =+$I$1 -> 0.75 | G76: =ROUNDUP(E76/F76,-1) -> 45170 | H76: =+G76*C76 -> 587210
A77: C2.4 | B77: In staircases | C77: 1.5 | D77: m3 | E77: =+E74*1.15 -> 38952.731 | F77: =+$I$1 -> 0.75 | G77: =ROUNDUP(E77/F77,-1) -> 51940 | H77: =+G77*C77 -> 77910
A79: C 03 | B79: Volume Batched Grade 20/ready mix reinforced concrete floors laid on ground. Rate shall include the cost of curing continously for 10 days. ( rate include to transport from batching plant. Rate shall inclue for placing, levelling, vibrating & curing the concrete & pump car cost)
A80: C3.1 | B80: Ground floor concrete(100mm thick) | C80: 25 | D80: m3 | E80: =+RBD!F160 -> 30459.227 | F80: =+$I$1 -> 0.75 | G80: =ROUNDUP(E80/F80,-1) -> 40620 | H80: =+G80*C80 -> 1015500
B82: SUPER STRUCTURE
A84: C 04 | B84: Volume Batched Grade 25 concrete prepared at site using mixer or Grade 25 ready mix( rate include to transport from batching plant. Rate shall inclue for placing, levelling, vibrating & curing the concrete & pump car cost) and vibrator in ground floor. Rate shall include the cost of curing continously for 7 days.
A85: C4.1 | B85: In column shaft from ground floor level to First floor level | C85: 7 | D85: m3 | E85: =+E75 -> 37259.134 | F85: =+$I$1 -> 0.75 | G85: =ROUNDUP(E85/F85,-1) -> 49680 | H85: =+G85*C85 -> 347760
A87: C4.2 | B87: In column shaft from First floor level to Second floor level | C87: 6 | D87: m3 | E87: =+E85*1.05 -> 39122.09 | F87: =+$I$1 -> 0.75 | G87: =ROUNDUP(E87/F87,-1) -> 52170 | H87: =+G87*C87 -> 313020
A89: C4.3 | B89: In column shaft from Second floor level to Roof floor level | C89: 3 | D89: m3 | E89: =+E85*1.1 -> 40985.047 | F89: =+$I$1 -> 0.75 | G89: =ROUNDUP(E89/F89,-1) -> 54650 | H89: =+G89*C89 -> 163950
B90: READY MIX CONCRETE
B91: Requirement for Ready mixed concrete
B92: (i) Ready mix concrete is confirming to SLS 1144-1997.
B93: (ii) Minimum cement content shall be 300 kg/m3
B94: (iii) Nominal maximum size of aggregate shall be 20mm.
B95: (iv) Slump shall be as per the mix design.
B96: (v) Maximum temperature 30 Celsius
B97: (vi) Maximum free water / cement ratio to be 0.5
B98: (vii) Coarse and Fine aggregate used shall confirm to BS 882 latest version. Seive analysis reports within 6 months should be submitted for approval .
B99: (viii) Concrete grade shall be as specified.
B100: (ix) Concrete mix design shall be approved by the Engineer
B101: (x) The Ready mix supplier's plant should have been calibrated in the recent past.
... B105: Rate to include the transport from batching plant.
A107: C 05 | B107: Ready mix concrete of grade 25(25 N/mm2) confirming to SLS 1144- 1997, rate include to transport from batching plant. Rate shall inclue for placing, levelling, vibrating & curing the concrete & pump car cost | Q107: =32294/30 -> 1076.4667
A108: C5.1 | B108: In Reinforced beam at First floor level | C108: 15 | D108: Cu.m | E108: =+RBD!F160 -> 30459.227 | F108: =+$I$1 -> 0.75 | G108: =ROUNDUP(E108/F108,-1) -> 40620 | H108: =+G108*C108 -> 609300 | Q108: =+P108/M108 -> #DIV/0!
A109: C5.2 | B109: In Reinforced beam at second floor level | C109: 14 | D109: Cu.m | E109: =+E108*1.05 -> 31982.188 | F109: =+$I$1 -> 0.75 | G109: =ROUNDUP(E109/F109,-1) -> 42650 | H109: =+G109*C109 -> 597100 | Q109: =+P109/M109 -> #DIV/0! | R109: =10.7+5.9 -> 16.6 | S109: =R109*0.55*0.3 -> 2.739
A110: C5.3 | B110: In Reinforced beam at Roof Top floor level | C110: 8 | D110: Cu.m | E110: =+E108*1.1 -> 33505.15 | F110: =+$I$1 -> 0.75 | G110: =ROUNDUP(E110/F110,-1) -> 44680 | H110: =+G110*C110 -> 357440
A112: C5.3 | B112: In Reinforced slab at First floor level | C112: 31 | D112: Cu.m | E112: =+E108 -> 30459.227 | F112: =+$I$1 -> 0.75 | G112: =ROUNDUP(E112/F112,-1) -> 40620 | H112: =+G112*C112 -> 1259220
A113: C5.4 | B113: In Reinforced Slab at second floor level | C113: 30 | D113: Cu.m | E113: =+E109 -> 31982.188 | F113: =+$I$1 -> 0.75 | G113: =ROUNDUP(E113/F113,-1) -> 42650 | H113: =+G113*C113 -> 1279500
A114: C5.5 | B114: In Reinforced Slab at Roof Top floor level | C114: 8 | D114: Cu.m | E114: =+E110 -> 33505.15 | F114: =+$I$1 -> 0.75 | G114: =ROUNDUP(E114/F114,-1) -> 44680 | H114: =+G114*C114 -> 357440
B116: D - FORM WORK
B117: Note:
B118: Shuttering boxes for columns of over 5'-0" height are not permitted under any circumstances for the pouring of manually produced (site mix) concrete.
B119: If a contractor made an appeal to use shuttering boxes (Customary steel boxes or plywood boxes) of over 5'-0" height, then ,Engineer may personally approve for casting a column shaft up to a maximum height of 4'-0" at a time subject to the fulfillment of following conditions.
B120: (a) The concrete mix designed based on material available at the site for a W/C ratio of 0.45 and to be able to Pour without segregation.
B121: (b) The method statement of pouring concrete in to the column shaft signed by a competent technical person from the contractor's side should be submitted.
B122: (c)In case of tremie pipe, it shall have a diameter of not less than 4" with a funnel.
B123: (d)How the funnel and pipe is lowered and kept in position without disturbing the formwork shall be indicated in the method statement.
B124: (e) A Method statement for compaction shall be submitted.
B125: (f)Engineer, upon satisfaction himself/herself to the arrangement of placing concrete and having paying special attention to the method of compaction by a person standing at a height and lowering his head and doing compaction in a restricted cross-section with a tremie pipe inside; may be allowed to proceed with a log note.
A127: (a) | B127: The rates given for items herein are applicable for plywood sheets of 15 mm thick. Hence the rate is valid only if the shuttering / formwork for footing , column , beams , lintel, walls, slabs are of 15 mm thick ply boards.
A129: (b) | B129: Any deviation from the specified materials, specified thickness and the arrangement of formwork given in this document should require the written approval of the Divisional Engineer. Rate for such deviation from the item description will be decided by the D(B/SW)
A131: (c) | B131: For ordinary plywood of 15 mm thick boarding as shuttering, (Even for WBP sheets the same rate shall be applicable).
B133: Up to DPC level
A134: D 01 | B134: Shuttering for sides of foundation with 15mm thick Plywood board including dismantling
A136: D 1.1 | B136: In stairacse | C136: 8 | D136: Sqm | E136: 2650 | F136: =+$I$1 -> 0.75 | G136: =ROUNDUP(E136/F136,-1) -> 3540 | H136: =+G136*C136 -> 28320
A138: D 02 | B138: Shuttering for sides and bottom of plinth beams, ground beams including dismantling in 15mm thick plywood board.
B139: Plinth beam | C139: 108 | D139: Sqm | E139: 2100 | F139: =+$I$1 -> 0.75 | G139: =ROUNDUP(E139/F139,-1) -> 2800 | H139: =+G139*C139 -> 302400
B140: Column base | C140: 43 | D140: Sqm | E140: 2100 | F140: =+$I$1 -> 0.75 | G140: =ROUNDUP(E140/F140,-1) -> 2800 | H140: =+G140*C140 -> 120400
B141: Column Stub | C141: 21 | D141: Sqm | E141: 2250 | F141: =+$I$1 -> 0.75 | G141: =ROUNDUP(E141/F141,-1) -> 3000 | H141: =+G141*C141 -> 63000
A143: D 03 | B143: Shuttering for Columns including dismantling using pre-fabricated steel shutter halves including dismantling.
A145: D 3.1 | B145: In column shaft from Base/ ground floor level to First floor level | C145: 98 | D145: Sqm | E145: 2350 | F145: =+$I$1 -> 0.75 | G145: =ROUNDUP(E145/F145,-1) -> 3140 | H145: =+G145*C145 -> 307720
A147: D 3.2 | B147: In column shaft from First floor level to Second floor level | C147: 87 | D147: Sqm | E147: =+E145*1.05 -> 2467.5 | F147: =+$I$1 -> 0.75 | G147: =ROUNDUP(E147/F147,-1) -> 3290 | H147: =+G147*C147 -> 286230
A149: D 3.3 | B149: In column shaft from Second floor level to Roof floor Level | C149: 44 | D149: Sqm | E149: =+E145*1.1 -> 2585 | F149: =+$I$1 -> 0.75 | G149: =ROUNDUP(E149/F149,-1) -> 3450 | H149: =+G149*C149 -> 151800
A151: D 04 | B151: Shuttering for floor slab including dismantling in 15mm thick Plywood board or steel boarding support by steel jack
A152: D 4.1 | B152: In slab at First floor level | C152: 237 | D152: Sqm | E152: 2250 | F152: =+$I$1 -> 0.75 | G152: =ROUNDUP(E152/F152,-1) -> 3000 | H152: =+G152*C152 -> 711000
A153: D 4.2 | B153: In Slab at second floor level | C153: 227 | D153: Sqm | E153: =+E152*1.05 -> 2362.5 | F153: =+$I$1 -> 0.75 | G153: =ROUNDUP(E153/F153,-1) -> 3150 | H153: =+G153*C153 -> 715050
A154: D 4.3 | B154: In Slab at Roof Top floor level | C154: 61 | D154: =D153 -> Sqm | E154: =+E152*1.1 -> 2475 | F154: =+$I$1 -> 0.75 | G154: =ROUNDUP(E154/F154,-1) -> 3300 | H154: =+G154*C154 -> 201300
A156: D 05 | B156: Shuttering for floor Beams including dismantling in 15mm thick plywood board or steel formwork
A157: D 5.1 | B157: In beam at First floor level | C157: 130 | D157: Sqm | E157: 2550 | F157: =+$I$1 -> 0.75 | G157: =ROUNDUP(E157/F157,-1) -> 3400 | H157: =+G157*C157 -> 442000
A158: D 5.2 | B158: In beam at second floor level | C158: 118 | D158: Sqm | E158: =+E157*1.05 -> 2677.5 | F158: =+$I$1 -> 0.75 | G158: =ROUNDUP(E158/F158,-1) -> 3570 | H158: =+G158*C158 -> 421260 | Q158: =11+0.9 -> 11.9 | R158: =0.55+0.55+0.3 -> 1.4 | S158: =R158*Q158 -> 16.66
A159: D 5.3 | B159: In Reinforced beam at Roof Top floor level | C159: 68 | D159: =D158 -> Sqm | E159: =+E157*1.1 -> 2805 | F159: =+$I$1 -> 0.75 | G159: =ROUNDUP(E159/F159,-1) -> 3740 | H159: =+G159*C159 -> 254320
B162: E - REINFORCEMENT
B163: Mild steel and Tor steel bars confirming to BS specifications, tensile strength 250 N/mm2 and 460 N/mm2 respectively, in reinforcements. Rate shall included for lapping, cutting, bending, fabricating, concrete distance blocks, stools, and fixing with binding wires in: spacer bars, placing in position as per the structural drawings
A165: E 01 | B165: Mild/Tor steel reinforcement to slabs, beams, lintols, columns, footings & etc.. bent to shape, laid in position and tied with 16 B.W.G. Aneal binding wire up to Dpc .
A166: E1.2 | B166: In Tie Beams | C166: 1950 | D166: Kg | E166: =+RBD!F57 -> 452.8751 | F166: =+$I$1 -> 0.75 | G166: =ROUNDUP(E166/F166,-1) -> 610 | H166: =+G166*C166 -> 1189500
A167: E1.3 | B167: in Column Base | C167: 1520 | D167: Kg | E167: =+E166*1.1 -> 498.16261 | F167: =+$I$1 -> 0.75 | G167: =ROUNDUP(E167/F167,-1) -> 670 | H167: =+G167*C167 -> 1018400
A168: E1.4 | B168: In Floor Slab | C168: 2125 | D168: Kg | E168: =+E166 -> 452.8751 | F168: =+$I$1 -> 0.75 | G168: =ROUNDUP(E168/F168,-1) -> 610 | H168: =+G168*C168 -> 1296250
A169: E1.5 | B169: in Column Stub | C169: 350 | D169: Kg | E169: =+E166 -> 452.8751 | F169: =+$I$1 -> 0.75 | G169: =ROUNDUP(E169/F169,-1) -> 610 | H169: =+G169*C169 -> 213500
...

Sheet RBD
A1: REINFORCEMENT
A4: R/F cost delivered to Site
B5: Decription | C5: Unit | D5: Qty | E5: Rate | F5: Amount
B7: Price per Ton | C7: Ton | D7: 1 | E7: =+'RBD Material'!D3*1000 -> 365000 | F7: =D7*E7 -> 365000
B8: Loading & Unloading Cost (1hr Un/Sk Labour per 1 Ton) | C8: hr | D8: 3 | E8: 375 | F8: =D8*E8 -> 1125
B9: Transport Cost (Miximum 20km range) | C9: Turn | D9: 1 | E9: 6500 | F9: =D9*E9 -> 6500
A13: Total Cost per 1 Ton of R/F Delivered to Site | F13: =SUM(F7:F12) -> 372625
A14: Total Cost per 1 Kg R/F Delivered to Site | F14: =F13/1000 -> 372.625
B15: Rate Analysis for BOQ Work Items
B16: Pay Item No:
B17: Work Item : | C17: Rebar work
B18: Assumed Quantity for rate build-up : | C18: 500 | D18: Kg
B19: Norm Ref. :
A21: Item no. | B21: Component | C21: Unit | D21: Quantity | E21: Rate (LKR) | F21: Amount (LKR) | G21: Remarks
A23: A.1 | B23: Subcontract for Rebar Bending / Binding | C23: Kg | D23: =+C18 -> 500 | E23: =+'RBD Material'!H5 -> 30 | F23: =+E23*D23 -> 15000
B25: Subtotal -A | F25: =SUM(F23:F24) -> 15000
A27: Item no. | B27: Plant/Equipment Component | C27: Unit | D27: Quantity | E27: Rate (LKR) | F27: Amount (LKR)
B32: Total Cost for Plant/Equipment - B
A34: Item no. | B34: Material Component | C34: Unit | D34: Quantity | E34: Rate (LKR) | F34: Amount (LKR)
A36: C.1 | B36: Rebar | C36: Kg | D36: =+C18 -> 500 | E36: =+F14 -> 372.625 | F36: =+E36*D36 -> 186312.5
A37: C.2 | B37: Cover Blocks | C37: Ps | F37: =+F36*4% -> 7452.5
A38: C.3 | B38: Binding wire | C38: Kg | D38: =+D36*0.02 -> 10 | E38: =+'RBD Material'!D4 -> 370 | F38: =+E38*D38 -> 3700
B40: Total Cost for Material - C | F40: =SUM(F35:F39) -> 197465
A42: Item no. | B42: Miscellaneous Cost Component | C42: Unit | D42: Quantity | E42: Rate (LKR) | F42: Amount (LKR)
A44: 4 | B44: Allow for tools | C44: Allow | D44: 0.01 | E44: =+F25 -> 15000 | F44: =+E44*D44 -> 150
A45: 5 | B45: Allow for Material wastage | C45: Allow | D45: 0.07 | E45: =+F40 -> 197465 | F45: =+E45*D45 -> 13822.55
B47: Total Cost for Miscellaneous - D | F47: =SUM(F44:F46) -> 13972.55
B49: Estimated Direct Cost - E | C49: ( A + B + C + D ) | F49: =+F47+F40+F32+F25 -> 226437.55
B51: Overheads/Preliminary and Profit - F | C51: 0 | D51: of E
B53: Total - H | C53: ( E + F ) | F53: =+F49+F51 -> 226437.55
B55: Rate per unit | C55: ( H / + | D55: 10 | E55: =+C18 -> 500 | F55: =+F53/E55 -> 452.8751
B57: Say Rate(LKR) | C57: per 1 Kg | F57: =+F55 -> 452.8751
A59: CONCRETE
A62: Cement Bag cost delivered to Site
B63: Decription | C63: Unit | D63: Qty | E63: Rate | F63: Amount
B65: Cement Bag (50kg) | C65: Bag | D65: 100 | E65: =+'RBD Material'!D5 -> 2200 | F65: =D65*E65 -> 220000
B66: Loading & Unloading Cost | C66: Bag | D66: =+D65 -> 100 | E66: 30 | F66: =D66*E66 -> 3000
B67: Transport Cost (Miximum 20km range) | C67: Load | D67: 1 | E67: 9000 | F67: =D67*E67 -> 9000
A71: Total Cost per 50 Cement bags | F71: =SUM(F65:F70) -> 232000
A72: Total Cost per 1nr Cement bag delivered to Site | F72: =+F71/D65 -> 2320
B73: Rate Analysis for BOQ Work Items
B74: Pay Item No:
B75: Work Item : | C75: G 15 Concrete
B76: Assumed Quantity for rate build-up : | C76: 5 | D76: m3
B77: Norm Ref. :
A79: Item no. | B79: Component | C79: Unit | D79: Quantity | E79: Rate (LKR) | F79: Amount (LKR) | G79: Remarks
A81: A.1 | B81: Subcontract for Concrete Mixing | C81: m3 | D81: =+C76 -> 5 | E81: =+'RBD Material'!H14 -> 3500 | F81: =+E81*D81 -> 17500
A82: A.2 | B82: Subcontract for Concrete Laying/Leveling/Curring | C82: m3 | D82: =+C76 -> 5 | E82: =+'RBD Material'!H15 -> 1700 | F82: =+E82*D82 -> 8500
B84: Subtotal -A | F84: =SUM(F81:F83) -> 26000
A86: Item no. | B86: Plant/Equipment Component | C86: Unit | D86: Quantity | E86: Rate (LKR) | F86: Amount (LKR)
A88: B.1 | B88: Concrete Mixture | C88: Day | D88: 0.75 | E88: =+'RBD Material'!L3 -> 6000 | F88: =+E88*D88 -> 4500
A89: B.2 | B89: Poker Vibrator | C89: Day | D89: 1 | E89: =+'RBD Material'!L4 -> 2400 | F89: =+E89*D89 -> 2400
B91: Total Cost for Plant/Equipment - B | F91: =SUM(F88:F90) -> 6900
A93: Item no. | B93: Material Component | C93: Unit | D93: Quantity | E93: Rate (LKR) | F93: Amount (LKR)
A95: C.1 | B95: Cement | C95: Bag | D95: =+C76*4.3 -> 21.5 | E95: =+'RBD Material'!D6 -> 2320 | F95: =+E95*D95 -> 49880
A96: C.2 | B96: River Sand | C96: Cube | D96: =+C76*0.53/2.83 -> 0.93639576 | E96: =+'RBD Material'!D7 -> 24500 | F96: =+E96*D96 -> 22941.696
A97: C.3 | B97: Metal (3/4" Agg) | C97: Cube | D97: =C76*0.93/2.83 -> 1.6431095 | E97: =+'RBD Material'!D8 -> 13500 | F97: =+E97*D97 -> 22181.979
B99: Total Cost for Material - C | F99: =SUM(F94:F98) -> 95003.675
A101: Item no. | B101: Miscellaneous Cost Component | C101: Unit | D101: Quantity | E101: Rate (LKR) | F101: Amount (LKR)
A103: 4 | B103: Allow for tools | C103: Allow | D103: 0.02 | E103: =+F84 -> 26000 | F103: =+E103*D103 -> 520
A104: 5 | B104: Allow for Material wastage | C104: Allow | D104: 0.05 | E104: =+F99 -> 95003.675 | F104: =+E104*D104 -> 4750.1837
B106: Total Cost for Miscellaneous - D | F106: =SUM(F103:F105) -> 5270.1837
B108: Estimated Direct Cost - E | C108: ( A + B + C + D ) | F108: =+F106+F99+F91+F84 -> 133173.86
B110: Overheads/Preliminary and Profit - F | C110: 0 | D110: of E
B112: Total - H | C112: ( E + F ) | F112: =+F108+F110 -> 133173.86
B114: Rate per unit | C114: H / | D114: 10 | E114: =+C76 -> 5 | F114: =+F112/E114 -> 26634.772
B116: Say Rate(LKR) | C116: per 1 | E116: =+D76 -> m3 | F116: =+F114 -> 26634.772 | H116: =0.05*F116 -> 1331.7386
B117: Rate Analysis for BOQ Work Items
B118: Pay Item No:
B119: Work Item : | C119: G 20 Concrete
B120: Assumed Quantity for rate build-up : | C120: 5 | D120: m3
B121: Norm Ref. :
A123: Item no. | B123: Component | C123: Unit | D123: Quantity | E123: Rate (LKR) | F123: Amount (LKR) | G123: Remarks
A125: A.1 | B125: Subcontract for Concrete Mixing | C125: m3 | D125: =+C120 -> 5 | E125: =+'RBD Material'!H14 -> 3500 | F125: =+E125*D125 -> 17500
A126: A.2 | B126: Subcontract for Concrete Laying/Leveling/Curring | C126: m3 | D126: =+C120 -> 5 | E126: =+'RBD Material'!H15 -> 1700 | F126: =+E126*D126 -> 8500
B128: Subtotal -A | F128: =SUM(F125:F127) -> 26000
A130: Item no. | B130: Plant/Equipment Component | C130: Unit | D130: Quantity | E130: Rate (LKR) | F130: Amount (LKR)
A132: B.1 | B132: Concrete Mixture | C132: Day | D132: 0.35 | E132: =+'RBD Material'!L3 -> 6000 | F132: =+E132*D132 -> 2100
A133: B.2 | B133: Poker Vibrator | C133: Day | D133: 0.4 | E133: =+'RBD Material'!L4 -> 2400 | F133: =+E133*D133 -> 960
B135: Total Cost for Plant/Equipment - B | F135: =SUM(F132:F134) -> 3060
A137: Item no. | B137: Material Component | C137: Unit | D137: Quantity | E137: Rate (LKR) | F137: Amount (LKR)
A139: C.1 | B139: Cement | C139: Bag | D139: =+C120*6.4 -> 32 | E139: =+'RBD Material'!D6 -> 2320 | F139: =+E139*D139 -> 74240
A140: C.2 | B140: River Sand | C140: Cube | D140: =+C120*0.5/2.83 -> 0.88339223 | E140: =+'RBD Material'!D7 -> 24500 | F140: =+E140*D140 -> 21643.11
A141: C.3 | B141: Metal (3/4" Agg) | C141: Cube | D141: =C120*0.88/2.83 -> 1.5547703 | E141: =+'RBD Material'!D8 -> 13500 | F141: =+E141*D141 -> 20989.399
B143: Total Cost for Material - C | F143: =SUM(F138:F142) -> 116872.51
A145: Item no. | B145: Miscellaneous Cost Component | C145: Unit | D145: Quantity | E145: Rate (LKR) | F145: Amount (LKR)
A147: 4 | B147: Allow for tools | C147: Allow | D147: 0.02 | E147: =+F128 -> 26000 | F147: =+E147*D147 -> 520
A148: 5 | B148: Allow for Material wastage | C148: Allow | D148: 0.05 | E148: =+F143 -> 116872.51 | F148: =+E148*D148 -> 5843.6254
B150: Total Cost for Miscellaneous - D | F150: =SUM(F147:F149) -> 6363.6254
B152: Estimated Direct Cost - E | C152: ( A + B + C + D ) | F152: =+F150+F143+F135+F128 -> 152296.13
B154: Overheads/Preliminary and Profit - F | C154: 0 | D154: of E
B156: Total - H | C156: ( E + F ) | F156: =+F152+F154 -> 152296.13
B158: Rate per unit | C158: H / | D158: 10 | E158: =+C120 -> 5 | F158: =+F156/E158 -> 30459.227
B160: Say Rate(LKR) | C160: per 1 | E160: =+D120 -> m3 | F160: =+F158 -> 30459.227
B161: Rate Analysis for BOQ Work Items
B162: Pay Item No:
B163: Work Item : | C163: G 25 Concrete
B164: Assumed Quantity for rate build-up : | C164: 5 | D164: m3
B165: Norm Ref. :
A167: Item no. | B167: Component | C167: Unit | D167: Quantity | E167: Rate (LKR) | F167: Amount (LKR) | G167: Remarks
...

Sheet masnry
A1: Nos | B1: Description | C1: Qty | D1: Unit | E1: COST | F1: OHP% | G1: Rate | H1: Amount | I1: =+summary!D12 -> 0.75
B2: F - MASONRY WORKS
A3: F | B3: BRICK MASONRY
A4: 1 | B4: Note :
B5: For the full description of materials
B6: and workmanship refer "Specification
B7: of works", "Pricing Preambles" and
B8: "Drawings".
B10: Vertical solid walls, 225mm thick.
A11: =A4+0.01 -> 1.01 | B11: Brick work in cement and sand 1:5 in super Structure in ground floor. ( 9" thick brick work) | C11: ='m shet Mr Ratheshon'!N30 -> 221 | D11: Sqm | E11: =+'Rate Breakdowns'!G669 -> 5906.8084 | F11: =+$I$1 -> 0.75 | G11: =ROUNDUP(E11/F11,-1) -> 7880 | H11: =+G11*C11 -> 1741480
A13: =A11+0.01 -> 1.02 | B13: Brick work in cement and sand 1:5 in First floor level.(9" thick brick work) | C13: ='m shet Mr Ratheshon'!N46 -> 227 | D13: Sqm | E13: =+E11*1.05 -> 6202.1488 | F13: =+$I$1 -> 0.75 | G13: =ROUNDUP(E13/F13,-1) -> 8270 | H13: =+G13*C13 -> 1877290
A15: =A13+0.01 -> 1.03 | B15: Brick work in cement and sand 1:5 in Roof floor level.(9" thick brick work) | C15: ='m shet Mr Ratheshon'!N53 -> 58 | D15: Sqm | E15: =+E11*1.1 -> 6497.4892 | F15: =+$I$1 -> 0.75 | G15: =ROUNDUP(E15/F15,-1) -> 8670 | H15: =+G15*C15 -> 502860
B17: Vertical solid walls, 150mm thick.
A18: =A15+0.01 -> 1.04 | B18: Brick work in cement and sand 1:5 in super Structure in ground floor. ( 6" thick brick work) | C18: ='m shet Mr Ratheshon'!N65 -> 70 | D18: Sqm | E18: =+'Rate Breakdowns'!G696 -> 4023.0288 | F18: =+$I$1 -> 0.75 | G18: =ROUNDUP(E18/F18,-1) -> 5370 | H18: =+G18*C18 -> 375900
A20: =A18+0.01 -> 1.05 | B20: Brick work in cement and sand 1:5 in super Structure in First floor level. ( 6" thick brick work) | C20: ='m shet Mr Ratheshon'!N76 -> 119 | D20: Sqm | E20: =+E18*1.05 -> 4224.1802 | F20: =+$I$1 -> 0.75 | G20: =ROUNDUP(E20/F20,-1) -> 5640 | H20: =+G20*C20 -> 671160
A22: =A20+0.01 -> 1.06 | B22: Brick work in cement and sand 1:5 in Roof floor level.(6" thick brick work) | C22: ='m shet Mr Ratheshon'!N85 -> 70 | D22: Sqm | E22: =+E18*1.1 -> 4425.3317 | F22: =+$I$1 -> 0.75 | G22: =ROUNDUP(E22/F22,-1) -> 5910 | H22: =+G22*C22 -> 413700
B24: Vertical solid walls, 100mm thick.
A25: =A22+0.01 -> 1.07 | B25: Brick work in cement and sand 1:5 in super Structure in ground floor. ( 4" thick brick work) | C25: ='m shet Mr Ratheshon'!N95 -> 68 | D25: Sqm | E25: =+'Rate Breakdowns'!G722 -> 2960.7649 | F25: =+$I$1 -> 0.75 | G25: =ROUNDUP(E25/F25,-1) -> 3950 | H25: =+G25*C25 -> 268600
B27: H - RUBBLE MASONRY
A28: H 01 | B28: Random rubble (6"-9") masonry in cement mortar 1:5 in wall foundation. | C28: 80 | D28: m3 | E28: =+'Rate Breakdowns'!G644 -> 17854.461 | F28: =+$I$1 -> 0.75 | G28: =ROUNDUP(E28/F28,-1) -> 23810 | H28: =+G28*C28 -> 1904800
B30: MASONRY WORKS CARRIED TO COLLECTION | H30: =SUM(H9:H28) -> 7755790

Sheet plumbing
A1: Nos | B1: Description | C1: Qty | D1: Unit | E1: COST | F1: OHP% | G1: Rate | H1: Amount | I1: =+summary!D15 -> 0.75
B2: S - PLUMBING AND DRAINAGE WORK
B3: S - SANITARY FITTINGS
B4: Note :
B5: In view of the variety of sanitary ware and fittings available in the market, it has become necessary to prescribe the exact quality requirements in terms of performance and durability aspects. The "Rocell , American Standard, Lanka Tiles - coloma " brands and respective model numbers have been chosen as a bench mark to establish the said requirements.
B7: The brand name and model number appearing in the respective BSR items are purely meant to describe the performance standard of the said fitting/item and does not imply in any way that only the "Rocell ,American Standard, Lanka Tiles - coloma " brands are recommended or considered to be restricted to the "Rocell & American Standard" brands.
B9: Any other make/brand that has equivalent performance characteristics are considered as equivalent provided such fittings meet with the following criteria.
B10: (a). Has an authorized local agent in Sri Lanka
B11: (b). The local agent has been in the trade of the offered make for not less than 5 years.
B12: (c).The cistern mechanism shall have an assurance for the availability of spares for the next 3 years.
B13: (d). The fittings are manufactured in conformity to BS, JIS, A.S.T.M., A.S. or S.L.S. standards.
B14: (e).The dimensions and performance characteristics are in par with the stated model.
B15: (f).Contractor should submit the purchasing bill and the required warranty for all "Rocell , American Standard, Lanka Tiles - coloma " products
... B22: (c).Manufacturer's Warranty for Lanka Tiles - coloma Brand.
A24: S 01 | B24: Supply and fix white vitreous china (vc) floor standing Vanity wash basin with overflow hole and single tap hole in center of "Rocell" brand or approved equivalent complete to working order inclusive of the 1 1/4" chromium plated waste outlet of "Rocell" brand or approved equivalent and 1 1/4" chromium plated siphon cleanable bottle trap of "Rocell" brand or approved equivalent. (Prime cost of the floor standing wash basin is Rs.40,000.00)
B25: Ground Floor | C25: 4 | D25: Nr | E25: =40000+4500 -> 44500 | F25: =+$I$1 -> 0.75 | G25: =ROUNDUP(E25/F25,-1) -> 59340 | H25: =+G25*C25 -> 237360
B26: First Floor | C26: 3 | D26: Nr | E26: =+E25*1.03 -> 45835 | F26: =+$I$1 -> 0.75 | G26: =ROUNDUP(E26/F26,-1) -> 61120 | H26: =+G26*C26 -> 183360
B27: Second Floor | C27: 1 | D27: Nr | E27: =+E25*1.06 -> 47170 | F27: =+$I$1 -> 0.75 | G27: =ROUNDUP(E27/F27,-1) -> 62900 | H27: =+G27*C27 -> 62900
A29: S 02 | B29: Supply and fix white vitreous china (vc) floor standing close coupled semi . back to wall water closet suite with wash down flushing with 6/3 liters dual flushing has horizontal outlet with vario drain bend and two lateral holes for bottom water connection , P trap, cistern with water inlet from rear of "Rocell" brand or approved equivalent complete to working order inclusive of universal bend of "Rocell" brand. (Prime cost of the water closet, tank and seat cover is Rs.60,000.00)
B30: Ground Floor | C30: 3 | D30: Nr | E30: =60000+4800 -> 64800 | F30: =+$I$1 -> 0.75 | G30: =ROUNDUP(E30/F30,-1) -> 86400 | H30: =+G30*C30 -> 259200
B31: First Floor | C31: 3 | D31: Nr | E31: =+E30*1.03 -> 66744 | F31: =+$I$1 -> 0.75 | G31: =ROUNDUP(E31/F31,-1) -> 89000 | H31: =+G31*C31 -> 267000
B32: Second Floor | C32: 1 | D32: Nr | E32: =+E30*1.06 -> 68688 | F32: =+$I$1 -> 0.75 | G32: =ROUNDUP(E32/F32,-1) -> 91590 | H32: =+G32*C32 -> 91590
A34: S 07 | B34: Supply and fix Chromium plated 1/2" dia. angle valve of "Rocell" brand . model or approved equivalent. (Prime cost of the Chromium plated 1/2" dia. angle valve is Rs. 2,500.00)
B35: Ground Floor | C35: 4 | D35: Nr | E35: =2500+450 -> 2950 | F35: =+$I$1 -> 0.75 | G35: =ROUNDUP(E35/F35,-1) -> 3940 | H35: =+G35*C35 -> 15760
B36: First Floor | C36: 3 | D36: Nr | E36: =+E35*1.03 -> 3038.5 | F36: =+$I$1 -> 0.75 | G36: =ROUNDUP(E36/F36,-1) -> 4060 | H36: =+G36*C36 -> 12180
B37: Second Floor | C37: 1 | D37: Nr | E37: =+E35*1.06 -> 3127 | F37: =+$I$1 -> 0.75 | G37: =ROUNDUP(E37/F37,-1) -> 4170 | H37: =+G37*C37 -> 4170
A39: S 08 | B39: Supply and fix Chromium plated 1 1/4" chromium plated push type waste outlet of "Rocell" brand or approved equivalent. (Prime cost of the Chromium plated 1 1/4" chromium plated waste outlet is Rs. 2,500.00)
B40: Ground Floor | C40: 3 | D40: Nr | E40: =2500+400 -> 2900 | F40: =+$I$1 -> 0.75 | G40: =ROUNDUP(E40/F40,-1) -> 3870 | H40: =+G40*C40 -> 11610
B41: First Floor | C41: 3 | D41: Nr | E41: =+E40*1.03 -> 2987 | F41: =+$I$1 -> 0.75 | G41: =ROUNDUP(E41/F41,-1) -> 3990 | H41: =+G41*C41 -> 11970
B42: Second Floor | C42: 1 | D42: Nr | E42: =+E40*1.06 -> 3074 | F42: =+$I$1 -> 0.75 | G42: =ROUNDUP(E42/F42,-1) -> 4100 | H42: =+G42*C42 -> 4100
A44: S 09 | B44: Supply and fix Chromium plated 1/2" dia. 36" long flexible horse of "Rocell" brand or approved equivalent. (Prime cost of the Chromium plated 1/2" dia. 18" long flexible horse is Rs. 3,000.00)
B45: Ground Floor | C45: 4 | D45: Nr | E45: =3000+450 -> 3450 | F45: =+$I$1 -> 0.75 | G45: =ROUNDUP(E45/F45,-1) -> 4600 | H45: =+G45*C45 -> 18400
B46: First Floor | C46: 3 | D46: Nr | E46: =+E45*1.03 -> 3553.5 | F46: =+$I$1 -> 0.75 | G46: =ROUNDUP(E46/F46,-1) -> 4740 | H46: =+G46*C46 -> 14220
B47: Second Floor | C47: 1 | D47: Nr | E47: =+E45*1.06 -> 3657 | F47: =+$I$1 -> 0.75 | G47: =ROUNDUP(E47/F47,-1) -> 4880 | H47: =+G47*C47 -> 4880
A49: S 10 | B49: Supply and fix chromium plated Bidet Spray of "Rocell" brand or . approved equivalent. (Prime cost of the chromium plated Bidet Spray is Rs. 5,000.00)
B50: Ground Floor | C50: 3 | D50: Nr | E50: =5000+500 -> 5500 | F50: =+$I$1 -> 0.75 | G50: =ROUNDUP(E50/F50,-1) -> 7340 | H50: =+G50*C50 -> 22020
B51: First Floor | C51: 3 | D51: Nr | E51: =+E50*1.03 -> 5665 | F51: =+$I$1 -> 0.75 | G51: =ROUNDUP(E51/F51,-1) -> 7560 | H51: =+G51*C51 -> 22680
B52: Second Floor | C52: 1 | D52: Nr | E52: =+E50*1.06 -> 5830 | F52: =+$I$1 -> 0.75 | G52: =ROUNDUP(E52/F52,-1) -> 7780 | H52: =+G52*C52 -> 7780
A54: S 12 | B54: Supply and fix 5mm thick mirror of size 18" x 24" double coated with pencil edge back strecher. (Prime cost of the 5mm thick mirror of size 18" x 24" is Rs. 4,000.00)
B55: Ground Floor | D55: Nr
B56: First Floor | D56: Nr
B57: Third Floor | D57: Nr
B58: Fourth Floor | D58: Nr
A60: S 11 | B60: Supply and fix Chromium plated pillar tap (cold water) for wash basin of "Rocell" brand or approved equivalent. (Prime cost of the Chromium plated pillar tap (cold water) for wash basin is Rs. 6,000.00)
B61: Ground Floor | C61: 3 | D61: Nr | E61: =6000+550 -> 6550 | F61: =+$I$1 -> 0.75 | G61: =ROUNDUP(E61/F61,-1) -> 8740 | H61: =+G61*C61 -> 26220
B62: First Floor | C62: 3 | D62: Nr | E62: =+E61*1.03 -> 6746.5 | F62: =+$I$1 -> 0.75 | G62: =ROUNDUP(E62/F62,-1) -> 9000 | H62: =+G62*C62 -> 27000
B63: Second Floor | C63: 1 | D63: Nr | E63: =+E61*1.06 -> 6943 | F63: =+$I$1 -> 0.75 | G63: =ROUNDUP(E63/F63,-1) -> 9260 | H63: =+G63*C63 -> 9260
A65: S 12 | B65: Supply and fix Chromium plated Bip tap of of "Rocell" brand or approved equivalent. (Prime cost of the Chromium plated Bip tap is Rs. 5,000.00)
B66: Ground Floor | C66: 3 | D66: Nr | E66: =5000+550 -> 5550 | F66: =+$I$1 -> 0.75 | G66: =ROUNDUP(E66/F66,-1) -> 7400 | H66: =+G66*C66 -> 22200
B67: First Floor | C67: 3 | D67: Nr | E67: =+E66*1.03 -> 5716.5 | F67: =+$I$1 -> 0.75 | G67: =ROUNDUP(E67/F67,-1) -> 7630 | H67: =+G67*C67 -> 22890
B68: Second Floor | C68: 1 | D68: Nr | E68: =+E66*1.06 -> 5883 | F68: =+$I$1 -> 0.75 | G68: =ROUNDUP(E68/F68,-1) -> 7850 | H68: =+G68*C68 -> 7850
B70: Bathroom Accessories
A71: S 13 | B71: Supply and fix chromium plated Soap holder of "Rocell" brand or . approved equivalent. (Prime cost of the chromium plated Soap holder is Rs. 3,500.00)
B72: Ground Floor | C72: 6 | D72: Nr | E72: =3500+450 -> 3950 | F72: =+$I$1 -> 0.75 | G72: =ROUNDUP(E72/F72,-1) -> 5270 | H72: =+G72*C72 -> 31620
B73: First Floor | C73: 6 | D73: Nr | E73: =+E72*1.02 -> 4029 | F73: =+$I$1 -> 0.75 | G73: =ROUNDUP(E73/F73,-1) -> 5380 | H73: =+G73*C73 -> 32280
B74: Second Floor | C74: 2 | D74: Nr | E74: =+E72*1.04 -> 4108 | F74: =+$I$1 -> 0.75 | G74: =ROUNDUP(E74/F74,-1) -> 5480 | H74: =+G74*C74 -> 10960
A76: S 14 | B76: Supply and fix chromium plated Towel Ring of "Rocell" brand or . approved equivalent. (Prime cost of the chromium plated Towel Ring is Rs. 3,500.00)
B77: Ground Floor | C77: 6 | D77: Nr | E77: =3500+650 -> 4150 | F77: =+$I$1 -> 0.75 | G77: =ROUNDUP(E77/F77,-1) -> 5540 | H77: =+G77*C77 -> 33240
B78: First Floor | C78: 6 | D78: Nr | E78: =+E77*1.02 -> 4233 | F78: =+$I$1 -> 0.75 | G78: =ROUNDUP(E78/F78,-1) -> 5650 | H78: =+G78*C78 -> 33900
B79: Second Floor | C79: 2 | D79: Nr | E79: =+E77*1.04 -> 4316 | F79: =+$I$1 -> 0.75 | G79: =ROUNDUP(E79/F79,-1) -> 5760 | H79: =+G79*C79 -> 11520
A81: S 15 | B81: Supply and fix chromium plated Toilet Paper Holder of "Rocell" brand or . approved equivalent. (Prime cost of the chromium plated Toilet Paper Holder is Rs. 3,500.00)
B82: Ground Floor | C82: 3 | D82: Nr | E82: =3500+600 -> 4100 | F82: =+$I$1 -> 0.75 | G82: =ROUNDUP(E82/F82,-1) -> 5470 | H82: =+G82*C82 -> 16410
B83: First Floor | C83: 3 | D83: Nr | E83: =+E82*1.02 -> 4182 | F83: =+$I$1 -> 0.75 | G83: =ROUNDUP(E83/F83,-1) -> 5580 | H83: =+G83*C83 -> 16740
B84: Second Floor | C84: 1 | D84: Nr | E84: =+E82*1.04 -> 4264 | F84: =+$I$1 -> 0.75 | G84: =ROUNDUP(E84/F84,-1) -> 5690 | H84: =+G84*C84 -> 5690
A86: S 16 | B86: Supply and fix Chromium plated bathroom floor gully cover square type of "Lanka Tiles Coloma " brand or approved equivalent. (Prime cost of the Chromium plated bathroom floor gully cover square type is Rs. 8,000.00)
B87: Ground Floor | C87: 6 | D87: Nr | E87: =8000+950 -> 8950 | F87: =+$I$1 -> 0.75 | G87: =ROUNDUP(E87/F87,-1) -> 11940 | H87: =+G87*C87 -> 71640
B88: First Floor | C88: 6 | D88: Nr | E88: =+E87*1.02 -> 9129 | F88: =+$I$1 -> 0.75 | G88: =ROUNDUP(E88/F88,-1) -> 12180 | H88: =+G88*C88 -> 73080
B89: Second Floor | C89: 2 | D89: Nr | E89: =+E87*1.04 -> 9308 | F89: =+$I$1 -> 0.75 | G89: =ROUNDUP(E89/F89,-1) -> 12420 | H89: =+G89*C89 -> 24840
A91: S 17 | B91: Supply and fix chromium plated Toilet Brush Holder of "Lanka Tiles Coloma - Angelo " brand or approved equivalent. (Prime cost of the chromium plated Toilet Brush Holder is Rs. 3,000.00)
B92: Ground Floor | C92: 3 | D92: Nr | E92: =3000+450 -> 3450 | F92: =+$I$1 -> 0.75 | G92: =ROUNDUP(E92/F92,-1) -> 4600 | H92: =+G92*C92 -> 13800
B93: First Floor | C93: 3 | D93: Nr | E93: =+E92*1.02 -> 3519 | F93: =+$I$1 -> 0.75 | G93: =ROUNDUP(E93/F93,-1) -> 4700 | H93: =+G93*C93 -> 14100
B94: =B89 -> Second Floor | C94: 1 | D94: Nr | E94: =+E92*1.04 -> 3588 | F94: =+$I$1 -> 0.75 | G94: =ROUNDUP(E94/F94,-1) -> 4790 | H94: =+G94*C94 -> 4790
B96: Water Tanks
B97: Water tank should combined with three layers of high density polyethylene except 5000 Ltr. Water tank.
B99: The inner and outer layers made of 100% FDA approved virgin raw materials , ensuring non-contamination.
B101: Contractor should submit the purchasing bill and the required warranty for water tanks (10 year warranty) manufactured by "Anton , Arpico" to the Divisional Engineer.
A103: S 18 | B103: Supplying and installing of water tank 2000 ltr. Capacity rate to including the cost of transport. Hoisting in position and specials,rate to include to necessary ball valve and other related fixtures and accessories | C103: 1 | D103: Nr | E103: =95000+32500 -> 127500 | F103: =+$I$1 -> 0.75 | G103: =ROUNDUP(E103/F103,-1) -> 170000 | H103: =+G103*C103 -> 170000
B105: Test
A106: S 19 | B106: Water Pressure testing for PVC pipes. | C106: 1 | D106: Item | E106: 35000 | F106: =+$I$1 -> 0.75 | G106: =ROUNDUP(E106/F106,-1) -> 46670 | H106: =+G106*C106 -> 46670
A108: S 20 | B108: Testing of Water tanks & Sumps as per clause | C108: 1 | D108: Item | E108: 30000 | F108: =+$I$1 -> 0.75 | G108: =ROUNDUP(E108/F108,-1) -> 40000 | H108: =+G108*C108 -> 40000
B110: Pipe Works/Manhole/ Septic Tanks
A111: S 21 | B111: Water supply,waste and sewarage line plumbing work | C111: 1 | D111: P.S | E111: 610000 | F111: =+$I$1 -> 0.75 | G111: =ROUNDUP(E111/F111,-1) -> 813340 | H111: =+G111*C111 -> 813340
B112: DRAINAGE
B113: Waste Water Manhole - Concrete
A114: S 22 | B114: MH- Construction of waste water concrete manhole internal size of 450mm x 450mm & depth vary from 600mm to 900mm ,, consist of 3" thick Grade15 lean concrete & 5" thick Grade 25 RCC base and sides, 1/2" thick cement sand rendering in 1:2 mix trowel smooth with neat grey cement to all internal surfaces and external exposed surfaces. Excavation and 3" thick Grade 20 RCC cover slab with lifting hooks ( Reinforced with 10mm dia.M.S. rods @ 6" c/c both ways) | C114: 4 | D114: Nr | E114: 25500 | F114: =+$I$1 -> 0.75 | G114: =ROUNDUP(E114/F114,-1) -> 34000 | H114: =+G114*C114 -> 136000
B117: Soakage Pits
A118: S 23 | B118: Supplying and fixing 1800mm internal dia.x 2'-6" depth Pre-cast Soakage ( 7 nr of rings) pit with concrete cover and gaps filler with mortar works, and perporated holes manufactured by "SEC" or approved equivalent. Rate shall include to excavtion,back filling, taransporting and hire charges of boomtruck for placing and complete with all the necessary connection to working order and subject to specific approval by the Engineer and detail drawings | C118: 1 | D118: Item | E118: =11000*7+25000+22000 -> 124000 | F118: =+$I$1 -> 0.75 | G118: =ROUNDUP(E118/F118,-1) -> 165340 | H118: =+G118*C118 -> 165340
B120: Septic tanks
A121: S 24 | B121: Construction of Septic tank 5700mm (L) X 2500mm(W) X 3200mm (invet depth) Including excavation ,backfilling, masonry work,concrete work.opening cover with lifting handles,complete with all necessary connection to working order and complete as per the detailded drawings | C121: 1 | D121: Item | E121: 630000 | F121: =+$I$1 -> 0.75 | G121: =ROUNDUP(E121/F121,-1) -> 840000 | H121: =+G121*C121 -> 840000 | L121: =10*4.5*8 -> 360 | M121: =G121/J121*L121 -> #DIV/0!
B123: Waste Water pit
A124: S 25 | B124: Supplying and fixing 1800mm internal dia.x 4'-0" depth Pre-cast waste water ( 2 nr of rings) pit with concrete cover and gaps filler with mortar works, and perporated holes manufactured by "SEC" or approved equivalent. Rate shall include to excavtion,back filling, taransporting and hire charges of boomtruck for placing and complete with all the necessary connection to working order and subject to specific approval by the Engineer and detail drawings | C124: 1 | D124: Item | E124: =11000*2+15000+12500 -> 49500 | F124: =+$I$1 -> 0.75 | G124: =ROUNDUP(E124/F124,-1) -> 66000 | H124: =+G124*C124 -> 66000
B126: Sump Construction
A127: S 26 | B127: Slon underground water sump of water sump , 5000L rate to include excavation and back filling,cover slab and sump open grating , formwork,concrete works, reinforcement work and other all related work, and neat finish and as per the details | C127: 1 | D127: nr | E127: =246000+45000 -> 291000 | F127: =+$I$1 -> 0.75 | G127: =ROUNDUP(E127/F127,-1) -> 388000 | H127: =+G127*C127 -> 388000
B129: PLUMBING AND DRAINAGE WORK CARRIED TO COLLECTION | H129: =SUM(H5:H128) -> 4426560

Sheet metal
A1: Nos | B1: Description | C1: Qty | D1: Unit | E1: COST | F1: OHP% | G1: Rate | H1: Amount | I1: =+summary!D17 -> 0.85
B2: W - METAL WORK
B3: Note:
B4: Aluminium doors, windows and partitions shall confirm to the following requirements:
B6: 1. Aluminium alloy should confirm to- ISO - 9001:2008, SLS 1410:2011 / SLS 1411:2011
B8: 2. Anodized coating thickness should be 25 ± 5 microns
B10: 3.Aluminium extrusions available in the Local Market are being either manufactured in Sri Lanka or imported material. Due to the continuous change of the extrusion profiles and thicknesses from time to time, it has become very difficult to specify standard section sizes that are to be used for door /window frames and sash members. Hence the rates given herein are based on the recommended minimum sizes and thicknesses of profiles published by leading Aluminium profile manufacturers (Alumex Plc, Swisstek Aluminium Limited) as at present for the doors, windows, fanlights and partitions.
B12: before the fabrication contractor must submitt the following information.
B13: 1. The specifications and thickness of Aluminium extrusions proposes to use on the works.
B14: 2. Full size cross sections of profiles.
B15: 3. Documentary evidence from the Profile Manufacture to the effect that the proposed profile will serve for the intended purpose.
B16: 4. A Manufacturer's test certificate be produced as evidence that the powder coating is of required thickness.
B18: 5. Physical properties :-
... B30: The rates shall include Neoprene gasket, pop rivets, Rawl plugs,Screws,Aluminium cleats etc.
A32: 1 | B32: Metal Ceiling
A33: =A32+0.01 -> 1.01 | B33: Supplying & Installing of 600mmx 600mm non perforated white metal sheet ceiling, supported by concealed type furring suspended system installed in a flat horizontal manner using furing bars clipped on to inter locking hot dipped GI main tees with clips, ciling to be susppended using GI 04mm thick hanger rods (Prime cost of 2'-0" x 2'-0" sheet is Rs.2,640.00)
B34: Ground Floor- banak area | D34: Sqr.
B36: Aluminium Panel Ceiling
A37: =A32+0.01 -> 1.01 | B37: Supplying & installing of suspended Aluminium Panel Ceiling in 600mm x 600 grid size reveal / bevel type using hot dipped GI pre –engineered inter - locking main tees (38mm x 14mm) and cross tees (25mm x 14mm) and wall angles expose areas finished with white baked enamel finish and suspended on 4 mm dia. adjustable hanger rods with spring clips. Ceiling panels will be Compton aluminium tiles 600mm x 600mm x 0.7mm (thickness) and complete to working order as per manufacture's specifications..
B38: Ground Floor- | D38: Sqm
A40: 1 | B40: Hand Rail
B41: G.I Tube Hand Rail
A42: =A40+0.01 -> 1.01 | B42: Staircase handr/Balcony rail as per the design | C42: 1 | D42: P.S | E42: =45*11500*3.28 -> 1697400 | F42: =+$I$1 -> 0.85 | G42: =ROUNDUP(E42/F42,-1) -> 1996950 | H42: =+G42*C42 -> 1996950
A44: =A42+0.01 -> 1.02 | B44: Powder coated perforated mesh Hand Rail
B45: Supplying, fabricating & fixing of perforated mesh hand rail upto 1.2m height 50mm dia 2.3mm thick G.I round bar upright @ 3000mm c/c as vertical members fixed bottom end to steps with the 150mm dia 8mm thick M.S. plate connecting with 4 nos of 8mm dia.anchor bolts and work complete in order. Rate Shall include for applying one coat of etch primer (50% of etch primer base and 50% etch primer activator),one coat of anti-corrosive primer with two coats of enamel paint. (Prime cost is Rs, 1,250.00 per sqft)
A47: 3 | B47: Partitions
A49: =A47+0.01 -> 3.01 | B49: Tempored Glass Partition
B50: P1 in 37.5mm x 25mm x 1.4mm thick hairline finished stainless steel 'U' channel framed work and 12mm thick tempered glass with printed PVC stickering fixed with silicon joints as per the detailed drawing and finishes as specified as per the drawings | D50: Sqr.
A52: =A49+0.01 -> 3.02 | B52: HPL Partition
B54: First Floor | D54: Sqm
A56: =A52+0.01 -> 3.03 | B56: Tempored fixed Glass
B57: 37.5mm x 25mm x 1.4mm thick hairline finished stainless steel 'U' channel framed work and 12mm thick tempered glass with printed PVC stickering fixed with silicon joints as per the detailed drawing and finishes as specified as per the drawings
B58: Second Floor | D58: Sqr.
A60: 2 | B60: Doors & Windows
B61: Doors
A63: =A60+0.01 -> 2.01 | B63: Door type D1 size 1200mm x 3600mm class I teak timber solid Paneled door per the detail drawings with all necessary iron mongaries | C63: 1 | D63: nr | E63: =+K63 -> 320734.08 | F63: =+$I$1 -> 0.85 | G63: =ROUNDUP(E63/F63,-1) -> 377340 | H63: =+G63*C63 -> 377340 | I63: =1.2*3.6*10.76 -> 46.4832 | J63: 6900 | K63: =+J63*I63 -> 320734.08
A65: =A63+0.01 -> 2.02 | B65: Door type D2 size 900mm x 2600mm class I teak timber solid Paneled door per the detail drawings with all necessary iron mongaries | C65: 1 | D65: =D63 -> nr | E65: =+K65 -> 157365 | F65: =+$I$1 -> 0.85 | G65: =ROUNDUP(E65/F65,-1) -> 185140 | H65: =+G65*C65 -> 185140 | I65: =0.9*2.6*10.76 -> 25.1784 | J65: 6250 | K65: =+J65*I65 -> 157365
A67: =A65+0.01 -> 2.03 | B67: Door type D3 size 900mm x 3000mm class I teak timber solid Paneled door per the detail drawings with all necessary iron mongaries | C67: 1 | D67: =D65 -> nr | E67: =+K67 -> 181575 | F67: =+$I$1 -> 0.85 | G67: =ROUNDUP(E67/F67,-1) -> 213620 | H67: =+G67*C67 -> 213620 | I67: =0.9*3*10.76 -> 29.052 | J67: 6250 | K67: =+J67*I67 -> 181575
A69: =A67+0.01 -> 2.04 | B69: Door type D4 size 900mm x 2100mm class I teak timber solid Paneled door per the detail drawings with all necessary iron mongaries | C69: 5 | D69: =D67 -> nr | E69: =+K69 -> 127102.5 | F69: =+$I$1 -> 0.85 | G69: =ROUNDUP(E69/F69,-1) -> 149540 | H69: =+G69*C69 -> 747700 | I69: =0.9*2.1*10.76 -> 20.3364 | J69: 6250 | K69: =+J69*I69 -> 127102.5
A71: =A69+0.01 -> 2.05 | B71: Door type D5 size 750mm x 2100mm class I teak timber solid Paneled door per the detail drawings with all necessary iron mongaries | C71: 7 | D71: =D69 -> nr | E71: =+K71 -> 105918.75 | F71: =+$I$1 -> 0.85 | G71: =ROUNDUP(E71/F71,-1) -> 124620 | H71: =+G71*C71 -> 872340 | I71: =0.75*2.1*10.76 -> 16.947 | J71: 6250 | K71: =+J71*I71 -> 105918.75
A73: =A71+0.01 -> 2.06 | B73: Door type D6 size 1320mm x 3000mm class I teak timber solid Paneled door per the detail drawings with all necessary iron mongaries | C73: 1 | D73: =D71 -> nr | E73: =+K73 -> 266310 | F73: =+$I$1 -> 0.85 | G73: =ROUNDUP(E73/F73,-1) -> 313310 | H73: =+G73*C73 -> 313310 | I73: =1.32*3*10.76 -> 42.6096 | J73: 6250 | K73: =+J73*I73 -> 266310
A75: =A73+0.01 -> 2.07 | B75: Door type D7 size 2025mm x 3000mm Aluminium Glass Door per the detail drawings with all necessary iron mongaries | C75: 1 | D75: =D73 -> nr | E75: =+K75 -> 271273.05 | F75: =+$I$1 -> 0.85 | G75: =ROUNDUP(E75/F75,-1) -> 319150 | H75: =+G75*C75 -> 319150 | I75: =2.025*3*10.76 -> 65.367 | J75: 4150 | K75: =+J75*I75 -> 271273.05
A77: =A75+0.01 -> 2.08 | B77: Door type D8 size 1900mm x 2100mm Aluminium Glass Door per the detail drawings with all necessary iron mongaries | C77: 1 | D77: =D75 -> nr | E77: =+K77 -> 178169.46 | F77: =+$I$1 -> 0.85 | G77: =ROUNDUP(E77/F77,-1) -> 209620 | H77: =+G77*C77 -> 209620 | I77: =1.9*2.1*10.76 -> 42.9324 | J77: 4150 | K77: =+J77*I77 -> 178169.46
A79: =A77+0.01 -> 2.09 | B79: Door type D9 size 900mm x 3000mm Aluminium Glass Door per the detail drawings with all necessary iron mongaries | C79: 1 | D79: =D77 -> nr | E79: =+K79 -> 120565.8 | F79: =+$I$1 -> 0.85 | G79: =ROUNDUP(E79/F79,-1) -> 141850 | H79: =+G79*C79 -> 141850 | I79: =0.9*3*10.76 -> 29.052 | J79: 4150 | K79: =+J79*I79 -> 120565.8
A81: =A79+0.01 -> 2.1 | B81: Door type D10 size 1100mm x 3000mm Aluminium Glass Door per the detail drawings with all necessary iron mongaries | C81: 1 | D81: =D79 -> nr | E81: =+K81 -> 147358.2 | F81: =+$I$1 -> 0.85 | G81: =ROUNDUP(E81/F81,-1) -> 173370 | H81: =+G81*C81 -> 173370 | I81: =1.1*3*10.76 -> 35.508 | J81: 4150 | K81: =+J81*I81 -> 147358.2
A83: =A81+0.01 -> 2.11 | B83: Door type D11 size 1100mm x 3000mm Aluminium Glass Door per the detail drawings with all necessary iron mongaries | C83: 1 | D83: =D81 -> nr | E83: =+K83 -> 147358.2 | F83: =+$I$1 -> 0.85 | G83: =ROUNDUP(E83/F83,-1) -> 173370 | H83: =+G83*C83 -> 173370 | I83: =1.1*3*10.76 -> 35.508 | J83: 4150 | K83: =+J83*I83 -> 147358.2
A85: 3 | B85: Windows
A87: =A85+0.01 -> 3.01 | B87: French Window type FW1 , size 3000mmX3000mmm Aluminium Glass French Window per the detail drawings with all necessary iron mongaries | C87: 2 | D87: nr | E87: =+K87 -> 416412 | F87: =+$I$1 -> 0.85 | G87: =ROUNDUP(E87/F87,-1) -> 489900 | H87: =+G87*C87 -> 979800 | I87: =3*3*10.76 -> 96.84 | J87: 4300 | K87: =+J87*I87 -> 416412
A89: =A87+0.01 -> 3.02 | B89: French Window type FW2 , size 2100mmX3000mmm Aluminium Glass French Window per the detail drawings with all necessary iron mongaries | C89: 1 | D89: nr | E89: =+K89 -> 291488.4 | F89: =+$I$1 -> 0.85 | G89: =ROUNDUP(E89/F89,-1) -> 342930 | H89: =+G89*C89 -> 342930 | I89: =2.1*3*10.76 -> 67.788 | J89: 4300 | K89: =+J89*I89 -> 291488.4
A91: =A89+0.01 -> 3.03 | B91: French Window type FW3 , size 2075mmX3000mmm Aluminium Glass French Window per the detail drawings with all necessary iron mongaries | C91: 1 | D91: nr | E91: =+K91 -> 288018.3 | F91: =+$I$1 -> 0.85 | G91: =ROUNDUP(E91/F91,-1) -> 338850 | H91: =+G91*C91 -> 338850 | I91: =2.075*3*10.76 -> 66.981 | J91: 4300 | K91: =+J91*I91 -> 288018.3
A93: =A91+0.01 -> 3.04 | B93: French Window type FW4 , size 3000mmX3000mmm Aluminium Glass French Window per the detail drawings with all necessary iron mongaries | C93: 1 | D93: nr | E93: =+K93 -> 416412 | F93: =+$I$1 -> 0.85 | G93: =ROUNDUP(E93/F93,-1) -> 489900 | H93: =+G93*C93 -> 489900 | I93: =3*3*10.76 -> 96.84 | J93: 4300 | K93: =+J93*I93 -> 416412
A95: =A93+0.01 -> 3.05 | B95: French Window type FW5 , size 2100mmX3000mmm Aluminium Glass French Window per the detail drawings with all necessary iron mongaries | C95: 1 | D95: nr | E95: =+K95 -> 291488.4 | F95: =+$I$1 -> 0.85 | G95: =ROUNDUP(E95/F95,-1) -> 342930 | H95: =+G95*C95 -> 342930 | I95: =2.1*3*10.76 -> 67.788 | J95: 4300 | K95: =+J95*I95 -> 291488.4
A97: =A95+0.01 -> 3.06 | B97: French Window type FW6 , size 5775mmX3000mmm Aluminium Glass French Window per the detail drawings with all necessary iron mongaries | C97: 2 | D97: nr | E97: =+K97 -> 801593.1 | F97: =+$I$1 -> 0.85 | G97: =ROUNDUP(E97/F97,-1) -> 943060 | H97: =+G97*C97 -> 1886120 | I97: =5.775*3*10.76 -> 186.417 | J97: 4300 | K97: =+J97*I97 -> 801593.1
A99: =A97+0.01 -> 3.07 | B99: French Window type FW7 , size 3075mmX3000mmm Aluminium Glass French Window per the detail drawings with all necessary iron mongaries | C99: 5 | D99: nr | E99: =+K99 -> 426822.3 | F99: =+$I$1 -> 0.85 | G99: =ROUNDUP(E99/F99,-1) -> 502150 | H99: =+G99*C99 -> 2510750 | I99: =3.075*3*10.76 -> 99.261 | J99: 4300 | K99: =+J99*I99 -> 426822.3
A101: =A99+0.01 -> 3.08 | B101: Window type W1 size 3050mm x 600mm Aluminium Glass French Window per the detail drawings with all necessary iron mongaries | C101: 1 | D101: =D71 -> nr | E101: =+K101 -> 84670.44 | F101: =+$I$1 -> 0.85 | G101: =ROUNDUP(E101/F101,-1) -> 99620 | H101: =+G101*C101 -> 99620 | I101: =3.05*0.6*10.76 -> 19.6908 | J101: 4300 | K101: =+J101*I101 -> 84670.44
A103: =A101+0.01 -> 3.09 | B103: Fanlight type FL1 , size 1100mmX1500mm Aluminium Glass Fanlight per the detail drawings with all necessary iron mongaries | C103: 4 | D103: =D99 -> nr | E103: =+K103 -> 61251.3 | F103: =+$I$1 -> 0.85 | G103: =ROUNDUP(E103/F103,-1) -> 72070 | H103: =+G103*C103 -> 288280 | I103: =1.1*1.5*10.76 -> 17.754 | J103: 3450 | K103: =+J103*I103 -> 61251.3
A105: =A103+0.01 -> 3.1 | B105: Fanlight type FL2 , size 1050mmX3000mm Aluminium Glass Fanlight per the detail drawings with all necessary iron mongaries | C105: 2 | D105: =D101 -> nr | E105: =+K105 -> 116934.3 | F105: =+$I$1 -> 0.85 | G105: =ROUNDUP(E105/F105,-1) -> 137570 | H105: =+G105*C105 -> 275140 | I105: =1.05*3*10.76 -> 33.894 | J105: 3450 | K105: =+J105*I105 -> 116934.3
A107: =A105+0.01 -> 3.11 | B107: Fanlight type FL3 , size 1425mmX1500mm Aluminium Glass Fanlight per the detail drawings with all necessary iron mongaries | C107: 2 | D107: =D103 -> nr | E107: =+K107 -> 79348.275 | F107: =+$I$1 -> 0.85 | G107: =ROUNDUP(E107/F107,-1) -> 93360 | H107: =+G107*C107 -> 186720 | I107: =1.425*1.5*10.76 -> 22.9995 | J107: 3450 | K107: =+J107*I107 -> 79348.275
A109: =A107+0.01 -> 3.12 | B109: Window type FG1 , size 3700mmX3000mm Aluminium Glass Fixe Glass Window per the detail drawings with all necessary iron mongaries | C109: 1 | D109: =D101 -> nr | E109: =+K109 -> 340392.6 | F109: =+$I$1 -> 0.85 | G109: =ROUNDUP(E109/F109,-1) -> 400470 | H109: =+G109*C109 -> 400470 | I109: =3.7*3*10.76 -> 119.436 | J109: 2850 | K109: =+J109*I109 -> 340392.6
A111: =A109+0.01 -> 3.13 | B111: Window type FG2 , size 1200mmX3000mm Aluminium Glass Fixe Glass Window per the detail drawings with all necessary iron mongaries | C111: 1 | D111: =D109 -> nr | E111: =+K111 -> 110397.6 | F111: =+$I$1 -> 0.85 | G111: =ROUNDUP(E111/F111,-1) -> 129880 | H111: =+G111*C111 -> 129880 | I111: =1.2*3*10.76 -> 38.736 | J111: 2850 | K111: =+J111*I111 -> 110397.6
A113: =A111+0.01 -> 3.14 | B113: Window type FG3 , size 1000mmX3000mm Aluminium Glass Fixe Glass Window per the detail drawings with all necessary iron mongaries | C113: 2 | D113: =D111 -> nr | E113: =+K113 -> 91998 | F113: =+$I$1 -> 0.85 | G113: =ROUNDUP(E113/F113,-1) -> 108240 | H113: =+G113*C113 -> 216480 | I113: =1*3*10.76 -> 32.28 | J113: 2850 | K113: =+J113*I113 -> 91998
A115: =A113+0.01 -> 3.15 | B115: Window type FG4 , size 3700mmX3000mm Aluminium Glass Fixe Glass Window per the detail drawings with all necessary iron mongaries | C115: 2 | D115: =D113 -> nr | E115: =+K115 -> 340392.6 | F115: =+$I$1 -> 0.85 | G115: =ROUNDUP(E115/F115,-1) -> 400470 | H115: =+G115*C115 -> 800940 | I115: =3.7*3*10.76 -> 119.436 | J115: 2850 | K115: =+J115*I115 -> 340392.6
A117: =A115+0.01 -> 3.16 | B117: Window type FG5 , size 5775mmX3000mm Aluminium Glass Fixe Glass Window per the detail drawings with all necessary iron mongaries | C117: 1 | D117: =D115 -> nr | E117: =+K117 -> 531288.45 | F117: =+$I$1 -> 0.85 | G117: =ROUNDUP(E117/F117,-1) -> 625050 | H117: =+G117*C117 -> 625050 | I117: =5.775*3*10.76 -> 186.417 | J117: 2850 | K117: =+J117*I117 -> 531288.45
A119: =A117+0.01 -> 3.17 | B119: Window type FG6 , size 3750mmX3000mm Aluminium Glass Fixe Glass Window per the detail drawings with all necessary iron mongaries | C119: 1 | D119: =D117 -> nr | E119: =+K119 -> 344992.5 | F119: =+$I$1 -> 0.85 | G119: =ROUNDUP(E119/F119,-1) -> 405880 | H119: =+G119*C119 -> 405880 | I119: =3.75*3*10.76 -> 121.05 | J119: 2850 | K119: =+J119*I119 -> 344992.5
A121: =A119+0.01 -> 3.18 | B121: Window type FG7 , size 750mmX3000mm Aluminium Glass Fixe Glass Window per the detail drawings with all necessary iron mongaries | C121: 3 | D121: =D119 -> nr | E121: =+K121 -> 68998.5 | F121: =+$I$1 -> 0.85 | G121: =ROUNDUP(E121/F121,-1) -> 81180 | H121: =+G121*C121 -> 243540 | I121: =0.75*3*10.76 -> 24.21 | J121: 2850 | K121: =+J121*I121 -> 68998.5
A123: =A121+0.01 -> 3.19 | B123: Window type FG8 , size 750mmX3000mm Aluminium Glass Fixe Glass Window per the detail drawings with all necessary iron mongaries | C123: 1 | D123: =D121 -> nr | E123: =+K123 -> 68998.5 | F123: =+$I$1 -> 0.85 | G123: =ROUNDUP(E123/F123,-1) -> 81180 | H123: =+G123*C123 -> 81180 | I123: =0.75*3*10.76 -> 24.21 | J123: 2850 | K123: =+J123*I123 -> 68998.5
A125: =A123+0.01 -> 3.2 | B125: Window type FG9 , size 6440mmX3000mm Aluminium Glass Fixe Glass Window per the detail drawings with all necessary iron mongaries | C125: 1 | D125: =D123 -> nr | E125: =+K125 -> 592467.12 | F125: =+$I$1 -> 0.85 | G125: =ROUNDUP(E125/F125,-1) -> 697030 | H125: =+G125*C125 -> 697030 | I125: =3*6.44*10.76 -> 207.8832 | J125: 2850 | K125: =+J125*I125 -> 592467.12
B131: METAL WORK CARRIED TO COLLECTION | H131: =SUM(H2:H130) -> 17065250

Sheet tile
A1: Nos | B1: Description | C1: Qty | D1: Unit | E1: COST | F1: OHP% | G1: Rate | H1: Amount | I1: =+summary!D13 -> 0.85
B2: L -TILING WORK
B3: Note:
B5: Ceramic Tiles should comply to SLS 1181:2019 "specification and shall comply to relevant abrasion resistant class.
B7: Copy of the first grade tile purchase bill should be produced at the time of payment.
B9: Tiles should comply with European standard specification CEN 177.
B11: Rates include the cost of 1:3 cement:sand motar leveling bed and adhesives
B13: For tile item Should be tile range manufractured by Lanka Floor, Wall Tile or approved equivalant.
A15: L. 01 | B15: Wall Tiling
B16: Glazed wall tiling of size 300mm x 600mm approved colour, supplying and fixing to walls on a 1:3 cement sand mortar layer, and pointed with tile grout to match the tile. (Prime Cost of tile Rs.600.00 per sqft)
A17: L.01.1 | B17: Ground Floor | C17: ='m shet Mr Ratheshon'!N722 -> 83 | D17: Sqm | E17: =+RBD!F633 -> 9228.4229 | F17: =+$I$1 -> 0.85 | G17: =ROUNDUP(E17/F17,-1) -> 10860 | H17: =+G17*C17 -> 901380
A18: L.01.2 | B18: First Floor | C18: ='m shet Mr Ratheshon'!N726 -> 102 | D18: Sqm | E18: =+E17*1.03 -> 9505.2756 | F18: =+$I$1 -> 0.85 | G18: =ROUNDUP(E18/F18,-1) -> 11190 | H18: =+G18*C18 -> 1141380
A19: L.01.3 | B19: Roof floor | C19: ='m shet Mr Ratheshon'!N728 -> 26 | D19: Sqm | E19: =+E17*1.06 -> 9782.1283 | F19: =+$I$1 -> 0.85 | G19: =ROUNDUP(E19/F19,-1) -> 11510 | H19: =+G19*C19 -> 299260
B21: Floor Tiling
B22: Note :
B23: Tile Shall be Homogenous, porcelain floor tiles of industrial grade floor tile range manufactured by Rocell , Lanka Wall Tile or approved equivalent.
B24: Rates include the cost of 1:3 cement:sand motar leveling bed and adhesives and matching grout
B26: Copy of the first grade tile purchase bill should be produced at the time of payment.
A28: L.02 | B28: Ground Floor
A29: L.02.1 | B29: (FF 08) Supplying of 300mm x 300mm temples stone work with masory work | C29: ='m shet Mr Ratheshon'!N731 -> 31 | D29: Sqm | E29: =+RBD!F857 -> 16506.29 | F29: =+$I$1 -> 0.85 | G29: =ROUNDUP(E29/F29,-1) -> 19420 | H29: =+G29*C28 -> 0
B30: In Ground floor
A32: L.02.2 | B32: (FF1) 600mmx1200mm homogeneous floor tile marble floor tile paving on 1:3 cement & sand bedding with suitable adhesives and pointed with tile grout to match the tile. (Prime Cost of tile Rs.600.00 per sqft)
B33: In Ground Floor | C33: ='m shet Mr Ratheshon'!N739 -> 138 | D33: Sqm | E33: =+RBD!F589 -> 8713.435 | F33: =+$I$1 -> 0.85 | G33: =ROUNDUP(E33/F33,-1) -> 10260 | H33: =+G33*C33 -> 1415880
B34: In First Floor | C34: ='m shet Mr Ratheshon'!N741 -> 17 | D34: Sqm | E34: =+E33*1.02 -> 8887.7037 | F34: =+$I$1 -> 0.85 | G34: =ROUNDUP(E34/F34,-1) -> 10460 | H34: =+G34*C34 -> 177820
B35: In Second Floor | C35: ='m shet Mr Ratheshon'!N743 -> 15 | D35: Sqm | E35: =+E33*1.04 -> 9061.9724 | F35: =+$I$1 -> 0.85 | G35: =ROUNDUP(E35/F35,-1) -> 10670 | H35: =+G35*C35 -> 160050
A41: L.02.3 | B41: (FF1) Supply and laying of 4" high skirting including tile grout to match the tile of tiling
B42: In Ground floor | C42: ='m shet Mr Ratheshon'!N748 -> 82 | D42: L.m | E42: =+RBD!F723 -> 956.60757 | F42: =+$I$1 -> 0.85 | G42: =ROUNDUP(E42/F42,-1) -> 1130 | H42: =+G42*C42 -> 92660
B43: =B34 -> In First Floor | C43: ='m shet Mr Ratheshon'!N751 -> 20 | D43: L.m | E43: =+E42*1.01 -> 966.17364 | F43: =+$I$1 -> 0.85 | G43: =ROUNDUP(E43/F43,-1) -> 1140 | H43: =+G43*C43 -> 22800
B44: =B35 -> In Second Floor | C44: ='m shet Mr Ratheshon'!N757 -> 19 | D44: L.m | E44: =+E42*1.02 -> 975.73972 | F44: =+$I$1 -> 0.85 | G44: =ROUNDUP(E44/F44,-1) -> 1150 | H44: =+G44*C44 -> 21850
A46: L.02.4 | B46: (FF2) 900mm x 900mm homogeneous floor tile full body matt floor tile paving on 1:3 cement & sand bedding with suitable adhesives and pointed with tile grout to match the tile. (Prime Cost of tile Rs.600.00 per sqft)
B47: In Ground Floor | C47: ='m shet Mr Ratheshon'!N760 -> 45 | D47: Sqm | E47: =+RBD!F589 -> 8713.435 | F47: =+$I$1 -> 0.85 | G47: =ROUNDUP(E47/F47,-1) -> 10260 | H47: =+G47*C47 -> 461700
A49: L.02.5 | B49: (FF2) Supply and laying of 4" high skirting including tile grout to match the tile of tiling
B50: In Ground floor | C50: ='m shet Mr Ratheshon'!N763 -> 11 | D50: L.m | E50: =+RBD!F723 -> 956.60757 | F50: =+$I$1 -> 0.85 | G50: =ROUNDUP(E50/F50,-1) -> 1130 | H50: =+G50*C50 -> 12430
A52: L.02.6 | B52: (FF3) 600mm x 600mm homogeneous floor tile Full Body Semi Matt Floor tile ( Type 01 ) paving on 1:3 cement & sand bedding with suitable adhesives and pointed with tile grout to match the tile. (Prime Cost of tile Rs.600.00 per sqft)
B53: =B44 -> In Second Floor | C53: ='m shet Mr Ratheshon'!N766 -> 20 | D53: Sqm | E53: =+E47*1.04 -> 9061.9724 | F53: =+$I$1 -> 0.85 | G53: =ROUNDUP(E53/F53,-1) -> 10670 | H53: =+G53*C53 -> 213400
A55: L.02.7 | B55: (FF3) Supply and laying of 4" high skirting including tile grout to match the tile of tiling
B56: =B53 -> In Second Floor | C56: ='m shet Mr Ratheshon'!N769 -> 17 | D56: L.m | E56: =+E50*1.04 -> 994.87187 | F56: =+$I$1 -> 0.85 | G56: =ROUNDUP(E56/F56,-1) -> 1180 | H56: =+G56*C56 -> 20060
A58: L.02.8 | B58: (FF4) 600mm x 600mm homogeneous floor tile Full Body Semi Matt Floor Tile ( Type 02 ) paving on 1:3 cement & sand bedding with suitable adhesives and pointed with tile grout to match the tile. (Prime Cost of tile Rs.600.00 per sqft)
B59: In Ground Floor | C59: ='m shet Mr Ratheshon'!N773 -> 18 | D59: Sqm | E59: =+RBD!F589 -> 8713.435 | F59: =+$I$1 -> 0.85 | G59: =ROUNDUP(E59/F59,-1) -> 10260 | H59: =+G59*C59 -> 184680
B60: In First Floor | C60: ='m shet Mr Ratheshon'!N776 -> 16 | D60: Sqm | E60: =+E59*1.02 -> 8887.7037 | F60: =+$I$1 -> 0.85 | G60: =ROUNDUP(E60/F60,-1) -> 10460 | H60: =+G60*C60 -> 167360
A62: L.02.9 | B62: (FF4) Supply and laying of 4" high skirting including tile grout to match the tile of tiling
B63: In Ground Floor | C63: 14 | D63: L.m | E63: =+RBD!F723 -> 956.60757 | F63: =+$I$1 -> 0.85 | G63: =ROUNDUP(E63/F63,-1) -> 1130 | H63: =+G63*C63 -> 15820
B64: In First Floor | C64: 10 | D64: L.m | E64: =+E63*1.02 -> 975.73972 | F64: =+$I$1 -> 0.85 | G64: =ROUNDUP(E64/F64,-1) -> 1150 | H64: =+G64*C64 -> 11500
A66: L.02.10 | B66: (FF5) 300mm x 300mm homogeneous floor tile Full Body Semi Matt Floor Tile ( Type 03 ) paving on 1:3 cement & sand bedding with suitable adhesives and pointed with tile grout to match the tile. (Prime Cost of tile Rs.600.00 per sqft)
B67: =B56 -> In Second Floor | C67: ='m shet Mr Ratheshon'!N779 -> 18 | D67: Sqm | E67: =+RBD!F589*1.04 -> 9061.9724 | F67: =+$I$1 -> 0.85 | G67: =ROUNDUP(E67/F67,-1) -> 10670 | H67: =+G67*C67 -> 192060
A69: L.02.11 | B69: (FF5) Supply and laying of 4" high skirting including tile grout to match the tile of tiling
B70: =B67 -> In Second Floor | C70: 3 | D70: L.m | E70: =+RBD!F723*1.04 -> 994.87187 | F70: =+$I$1 -> 0.85 | G70: =ROUNDUP(E70/F70,-1) -> 1180 | H70: =+G70*C70 -> 3540
A72: L.02.12 | B72: (FF6) Full Body Gloss floor tile Finishing homogeneous floor tile non slip floor tie paving on 1:3 cement & sand bedding with suitable adhesives and pointed with tile grout to match the tile. (Prime Cost of tile Rs.600.00 per sqft)
B73: In Ground Floor | C73: 4 | D73: Sqm | E73: =+RBD!F589 -> 8713.435 | F73: =+$I$1 -> 0.85 | G73: =ROUNDUP(E73/F73,-1) -> 10260 | H73: =+G73*C73 -> 41040
B74: =B64 -> In First Floor | C74: 3 | D74: Sqm | E74: =+E73*1.02 -> 8887.7037 | F74: =+$I$1 -> 0.85 | G74: =ROUNDUP(E74/F74,-1) -> 10460 | H74: =+G74*C74 -> 31380
B75: =B70 -> In Second Floor | C75: 2 | D75: Sqm | E75: =+E73*1.04 -> 9061.9724 | F75: =+$I$1 -> 0.85 | G75: =ROUNDUP(E75/F75,-1) -> 10670 | H75: =+G75*C75 -> 21340
A79: L.02.13 | B79: (FF7) Solid Timber flooring non slip floor with timber grout to match the tile. (Prime Cost of tile Rs.3,600.00 per sqft)
B80: In First floor | C80: ='m shet Mr Ratheshon'!N785 -> 75 | D80: Sqm | E80: =+E74 -> 8887.7037 | F80: =+$I$1 -> 0.85 | G80: =ROUNDUP(E80/F80,-1) -> 10460 | H80: =+G80*C80 -> 784500
A82: L.02.14 | B82: (FF7) Supply and laying of 4" high skirting including tile grout to match the tile of tiling
B83: In First floor | C83: 9 | D83: L.m | E83: =+E64 -> 975.73972 | F83: =+$I$1 -> 0.85 | G83: =ROUNDUP(E83/F83,-1) -> 1150 | H83: =+G83*C83 -> 10350
A85: L.02.15 | B85: (FF9) Supply and laying Heavy used floor carpet as per the architects direction and specification.. . (Prime Cost of tile Rs.2,100.00 per sqft)
B86: =B75 -> In Second Floor | C86: ='m shet Mr Ratheshon'!N788 -> 57 | D86: Sqm | E86: =2100*10.76*1.25 -> 28245 | F86: =+$I$1 -> 0.85 | G86: =ROUNDUP(E86/F86,-1) -> 33230 | H86: =+G86*C86 -> 1894110
A88: L.02.16 | B88: (FF10) 600mmx600mm(600 x 600)mm Full Body Non - Slip Floor Tile ( For Balcony ) paving on 1:3 cement & sand bedding with suitable adhesives and pointed with tile grout to match the tile. (Prime Cost of tile Rs.600.00 per sqft)
B89: In Ground Floor | C89: ='m shet Mr Ratheshon'!N792 -> 11 | D89: Sqm | E89: =+E73 -> 8713.435 | F89: =+$I$1 -> 0.85 | G89: =ROUNDUP(E89/F89,-1) -> 10260 | H89: =+G89*C89 -> 112860
B90: In First floor | C90: ='m shet Mr Ratheshon'!N797 -> 47 | D90: Sqm | E90: =+E74 -> 8887.7037 | F90: =+$I$1 -> 0.85 | G90: =ROUNDUP(E90/F90,-1) -> 10460 | H90: =+G90*C90 -> 491620
B91: In Second Floor | C91: ='m shet Mr Ratheshon'!N802 -> 72 | D91: Sqm | E91: =+E75 -> 9061.9724 | F91: =+$I$1 -> 0.85 | G91: =ROUNDUP(E91/F91,-1) -> 10670 | H91: =+G91*C91 -> 768240
A93: L.02.17 | B93: (FF11) 300mmx600mm homogeneous Full body Non - Slip Floor paving on 1:3 cement & sand bedding with suitable adhesives and pointed with tile grout to match the tile. (Prime Cost of tile Rs.600.00 per sqft)
B94: In Ground Floor | C94: ='m shet Mr Ratheshon'!N807 -> 11 | D94: Sqm | E94: =+E89 -> 8713.435 | F94: =+$I$1 -> 0.85 | G94: =ROUNDUP(E94/F94,-1) -> 10260 | H94: =+G94*C94 -> 112860
B95: In First floor | C95: ='m shet Mr Ratheshon'!N811 -> 15 | D95: Sqm | E95: =+E90 -> 8887.7037 | F95: =+$I$1 -> 0.85 | G95: =ROUNDUP(E95/F95,-1) -> 10460 | H95: =+G95*C95 -> 156900
B96: In Second Floor | C96: ='m shet Mr Ratheshon'!N813 -> 3 | D96: Sqm | E96: =+E91 -> 9061.9724 | F96: =+$I$1 -> 0.85 | G96: =ROUNDUP(E96/F96,-1) -> 10670 | H96: =+G96*C96 -> 32010
A98: L.02.18 | B98: (FF12) Supply and laying Rubber Matt carpet Floor as per the architects direction and specification.. . (Prime Cost of tile Rs.1,900.00 per sqft)
B99: =B96 -> In Second Floor | C99: ='m shet Mr Ratheshon'!N816 -> 37 | D99: Sqm | E99: =1900*10.76*1.3 -> 26577.2 | F99: =+$I$1 -> 0.85 | G99: =ROUNDUP(E99/F99,-1) -> 31270 | H99: =+G99*C99 -> 1156990
A101: L.02.19 | B101: (FF13) Mosaic Pool tlie paving on 1:3 cement & sand bedding with suitable adhesives and pointed with tile grout to match the tile. (Prime Cost of tile Rs.2,550.00 per sqft)
B102: In First floor | C102: ='m shet Mr Ratheshon'!N820 -> 56 | D102: Sqm | E102: =+RBD!F815 -> 34101.868 | F102: =+$I$1 -> 0.85 | G102: =ROUNDUP(E102/F102,-1) -> 40120 | H102: =+G102*C102 -> 2246720
A104: L.02.20 | B104: (FF14) Supply and laying W.P.C Deck as per the architects direction and specification.. . (Prime Cost of tile Rs.1,850.00 per sqft)
B105: In Ground Floor | C105: ='m shet Mr Ratheshon'!N823 -> 6 | D105: Sqm | E105: =1850*10.76*1.35 -> 26873.1 | F105: =+$I$1 -> 0.85 | G105: =ROUNDUP(E105/F105,-1) -> 31620 | H105: =+G105*C105 -> 189720
B106: In First floor | C106: ='m shet Mr Ratheshon'!N826 -> 33 | D106: Sqm | E106: =+E105*1.02 -> 27410.562 | F106: =+$I$1 -> 0.85 | G106: =ROUNDUP(E106/F106,-1) -> 32250 | H106: =+G106*C106 -> 1064250
A108: L.02.21 | B108: (FF14) Supply and laying 25mm Thick class 01 Solid timber plank as per the architects direction and specification.. . (Prime Cost of tile Rs.4,250.00 per sqft)
B109: In Ground Floor | C109: ='m shet Mr Ratheshon'!N829 -> 9 | D109: Sqm | E109: =4250*10.76*1.2 -> 54876 | F109: =+$I$1 -> 0.85 | G109: =ROUNDUP(E109/F109,-1) -> 64560 | H109: =+G109*C109 -> 581040
B110: In First floor | C110: =C109 -> 9 | D110: Sqm | E110: =+E109*1.02 -> 55973.52 | F110: =+$I$1 -> 0.85 | G110: =ROUNDUP(E110/F110,-1) -> 65860 | H110: =+G110*C110 -> 592740
B111: In Second Floor | C111: =C110 -> 9 | D111: Sqm | E111: =+E109*1.04 -> 57071.04 | F111: =+$I$1 -> 0.85 | G111: =ROUNDUP(E111/F111,-1) -> 67150 | H111: =+G111*C111 -> 604350
B115: TILING WORK CARRIED TO COLLECTION | H115: =SUM(H2:H114) -> 16408650

Sheet RBD Material
B2: Material | F2: Subcontract | J2: Machine
B3: Reinforcement | C3: Kg | D3: 365 | F3: Excavation | G3: m3 | H3: 2200 | J3: Concrete Mixture | K3: Day | L3: =5000+1000 -> 6000
B4: Binding wire | C4: Kg | D4: 370 | J4: Poker Vibrator | K4: Day | L4: =2000+400 -> 2400
B5: Cement | C5: Bag | D5: 2200 | F5: Rebar Binding / Bending | G5: Kg | H5: 30 | J5: Jumping Compactor | K5: Day | L5: 5000
B6: Cement (With Transport) | C6: Bag | D6: =+RBD!F72 -> 2320 | F6: FW - Footing | G6: m2 | H6: 2100 | J6: JCB | K6: Hr | L6: 5500
B7: River Sand | C7: Cube | D7: 24500 | F7: FW - Coulmn shaft | G7: m2 | H7: 2250 | J7: Tipper | K7: Trip | L7: 6000
B8: Metal (3/4" Agg) | C8: Cube | D8: 13500
B9: Checken Mesh | C9: Sqft | D9: =13500/300 -> 45 | F9: FW - Tie Beam | G9: m2 | H9: 1900
B10: Febmix (Admixture) | C10: Liter | D10: 330 | F10: FW - Column | G10: m2 | H10: 1950
F11: FW - Slab | G11: m2 | H11: 2300
B12: Skim Coat (20kg) | C12: Bag | D12: 1100 | F12: FW - Beam | G12: m2 | H12: 2450
B13: Acrylic Wall Filler | C13: Liter | D13: 650 | F13: FW - Staircase | G13: m2 | H13: 2650
B14: Emulsion Paints | C14: Liter | D14: 3100 | F14: Concrete Mixing | G14: m3 | H14: 3500
B15: Weathershield paint | C15: Liter | D15: 3700 | F15: Concrete Laying | G15: m3 | H15: 1700
B16: External Acrylic filler | C16: Liter | D16: 900
B17: Floor Tile | C17: Sqft | D17: 600 | F17: Internal Plaster (+Column & Beam) | G17: m2 | H17: =55*10.76 -> 591.8
B18: Bathroom Wall Tile | C18: Sqft | D18: 600 | F18: External Plaster (+Column & Beam) | G18: m2 | H18: =70*10.76 -> 753.2
B19: Bathroom Floor Tile | C19: Sqft | D19: 600 | F19: Reveal | G19: m | H19: =80*3.24 -> 259.2
B20: Pool Tiling (100 x 100mm) | C20: Sqft | D20: 2550 | F20: Checken mesh Attached | G20: m | H20: =50*3.24 -> 162
F21: Weather Gard | G21: m | H21: =230*3.24 -> 745.2
B22: Staircase Floor Tile | C22: Sqft | D22: 450 | N22: Pool Tiling (100 x 100mm)
B23: Tile Adhesive ( 25 Kg ) | C23: Bag | D23: 2650 | F23: Internal Paint | G23: m2 | H23: =45*10.76 -> 484.2
B24: Tile Grout (1Kg ) | C24: Bag | D24: 280 | F24: Internal Slab Soffit Paint | G24: m2 | H24: =60*10.76 -> 645.6
F25: External Paint | G25: m2 | H25: =33*10.76 -> 355.08
B26: Dry Soil | C26: Cube | D26: 8000
F27: Floor Tiling | G27: m2 | H27: =90*10.76 -> 968.4
F28: Bathroom Floor Tiling | G28: m2 | H28: =120*10.76 -> 1291.2
F29: Tile Skirting | G29: m | H29: =120*3.28 -> 393.6
F30: Wall Tiling | G30: m2 | H30: =180*10.76 -> 1936.8
F31: Staircase Tiling | G31: m2 | H31: =400*10.76 -> 4304
F32: Pool Tiling | G32: m2 | H32: =270*10.76 -> 2905.2
F33: Granite work (With M) | G33: Sqft | H33: =2450 -> 2450
F34: Laying Point Stone | G34: Sqft | H34: 700
F36: Waterproofing work (with material / 4 coat) | G36: Sqft | H36: 310
F37: Waterproofing work (with material / 6 coat) | G37: Sqft | H37: 410
F38: Waterproofing work (Roof Top) Torch Membrane | G38: Sqft | H38: 445
F39: Angle fillet preparation | G39: ft | H39: 190
F41: Titanium works (with material) | G41: Sqft | H41: 660

Sheet floring
A1: Nos | B1: Description | C1: Qty | D1: Unit | E1: COST | F1: OHP% | G1: Rate | H1: Amount | I1: =+summary!D10 -> 0.75
B2: J - FLOORING WORK
A4: J 01 | B4: 3/4" thick D.P.C. in cement sand 1:3 finished with 2 coats of D.P.C. tar and blinded with sand. | C4: ='m shet Mr Ratheshon'!N717 -> 102 | D4: Sqm | E4: 670 | F4: =+$I$1 -> 0.75 | G4: =ROUNDUP(E4/F4,-1) -> 900 | H4: =+G4*C4 -> 91800
A6: J 02 | B6: Gauge 750 polythene damp proof membrane with 6" laps laid under floors. | C6: ='m shet Mr Ratheshon'!N98 -> 265 | D6: Sqm | E6: 228 | F6: =+$I$1 -> 0.75 | G6: =ROUNDUP(E6/F6,-1) -> 310 | H6: =+G6*C6 -> 82150
A8: J 03 | B8: Rendering 1/2" thick in cement sand 1:3 finished smooth with cement slurry without colour pigment and expansion joints filled with construction expansion joint sealent including the cost for cleaning the joints prior application of construction expansion joint sealent by M/s Bitumix or approved equivalent.
B9: Water tank slab/Roof Slab | C9: ='m shet Mr Ratheshon'!N673 -> 61 | D9: Sqm | E9: 1219 | F9: =+$I$1 -> 0.75 | G9: =ROUNDUP(E9/F9,-1) -> 1630 | H9: =+G9*C9 -> 99430
B11: FLOORING WORK CARRIED TO COLLECTION | H11: =SUM(H3:H9) -> 273380

Sheet exca
A1: Nos | B1: Description | C1: Qty | D1: Unit | E1: COST | F1: OHP% | G1: Rate | H1: Amount | I1: =+summary!D7 -> 0.75
B2: B - EXCAVATION & EARTH WORK
B3: SITE PREPERATION
B4: Note :
B5: For the full description of materials
B6: and workmanship refer "Specification
B7: of works", "Pricing Preambles" and
B8: "Drawings".
A10: B 01 | B10: Clearing site vegetation manually including removal of bushes, shurb removing rubbish. | C10: ='m shet Mr Ratheshon'!N196 -> 285 | D10: Sqm | E10: =+RBD!F985 -> 133.75 | F10: =+$I$1 -> 0.75 | G10: =ROUNDUP(E10/F10,-1) -> 180 | H10: =+G10*C10 -> 51300
A12: B 02 | B12: Removing top soil including mud, machinery to a nessasary depth and removing all debris away from site, location decided by client withing 3 km | C12: =C10 -> 285 | D12: Sqm | E12: =+RBD!F1028 -> 331.66667 | F12: =+$I$1 -> 0.75 | G12: =ROUNDUP(E12/F12,-1) -> 450 | H12: =+G12*C12 -> 128250
B14: EXCAVATION
B16: Note:
B17: All excavations are measured net. No allowance made for working space.
B19: Excavations as follows in any materials met with except in rock requiring blasting.
B21: Excavation for foundation commencing from formed ground level.
A22: B 03 | B22: Excavation for column, wall, staircase foundations in any material (except rock requiring blasting) up to depth (as per the drawings), part return fill in and ram and surplus depositted within site as directed. | C22: ='m shet Mr Ratheshon'!N243 -> 128 | D22: m3 | E22: =+RBD!F1069 -> 2310 | F22: =+$I$1 -> 0.75 | G22: =ROUNDUP(E22/F22,-1) -> 3080 | H22: =+G22*C22 -> 394240
B24: Filling & Compaction
B25: Note:-
B26: Approved earth shall mean filling materials that comply to the following :
A27: ( a ) | B27: The earth shall be free of vegetation, roots, boulders, easily decomposable materials, chemicals, industrial waste, plastic etc.
A28: ( b ) | B28: The maximum size of particle shall not exceed 75mm.
A29: ( c ) | B29: The earth shall be well graded and the silt and clay (fines) content shall not be more than 25%
A30: ( d ) | B30: The Standerd proctor density shall be grater than 1.70g/cm3
B32: Back Filling
A33: B 04 | B33: Supplying and compaction of Approved earth,compaction of earth including watering and compaction in 225mm thick layers with proctor density, using machine rammer or roller vibrator, rate to include to compaction maching charges and other nessasary related work | C33: 65 | D33: m3 | E33: =+RBD!F1110 -> 5207.0671 | F33: =+$I$1 -> 0.75 | G33: =ROUNDUP(E33/F33,-1) -> 6950 | H33: =+G33*C33 -> 451750
B35: Antitermite -Tretement
A36: B 05 | B36: Antitermite-treatement for the new construction with applying Biflexthrine 10Tc (Biflex ) or approved equivelant , Dialuted chemicals 1:200 ratio with water after supplying the sealed bottle with lables to the site and should be followed the manufacture standards of application including horizontal & vertical barriers. It should be 10 years warranty on application. | C36: =C12 -> 285 | D36: Sqm | E36: =+(75+15)*10.76 -> 968.4 | F36: =+$I$1 -> 0.75 | G36: =ROUNDUP(E36/F36,-1) -> 1300 | H36: =+G36*C36 -> 370500
B38: Transport
A39: B 09 | B39: Transport of any Material / Debris by any means in bulk including loading | D39: Item
B41: Water Disposal
A42: B 10 | B42: Disposal of Ground Water and Surface Water | D42: Item
B44: EXCAVATION & EARTH WORK CARRIED TO COLLECTION | H44: =SUM(H2:H43) -> 1396040

Sheet plastering
A1: Nos | B1: Description | C1: Qty | D1: Unit | E1: COST | F1: OHP% | G1: Rate | H1: Amount | I1: =+summary!D12 -> 0.75
B2: K - PLASTERING WORK
B3: Note:
B4: 1. The rate for plastering items includes the cost of "Febmix"as a workability enhancer.
B6: 2. For coarse textured plaster ( identified as "semi-rough") all the sand should pass through 4.0mm sieve.
B8: External Plaster
A9: K 01 | B9: Plastering 5/8" thick to walls in cement and sand 1:5 finished semi-rough. Rate includes cost of "Febmix"as a workability enhancer.
A10: K1.1 | B10: In Ground floor | C10: 156 | D10: S.qm | E10: =+RBD!F332 -> 1875.4971 | F10: =+$I$1 -> 0.75 | G10: =ROUNDUP(E10/F10,-1) -> 2510 | H10: =+G10*C10 -> 391560
A11: K1.2 | B11: In First floor | C11: 226 | D11: S.qm | E11: =+E10*1.05 -> 1969.272 | F11: =+$I$1 -> 0.75 | G11: =ROUNDUP(E11/F11,-1) -> 2630 | H11: =+G11*C11 -> 594380
A12: K1.3 | B12: In Roof top Floor | C12: 138 | D12: S.qm | E12: =+E10*1.1 -> 2063.0468 | F12: =+$I$1 -> 0.75 | G12: =ROUNDUP(E12/F12,-1) -> 2760 | H12: =+G12*C12 -> 380880
A14: K 02 | B14: External revels
A15: K 02.1 | B15: Plastering 5/8" thick to reveals in ground floor in cement and sand 1:5 finished semi-rough. Rate includes cost of "Febmix"as a workability enhancer. | C15: 204 | D15: L.m | E15: =+RBD!F371 -> 389.384 | F15: =+$I$1 -> 0.75 | G15: =ROUNDUP(E15/F15,-1) -> 520 | H15: =+G15*C15 -> 106080
A17: K 02.2 | B17: Plastering 5/8" thick to reveals in first floor in cement and sand 1:5 finished semi-rough in first floor. Rate includes cost of "Febmix"as a workability enhancer. | C17: 92 | D17: L.m | E17: =+E15*1.1 -> 428.3224 | F17: =+$I$1 -> 0.75 | G17: =ROUNDUP(E17/F17,-1) -> 580 | H17: =+G17*C17 -> 53360
A19: K 02.3 | B19: Plastering 5/8" thick to reveals in second floor in cement and sand 1:5 finished semi-rough in Second floor. Rate includes cost of "Febmix"as a workability enhancer. | C19: 90 | D19: L.m | E19: =+E15*1.2 -> 467.2608 | F19: =+$I$1 -> 0.75 | G19: =ROUNDUP(E19/F19,-1) -> 630 | H19: =+G19*C19 -> 56700
B21: Internal Plaster
A22: K 03 | B22: Plastering 5/8" thick to walls,columns in cement and sand 1:5 finished smooth with two coats of skim coat.
A23: K3.1 | B23: In Ground floor | C23: 359 | D23: S.qm | E23: =+RBD!F249 -> 1556.7514 | F23: =+$I$1 -> 0.75 | G23: =ROUNDUP(E23/F23,-1) -> 2080 | H23: =+G23*C23 -> 746720
A24: K3.2 | B24: In First floor | C24: 346 | D24: S.qm | E24: =+E23*1.02 -> 1587.8864 | F24: =+$I$1 -> 0.75 | G24: =ROUNDUP(E24/F24,-1) -> 2120 | H24: =+G24*C24 -> 733520
A25: K3.3 | B25: =B12 -> In Roof top Floor | C25: 126 | D25: S.qm | E25: =+E23*1.04 -> 1619.0214 | F25: =+$I$1 -> 0.75 | G25: =ROUNDUP(E25/F25,-1) -> 2160 | H25: =+G25*C25 -> 272160
A27: K 05 | B27: Internal Revels
A28: K 05.1 | B28: Plastering 5/8" thick to reveals in ground floor in cement andsand 1:5 finished smooth with two coats of skim coat in ground floor.Rate includes cost of "Febmix"as a workability enhancer. | C28: 204 | D28: =D17 -> L.m | E28: =+RBD!F288 -> 276.884 | F28: =+$I$1 -> 0.75 | G28: =ROUNDUP(E28/F28,-1) -> 370 | H28: =+G28*C28 -> 75480
A30: K 05.2 | B30: Plastering 5/8" thick to reveals in first floor in cement and sand 1:5 finished smooth with two coats of skim coat in first floor. Rate includes cost of "Febmix"as a workability enhancer. | C30: 92 | D30: =D28 -> L.m | E30: =+E28*1.02 -> 282.42168 | F30: =+$I$1 -> 0.75 | G30: =ROUNDUP(E30/F30,-1) -> 380 | H30: =+G30*C30 -> 34960
A32: K 05.3 | B32: Plastering 5/8" thick to reveals in second floor in cement and sand 1:5 finished smooth with two coats of skim coat in Second floor. Rate includes cost of "Febmix"as a workability enhancer. | C32: 90 | D32: =D30 -> L.m | E32: =+E28*1.04 -> 287.95936 | F32: =+$I$1 -> 0.75 | G32: =ROUNDUP(E32/F32,-1) -> 390 | H32: =+G32*C32 -> 35100
A34: K 06 | B34: Applying two coats of skim coat ( Not exceeding 3 mm thick) to soffit of slab,beams sunshade & stair cases Inc. preparation surface.
A35: K6.1 | B35: In Ground floor | C35: 198 | D35: S.qm | E35: =+'RBD Material'!D12/60+300 -> 318.33333 | F35: =+$I$1 -> 0.75 | G35: =ROUNDUP(E35/F35,-1) -> 430 | H35: =+G35*C35 -> 85140
A36: K6.2 | B36: In First floor | C36: 110 | D36: S.qm | E36: =+E35*1.2 -> 382 | F36: =+$I$1 -> 0.75 | G36: =ROUNDUP(E36/F36,-1) -> 510 | H36: =+G36*C36 -> 56100
B39: PLASTERING WORK CARRIED TO COLLECTION | H39: =SUM(H5:H38) -> 3622140

Sheet paint
A1: Nos | B1: Description | C1: Qty | D1: Unit | E1: COST | F1: OHP% | G1: Rate | H1: Amount | I1: =+summary!D14 -> 0.75
B2: M - COLOUR WASHING, PAINTING & POLISHING
B3: Method of application is accordiong to the manufacturer's method specifications
B5: Internal Emultion Paint
A6: M 01 | B6: Painting walls, columns, Revels with one coat of wall primer and two coats of emulsion paint including preparing surface.
A7: M1.1 | B7: In Ground floor | C7: =plastering!C23 -> 359 | D7: Sqm | E7: =+RBD!F455 -> 1135.4859 | F7: =+$I$1 -> 0.75 | G7: =ROUNDUP(E7/F7,-1) -> 1520 | H7: =+G7*C7 -> 545680
A8: M1.2 | B8: In First floor | C8: =plastering!C24 -> 346 | D8: Sqm | E8: =+E7*1.02 -> 1158.1956 | F8: =+$I$1 -> 0.75 | G8: =ROUNDUP(E8/F8,-1) -> 1550 | H8: =+G8*C8 -> 536300
A9: M1.3 | B9: In Second Floor | C9: =plastering!C25 -> 126 | D9: Sqm | E9: =+E7*1.04 -> 1180.9053 | F9: =+$I$1 -> 0.75 | G9: =ROUNDUP(E9/F9,-1) -> 1580 | H9: =+G9*C9 -> 199080
A10: M1.4 | B10: In Third Floor | D10: Sqm
A12: M 03 | B12: Painting soffit & Beams with one coat of wall primer and two coats of emulsion paint including preparing surface.
A13: M3.1 | B13: In Ground floor | C13: =plastering!C35 -> 198 | D13: Sqm | E13: =+RBD!F500 -> 1300.1139 | F13: =+$I$1 -> 0.75 | G13: =ROUNDUP(E13/F13,-1) -> 1740 | H13: =+G13*C13 -> 344520
A14: M3.2 | B14: In First floor | C14: =plastering!C36 -> 110 | D14: Sqm | E14: =+E13*1.02 -> 1326.1161 | F14: =+$I$1 -> 0.75 | G14: =ROUNDUP(E14/F14,-1) -> 1770 | H14: =+G14*C14 -> 194700
B16: Exterior Emultion Paint
A17: M 04 | B17: Painting walls,slab and revels with one coat of Exterior wall primer and two coats of weathershield weatherproof acrylic exterior emultion paint including preparing surface. including preparing surface for exterior application before applicatin of emulsion paint.
A18: M4.1 | B18: In Ground floor | C18: =plastering!C10 -> 156 | D18: Sqm | E18: =+RBD!F543 -> 1216.446 | F18: =+$I$1 -> 0.75 | G18: =ROUNDUP(E18/F18,-1) -> 1630 | H18: =+G18*C18 -> 254280
A19: M4.2 | B19: In First floor | C19: =plastering!C11 -> 226 | D19: Sqm | E19: =+E18*1.05 -> 1277.2683 | F19: =+$I$1 -> 0.75 | G19: =ROUNDUP(E19/F19,-1) -> 1710 | H19: =+G19*C19 -> 386460
A20: M4.3 | B20: In Second Floor | C20: =plastering!C12 -> 138 | D20: Sqm | E20: =+E18*1.1 -> 1338.0906 | F20: =+$I$1 -> 0.75 | G20: =ROUNDUP(E20/F20,-1) -> 1790 | H20: =+G20*C20 -> 247020
B22: Titanium works
A23: M 05 | B23: Supplying and laying 3mm thick titanium layer on the 12mm thick 1:3 cement sand rough finish bed including 3mm thick glass expansions,after 24 hours wetting the floor for 4 -5 days, and cutting with 100 sanding grit while watering , then cut with 400 sanding grit & after that smooth the floor with 1000 sanding grit pads & apply two coats of sealer on dried clean floor. sealering should be carried out as per the manufacturer's specification. Finally polish with buffing pads to achieve good shine. | C23: 9 | D23: Sqm | E23: =+'RBD Material'!H41*10.76 -> 7101.6 | F23: =+$I$1 -> 0.75 | G23: =ROUNDUP(E23/F23,-1) -> 9470 | H23: =+G23*C23 -> 85230
B26: COLOUR WASHING, PAINTING & POLISHING WORK CARRIED TO COLLECTION | H26: =SUM(H3:H25) -> 2793270

Sheet electicle 
A1: Nos | B1: Description | C1: Qty | D1: Unit | E1: COST | F1: OHP% | G1: Rate | H1: Amount | I1: =+summary!D16 -> 0.75
B2: V - ELECTRICAL INSTALLATION. | I2: 0.9
B3: Note:
B4: Work shall be done in accordance with specifications for electrical and mechanical works - ICTAD Publication No.SCA/8 of Aug.2000(2nd Edition -Revised)
B6: Internal light wiring shall comply with the drawings and shall be in 230/440 volt PVC insulated copper cables
B8: All switches and socket outlets shall be plated type make"Clipsal", " Orange X5", "Krypton" or any other approved equivalent complying to SLS1000:1993 for switches & SLS 1998 : 1991 for soket outlets .
B10: Rate to include switch boxes, Rowl plugs, square pin plug base, Chromium plated M.S. chains, brass hooks, ceiling roses, holders and any other item necessary.
B12: All distribution boards should be incorporated with multi 9, Orange Industrial, Merlin Gerin, , Hager, LS, Moeller/EATON, clipsal,SIEMENS make MCB's (Miniature circuit Breaker ) and cabtree, Clipsal ,Orange Industrial 10 kA, LS , Merlin Gerin,Schinieider make R.C.C.B.'s (Residual Current circuit Breaker) and Schinieider, Merlin Gerin, LS, Dormans Smith ,Orange Industrial (10K), Biticano , Clockner moeller make M.C.C.B.'s (Moulded Case Circuit Breakers)
B14: The whole installation shall be carried out according to CEB/IEE wiring regulations.
B16: All the M.C.C.B.'s, MCB's and RCCB's for the distribution boards should be purchased from the following authorized agents or from heir dealers and a certificate or invoice along with their Company seal and Part No., numbers and warranty should be produced at the time of payment.
B17: a). All MCB, RCCB, shall have 20 Years warranty and hence products which comes with 20 years warranty are permitted.
B18: b). All MCCB shall have 2 Years warranty and hence products which comes with 2 years warranty are permitted.
B19: e). All socket and switches shall have 20 Years warranty and hence products which comes with 20 years warranty are permitted.
B21: Point wiring only with and including switches (Rate includes wiring from MCB through switch to lamp point and includes the switch, switch box, lamp holder wire and conduit)
... B53: Breaker's - European Brand
B55: Inspection and testing | M55: =32000*0.05 -> 1600
A57: V01.01 | B57: Testing of the electrical installation and submission of certificate from a chartered Electrical Engineer registered at CEB. | C57: 1 | D57: Item | G57: 45000 | H57: =+G57*C57 -> 45000
A59: V01.02 | B59: Charges for verifying the wiring done with meggar test & continuity test before commensing installation of Distribution Board & Electrical Fittings | C59: 1 | D59: Item | G59: 55000 | H59: =+G59*C59 -> 55000
A61: V02 | B61: Main Cabling System
B63: All the Cables quoted below shall be on measure and pay basis.
B65: Rates should include for all necessary cable accessories such as cable ties, Cable Lugs, Glands, identification tags, and all accessories for complete installation
B67: Rate shall include for supply and installation of following cables including cable trays, ladders and trunking, conduits,Underground Installments incuding sand beddings ,concrete tiles warning tapes etc. including termination.
B69: All horizontal and vertical Cable trays , trunking , conduits & ladders should be adequately sized to provide 25% spare space. Installation method shall be according to BS 7671
B71: Contractor shall investigate the site conditions and include all the cost involved in point rates given below.
B73: All wiring shall be in securely fixed conduits /trunkig above the ceiling
B75: Main cables for sub distribution boards of each floor shall be tapped from the bus bar riser
A77: V02.01 | B77: Supply, installation & termination of main cable from CEB supply to MDB | C77: 1 | D77: Item | G77: 75000 | H77: =+G77*C77 -> 75000
A79: V02.03 | B79: Supply, installation & termination of from MDB to each DBs. | C79: 1 | D79: Item | G79: 60000 | H79: =+G79*C79 -> 60000
A81: V03 | B81: Main Distribution Board and SUB Distribution Boards and Isolators
B83: All the Distribution Boards shall be surface/flush mounted type Distribution Boards complete with powder coated steel enclosure with lockable doors.
B85: The panel board should have wire numbering and a laminated circuit diagram pasted on the inside surface of the door.
B87: Distribution Boards shall be completed with necessary protection
B89: Make of MCCBs and MCBs, etc shall be Schnider / ABB / Terasaki or equivalent make, approved by the Consultant.
B91: Manufactures shop drawings should be submitted and approved by the Consultant before fabrication
B93: All switches and socket outlets shall be plated type make"Clipsal", " Orange X5", "Krypton" or any other approved equivalent complying to SLS1000:1993 for switches & SLS 1998 : 1991 for soket outlets .
B95: Rate to include switch boxes, Rowl plugs, square pin plug base, Chromium plated M.S. chains, brass hooks, ceiling roses, holders and any other item necessary.
B97: All distribution boards should be incorporated with multi 9, Orange Industrial, Merlin Gerin, , Hager, LS, Moeller/EATON, clipsal, SIEMENS make MCB's (Miniature circuit Breaker ) and cabtree, Clipsal ,Orange Industrial 10 kA, LS , Merlin Gerin,Schinieider make R.C.C.B.'s (Residual Current circuit Breaker) and Schinieider, Merlin Gerin, LS, Dormans Smith ,Orange Industrial (10K), Biticano , Clockner moeller make M.C.C.B.'s (Moulded Case Circuit Breakers)
B99: The whole installation shall be carried out according to CEB/IEE wiring regulations.
B101: All the M.C.C.B.'s, MCB's and RCCB's for the distribution boards should be purchased from the following authorized agents or from their dealers and a certificate or invoice along with their Company seal and Part No., numbers and warranty should be produced at the time of payment.
B103: a). All MCB, RCCB, shall have 20 Years warranty and hence products which comes with 20 years warranty are permitted.
B105: b). All MCCB shall have 2 Years warranty and hence products which comes with 2 years warranty are permitted.
... B123: Supply and Installation of Power Distribution Panels
A124: V03.01 | B124: MDB/DB
B125: Supply and mounted (LED Phase indicator lamps ) Wall/Surface mounted Powder Coated Steel Enclosure with lockable doors ,cover plate & internal wiring c/w bus bars and Accessories.(Rate to include necessary MCCB,MCB,RCCB,and other necessary fixturesand Other required supportive materials should include ) The contractor shoud take advise an electricle engineer before undataking the work and | C125: 1 | D125: Nr | E125: 105000 | F125: =+$I$1 -> 0.75 | G125: =ROUNDUP(E125/F125,-1) -> 140000 | H125: =+G125*C125 -> 140000
A127: V04 | B127: Wiring for light points, ceiling fans, socket outlets
B129: Rate for point wiring shall include for all the cables trays/ladders,conduits, conduit fittings, casings,surface cable trunks, fixing material, switches, wiring and terminations, holders for light fittings and socket outlets for power points. Contractor shall obtain approvals from the Consultant/CEE for above items
B131: As a standard of quality for switches and socket outlets, the contractor may use 'ML/Legrand /ACL or approved equal'.
B133: Light fittings / Fans
B135: The light fittings supplied and installed under this contract shall be in every respect suitable for the intended purpose.
B137: Each fitting shall include bulbs, internal wiring, hanging and fixing material and be complete without any additional item/material being required to make it so.
B138: The contractor shall obtain consultants and clients approval for the fittings before fixing the fittings in the site
B140: As a standard of quality for Light fittings, the contractor may use 'Philips/Osram or approved equal'.
B142: Rate for items shall include the cost of fixing,adapter,connecting 2core 1mm2 . And any other related cost
B144: Lamp fitting shall include the cost of fitting and bulb & shall be given a two year Warranty and one year warranty for bulb
B146: Lamp fitting with given a two year Warranty for fitting
B148: Light Fittings
B149: Rate for items shall include the cost of adapter, connecting 2core 1mm 2 cable o ,galvanized hanging chain.
... B162: GROUND FLOOR
A164: V04.01 | B164: Point wiring for socket outlets 13A - ( 16A Circuits) Supply, Installation & wiring of 13A power Socket Outlet, by using 2x1C 2.5mm^2 Cu /PVC/PVC Cable + 1C 2.5 mm^2 Cu/PVC Earth Cable (in radial circuit) through slab & wall in PVC conduits including PVC conduits, sunk box, junction box, outlet and complete with all other relevant accessories. | C164: 28 | D164: nr | E164: 9000 | F164: =+$I$1 -> 0.75 | G164: =ROUNDUP(E164/F164,-1) -> 12000 | H164: =+G164*C164 -> 336000
A166: V04.02 | B166: Light Point Wiring (10A Circuits)-indoor/outdoor Supply & Installation of light Point Wiring, by using 2x1C 1.5mm^2 Cu/PVC/PVC Cable + 1C 1.5 mm^2 Cu/PVC Earth Cable through slab & wall in PVC conduits including PVC conduits, sunk box, junction box, 10A PVC Switch and complete with all other relevant accessories. | C166: =28 -> 28 | D166: nr | E166: 7500 | F166: =+$I$1 -> 0.75 | G166: =ROUNDUP(E166/F166,-1) -> 10000 | H166: =+G166*C166 -> 280000
A168: V04.03 | B168: Two way light Point Wiring (10A Circuits) Supply & Installation of 2way light Point Wiring, by using 2x1C 1.5mm^2 Cu/PVC/PVC Cable + 1C 1.5 mm^2 Cu/PVC Earth Cable through slab & wall in PVC conduits including PVC conduits, sunk box, junction box, 10A PVC 2 way Switches and complete with all other relevant accessories. | C168: 8 | D168: nr | E168: 8500 | F168: =+$I$1 -> 0.75 | G168: =ROUNDUP(E168/F168,-1) -> 11340 | H168: =+G168*C168 -> 90720
B170: Light Fittings
A172: V04.04 | B172: Installation of light fittings-indoor/outdoor Installation of light fittings including roll plugs, screws and complete with all other relevant accessories. | C172: 81 | D172: nr | E172: 900 | F172: =+$I$2 -> 0.9 | G172: =ROUNDUP(E172/F172,-1) -> 1000 | H172: =+G172*C172 -> 81000
A174: V04.05 | B174: Supplying of Wall Bracket light fittings -(Prime cost is Rs.6,500.00) | C174: 12 | D174: nr | E174: =6500+550 -> 7050 | F174: =+$I$2 -> 0.9 | G174: =ROUNDUP(E174/F174,-1) -> 7840 | H174: =+G174*C174 -> 94080
A176: V04.06 | B176: Inner diameter of 150mm dia Ceiling/slab mounted down light complete with 18w LED lamp. (Prime cost is Rs.6,000.00) | C176: 60 | D176: Nr. | E176: =6000+650 -> 6650 | F176: =+$I$2 -> 0.9 | G176: =ROUNDUP(E176/F176,-1) -> 7390 | H176: =+G176*C176 -> 443400
A178: V04.07 | B178: TY 01 pendant light type 01 as per the 3d drawing (Prime cost is Rs.46,000.00) | C178: 3 | D178: Nr. | E178: =46000+2500 -> 48500 | F178: =+$I$2 -> 0.9 | G178: =ROUNDUP(E178/F178,-1) -> 53890 | H178: =+G178*C178 -> 161670
A180: V04.08 | B180: Inner diameter of 100mm dia Ceiling/slab mounted down light complete with 18w LED lamp. (Prime cost is Rs.6,000.00) | C180: 3 | D180: Nr. | E180: =6000+550 -> 6550 | F180: =+$I$2 -> 0.9 | G180: =ROUNDUP(E180/F180,-1) -> 7280 | H180: =+G180*C180 -> 21840
A182: V04.09 | B182: LED 6w Mirror lamp fitting.- (Prime cost is Rs.5,500.00) | C182: 3 | D182: Nr | E182: =5500+700 -> 6200 | F182: =+$I$2 -> 0.9 | G182: =ROUNDUP(E182/F182,-1) -> 6890 | H182: =+G182*C182 -> 20670
A184: V04.10 | B184: Supplying and installation of ceiling fan with all fittings (Pc sum is Rs. 60,000.00) | C184: 6 | D184: nr | E184: =60000+4000 -> 64000 | F184: =+$I$2 -> 0.9 | G184: =ROUNDUP(E184/F184,-1) -> 71120 | H184: =+G184*C184 -> 426720
A186: V04.11 | B186: Supplying of Outdoor light fittings -(Prime cost is Rs.9500.00) | C186: 35 | D186: nr | E186: =9500+750 -> 10250 | F186: =+$I$2 -> 0.9 | G186: =ROUNDUP(E186/F186,-1) -> 11390 | H186: =+G186*C186 -> 398650 | I186: eth
I187: BTC
B188: FIRST FLOOR
A190: V04.12 | B190: Point wiring for socket outlets 13A - ( 16A Circuits) Supply, Installation & wiring of 13A power Socket Outlet, by using 2x1C 2.5mm^2 Cu /PVC/PVC Cable + 1C 2.5 mm^2 Cu/PVC Earth Cable (in radial circuit) through slab & wall in PVC conduits including PVC conduits, sunk box, junction box, outlet and complete with all other relevant accessories. | C190: 25 | D190: nr | E190: =+E164 -> 9000 | F190: =+$I$1 -> 0.75 | G190: =ROUNDUP(E190/F190,-1) -> 12000 | H190: =+G190*C190 -> 300000
A192: V04.13 | B192: Light Point Wiring (10A Circuits)-indoor/outdoor Supply & Installation of light Point Wiring, by using 2x1C 1.5mm^2 Cu/PVC/PVC Cable + 1C 1.5 mm^2 Cu/PVC Earth Cable through slab & wall in PVC conduits including PVC conduits, sunk box, junction box, 10A PVC Switch and complete with all other relevant accessories. | C192: 25 | D192: nr | E192: =+E166 -> 7500 | F192: =+$I$1 -> 0.75 | G192: =ROUNDUP(E192/F192,-1) -> 10000 | H192: =+G192*C192 -> 250000
A194: V04.14 | B194: Two way light Point Wiring (10A Circuits) Supply & Installation of 2way light Point Wiring, by using 2x1C 1.5mm^2 Cu/PVC/PVC Cable + 1C 1.5 mm^2 Cu/PVC Earth Cable through slab & wall in PVC conduits including PVC conduits, sunk box, junction box, 10A PVC 2 way Switches and complete with all other relevant accessories. | C194: 4 | D194: nr | E194: =+E168 -> 8500 | F194: =+$I$1 -> 0.75 | G194: =ROUNDUP(E194/F194,-1) -> 11340 | H194: =+G194*C194 -> 45360
B196: Light Fittings
A198: V04.15 | B198: Installation of light fittings-indoor/outdoor Installation of light fittings including roll plugs, screws and complete with all other relevant accessories. | C198: 65 | D198: nr | E198: =+E172 -> 900 | F198: =+$I$2 -> 0.9 | G198: =ROUNDUP(E198/F198,-1) -> 1000 | H198: =+G198*C198 -> 65000
A200: V04.16 | B200: Inner diameter of 150mm dia Ceiling/slab mounted down light complete with 18w LED lamp. (Prime cost is Rs.6,000.00) | C200: 45 | D200: Nr. | E200: =+E176 -> 6650 | F200: =+$I$2 -> 0.9 | G200: =ROUNDUP(E200/F200,-1) -> 7390 | H200: =+G200*C200 -> 332550
A202: V04.17 | B202: Supplying of Wall Bracket light fittings -(Prime cost is Rs.6,500.00) | C202: 6 | D202: nr | E202: =6500+550 -> 7050 | F202: =+$I$2 -> 0.9 | G202: =ROUNDUP(E202/F202,-1) -> 7840 | H202: =+G202*C202 -> 47040
A204: V04.18 | B204: Chandelier light type 02 as per the 3d drawing (Prime cost is Rs.146,000.00) | C204: 1 | D204: Nr. | E204: =146000+7500 -> 153500 | F204: =+$I$2 -> 0.9 | G204: =ROUNDUP(E204/F204,-1) -> 170560 | H204: =+G204*C204 -> 170560
A206: V04.19 | B206: LED 6w Mirror lamp fitting.- (Prime cost is Rs.5,500.00) | C206: 3 | D206: Nr | E206: =5500+750 -> 6250 | F206: =+$I$2 -> 0.9 | G206: =ROUNDUP(E206/F206,-1) -> 6950 | H206: =+G206*C206 -> 20850
A208: V04.20 | B208: Supplying and installation of ceiling fan with all fittings (Pc sum is Rs. 60,000.00) | C208: 4 | D208: nr | E208: =60000+4500 -> 64500 | F208: =+$I$2 -> 0.9 | G208: =ROUNDUP(E208/F208,-1) -> 71670 | H208: =+G208*C208 -> 286680
B210: Second Top Floor
A212: V04.21 | B212: Point wiring for socket outlets 13A - ( 16A Circuits) Supply, Installation & wiring of 13A power Socket Outlet, by using 2x1C 2.5mm^2 Cu /PVC/PVC Cable + 1C 2.5 mm^2 Cu/PVC Earth Cable (in radial circuit) through slab & wall in PVC conduits including PVC conduits, sunk box, junction box, outlet and complete with all other relevant accessories. | C212: 15 | D212: nr | E212: =+E164 -> 9000 | F212: =+$I$1 -> 0.75 | G212: =ROUNDUP(E212/F212,-1) -> 12000 | H212: =+G212*C212 -> 180000
A214: V04.22 | B214: Light Point Wiring (10A Circuits)-indoor/outdoor Supply & Installation of light Point Wiring, by using 2x1C 1.5mm^2 Cu/PVC/PVC Cable + 1C 1.5 mm^2 Cu/PVC Earth Cable through slab & wall in PVC conduits including PVC conduits, sunk box, junction box, 10A PVC Switch and complete with all other relevant accessories. | C214: 15 | D214: nr | E214: =+E166 -> 7500 | F214: =+$I$1 -> 0.75 | G214: =ROUNDUP(E214/F214,-1) -> 10000 | H214: =+G214*C214 -> 150000
A216: V04.23 | B216: Two way light Point Wiring (10A Circuits) Supply & Installation of 2way light Point Wiring, by using 2x1C 1.5mm^2 Cu/PVC/PVC Cable + 1C 1.5 mm^2 Cu/PVC Earth Cable through slab & wall in PVC conduits including PVC conduits, sunk box, junction box, 10A PVC 2 way Switches and complete with all other relevant accessories. | C216: 10 | D216: nr | E216: =+E168 -> 8500 | F216: =+$I$1 -> 0.75 | G216: =ROUNDUP(E216/F216,-1) -> 11340 | H216: =+G216*C216 -> 113400
B221: Light Fittings
A223: V04.24 | B223: Installation of light fittings-indoor/outdoor Installation of light fittings including roll plugs, screws and complete with all other relevant accessories. | C223: 45 | D223: nr | E223: =+E198 -> 900 | F223: =+$I$2 -> 0.9 | G223: =ROUNDUP(E223/F223,-1) -> 1000 | H223: =+G223*C223 -> 45000
A225: V04.25 | B225: Inner diameter of 150mm dia Ceiling/slab mounted down light complete with 18w LED lamp. (Prime cost is Rs.6,000.00) | C225: 22 | D225: Nr. | E225: =6000+750 -> 6750 | F225: =+$I$2 -> 0.9 | G225: =ROUNDUP(E225/F225,-1) -> 7500 | H225: =+G225*C225 -> 165000
A227: V04.26 | B227: LED 6w Mirror lamp fitting.- (Prime cost is Rs.5,500.00) | C227: 1 | D227: Nr | E227: =5500+750 -> 6250 | F227: =+$I$2 -> 0.9 | G227: =ROUNDUP(E227/F227,-1) -> 6950 | H227: =+G227*C227 -> 6950
A229: V04.27 | B229: Supplying of Wall Bracket light fittings -(Prime cost is Rs.6,500.00) | C229: 10 | D229: nr | E229: =6500+650 -> 7150 | F229: =+$I$2 -> 0.9 | G229: =ROUNDUP(E229/F229,-1) -> 7950 | H229: =+G229*C229 -> 79500
A231: V04.28 | B231: Inner diameter of 100mm dia Ceiling/slab mounted down light complete with 18w LED lamp. (Prime cost is Rs.6,000.00) | C231: 4 | D231: Nr. | E231: =6000+650 -> 6650 | F231: =+$I$2 -> 0.9 | G231: =ROUNDUP(E231/F231,-1) -> 7390 | H231: =+G231*C231 -> 29560
A233: 5 | B233: Earthing System
B234: Contractor shall be responsible for earthing the system in order to have an earth resistance below 10 Ohms. | C234: 1 | D234: P.S | E234: 95000 | F234: =+$I$1 -> 0.75 | G234: =ROUNDUP(E234/F234,-1) -> 126670 | H234: =+G234*C234 -> 126670
B236: ELECTRICAL INSTALLATION WORK CARRIED TO COLLECTION | H236: =SUM(H4:H235) -> 5143870

Sheet Rate Breakdowns
A2: EXCAVATION & EARTH WORK
A4: Site Clearing & Removing top soil
A5: Per 1 Sqr
B6: Decription | C6: Unit | D6: Qty | E6: Rate | F6: Amount | G6: Total
B8: Labour | F8: =D8*E8 -> 0
B9: Un/Skilled | C9: Sqr | D9: 10 | E9: 2500 | F9: =D9*E9 -> 25000
B11: Total Labour Cost | F11: =D11*E11 -> 0 | G11: =SUM(F9:F11) -> 25000
B13: Transport (Disposal of Excavated material) | C13: Day | D13: 0.2 | E13: 15000 | F13: =D13*E13 -> 3000 | G13: =+F13 -> 3000
A15: Basic Cost per 10 Sqr | G15: =SUM(G11:G14) -> 28000
A16: Basic Cost per 1 sqr | G16: =G15/10 -> 2800
A17: Basic Cost per 1m2 | G17: =G16/9.29 -> 301.39935
A20: Excavation for foundations depth not exceeding 1.5m (Manual Excavation)
A21: Per 1 Cube
B22: Decription | C22: Unit | D22: Qty | E22: Rate | F22: Amount | G22: Total
B24: Labour | F24: =D24*E24 -> 0
B25: Sub Contractor's Rate | C25: Cube | D25: 1 | E25: 6000 | F25: =D25*E25 -> 6000
B27: Total Labour Cost | F27: =D27*E27 -> 0 | G27: =SUM(F25:F27) -> 6000
A31: Basic Cost per 1 Cube | G31: =G27 -> 6000
A32: Basic Cost per 1 m3 | G32: =G31/2.83 -> 2120.1413
A35: Earth Filling (Excavated material)
A36: Per 1 Cube
B37: Decription | C37: Unit | D37: Qty | E37: Rate | F37: Amount | G37: Total
B38: Consider 12 Cubes
B40: Material
F41: =D41*E41 -> 0
F42: =D42*E42 -> 0
B43: Total Material Cost | F43: =D43*E43 -> 0 | G43: =SUM(F40:F43) -> 0
B44: Labour
B45: Un/Skilled Labour for levelling & Compaction | C45: Days | D45: 4 | E45: 2500 | F45: =D45*E45 -> 10000
B47: Total Labour Cost | F47: =D47*E47 -> 0 | G47: =SUM(F45:F47) -> 10000
B48: Plant & Machinery
B50: Jumping Compactor | C50: hr | D50: 24 | E50: 625 | F50: =D50*E50 -> 15000
B52: Total Plant & Machinery Cost | F52: =D52*E52 -> 0 | G52: =SUM(F49:F52) -> 15000
A55: Basic Cost per 12 Cube | G55: =G43+G47+G52 -> 25000
A56: Basic Cost per 1 Cube | G56: =G55/12 -> 2083.3333
A57: Basic Cost per 1 m3 | G57: =G56/2.83 -> 736.16019
A63: Imported Soil Filling
A64: Per 1 Cube
B65: Decription | C65: Unit | D65: Qty | E65: Rate | F65: Amount | G65: Total
B66: Consider 12 Cubes
B68: Material
B69: Cost of Imported Soil Transport to Site | C69: Cube | D69: 12 | E69: =[19]Material!E23 -> 8000 | F69: =D69*E69 -> 96000
B70: 35% of Additional Soil for Compaction | F70: =F69*35% -> 33600
F71: =D71*E71 -> 0
F72: =D72*E72 -> 0
B73: Total Material Cost | F73: =D73*E73 -> 0 | G73: =SUM(F68:F73) -> 129600
B74: Labour | F74: =D74*E74 -> 0
B75: Un/Skilled Labour for levelling & Compaction | C75: Days | D75: 3 | E75: 2500 | F75: =D75*E75 -> 7500
B77: Total Labour Cost | F77: =D77*E77 -> 0 | G77: =SUM(F75:F77) -> 7500
B78: Plant & Machinery
B80: Jumping Compactor | C80: hr | D80: 24 | E80: 625 | F80: =D80*E80 -> 15000
B82: Total Plant & Machinery Cost | F82: =D82*E82 -> 0 | G82: =SUM(F79:F82) -> 15000
A85: Basic Cost per 12 Cube | G85: =G73+G77+G82 -> 152100
A86: Basic Cost per 1 Cube | G86: =G85/12 -> 12675
A87: Basic Cost per 1 m3 | G87: =G86/2.83 -> 4478.7986
A90: Qurry Dust Filling
A91: Per 1 Cube
B92: Decription | C92: Unit | D92: Qty | E92: Rate | F92: Amount | G92: Total
B93: Consider 12 Cubes
B95: Material
B96: Cost of Qurry Dust Transport to Site | C96: Cube | D96: 5 | E96: =+[19]Material!E24 -> 17000 | F96: =D96*E96 -> 85000
B97: 10% of Additional Quarry Dust for Compaction | F97: =F96*10% -> 8500
F98: =D98*E98 -> 0
F99: =D99*E99 -> 0
B100: Total Material Cost | F100: =D100*E100 -> 0 | G100: =SUM(F95:F100) -> 93500
B101: Labour | F101: =D101*E101 -> 0
B102: Un/Skilled Labour for levelling & Compaction | C102: Days | D102: 3 | E102: 2500 | F102: =D102*E102 -> 7500
B104: Total Labour Cost | F104: =D104*E104 -> 0 | G104: =SUM(F102:F104) -> 7500
B105: Plant & Machinery
B107: JCB with Operator | C107: hr | D107: 3 | E107: 7000 | F107: =D107*E107 -> 21000
B108: Jumping Compactor | C108: hr | D108: 10 | E108: 625 | F108: =D108*E108 -> 6250
B110: Total Plant & Machinery Cost | F110: =D110*E110 -> 0 | G110: =SUM(F106:F110) -> 27250
A113: Basic Cost per 12 Cube | G113: =G100+G104+G110 -> 128250
A114: Basic Cost per 1 Cube | G114: =G113/12 -> 10687.5
A115: Basic Cost per 1 m3 | G115: =G114/2.83 -> 3776.5018
A120: Dam Proof Membrane ; Gauge 1000 Polythene
A121: Per 1 Sqr
B122: Decription | C122: Unit | D122: Qty | E122: Rate | F122: Amount | G122: Total
B124: Material
B125: Gauge 1000 polythene | C125: Kg | D125: 2.5 | E125: =[19]Material!E63 -> 650 | F125: =D125*E125 -> 1625
F128: =D128*E128 -> 0
B129: Total Material Cost | F129: =D129*E129 -> 0 | G129: =SUM(F124:F129) -> 1625
B130: Labour | F130: =D130*E130 -> 0
B131: Laying | C131: ft2 | D131: 100 | E131: 5 | F131: =D131*E131 -> 500
B133: Total Labour Cost | F133: =D133*E133 -> 0 | G133: =SUM(F131:F133) -> 500
A136: Basic Cost per 1 Sqr | G136: =G129+G133 -> 2125
A137: Basic Cost per 1 m2 | G137: =G136/9.29 -> 228.74058
A138: Basic Cost per 1 ft2 | G138: =G137/10.76 -> 21.258418
A140: 3/4" thick D.P.C. in cement sand 1:3 finished with 2 coats of D.P.C. tar and blinded with sand.
A141: Per 1 Sqr
B142: Decription | C142: Unit | D142: Qty | E142: Rate | F142: Amount | G142: Total
B144: Material
B145: Cement | C145: Bag | D145: 0.8 | E145: =+F197 -> 2235.625 | F145: =D145*E145 -> 1788.5
B146: Sand | C146: Sand | D146: 0.03 | E146: =+[19]Material!E13 -> 23500 | F146: =D146*E146 -> 705
B148: Bitumix (20 L 18,500 LKR) | C148: Lit | D148: 3.5 | E148: 925 | F148: =+E148*D148 -> 3237.5
B151: Total Material Cost | G151: =SUM(F144:F151) -> 5731
B152: Labour
B153: Laying | C153: ft2 | D153: 100 | E153: 5 | F153: =D153*E153 -> 500
B155: Total Labour Cost | F155: =D155*E155 -> 0 | G155: =SUM(F153:F155) -> 500
A158: Basic Cost per 1 Sqr | G158: =G151+G155 -> 6231
...

Sheet grnd summry- tender
A1: PROPOSED HOUSE DESIGN FOR MR.RATHEESHAN AT JAFFNA.
A2: MAIN SUMMARY
A3: BILL NO | B3: DESCRIPTION | C3: AMOUNT (Rs.)
A5: Bill No. 01 | B5: PRELIMINARIES | C5: =prelims!I120 -> 405000
A7: Bill No. 02 | B7: MAIN BUILDING | C7: =summary!C20 -> 88502630
B9: SUB TOTAL-I | C9: =SUM(C5:C8) -> 88907630
B11: Less : Discount (If any)
B13: SUB TOTAL-II-CARRIED TO FORM OF BID | C13: =SUM(C9:C12) -> 88907630
A15: Bill No. 03 | B15: PROVISIONAL SUM | C15: =Ps!F14 -> 0
B17: SUB TOTAL III | C17: =SUM(C13:C16) -> 88907630
A19: Bill No. 05 | B19: ADD- CONTINGENCIES- 10%
B21: SUB TOTAL IV | C21: =SUM(C17:C20) -> 88907630
B23: ADD 15% VAT
B25: TOTAL PROJECT COST WITH VAT | C25: =SUM(C21:C24) -> 88907630
C117: =C113/450 -> 0

Sheet m shet Mr Ratheshon
A1: NO | B1: DESCRIPTION | C1: NOS | F1: LENGTH | G1: WIDTH | H1: HEIGHT | I1: QTY | J1: T.QTY | O1: UNIT
K2: 1.05
A3: =exca!A10 -> B 01 | B3: =exca!B10 -> Clearing site vegetation manually including removal of bushes, shurb removing rubbish. | I3: 252.28084 | J3: =I3 -> 252.28084 | K3: =$K$2 -> 1.05 | L3: =K3*J3 -> 264.89488 | M3: =ROUND(L3,1) -> 264.9 | N3: =ROUNDUP(M3,0) -> 265 | O3: m2 | P3: 1.1
A6: =masnry!A3 -> F | B6: =masnry!B2 -> F - MASONRY WORKS
A8: =masnry!A11 -> 1.01 | B8: =masnry!B11 -> Brick work in cement and sand 1:5 in super Structure in ground floor. ( 9" thick brick work) | E8: 1 | F8: 11.9 | H8: 3.95 | I8: =H8*F8*E8 -> 47.005
D9: FG1 | E9: -1 | F9: 3.7 | H9: 3 | I9: =H9*F9*E9 -> -11.1
D10: FG2 | E10: -1 | F10: 1.2 | H10: 3 | I10: =H10*F10*E10 -> -3.6
D11: FW4 | E11: -1 | F11: 3 | H11: 3 | I11: =H11*F11*E11 -> -9
E12: 1 | F12: 3.95 | H12: 3.95 | I12: =H12*F12*E12 -> 15.6025
E13: 1 | F13: 3.115 | H13: 3.95 | I13: =H13*F13*E13 -> 12.30425
D14: F3 | E14: -1 | F14: 1.425 | H14: 1.5 | I14: =H14*F14*E14 -> -2.1375
D15: F3 | E15: -1 | F15: 1.425 | H15: 1.5 | I15: =H15*F15*E15 -> -2.1375
E16: 1 | F16: 3.92 | H16: 3.95 | I16: =H16*F16*E16 -> 15.484
E17: 1 | F17: 9.8 | H17: 3.95 | I17: =H17*F17*E17 -> 38.71
D18: FW7 | E18: -1 | F18: 3.076 | H18: 3 | I18: =H18*F18*E18 -> -9.228
E19: 1 | F19: 10.8 | H19: 3.95 | I19: =H19*F19*E19 -> 42.66
D20: W1 | E20: -1 | F20: 3.06 | H20: 0.6 | I20: =H20*F20*E20 -> -1.836
D21: D2 | E21: -1 | F21: 0.9 | H21: 2.8 | I21: =H21*F21*E21 -> -2.52
E22: 1 | F22: 16.33 | H22: 3.95 | I22: =H22*F22*E22 -> 64.5035
D23: FW5 | E23: -1 | F23: 2.1 | H23: 3 | I23: =H23*F23*E23 -> -6.3
D24: FW2 | E24: -1 | F24: 2.1 | H24: 3 | I24: =H24*F24*E24 -> -6.3
D25: FW1 | E25: -1 | F25: 2 | H25: 3 | I25: =H25*F25*E25 -> -6
E26: 1 | F26: 8.2 | H26: 3.95 | I26: =H26*F26*E26 -> 32.39
D27: D1 | E27: -1 | F27: 1.2 | H27: 3.6 | I27: =H27*F27*E27 -> -4.32
D28: FG4 | E28: -1 | F28: 3.7 | H28: 3 | I28: =H28*F28*E28 -> -11.1
D29: FG3 | E29: -1 | F29: 1 | H29: 3 | I29: =H29*F29*E29 -> -3
E30: 1 | F30: 5.125 | H30: 3.95 | I30: =H30*F30*E30 -> 20.24375 | J30: =SUM(I8:I30) -> 210.324 | K30: =$K$2 -> 1.05 | L30: =K30*J30 -> 220.8402 | M30: =ROUND(L30,1) -> 220.8 | N30: =ROUNDUP(M30,0) -> 221 | O30: m2
A32: =masnry!A13 -> 1.02 | B32: =masnry!B13 -> Brick work in cement and sand 1:5 in First floor level.(9" thick brick work) | E32: 1 | F32: 13.295 | H32: 3.45 | I32: =H32*F32*E32 -> 45.86775
D33: FW7 | E33: -1 | F33: 3.075 | H33: 3 | I33: =H33*F33*E33 -> -9.225
E34: 1 | F34: 3.45 | H34: 3.45 | I34: =H34*F34*E34 -> 11.9025
E35: 1 | F35: 22.18 | H35: 3.45 | I35: =H35*F35*E35 -> 76.521
D36: F2 | E36: -1 | F36: 1.05 | H36: 3 | I36: =H36*F36*E36 -> -3.15
D37: FW7 | E37: -2 | F37: 3.075 | H37: 3 | I37: =H37*F37*E37 -> -18.45
E38: 1 | F38: 0.9 | H38: 3.45 | I38: =H38*F38*E38 -> 3.105
D39: D4 | E39: -1 | F39: 0.9 | H39: 2.1 | I39: =H39*F39*E39 -> -1.89
E40: 1 | F40: 21.5 | H40: 3.45 | I40: =H40*F40*E40 -> 74.175
D41: D4 | E41: -1 | F41: 0.9 | H41: 2.1 | I41: =H41*F41*E41 -> -1.89
D42: FW1 | E42: -1 | F42: 2 | H42: 3 | I42: =H42*F42*E42 -> -6
E43: 1 | F43: 12.45 | H43: 3.45 | I43: =H43*F43*E43 -> 42.9525
D44: FG6 | E44: -1 | F44: 3.75 | H44: 3 | I44: =H44*F44*E44 -> -11.25
E45: 1 | F45: 6.5 | H45: 3.45 | I45: =H45*F45*E45 -> 22.425
D46: FW7 | E46: -1 | F46: 3.075 | H46: 3 | I46: =H46*F46*E46 -> -9.225 | J46: =SUM(I32:I46) -> 215.86875 | K46: =$K$2 -> 1.05 | L46: =K46*J46 -> 226.66219 | M46: =ROUND(L46,1) -> 226.7 | N46: =ROUNDUP(M46,0) -> 227 | O46: m2
A48: =masnry!A15 -> 1.03 | B48: =masnry!B15 -> Brick work in cement and sand 1:5 in Roof floor level.(9" thick brick work) | E48: 1 | F48: 18.82 | H48: 3.45 | I48: =H48*F48*E48 -> 64.929
D49: D6 | E49: -1 | F49: 1.32 | H49: 3 | I49: =H49*F49*E49 -> -3.96
D50: FG6 | E50: -3 | F50: 3.75 | H50: 3 | I50: =H50*F50*E50 -> -33.75
E51: 1 | F51: 1.89 | H51: 3.45 | I51: =H51*F51*E51 -> 6.5205
E52: 1 | F52: 4.19 | H52: 3.45 | I52: =H52*F52*E52 -> 14.4555
E53: 1 | F53: 2.05 | H53: 3.45 | I53: =H53*F53*E53 -> 7.0725 | J53: =SUM(I48:I53) -> 55.2675 | K53: =$K$2 -> 1.05 | L53: =K53*J53 -> 58.030875 | M53: =ROUND(L53,1) -> 58 | N53: =ROUNDUP(M53,0) -> 58 | O53: m2
A55: =masnry!A18 -> 1.04 | B55: =masnry!B18 -> Brick work in cement and sand 1:5 in super Structure in ground floor. ( 6" thick brick work) | E55: 1 | F55: 3.115 | H55: 3.95 | I55: =H55*F55*E55 -> 12.30425
E56: 1 | F56: 5.41 | H56: 3.95 | I56: =H56*F56*E56 -> 21.3695
E57: 1 | F57: 3.15 | H57: 3.95 | I57: =H57*F57*E57 -> 12.4425
D58: D5 | E58: -2 | F58: 0.75 | H58: 2.1 | I58: =H58*F58*E58 -> -3.15
E59: 1 | F59: 1.65 | H59: 3.95 | I59: =H59*F59*E59 -> 6.5175
E60: 1 | F60: 0.9 | H60: 3.95 | I60: =H60*F60*E60 -> 3.555
D61: D4 | E61: -1 | F61: 0.9 | H61: 2.1 | I61: =H61*F61*E61 -> -1.89
E62: 1 | F62: 2.97 | H62: 3.95 | I62: =H62*F62*E62 -> 11.7315
D63: FW3 | E63: -1 | F63: 2.075 | H63: 3 | I63: =H63*F63*E63 -> -6.225
D64: D3 | E64: -1 | F64: 0.9 | H64: 3 | I64: =H64*F64*E64 -> -2.7
E65: 1 | F65: 3.115 | H65: 3.95 | I65: =H65*F65*E65 -> 12.30425 | J65: =SUM(I55:I65) -> 66.2595 | K65: =$K$2 -> 1.05 | L65: =K65*J65 -> 69.572475 | M65: =ROUND(L65,1) -> 69.6 | N65: =ROUNDUP(M65,0) -> 70 | O65: m2
A67: =masnry!A20 -> 1.05 | B67: =masnry!B20 -> Brick work in cement and sand 1:5 in super Structure in First floor level. ( 6" thick brick work) | E67: 1 | F67: 13.425 | H67: 3.45 | I67: =H67*F67*E67 -> 46.31625
D68: F1 | E68: -1 | F68: 1.1 | H68: 1.5 | I68: =H68*F68*E68 -> -1.65
E69: 1 | F69: 2.35 | H69: 3.45 | I69: =H69*F69*E69 -> 8.1075
E70: 1 | F70: 4.05 | H70: 3.45 | I70: =H70*F70*E70 -> 13.9725
E71: 1 | F71: 5.2 | H71: 3.45 | I71: =H71*F71*E71 -> 17.94
E72: 1 | F72: 3.15 | H72: 3.45 | I72: =H72*F72*E72 -> 10.8675
D73: D5 | E73: -2 | F73: 0.75 | H73: 2.1 | I73: =H73*F73*E73 -> -3.15
E74: 1 | F74: 1.65 | H74: 3.45 | I74: =H74*F74*E74 -> 5.6925
E75: 1 | F75: 4.75 | H75: 3.45 | I75: =H75*F75*E75 -> 16.3875
D76: D4 | E76: -1 | F76: 0.9 | H76: 2.1 | I76: =H76*F76*E76 -> -1.89 | J76: =SUM(I67:I76) -> 112.59375 | K76: =$K$2 -> 1.05 | L76: =K76*J76 -> 118.22344 | M76: =ROUND(L76,1) -> 118.2 | N76: =ROUNDUP(M76,0) -> 119 | O76: m2
A78: =masnry!A22 -> 1.06 | B78: =masnry!B22 -> Brick work in cement and sand 1:5 in Roof floor level.(6" thick brick work) | E78: 1 | F78: 6.3 | H78: 3.45 | I78: =H78*F78*E78 -> 21.735
D79: FW7 | E79: -1 | F79: 3.075 | H79: 3 | I79: =H79*F79*E79 -> -9.225
E80: 1 | F80: 6.09 | H80: 3.45 | I80: =H80*F80*E80 -> 21.0105
D81: F1 | E81: -1 | F81: 1.1 | H81: 1.5 | I81: =H81*F81*E81 -> -1.65
E82: 1 | F82: 3.625 | H82: 3.45 | I82: =H82*F82*E82 -> 12.50625
D83: D5 | E83: -1 | F83: 0.75 | H83: 2.1 | I83: =H83*F83*E83 -> -1.575
E84: 1 | F84: 12.4 | H84: 3.45 | I84: =H84*F84*E84 -> 42.78
D85: FG9 | E85: -1 | F85: 6.44 | H85: 3 | I85: =H85*F85*E85 -> -19.32 | J85: =SUM(I78:I85) -> 66.26175 | K85: =$K$2 -> 1.05 | L85: =K85*J85 -> 69.574838 | M85: =ROUND(L85,1) -> 69.6 | N85: =ROUNDUP(M85,0) -> 70 | O85: m2
A87: =masnry!A25 -> 1.07 | B87: =masnry!B25 -> Brick work in cement and sand 1:5 in super Structure in ground floor. ( 4" thick brick work) | E87: 1 | F87: 3.825 | H87: 3.95 | I87: =H87*F87*E87 -> 15.10875
D88: D5 | E88: -1 | F88: 0.75 | H88: 2.1 | I88: =H88*F88*E88 -> -1.575
D89: F1 | E89: -1 | F89: 1.1 | H89: 1.6 | I89: =H89*F89*E89 -> -1.76
E90: 1 | F90: 6 | H90: 3.95 | I90: =H90*F90*E90 -> 23.7
D91: D4 | E91: -1 | F91: 0.9 | H91: 2.1 | I91: =H91*F91*E91 -> -1.89
E92: 1 | F92: 2.935 | H92: 3.95 | I92: =H92*F92*E92 -> 11.59325
E93: 1 | F93: 6.05 | H93: 3.95 | I93: =H93*F93*E93 -> 23.8975
D94: D9 | E94: -1 | F94: 0.9 | H94: 3 | I94: =H94*F94*E94 -> -2.7
D95: F2 | E95: -1 | F95: 1.05 | H95: 2 | I95: =H95*F95*E95 -> -2.1 | J95: =SUM(I87:I95) -> 64.2745 | K95: =$K$2 -> 1.05 | L95: =K95*J95 -> 67.488225 | M95: =ROUND(L95,1) -> 67.5 | N95: =ROUNDUP(M95,0) -> 68 | O95: m2
A98: =floring!A6 -> J 02 | B98: =floring!B6 -> Gauge 750 polythene damp proof membrane with 6" laps laid under floors. | I98: =I3 -> 252.28084 | J98: =I98 -> 252.28084 | K98: =$K$2 -> 1.05 | L98: =K98*J98 -> 264.89488 | M98: =ROUND(L98,1) -> 264.9 | N98: =ROUNDUP(M98,0) -> 265 | O98: m2
A100: E | B100: =waterprof!B2 -> E - WATER PROOFING WORK
A102: =waterprof!A19 -> E. 01 | B102: Wall waterprofing | E102: 2 | F102: 7.725 | H102: 1.5 | I102: =H102*F102*E102 -> 23.175
B103: =waterprof!B21 -> Ground Floor | E103: 1 | F103: 4.275 | H103: 1.5 | I103: =H103*F103*E103 -> 6.4125 | J103: =SUM(I102:I103) -> 29.5875 | K103: =$K$2 -> 1.05 | L103: =K103*J103 -> 31.066875 | M103: =ROUND(L103,1) -> 31.1 | N103: =ROUNDUP(M103,0) -> 32 | O103: m2
B105: =waterprof!B22 -> First Floor | E105: 2 | F105: 7.69 | H105: 1.5 | I105: =H105*F105*E105 -> 23.07
E106: 1 | F106: 8.5 | H106: 1.5 | I106: =H106*F106*E106 -> 12.75 | J106: =SUM(I105:I106) -> 35.82 | K106: =$K$2 -> 1.05 | L106: =K106*J106 -> 37.611 | M106: =ROUND(L106,1) -> 37.6 | N106: =ROUNDUP(M106,0) -> 38 | O106: m2
B108: =waterprof!B23 -> Roof top Floor | E108: 1 | F108: 4.3 | H108: 1.5 | I108: =H108*F108*E108 -> 6.45
E109: 1 | F109: 0.8 | H109: 1.5 | I109: =H109*F109*E109 -> 1.2
E110: 1 | F110: 5.3 | H110: 1.5 | I110: =H110*F110*E110 -> 7.95
E111: 1 | F111: 6.2 | H111: 1.5 | I111: =H111*F111*E111 -> 9.3
E112: 1 | F112: 9.2 | H112: 1.5 | I112: =H112*F112*E112 -> 13.8 | J112: =SUM(I111:I112) -> 23.1 | K112: =$K$2 -> 1.05 | L112: =K112*J112 -> 24.255 | M112: =ROUND(L112,1) -> 24.3 | N112: =ROUNDUP(M112,0) -> 25 | O112: m2
A113: =waterprof!A26 -> E. 02 | B113: Floor waterprofing
B115: =B103 -> Ground Floor | E115: 1 | F115: 1.576337 | H115: 1 | I115: =H115*F115*E115 -> 1.576337
E116: 1 | F116: 8.758431 | H116: 1 | I116: =H116*F116*E116 -> 8.758431 | J116: =SUM(I115:I116) -> 10.334768 | K116: =$K$2 -> 1.05 | L116: =K116*J116 -> 10.851506 | M116: =ROUND(L116,1) -> 10.9 | N116: =ROUNDUP(M116,0) -> 11 | O116: m2
...

Sheet Ps
A1: Nos | B1: Description | C1: Qty | D1: Unit | E1: Rate | F1: Amount
B2: BILL NO. 03
A3: 1 | B3: O - PROVISIONAL SUM
A5: =A3+0.01 -> 1.01 | B5: Allow Sum for Pool work | C5: 1 | D5: Pro. Sum
A7: =A5+0.01 -> 1.02 | B7: Allow Sum for other work , latter and desing other , CCTV | C7: 1 | D7: Pro. Sum
B14: V - PROVISIONAL SUM CARRIED TO GRAND SUMMARY | F14: =SUM(F4:F13) -> 0

Sheet cctv
A1: Supply, Installation, Testing and Commissioning of CCTV System
A2: Proposed Building For Hiroshan Hettiarachchi at Maharagama,
A3: BoQ and Specifications for CCTV System
A5: NO | B5: DESCRIPTION | C5: QTY | D5: UNIT | E5: RATE | F5: AMOUNT
B7: CCTV SYSTEM
B9: This Bills of Quantities shall be read in conjunction with all the other Bid Documents. All such provisions shall be included in rates and prices as applicable.
B11: This is a Measure & Pay Contract. All items should be checked, measured and verified with relevant drawings. | D11: Note
B13: Contractor must check the actual cable length @ site, before purchasing and start cable laying/implementation. | D13: Note
B15: Contractor must read the specifications, general notes given and submit the quotation accordingly. | D15: Note
B17: Contractor must perform site visits & check for practical & feasible conditions/options of the given designs based on practical site conditions & submit quotations accordingly. | D17: Note
B19: As this is a Measure & Pay Contract, Bidders are advised to carefully refer and understand all drawings, specifications and general notes before submission of their quotation and proposal. | D19: Note
B21: Contractor must submit shop drawings and get approval before start fabrication and installation. | D21: Note
B23: Contractor must submit brands and specifications of all items and get approval before start fabrication and installation. | D23: Note
B25: It’s bidders’ responsibility to refer drawings, relevant specifications and general notes thereby check and verify quantities. | D25: Note
B27: If any discrepancy identified, bidder should clarify the same with client/consultant engineer before submission of final quotation and proposal. | D27: Note
B29: Recommended Brands of Items
B31: Camera-Hikvision,Dahua or equivalent ( need consultant's approval)
B33: NVR-Hikvision,Dahua or equivalent ( need consultant's approval)
B35: Cables (Cat 6) - Schneider (France) or equivalent ( need consultant's approval)
B37: POE Switch - Schneider (France) or equivalent ( need consultant's approval)
B39: LED Monitor / TV-HP,Dell,Samsung,Panasonic or equivalent ( need consultant's approval)
B41: Storage Device-Seagate, Western Digital (WD) or equivalent ( need consultant's approval)
B43: Conduits / Junction Boxes / Sunk Boxes - National, Slon, Polychrome or equivalent (need consultant's approval)
B45: UPS-APC,DCP or equivalent ( need consultant's approval)
B47: U Rack - EMP or equivalent ( need consultant's approval)
B50: Supply and Installation, Testing and Commissioning of CCTV System
A52: =IF(C52>0,COUNT(C$12:C52),"") -> 1 | B52: Supply and installation of 3MP IP (at least 30m) HD resolution POE indoor camera with DWDR, Day/Night (ICR), 3DNR, AWB, AGC, BLC and c/w all other relevant accessories. (Need to submit all technical details of the camera with bid document) | C52: 14 | D52: Nos | E52: 37250 | F52: =E52*C52 -> 521500
A53: =IF(C53>0,COUNT(C$12:C53),"")
A54: =IF(C54>0,COUNT(C$12:C54),"") -> 2 | B54: Supply and installation of 3MP IP (at least 30m) HD resolution POE outdoor camera with DWDR, Day/Night (ICR), 3DNR, AWB, AGC, BLC and c/w all other relevant accessories. (Need to submit all technical details of the camera with bid document) | C54: 4 | D54: Nos | E54: 37250 | F54: =E54*C54 -> 149000
A56: =IF(C56>0,COUNT(C$12:C56),"") -> 3 | B56: Supply and installation of 3MP IP (at least 30m) HD resolution POE indoor camera with DWDR, Day/Night (ICR), 3DNR, AWB, AGC, BLC and c/w all other relevant accessories (inside passenger lifts).This shall be included under lift contractor's scope as per client's interest if required. In such case, this item shall be omitted from CCTV contractor's scope. (Need to submit all technical details of the camera with bid document) | C56: 1 | D56: Nos | E56: 37250 | F56: =E56*C56 -> 37250
A57: =IF(C57>0,COUNT(C$12:C57),"")
A58: =IF(C58>0,COUNT(C$12:C58),"") -> 4 | B58: Supply and installation of NVR system (01 No 24Ch NVRs) & complete with all other relevant accessories. Also provision should be included in the NVR system for connecting a link to provide monitoring facility at a remote location proposed by the client if required. (Need to mention relevant no of NVR units & respective channels per each unit if any deviations required in the given system as per contractor's interest) | C58: 1 | D58: Item | E58: 425000 | F58: =E58*C58 -> 425000
A59: =IF(C59>0,COUNT(C$12:C59),"")
A60: =IF(C60>0,COUNT(C$12:C60),"") -> 5 | B60: Supply and installation of storage facility for 01 month (at least). (Need to mention proposed storage capacity & HDD qty. to satisfy this requirement) | C60: 1 | D60: Item | E60: 292000 | F60: =E60*C60 -> 292000
A61: =IF(C61>0,COUNT(C$12:C61),"")
A62: =IF(C62>0,COUNT(C$12:C62),"") -> 6 | B62: Supply and installation of LED Full HD 24 inch Monitor/TV with mounting brackets at reception area & CCTV room @ first floor and complete with all other relevant accessories. ( Monitor size & quantity can be varied as per client requirement) | C62: 1 | D62: Nos | E62: 162500 | F62: =E62*C62 -> 162500
A64: 7 | B64: Supply & installation of wall mounted type 5U metal rack (with toughened glass front lockable door) as main CCTV rack @ panel room in first floor including mounting brackets,nut & bolts & complete with all other relevant accessories. | C64: 1 | D64: Item | E64: 260000 | F64: =E64*C64 -> 260000
A66: 8 | B66: Supply and installation of 24 Port POE switch inside main CCTV rack @ IT room, including POE switch, patch panels, patch chords (if required) and complete with all other relevant accessories. | C66: 1 | D66: Item | E66: 360000 | F66: =E66*C66 -> 360000
A67: =IF(C67>0,COUNT(C$12:C67),"")
A68: =IF(C68>0,COUNT(C$12:C68),"") -> 9 | B68: Supply and installation of CCTV camera point wiring with Cat 6 UTP cables through slab & wall in PVC conduits including connectors,PVC conduits, junction boxes, sunk boxes & complete with all other relevant accessories. Need to consider all camera point wiring & backbone wiring for switches from main CCTV rack.(actual length can be varied as per site conditions & breakdown of items need to be submitted with bid document) | C68: 1 | D68: Item | E68: 800000 | F68: =E68*C68 -> 800000
A70: =IF(C70>0,COUNT(C$12:C70),"") -> 10 | B70: Supply and installation of Cat 6 UTP cables for display units from main CCTV rack through slab & wall in PVC conduits including connectors,decoders,PVC conduits, junction boxes, sunk boxes & complete with all other relevant accessories. | C70: 1 | D70: Item | E70: 560000 | F70: =E70*C70 -> 560000
A72: =IF(C72>0,COUNT(C$12:C72),"") -> 11 | B72: Testing and commissioning of the system; Need to submit the certified test certificate, Testing of every CCTV outlet shall be done using cable tester. Contractor shall ensure clarity of Video. Test results report shall be submitted by the contractor. (contractor need to ensure the video quality expected by client / consultant after completion of works). | C72: 1 | D72: Item | E72: 60000 | F72: =E72*C72 -> 60000
A73: =IF(C73>0,COUNT(C$12:C73),"")
A74: =IF(C74>0,COUNT(C$12:C74),"") | B74: Total system should have at least 2 years of minimum warranty period. If any deviation, please mention | D74: Note
A75: =IF(C75>0,COUNT(C$12:C75),"")
A76: =IF(C76>0,COUNT(C$12:C76),"") | B76: Need to include annual maintenance agreement after the warranty period, Including cost for 5 years (Excluding spare parts cost). | D76: Note
A78: =IF(C78>0,COUNT(C$12:C78),"") | B78: Contractor need to submit, schematic drawings, design details, and data sheets of all items with tender document. | D78: Note
A80: =IF(C80>0,COUNT(C$12:C80),"") | B80: Shop Drawings
A81: =IF(C81>0,COUNT(C$12:C81),"") -> 12 | B81: Need to submit shop drawings and get approval from the consultant engineer before installation & starting of relevant works | C81: 1 | D81: Item | E81: 80000 | F81: =E81*C81 -> 80000
A82: =IF(C82>0,COUNT(C$12:C82),"")
A83: =IF(C83>0,COUNT(C$12:C83),"") | B83: As Built Drawings
A84: =IF(C84>0,COUNT(C$12:C84),"") -> 13 | B84: Submission of chartered engineer certified as built drawings for the total installation | C84: 1 | D84: Item | E84: 100000 | F84: =E84*C84 -> 100000
A85: =IF(C85>0,COUNT(C$12:C85),"")
A86: =IF(C86>0,COUNT(C$12:C86),"") | B86: Any Other Items
A87: =IF(C87>0,COUNT(C$12:C87),"") -> 14 | B87: Provide for any other item/s of CCTV System not listed above which in the opinion of bidder required as per the contract for the proper execution and completion of the Works. Bidder need to specify the items in adequate details and each item to be priced separately. | C87: 1 | D87: Item | F87: =E87*C87 -> 0
A89: =IF(C89>0,COUNT(C89:C$115),"") | B89: TOTAL in LKR (WITHOUT TAX) | E89: Rs. | F89: =SUM(F52:F88) -> 3807250
B92: Bidder need to mention proposed brands for below items/accessories along with the bid document.
A93: =IF(C93>0,COUNT(C$64:C93),"")
B94: Indoor Camera -
B96: Outdoor Camera -
B98: NVR -
B100: Cables (Cat 6) -
B102: POE Switch -
A103: .
B104: LED Monitor / TV -
B106: Storage Device -
A107: *+
B108: Conduits / Junction Boxes / Sunk Boxes -
B110: UPS -
B112: U Rack -
A114: =IF(C114>0,COUNT(C114:C$116),"") | B114: This is measure and pay contract. Bidders are advised to carefully refer and understand all drawings, specifications and general notes before submission of their quotation and proposal.
A115: =IF(C115>0,COUNT(C115:C$116),"")
A116: =IF(C116>0,COUNT(C116:C$116),"") | B116: It’s bidder's responsibility to refer drawings, relevant specifications and general notes thereby calculate actual quantities.
A117: =IF(C117>0,COUNT(C$116:C117),"")
A118: =IF(C118>0,COUNT(C$116:C118),"") | B118: If any discrepancy identified, bidder should verify the same with client/consultant engineer before submission of final quotation and proposal.
A119: =IF(C119>0,COUNT(C$64:C119),"")
A121: =IF(C121>0,COUNT(C$64:C121),"") | B121: Name of the Company: ………………………………………………….
A122: =IF(C122>0,COUNT(C$64:C122),"")
A123: =IF(C123>0,COUNT(C$64:C123),"")
A124: =IF(C124>0,COUNT(C$64:C124),"")
A125: =IF(C125>0,COUNT(C$64:C125),"") | B125: Name and Signature of Authorized personnel: ………………………………………………….
A126: =IF(C126>0,COUNT(C$64:C126),"")
A127: =IF(C127>0,COUNT(C$64:C127),"")
A128: =IF(C128>0,COUNT(C$64:C128),"")
A129: =IF(C129>0,COUNT(C$64:C129),"") | B129: Rubber Stamp: ………………………………….
A130: =IF(C130>0,COUNT(C$64:C130),"")
A131: =IF(C131>0,COUNT(C$64:C131),"")
A132: =IF(C132>0,COUNT(C$64:C132),"")
A133: =IF(C133>0,COUNT(C$64:C133),"") | B133: Date: ………….…………………….
