Workbook
Name ___REM1: #REF!
Name ___REM1: #REF!
Name ___REM1: #REF!
Name ___REM2: #REF!
Name ___REM2: #REF!
Name ___Val101: #REF!
Name ___Val101: #REF!
Name ___Val102: #REF!
Name ___Val102: #REF!
Name ___Val201: #REF!
Name ___Val201: #REF!
Name ___Val202: #REF!
Name ___Val202: #REF!
Name ___Val301: #REF!
Name ___Val301: #REF!
Name ___Val302: #REF!
Name ___Val302: #REF!
Name __REM1: #REF!
Name __REM1: #REF!
Name __REM2: #REF!
Name __REM2: #REF!
Name __Val101: #REF!
Name __Val101: #REF!
Name __Val102: #REF!
Name __Val102: #REF!
Name __Val201: #REF!
Name __Val201: #REF!
Name __Val202: #REF!
Name __Val202: #REF!
Name __Val301: #REF!
Name __Val301: #REF!
Name __Val302: #REF!
Name __Val302: #REF!
Name _REM1: #REF!
Name _REM1: #REF!
Name _REM1: #REF!
Name _REM2: #REF!
Name _REM2: #REF!
Name _REM2: #REF!
Name _Val101: #REF!
Name _Val101: #REF!
Name _Val101: #REF!
Name _Val102: #REF!
Name _Val102: #REF!
Name _Val201: #REF!
Name _Val201: #REF!
Name _Val202: #REF!
Name _Val202: #REF!
Name _Val301: #REF!
Name _Val301: #REF!
Name _Val302: #REF!
Name _Val302: #REF!
Name a: '[2]B-3.2 EB'!#REF!
Name A: #REF!
Name a: '[2]B-3.2 EB'!#REF!
Name a: '[2]B-3.2 EB'!#REF!
Name a: '[2]B-3.2 EB'!#REF!
Name a: '[2]B-3.2 EB'!#REF!
Name a: '[2]B-3.2 EB'!#REF!
Name a: '[2]B-3.2 EB'!#REF!

Sheet front
A11: BILLS OF QUANTITIES
A15: PROPOSED RESIDENT FOR MR. RIZWAN AT DEMATAGODA

Sheet grnd summry- tender
A1: PROPOSED RESIDENT FOR MR. RIZWAN AT DEMATAGODA
A2: MAIN SUMMARY
A3: BILL ITEM | B3: DESCRIPTION | C3: AMOUNT (Rs.)
A5: A.1 | B5: PRELIMINARIES | C5: =+prelims!I105 -> 760010
A7: A.2 | B7: MAIN BUILDING | C7: =summary!C21 -> 97007884
A9: B | B9: SUB TOTAL-I | C9: =SUM(C5:C8) -> 97767894
B11: Less : Discount (If any)
A13: C | B13: SUB TOTAL-II-CARRIED TO FORM OF BID | C13: =SUM(C9:C12) -> 97767894
B15: PROVISIONAL SUM
A17: D | B17: SUB TOTAL III | C17: =SUM(C13:C16) -> 97767894
B19: ADD- CONTINGENCIES- 10%
A21: E | B21: SUB TOTAL IV | C21: =SUM(C17:C20) -> 97767894
B23: ADD 15% VAT
A25: F | B25: TOTAL PROJECT COST WITH VAT | C25: =SUM(C21:C24) -> 97767894
A27: Total Bid Sum to be taken in to Form of Bid in words Rupees : …………………………………….
A28: …………………………………………………………………………………..…………………..Only
A31: Bidder's VAT Registration No: ………………………………...………………
A34: ……………………….
A35: Signature of Bidder: Date: ……………………………….
A38: Name and Address of Bidder:
A39: ………………………………………………………………….……….
A40: ……………………………………………….………………………….
A41: ………………………………………………………………….……….
A44: ……………………………. ……………………………….
A45: Signature of Witness: (1) Signature of Witness: (2)
A46: Name and Address of Witness: (1) Name and Address of Witness: (2)
... A50: Date: ………………………….. Date: ………………………………
B52: ground floor | C52: =97.7*10.76 -> 1051.252
B53: first floor | C53: =95*10.76 -> 1022.2
B54: second floor | C54: =95*10.76 -> 1022.2
B55: 3rd | C55: =95*10.76 -> 1022.2
B58: total floor area | C58: =SUM(C52:C55) -> 4117.852
B60: rate per sqft | C60: =C7/C58 -> 23557.885
A71: 60000000 | B71: 60000000 | C71: 60000000
B72: v bvbnbvnbn | C72: =A71*0.0144 -> 864000
C73: =C13*1.44% -> 1407857.7
B76: Prepare Schemetic design and detail drawings | C76: 0.23
B77: Prepare Building services detail drawings | C77: 0.18
B78: Prepare Structural detail drawings | C78: 0.22
B79: Prepare Cost Estimate | C79: 0.1
B80: Bidding document and procurement stage | C80: 0.12
B81: Bill checking | C81: 0.15
B84: site supervision
B85: site visit
C87: 100000
C94: =400000 -> 400000
C113: 7200000
C117: =C113/450 -> 16000
G118: =G113*0.015 -> 0

Sheet summary
A1: PROPOSED RESIDENT FOR MR. RIZWAN AT DEMATAGODA
A2: MAIN BUILDING
A4: Nos | B4: Description | C4: Amount
A7: B | B7: =exca!B2 -> EXCAVATION & EARTH WORK | C7: =exca!H39 -> 1432370 | D7: 0.75 | E7: =+C7/$C$21 -> 0.014765501
A8: C | B8: =concrete!B2 -> C - CONCRETE | C8: =concrete!H139 -> 24287535 | D8: 0.75 | E8: =+C8/$C$21 -> 0.25036661
A9: F | B9: =masnry!B2 -> F - MASONRY WORKS | C9: =masnry!H28 -> 7721693.5 | D9: 0.75 | E9: =+C9/$C$21 -> 0.079598618
A10: G | B10: =floring!B2 -> J - FLOORING WORK | C10: =floring!H11 -> 171350 | D10: 0.75 | E10: =+C10/$C$21 -> 0.0017663513
A11: H | B11: =waterprof!B2 -> R - WATER PROOFING WORK | C11: =waterprof!H20 -> 1695509 | D11: 0.75 | E11: =+C11/$C$21 -> 0.017478054
A12: J | B12: =plastering!B2 -> K - PLASTERING WORK | C12: =plastering!H56 -> 6189263 | D12: 0.75 | E12: =+C12/$C$21 -> 0.063801649
A13: K | B13: L - TILING WORK | C13: =+tile!H115 -> 9368340 | D13: 0.75 | E13: =+C13/$C$21 -> 0.096572975
A14: L | B14: =paint!B2 -> M - COLOUR WASHING, PAINTING & POLISHING | C14: =paint!H26 -> 4072270 | D14: 0.75 | E14: =+C14/$C$21 -> 0.041978753
A15: Q | B15: S - PLUMBING AND DRAINAGE WORK | C15: =+'plumbing '!H216 -> 6770880 | D15: 0.75 | E15: =+C15/$C$21 -> 0.069797213
A16: S | B16: V - ELECTRICAL INSTALLATION. | C16: =+'electicle '!H174 -> 7265890 | D16: 0.75 | E16: =+C16/$C$21 -> 0.074899994
A17: T | B17: W - METAL WORK | C17: =+'metal '!H105 -> 19471520 | D17: 0.85 | E17: =+C17/$C$21 -> 0.200721
A18: V | B18: V- SWIMMING POOL (700 CUFT) | C18: =+Pool!H55 -> 8561263.8 | D18: 0.75 | E18: =+C18/$C$21 -> 0.088253278
B21: TOTAL CARRIED TO GRAND SUMMARY | C21: =SUM(C7:C20) -> 97007884
B25: Floor Area | C25: =1993+1993+1993+661 -> 6640
C26: =+C21/C25 -> 14609.621
C28: 10500
C29: =+C26*C25 -> 97007884

Sheet Main sum
A2: PROPOSED RESIDENT FOR MR. RIZWAN AT DEMATAGODA
B3: MAIN SUMMARY
B5: PRELIMINARIES | C5: Rs. | D5: =+prelims!I105 -> 760010
B7: EXCAVATION & EARTH WORK | C7: Rs. | D7: =+exca!H39 -> 1432370
B9: CONCRETE / FORM WORK AND REINFORCEMENT | C9: Rs. | D9: =+concrete!H139 -> 24287535
B11: MASONRY WORKS | C11: Rs. | D11: =+masnry!H28 -> 7721693.5
B13: FLOORING WORK | C13: Rs. | D13: =+floring!H11 -> 171350
B15: PLASTERING WORK | C15: Rs. | D15: =+plastering!H56 -> 6189263
B17: TILING WORK | C17: Rs. | D17: =+tile!H115 -> 9368340
B19: COLOUR WASHING, PAINTING & POLISHING | C19: Rs. | D19: =+paint!H26 -> 4072270
B21: PLUMBING AND DRAINAGE WORK | C21: Rs. | D21: =+'plumbing '!H216 -> 6770880
B23: ELECTRICAL INSTALLATION. | C23: Rs. | D23: =+'electicle '!H174 -> 7265890
B25: HANDRAIL / DOORS AND WINDOWS | C25: Rs. | D25: =+'metal '!H105 -> 19471520
B27: WATER PROOFING WORK | C27: Rs. | D27: =+waterprof!H20 -> 1695509
C29: Rs. | D29: =+waterprof!H22 -> 0
C31: Rs. | D31: =+waterprof!H24 -> 0
C33: Rs. | D33: =+waterprof!H26 -> 0
B35: SUB TOTAL - 01 | D35: =SUM(D5:D28) -> 89206630
B36: 00% contingency | D36: =D35*0 -> 0
B37: SUB TOTAL | C37: Rs. | D37: =SUM(D35:D36) -> 89206630
B38: TOTAL ( Excluding VAT ) carried to Form of Bid | C38: Rs. | D38: =SUM(D37:D37) -> 89206630
B49: Date ………………………………………

Sheet prelims
A1: Nos | B1: Description | C1: Mode of payment catogary | D1: Qty | E1: Unit | F1: COST | G1: OHP% | H1: Rate | I1: Amount | J1: 0.75
B2: BILL NO. 01
A3: 1/PR | B3: PRELIMINARIES
A5: PR.1 | B5: Insurance and Securities
B7: Allow sum for Bonds and Gurantee | C7: A | I7: Provide by client.
A9: =A7+0.01 -> 0.01 | B9: Allow sum for providing advance payment security | C9: A | D9: 1 | E9: Item
A11: =A9+0.01 -> 0.02 | B11: Allow Sum for insurance of Works, Machinery & Equipment, Plant, Materials, Third party persons & property and Eimployer's personal & property at site per the Contract | C11: A | D11: 1 | E11: Item
B13: The minimim insurance.cover shall be:
B15: The minimum cover for insurance of the Works and Plant and Materials is 110% of the Initial Controct Price.
B17: The maximum deductible for insurance uf the Works and of Plant and Materials is 5% of the Initial Contract Price.
B19: The minimunm cover for loss or damage to Equipment is the replacement cost
B21: The maximum deductible for insurance of Equipment is 5% of minimun cover for equipment.
B23: The minimum cover for insurance of (orher propert other than the site) is Ra. 2Million per event and totul limit of indemnity shall be Rs 10 Million
B25: The mininum cover for insurance of personal injury or death.
B27: For third party and employees of the Employer and other persons engaged by the Employer in the Works is Rs.5,000,000/- per event
B29: Injury or damage to persons including employer and consultant and their employees and other consultants employed by the employer shall be covered by the personnel accident insurance cover for Rs 2 million per event effective from the date of commencement of contract until end of the defects liability period (total number of persons insured are not exceeding 10 nrs)
A31: =A11+0.01 -> 0.03 | B31: Allow Sum for insurance against accidents and injury to Contractor's personnel as per the Contract. | C31: A | D31: 1 | E31: Item
B33: The iminimum cover for personal injury or death
B34: For the Contractor's workmen is Rs. 500,000/= per event
B35: Contractor s employees other than workmen is Rs.5.000.000/= per event
A36: 2 | B36: Engineer's Facilities
A38: =A36+0.01 -> 2.01 | B38: Allow lump sum for constructing, maintaining, dismantling and removal on completion of the Works, a temporary air conditioned TFU for Engineer's office with toilet,elecricity facility in conformity with the plans provided for Engineer's requirements, including furniture and fittings, furnishing, sanitary facilities necessary and other facilities. | C38: C | D38: 1 | E38: Item
B39: The follwing facilities shall be provided
B40: (1) 2-0"x4-0" Table with drawers for Engineer's representative with medium back chair
B41: (2) Chair for Engineer's Representative( two nr of low back chair)
B42: (3) lockable Cupboard for storage of drawings, documents and stationery
B43: (4) Pedestal fan
B44: (5) 30 Gb monthly data package( WIFI Router),contractor should paid data package monthly
B45: (6) 1200mm X 1200mm white board
B46: (7) I5 computer with printer
B47: (8) Adequate Size Meeting table and 6 nr of chair
A49: PR.2 | B49: Contractor's Facilities
B51: Allow lump sum for constructing, maintaining, dismantling and removal on completion of the Works, a temporary office,stores and workshop with toilet,elecricity facility in conformity with the plans provided for Engineer's requirements, including furniture and fittings, furnishing, sanitary facilities necessary and other facilities. | C51: C | D51: 1 | E51: Item | F51: 175000 | G51: =+$J$1 -> 0.75 | H51: =ROUNDUP(F51/G51,-1) -> 233340 | I51: =+H51*D51 -> 233340
A53: =A51+0.01 -> 0.01 | B53: Allow lump sum for constructing, maintaining, dismantling and removal on completion of the Works, building to be uses as workshops and stores for perishable materials. Buildings shall be constructed in accordance with the drawing prepared by the Contractor and concurred by the Engineer | C53: C | D53: 1 | E53: Item
A55: =A53+0.01 -> 0.02 | B55: Allow lump sum for providing Accommodation, including all sanitory facility for Contractor's staff and workmen | C55: C | D55: 1 | E55: Item
A57: 3 | B57: Construction Managment and Supervision
A59: =A57+0.01 -> 3.01 | B59: Allow sum for employing suitable qualified and axperienced technical personnal on full time for construction maragement services at the site. | C59: E | D59: 1 | E59: Item
B60: Site Engineer( Full Time)
B61: Project Manager ( C.Eng with 10 year experience- part time)
B62: MEP Engineer( Building Service Eng with 10 year experience- part time)
B63: ( Site Engineer BSc.Eng with 5 years or NDT-Civil with 10 years experience- Full Time )
B64: (CV to be submitted with the bid)
A66: PR.3 | B66: Setting Out
B68: Allow sum for emplyoing a licensed land surveyor to define the building site work etc., check levels and carry out such other surveys as may be necessary to establish accrately the placing of forms and pouring of concrete and all other setting out in both vertical and horizontal plane. | C68: G | D68: 1 | E68: Item | F68: 65000 | G68: =+$J$1 -> 0.75 | H68: =ROUNDUP(F68/G68,-1) -> 86670 | I68: =+H68*D68 -> 86670
A70: PR.4 | B70: Quality, Standards and Progress
A72: =A70+0.01 -> #VALUE! | B72: Allow lump sum for provision of progress reports including photograplic records and other schedules included in the CIDA publication Guidelines for Effective Construction Managenent. (CIDA/CM/01), relevant administration as directed by the Engineer. | C72: E | D72: 1 | E72: Item
A74: =A70+0.01 -> #VALUE! | B74: Allow lunp sum for all cost in connection with preparing samples for testing, making arrangements for testing of Materials, Goods etc, submission of shop drawings as stipalated in the specification, obtaining test reports and submitting the same to the Engineer, | C74: F | D74: 1 | E74: Item
B76: Allow lunp sum for preparing As built drawings of following services. All drawings shall be produced in triplicate to a scale (3 set of binded hard copy) and one electronic copy in Auto CAD format | C76: E | I76: Free of charge
B77: 1.Architectural
B78: 2.Electricle
B79: 3.Water Supply,Sewarage and Waste Water lines
A81: PR.5 | B81: Health Safety and Environment
A83: =A81+0.01 -> #VALUE! | B83: Allow lump sum for providing and maintaining necessary hoarding and gates for safeguarding the Works, Materials and Plant, as directed by the Engineer. Corrugated sheet/Zn allow wall sheet GI gramed hoarding height 8ft and to necessary perimetor area | C83: E | D83: 1 | E83: Item
A85: PR.5.1 | B85: Allow lump sum for maintaining the site in a clean and orderly manner at all times and during the entire contract period. | C85: E | D85: 10 | E85: Month | F85: 15000 | G85: =+$J$1 -> 0.75 | H85: =ROUNDUP(F85/G85,-1) -> 20000 | I85: =+H85*D85 -> 200000
A87: PR.5.2 | B87: Allow lump sum for demobilization, removal of all rubbish & debris and clearing up site on completion, leaving all-in good order and handing over. | C87: G | D87: 10 | E87: Trip | F87: 18000 | G87: =+$J$1 -> 0.75 | H87: =ROUNDUP(F87/G87,-1) -> 24000 | I87: =+H87*D87 -> 240000
A88: =A87+0.01 -> #VALUE! | B88: Allow sum for removeing of surface water and ground water | C88: G | D88: 1 | E88: Item
A90: =A87+0.01 -> #VALUE! | B90: The Contractor shall protect and maintain the approaches to the site, clear of mud and debris including providing a water pressure gun with all connected services. The contractor also shall make good any damage attributable to the works at his own expense or pay all costs, charges in connection therewith. | C90: E | D90: 1 | E90: Item
A92: 6 | B92: Security and Protection
A94: =A92+0.01 -> 6.01 | B94: Allow lump sum for employing an adequate number of security personnesl and security systems on full time basis through out the period of construction, and provide for necessary security lighting and a warning systcm. | C94: E | D94: 1 | E94: Item
A95: =A94+0.01 -> 6.02 | B95: Allow lump sum for providing and maintaining necessary hoarding and gates for safeguarding the Works, Materials and Plant, as directed by the Engineer. Corrugated sheet/Zn allow wall sheet GI gramed hoarding height 8ft and to necessary perimetor area | C95: E | D95: 1 | E95: Item | P95: =O95*250 -> 0
A96: PR.6 | B96: Services and Facilities
A98: PR.6.1 | B98: Allow lump sum for supply of water for the Works and paying all charges and other expenses in connection with the supply from water mains or any other alternative method of water supply, storage and reticulation | C98: E | I98: Provide by Client
A100: PR.6.2 | B100: Allow lump sum for supplying temporary electricity for the works including connection, distribution system for the Works, internal arrangements and all payments to be authorities for consumption | C100: E | I100: Provide by Client
A101: =A100+0.01 -> #VALUE! | B101: Allow lump sum for erecting and maintaining scaffolding and/ self climbing platforms around the construction building wall area. Such scaffolding etc. shall be removed on completion and all Works disturbed shall be made good.rate to include to safety dust coverd green net for total building perimeter building height area | C101: F | D101: 1 | E101: Item
A103: =A101+0.01 -> #VALUE! | B103: Allow lump sum for providing and maintaining a name board, approximately 2.1mX1.5m size with GI frame at 2.1m above ground level as directed for construction pereiod. | C103: G | D103: 1 | E103: Item
B105: PRELIMINARIES CARRIED TO GRAND SUMMARY | I105: =SUM(I3:I104) -> 760010

Sheet exca
A1: Nos | B1: Description | C1: Qty | D1: Unit | E1: COST | F1: OHP% | G1: Rate | H1: Amount | I1: =+summary!D7 -> 0.75
A2: B | B2: EXCAVATION & EARTH WORK
B3: SITE PREPERATION
A5: B 01 | B5: Clearing site vegetation manually including removal of bushes, shurb removing rubbish. | C5: 316 | D5: Sqm | E5: 150 | F5: =+$I$1 -> 0.75 | G5: =ROUNDUP(E5/F5,-1) -> 200 | H5: =+G5*C5 -> 63200
A7: B 02 | B7: Removing top soil including mud, machinery to a nessasary depth and removing all debris away from site, location decided by client withing 3 km | C7: =C5 -> 316 | D7: Sqm | E7: =+'Rate Breakdowns'!G17 -> 301.39935 | F7: =+$I$1 -> 0.75 | G7: =ROUNDUP(E7/F7,-1) -> 410 | H7: =+G7*C7 -> 129560
B9: EXCAVATION
B11: Note:
B12: All excavations are measured net. No allowance made for working space.
B14: Excavations as follows in any materials met with except in rock requiring blasting.
B16: Excavation for foundation commencing from formed ground level.
A17: B 03 | B17: Excavation for column, wall, staircase foundations in any material (except rock requiring blasting) up to depth (as per the drawings), part return fill in and ram and surplus depositted within site as directed. | C17: =45+65+5 -> 115 | D17: m3 | E17: =+'Rate Breakdowns'!G32 -> 2120.1413 | F17: =+$I$1 -> 0.75 | G17: =ROUNDUP(E17/F17,-1) -> 2830 | H17: =+G17*C17 -> 325450
B19: Filling & Compaction
B20: Approved earth shall mean filling materials that comply to the following :
A21: ( a ) | B21: The earth will be free of vegetation, roots, boulders, easily decomposable materials, chemicals, industrial waste, plastic etc.
A22: ( b ) | B22: The maximum size of particle shall not exceed 75mm.
A23: ( c ) | B23: The earth shall be well graded and the silt and clay (fines) content shall not be more than 25%
B25: Dry Earth Filling
A26: B 05 | B26: Supplying and compaction of Approved earth,compaction of earth including watering and compaction in 225mm thick layers with proctor density, using machine rammer/roller vibrator, rate to include to compaction maching charges and other nessasary related work | C26: =+C32 -> 21 | D26: m3 | E26: =+'Rate Breakdowns'!G87 -> 4478.7986 | F26: =+$I$1 -> 0.75 | G26: =ROUNDUP(E26/F26,-1) -> 5980 | H26: =+G26*C26 -> 125580
B28: Back Filling
A29: B 06 | B29: Supplying and compaction of Approved earth,compaction of earth including watering and compaction in 225mm thick layers with proctor density, using machine rammer or roller vibrator, rate to include to compaction maching charges and other nessasary related work | C29: 70 | D29: m3 | E29: =+'Rate Breakdowns'!G87 -> 4478.7986 | F29: =+$I$1 -> 0.75 | G29: =ROUNDUP(E29/F29,-1) -> 5980 | H29: =+G29*C29 -> 418600
A31: B 07 | B31: Qurry Dust and ABC Filling
B32: Supplying and compaction of qurry dust compaction of earth including watering and compaction in 225mm thick layers with proctor density, using machine rammer/roller vibrator, rate to include to compaction maching charges and other nessasary related work | C32: 21 | D32: m3 | E32: =+'Rate Breakdowns'!G115 -> 3776.5018 | F32: =+$I$1 -> 0.75 | G32: =ROUNDUP(E32/F32,-1) -> 5040 | H32: =+G32*C32 -> 105840
A33: B 08 | B33: Antitermite -Tretement
B34: Antitermite-treatement for the new construction with applying Biflexthrine 10Tc (Biflex ) or approved equivelant , Dialuted chemicals 1:200 ratio with water after supplying the sealed bottle with lables to the site and should be followed the manufacture standards of application including horizontal & vertical barriers. It should be 10 years warranty on application. | C34: 210 | D34: Sqm | E34: =75*10.76 -> 807 | F34: =+$I$1 -> 0.75 | G34: =ROUNDUP(E34/F34,-1) -> 1080 | H34: =+G34*C34 -> 226800
B36: Water Disposal
A37: B 9 | B37: Disposal of Ground Water and Surface Water | C37: 1 | D37: Item | E37: 28000 | F37: =+$I$1 -> 0.75 | G37: =ROUNDUP(E37/F37,-1) -> 37340 | H37: =+G37*C37 -> 37340
B39: EXCAVATION & EARTH WORK CARRIED TO COLLECTION | H39: =SUM(H3:H38) -> 1432370
D71: =600/10.76 -> 55.762082 | I71: =1000/50 -> 20
D72: =D71*0.05 -> 2.7881041 | I72: =50/1000 -> 0.05 | K72: =D72/2.83 -> 0.98519579
C75: cemnt | D75: =13*K72 -> 12.807545
C76: sand | D76: =0.53*K72 -> 0.52215377
C77: metal | D77: =0.92*K72 -> 0.90638013

Sheet concrete
A1: Nos | B1: Description | C1: Qty | D1: Unit | E1: COST | F1: OHP% | G1: Rate | H1: Amount | I1: =+summary!D8 -> 0.75
B2: C - CONCRETE
B4: UP TO DPC LEVEL
B5: G50 Concrete (mixed at site either manually or with machine)
A7: C 01 | B7: Cement concrete 1:3:6 (1") laid to a thickness of 2" in wall foundations, under column/stair footings,plinth beams including placing in position,compacting and curing. | C7: 96 | D7: Sqm | E7: =+'Rate Breakdowns'!G311 -> 1656.2357 | F7: =+I1 -> 0.75 | G7: =ROUNDUP(E7/F7,-1) -> 2210 | H7: =+G7*C7 -> 212160
B9: IN - SITU REINFORCED CONCRETE
B11: In - Situ Reinforced Concrete Of Grade 25 &30 (mixed at site with a concrete mixer )
B13: Grade 25 concrete will be used for footings, columns, beams,staircases, tie-beams of reinforced concrete elements in multi-storied building (excluding lintols, stiffener columns, copings, non-structural columns and Drains).
A14: C 02 | B14: Volume Batched Grade 25 concrete prepared at site using mixer and vibrator in ground floor.Rate has been included the cost of curing continuously for 7 days. Upto DPC.
A15: C2.1 | B15: In column/strip footing | C15: 19 | D15: m3 | E15: =+'Rate Breakdowns'!G282 -> 32745.362 | F15: =+$I$1 -> 0.75 | G15: =ROUNDUP(E15/F15,-1) -> 43670 | H15: =+G15*C15 -> 829730
A16: C2.2 | B16: In column shaft | C16: 2 | D16: m3 | E16: =+E15 -> 32745.362 | F16: =+$I$1 -> 0.75 | G16: =ROUNDUP(E16/F16,-1) -> 43670 | H16: =+G16*C16 -> 87340
A17: C2.3 | B17: In plinth Beams | C17: 10 | D17: m3 | E17: =+E15 -> 32745.362 | F17: =+$I$1 -> 0.75 | G17: =ROUNDUP(E17/F17,-1) -> 43670 | H17: =+G17*C17 -> 436700
A18: C2.4 | B18: In staircases | C18: 1 | D18: m3 | E18: =+E15 -> 32745.362 | F18: =+$I$1 -> 0.75 | G18: =ROUNDUP(E18/F18,-1) -> 43670 | H18: =+G18*C18 -> 43670
A19: C2.5 | B19: In Lift base and lift wall | D19: m3
A21: C 03 | B21: Volume Batched Grade 20/ready mix reinforced concrete floors laid on ground. Rate has been included the cost of curing continously for 10 days. ( rate include to transport from batching plant. inclue for placing, levelling, vibrating & curing the concrete & pump car cost)
A22: C3.1 | B22: Ground floor concrete(75mm thick) | C22: 14 | D22: m3 | E22: =+'Rate Breakdowns'!G252 -> 29746.025 | F22: =+$I$1 -> 0.75 | G22: =ROUNDUP(E22/F22,-1) -> 39670 | H22: =+G22*C22 -> 555380
B24: SUPER STRUCTURE
A26: C3.5 | B26: Volume Batched Grade 20 concrete prepared at site using mixer and vibrator for reinforced cast in situ lintols, copings, stiffeners and drains and pantry slab, kitchen vanity slab
A27: C3.5.1 | B27: Ground Floor | D27: m3
A28: C3.5.2 | B28: First Floor | D28: m3
A29: C3.5.3 | B29: Second Floor | D29: m3
A30: C3.5.4 | B30: Third Floor | D30: m3
A31: C3.5.5 | B31: Fouth Floor | D31: m3
A33: C 04 | B33: Volume Batched Grade 25 concrete prepared at site using mixer or Grade 25 ready mix (rate include to transport from batching plant. Rate has been included for placing, levelling, vibrating & curing the concrete & pump car cost) and vibrator in ground floor. and include the cost of curing continously for 7 days.
A34: C4.1 | B34: In column shaft from ground floor level to First floor level | C34: 6 | D34: m3 | E34: =+'Rate Breakdowns'!G282 -> 32745.362 | F34: =+$I$1 -> 0.75 | G34: =ROUNDUP(E34/F34,-1) -> 43670 | H34: =+G34*C34 -> 262020 | I34: =+C34/0.125 -> 48
A35: C4.2 | B35: In column shaft from First floor level to Second floor level | C35: 6 | D35: m3 | E35: =+E34*1.03 -> 33727.723 | F35: =+$I$1 -> 0.75 | G35: =ROUNDUP(E35/F35,-1) -> 44980 | H35: =+G35*C35 -> 269880
A36: C4.3 | B36: In column shaft from Second floor level to Terrace floor level | C36: 6 | D36: m3 | E36: =+E34*1.06 -> 34710.084 | F36: =+$I$1 -> 0.75 | G36: =ROUNDUP(E36/F36,-1) -> 46290 | H36: =+G36*C36 -> 277740
A37: C4.3 | B37: In column shaft from Terrace floor level to Roof level | C37: 2.5 | D37: m3 | E37: =+E34*1.09 -> 35692.445 | F37: =+$I$1 -> 0.75 | G37: =ROUNDUP(E37/F37,-1) -> 47590 | H37: =+G37*C37 -> 118975
A39: C4.4 | B39: In staircase from ground floor level to First floor level | C39: 2.5 | D39: m3 | E39: =+E35 -> 33727.723 | F39: =+$I$1 -> 0.75 | G39: =ROUNDUP(E39/F39,-1) -> 44980 | H39: =+G39*C39 -> 112450
A40: C4.5 | B40: In staircase from First floor level to Second floor level | C40: 2.5 | D40: m3 | E40: =+E36 -> 34710.084 | F40: =+$I$1 -> 0.75 | G40: =ROUNDUP(E40/F40,-1) -> 46290 | H40: =+G40*C40 -> 115725
A41: C4.5 | B41: In staircase from Second floor level to Terrace floor level | C41: 2.5 | D41: m3 | E41: =+E37 -> 35692.445 | F41: =+$I$1 -> 0.75 | G41: =ROUNDUP(E41/F41,-1) -> 47590 | H41: =+G41*C41 -> 118975
B44: READY MIX CONCRETE
A46: C 05 | B46: Ready mix concrete of grade 20(20 N/mm2) confirming to SLS 1144- 1997, rate include to transport from batching plant. Rate has been inclued for placing, levelling, vibrating & curing the concrete & pump car cost. | Q46: =32294/30 -> 1076.4667
A47: C5.1 | B47: In Reinforced beam at First floor level | C47: 11 | D47: Cu.m | E47: =+E35 -> 33727.723 | F47: =+$I$1 -> 0.75 | G47: =ROUNDUP(E47/F47,-1) -> 44980 | H47: =+G47*C47 -> 494780 | Q47: =+P47/M47 -> #DIV/0!
A48: C5.2 | B48: In Reinforced beam at second floor level | C48: 11 | D48: Cu.m | E48: =+E36 -> 34710.084 | F48: =+$I$1 -> 0.75 | G48: =ROUNDUP(E48/F48,-1) -> 46290 | H48: =+G48*C48 -> 509190 | Q48: =+P48/M48 -> #DIV/0! | R48: =10.7+5.9 -> 16.6 | S48: =R48*0.55*0.3 -> 2.739
A49: C5.3 | B49: In Reinforced beam at Terrace floor level (with Swimming Pool) | C49: =6+13 -> 19 | D49: Cu.m | E49: =+E37 -> 35692.445 | F49: =+$I$1 -> 0.75 | G49: =ROUNDUP(E49/F49,-1) -> 47590 | H49: =+G49*C49 -> 904210
A50: C5.4 | B50: In Reinforced beam at Roof level | C50: 4 | D50: Cu.m | E50: =+E34*1.12 -> 36674.806 | F50: =+$I$1 -> 0.75 | G50: =ROUNDUP(E50/F50,-1) -> 48900 | H50: =+G50*C50 -> 195600
A52: C5.5 | B52: In Reinforced slab at First floor level | C52: 22 | D52: Cu.m | E52: =+E47 -> 33727.723 | F52: =+$I$1 -> 0.75 | G52: =ROUNDUP(E52/F52,-1) -> 44980 | H52: =+G52*C52 -> 989560 | I52: =+C52/0.125 -> 176 | J52: =+I52*10.76 -> 1893.76
A53: C5.6 | B53: In Reinforced Slab at second floor level | C53: 22 | D53: Cu.m | E53: =+E48 -> 34710.084 | F53: =+$I$1 -> 0.75 | G53: =ROUNDUP(E53/F53,-1) -> 46290 | H53: =+G53*C53 -> 1018380 | I53: =+C53/0.125 -> 176 | J53: =+I53*10.76 -> 1893.76
A54: C5.7 | B54: In Reinforced slab at Terrace floor level (with Swimming Pool) | C54: =8+20 -> 28 | D54: Cu.m | E54: =+E49 -> 35692.445 | F54: =+$I$1 -> 0.75 | G54: =ROUNDUP(E54/F54,-1) -> 47590 | H54: =+G54*C54 -> 1332520 | I54: =+C54/0.125 -> 224 | J54: =+I54*10.76 -> 2410.24
A55: C5.8 | B55: In Reinforced Slab at Roof level | C55: 7 | D55: Cu.m | E55: =+E50 -> 36674.806 | F55: =+$I$1 -> 0.75 | G55: =ROUNDUP(E55/F55,-1) -> 48900 | H55: =+G55*C55 -> 342300
B58: D - FORM WORK
A60: (a) | B60: The rates given for items herein are applicable for plywood sheets of 15 mm thick. Hence the rate is valid only if the shuttering / formwork for footing , column , beams , lintel, walls, slabs are of 15 mm thick ply boards.
A62: (b) | B62: For ordinary plywood of 15 mm thick boarding as shuttering, (Even for WBP sheets the same rate shall be applicable).
B64: Up to DPC level
A65: D 01 | B65: Shuttering for sides of foundation with 15mm thick Plywood board including dismantling.
A67: D 1.1 | B67: In stairacse | C67: 5 | D67: Sqm | E67: 2450 | F67: =+$I$1 -> 0.75 | G67: =ROUNDUP(E67/F67,-1) -> 3270 | H67: =+G67*C67 -> 16350
A69: D 02 | B69: Shuttering for sides and bottom of plinth beams, ground beams including dismantling in 15mm thick plywood board.
B70: Plinth beam | C70: 80 | D70: Sqm | E70: 2050 | F70: =+$I$1 -> 0.75 | G70: =ROUNDUP(E70/F70,-1) -> 2740 | H70: =+G70*C70 -> 219200
B71: Column base | C71: 45 | D71: Sqm | E71: 2100 | F71: =+$I$1 -> 0.75 | G71: =ROUNDUP(E71/F71,-1) -> 2800 | H71: =+G71*C71 -> 126000
B72: Column Stub | C72: 30 | D72: Sqm | E72: 2150 | F72: =+$I$1 -> 0.75 | G72: =ROUNDUP(E72/F72,-1) -> 2870 | H72: =+G72*C72 -> 86100
A74: D 03 | B74: Shuttering for Columns including dismantling using pre-fabricated steel shutter halves including dismantling.
A76: D 3.1 | B76: In column from ground floor level to First floor level | C76: 90 | D76: Sqm | E76: 2100 | F76: =+$I$1 -> 0.75 | G76: =ROUNDUP(E76/F76,-1) -> 2800 | H76: =+G76*C76 -> 252000
A77: D 3.2 | B77: In column shaft from First floor level to Second floor level | C77: 90 | D77: Sqm | E77: 2150 | F77: =+$I$1 -> 0.75 | G77: =ROUNDUP(E77/F77,-1) -> 2870 | H77: =+G77*C77 -> 258300
A78: D 3.3 | B78: In column shaft from Second floor level to Terrace Level | C78: 90 | D78: Sqm | E78: 2200 | F78: =+$I$1 -> 0.75 | G78: =ROUNDUP(E78/F78,-1) -> 2940 | H78: =+G78*C78 -> 264600
A79: D 3.4 | B79: In column shaft from Terrace Level to Roof Level | C79: 40 | D79: Sqm | E79: 2250 | F79: =+$I$1 -> 0.75 | G79: =ROUNDUP(E79/F79,-1) -> 3000 | H79: =+G79*C79 -> 120000
A82: D 3.5 | B82: In staircase from ground floor level to First floor level | C82: 18 | D82: Sqm | E82: =+E67 -> 2450 | F82: =+$I$1 -> 0.75 | G82: =ROUNDUP(E82/F82,-1) -> 3270 | H82: =+G82*C82 -> 58860
A83: D 3.6 | B83: In staircase from First floor level to Second floor level | C83: 18 | D83: Sqm | E83: =+E82*1.02 -> 2499 | F83: =+$I$1 -> 0.75 | G83: =ROUNDUP(E83/F83,-1) -> 3340 | H83: =+G83*C83 -> 60120
A84: D 3.7 | B84: In staircase from Second floor level to Terrace floor level | C84: 18 | D84: Sqm | E84: =+E82*1.04 -> 2548 | F84: =+$I$1 -> 0.75 | G84: =ROUNDUP(E84/F84,-1) -> 3400 | H84: =+G84*C84 -> 61200
A88: D 04 | B88: Shuttering for floor slab including dismantling in 15mm thick Plywood board or steel boarding support by steel jack
A89: D 4.1 | B89: In Slab at First floor level | C89: 152 | D89: Sqm | E89: 2050 | F89: =+$I$1 -> 0.75 | G89: =ROUNDUP(E89/F89,-1) -> 2740 | H89: =+G89*C89 -> 416480
A90: D 4.2 | B90: In Slab at second floor level | C90: 152 | D90: Sqm | E90: =+E89*1.02 -> 2091 | F90: =+$I$1 -> 0.75 | G90: =ROUNDUP(E90/F90,-1) -> 2790 | H90: =+G90*C90 -> 424080
A91: D 4.3 | B91: In Slab at Terrace floor level (with Swimming Pool) | C91: 180 | D91: =D90 -> Sqm | E91: =+E89*1.04 -> 2132 | F91: =+$I$1 -> 0.75 | G91: =ROUNDUP(E91/F91,-1) -> 2850 | H91: =+G91*C91 -> 513000
A92: D 4.4 | B92: In Slab at Roof Top floor level | C92: 55 | D92: =D91 -> Sqm | E92: =+E89*1.06 -> 2173 | F92: =+$I$1 -> 0.75 | G92: =ROUNDUP(E92/F92,-1) -> 2900 | H92: =+G92*C92 -> 159500
A94: D 05 | B94: Shuttering for floor Beams including dismantling in 15mm thick plywood board or steel formwork
A95: D 5.1 | B95: In beam at First floor level | C95: 23 | D95: Sqm | E95: 2200 | F95: =+$I$1 -> 0.75 | G95: =ROUNDUP(E95/F95,-1) -> 2940 | H95: =+G95*C95 -> 67620
A96: D 5.2 | B96: In beam at second floor level | C96: 23 | D96: Sqm | E96: =2200*1.02 -> 2244 | F96: =+$I$1 -> 0.75 | G96: =ROUNDUP(E96/F96,-1) -> 3000 | H96: =+G96*C96 -> 69000 | Q96: =11+0.9 -> 11.9 | R96: =0.55+0.55+0.3 -> 1.4 | S96: =R96*Q96 -> 16.66
A97: D 5.3 | B97: In beam at Terrace floor level (with Swimming Pool) | C97: 36 | D97: =D96 -> Sqm | E97: =+E95*1.04 -> 2288 | F97: =+$I$1 -> 0.75 | G97: =ROUNDUP(E97/F97,-1) -> 3060 | H97: =+G97*C97 -> 110160
A98: D 5.4 | B98: In beam at Roof Top floor level | C98: 9 | D98: =D97 -> Sqm | E98: =+E95*1.06 -> 2332 | F98: =+$I$1 -> 0.75 | G98: =ROUNDUP(E98/F98,-1) -> 3110 | H98: =+G98*C98 -> 27990
B101: E - REINFORCEMENT
B102: Mild steel and Tor steel bars confirming to BS specifications, tensile strength 250 N/mm2 and 460 N/mm2 respectively, in reinforcements. Rate has been included for lapping, cutting, bending, fabricating, concrete distance blocks, stools, and fixing with binding wires in: spacer bars, placing in position as per the structural drawings
A104: E 01 | B104: Mild/Tor steel reinforcement to slabs, beams, lintols, columns, footings & etc.. bent to shape, laid in position and tied with 16 B.W.G. Aneal binding wire up to Dpc .
A105: E1.2 | B105: In Tie Beams | C105: =+C17*78 -> 780 | D105: Kg | E105: =+'Rate Breakdowns'!G586 -> 470.34016 | F105: =+$I$1 -> 0.75 | G105: =ROUNDUP(E105/F105,-1) -> 630 | H105: =+G105*C105 -> 491400
A106: E1.3 | B106: in Column Base | C106: =+C16*126 -> 252 | D106: Kg | E106: =+'Rate Breakdowns'!G586 -> 470.34016 | F106: =+$I$1 -> 0.75 | G106: =ROUNDUP(E106/F106,-1) -> 630 | H106: =+G106*C106 -> 158760
A107: E1.4 | B107: In Floor Slab | C107: =+C22*6 -> 84 | D107: Kg | E107: =+E105 -> 470.34016 | F107: =+$I$1 -> 0.75 | G107: =ROUNDUP(E107/F107,-1) -> 630 | H107: =+G107*C107 -> 52920
A108: E1.5 | B108: in Column Stub | C108: =+C16*110 -> 220 | D108: Kg | E108: =+E105 -> 470.34016 | F108: =+$I$1 -> 0.75 | G108: =ROUNDUP(E108/F108,-1) -> 630 | H108: =+G108*C108 -> 138600
A109: E1.6 | B109: Staircase | C109: 90 | D109: Kg | E109: =+E105 -> 470.34016 | F109: =+$I$1 -> 0.75 | G109: =ROUNDUP(E109/F109,-1) -> 630 | H109: =+G109*C109 -> 56700
A111: E 02 | B111: Mild/Tor steel reinforcement to slabs, beams, lintols, columns, footings & etc.. bent to shape, laid in position and tied with 16 B.W.G. Aneal binding wire in Ground Floor.
A112: E2.1 | B112: In column shaft | C112: =+C34*126 -> 756 | D112: Kg | E112: =+E105 -> 470.34016 | F112: =+$I$1 -> 0.75 | G112: =ROUNDUP(E112/F112,-1) -> 630 | H112: =+G112*C112 -> 476280
A113: E2.2 | B113: In Beams (1st Floor Slab) | C113: =+C47*112 -> 1232 | D113: Kg | E113: =+E105 -> 470.34016 | F113: =+$I$1 -> 0.75 | G113: =ROUNDUP(E113/F113,-1) -> 630 | H113: =+G113*C113 -> 776160
A114: E2.3 | B114: In Floor Slab (1st Floor Slab) | C114: =+C52*95 -> 2090 | D114: Kg | E114: =+E105 -> 470.34016 | F114: =+$I$1 -> 0.75 | G114: =ROUNDUP(E114/F114,-1) -> 630 | H114: =+G114*C114 -> 1316700
A115: E2.4 | B115: Staircase (Ground Floor to 1st Floor) | C115: =+C39*96 -> 240 | D115: Kg | E115: =+E105 -> 470.34016 | F115: =+$I$1 -> 0.75 | G115: =ROUNDUP(E115/F115,-1) -> 630 | H115: =+G115*C115 -> 151200
A117: E 03 | B117: Mild/Tor steel reinforcement to slabs, beams, lintols, columns, footings & etc.. bent to shape, laid in position and tied with 16 B.W.G. Aneal binding wire in first floor .
A118: E3.1 | B118: In column shaft | C118: =+C35*126 -> 756 | D118: Kg | E118: =+E105*1.01 -> 475.04356 | F118: =+$I$1 -> 0.75 | G118: =ROUNDUP(E118/F118,-1) -> 640 | H118: =+G118*C118 -> 483840
A119: E3.2 | B119: In Beams (2nd Floor Slab) | C119: =+C48*112 -> 1232 | D119: Kg | E119: =+E118 -> 475.04356 | F119: =+$I$1 -> 0.75 | G119: =ROUNDUP(E119/F119,-1) -> 640 | H119: =+G119*C119 -> 788480
A120: E3.3 | B120: In Floor Slab (2nd Floor Slab) | C120: =+C53*95 -> 2090 | D120: Kg | E120: =+E118 -> 475.04356 | F120: =+$I$1 -> 0.75 | G120: =ROUNDUP(E120/F120,-1) -> 640 | H120: =+G120*C120 -> 1337600
A121: E3.4 | B121: Staircase (1st Floor to 2nd Floor) | C121: =+C40*96 -> 240 | D121: Kg | E121: =+E118 -> 475.04356 | F121: =+$I$1 -> 0.75 | G121: =ROUNDUP(E121/F121,-1) -> 640 | H121: =+G121*C121 -> 153600
A124: E 04 | B124: Mild/Tor steel reinforcement to slabs, beams, lintols, columns, footings & etc.. bent to shape, laid in position and tied with 16 B.W.G. Aneal binding wire in Second Floor
A125: E4.1 | B125: In column shaft | C125: =+C36*126 -> 756 | D125: Kg | E125: =+E105*1.02 -> 479.74696 | F125: =+$I$1 -> 0.75 | G125: =ROUNDUP(E125/F125,-1) -> 640 | H125: =+G125*C125 -> 483840
A126: E4.2 | B126: In Beams (Terrace Slab) | C126: =+C49*142 -> 2698 | D126: Kg | E126: =+E125 -> 479.74696 | F126: =+$I$1 -> 0.75 | G126: =ROUNDUP(E126/F126,-1) -> 640 | H126: =+G126*C126 -> 1726720
A127: E4.3 | B127: In Floor Slab (Terrace Slab) | C127: =+C54*122 -> 3416 | D127: Kg | E127: =+E125 -> 479.74696 | F127: =+$I$1 -> 0.75 | G127: =ROUNDUP(E127/F127,-1) -> 640 | H127: =+G127*C127 -> 2186240
A128: E4.4 | B128: In Staircase (2nd Floor to Terrace Floor) | C128: =+C41*96 -> 240 | D128: Kg | E128: =+E125 -> 479.74696 | F128: =+$I$1 -> 0.75 | G128: =ROUNDUP(E128/F128,-1) -> 640 | H128: =+G128*C128 -> 153600
A131: E 05 | B131: Mild/Tor steel reinforcement to slabs, beams, lintols, columns, footings & etc.. bent to shape, laid in position and tied with 16 B.W.G. Aneal binding wire in Roof Slab.
A132: E5.1 | B132: In column shaft | C132: =+C37*126 -> 315 | D132: Kg | E132: =+E112*1.03 -> 484.45036 | F132: =+$I$1 -> 0.75 | G132: =ROUNDUP(E132/F132,-1) -> 650 | H132: =+G132*C132 -> 204750
A133: E5.2 | B133: In Beams (Roof Slab) | C133: =+C50*92 -> 368 | D133: Kg | E133: =+E132 -> 484.45036 | F133: =+$I$1 -> 0.75 | G133: =ROUNDUP(E133/F133,-1) -> 650 | H133: =+G133*C133 -> 239200
A134: E5.3 | B134: In Floor Slab (Roof Slab) | C134: =+C55*82 -> 574 | D134: Kg | E134: =+E132 -> 484.45036 | F134: =+$I$1 -> 0.75 | G134: =ROUNDUP(E134/F134,-1) -> 650 | H134: =+G134*C134 -> 373100
B139: CONCRETE WORK CARRIED TO COLLECTION | H139: =SUM(H3:H138) -> 24287535

Sheet masnry
A1: Nos | B1: Description | C1: Qty | D1: Unit | E1: COST | F1: OHP% | G1: Rate | H1: Amount | I1: =+summary!D9 -> 0.75
B2: F - MASONRY WORKS
A3: F | B3: BRICK MASONRY
B5: Vertical solid walls, 225mm thick.
B6: Brick work in cement and sand 1:5 in super Structure. ( 9" thick brick work)
A7: F.1 | B7: Ground Floor | C7: 184 | D7: Sqm | E7: =+'Rate Breakdowns'!G669 -> 5906.8084 | F7: =+$I$1 -> 0.75 | G7: =ROUNDUP(E7/F7,-1) -> 7880 | H7: =+G7*C7 -> 1449920
A8: F.2 | B8: 1st Floor | C8: 247 | D8: Sqm | E8: =+E7*1.01 -> 5965.8765 | F8: =+$I$1 -> 0.75 | G8: =ROUNDUP(E8/F8,-1) -> 7960 | H8: =+G8*C8 -> 1966120
A9: F.3 | B9: 2nd Floor | C9: 247 | D9: Sqm | E9: =+E7*1.02 -> 6024.9446 | F9: =+$I$1 -> 0.75 | G9: =ROUNDUP(E9/F9,-1) -> 8040 | H9: =+G9*C9 -> 1985880
A10: F.4 | B10: 3rd Floor /Terrace Floor | C10: 93 | D10: Sqm | E10: =+E7*1.03 -> 6084.0126 | F10: =+$I$1 -> 0.75 | G10: =ROUNDUP(E10/F10,-1) -> 8120 | H10: =+G10*C10 -> 755160
A12: G | B12: CELLULAR AND BLOCK MASONRY
B14: Vertical solid walls,115mm thick.
B15: Brick Work in cement and sand 1:8 . (4 1/2" thick brick work)
A16: G.1 | B16: Ground Floor | C16: 64 | D16: Sqm | E16: =+'Rate Breakdowns'!G722 -> 2960.7649 | F16: =+$I$1 -> 0.75 | G16: =ROUNDUP(E16/F16,-1) -> 3950 | H16: =+G16*C16 -> 252800
A17: G.2 | B17: 1st Floor | C17: 20 | D17: Sqm | E17: =+E16*1.01 -> 2990.3726 | F17: =+$I$1 -> 0.75 | G17: =ROUNDUP(E17/F17,-1) -> 3990 | H17: =+G17*C17 -> 79800
A18: G.3 | B18: 2nd Floor | C18: 20 | D18: Sqm | E18: =+E16*1.02 -> 3019.9802 | F18: =+$I$1 -> 0.75 | G18: =ROUNDUP(E18/F18,-1) -> 4030 | H18: =+G18*C18 -> 80600
A19: G.4 | B19: 3rd Floor /Terrace Floor | C19: 41 | D19: Sqm | E19: =+E16*1.03 -> 3049.5879 | F19: =+$I$1 -> 0.75 | G19: =ROUNDUP(E19/F19,-1) -> 4070 | H19: =+G19*C19 -> 166870
B21: H - RUBBLE MASONRY
A22: H 01 | B22: Random rubble (6"-9") masonry in cement mortar 1:5 in wall foundation. | C22: 41.35 | D22: m3 | E22: =+'Rate Breakdowns'!G644 -> 17854.461 | F22: =+$I$1 -> 0.75 | G22: =ROUNDUP(E22/F22,-1) -> 23810 | H22: =+G22*C22 -> 984543.5
B28: MASONRY WORKS CARRIED TO COLLECTION | H28: =SUM(H2:H27) -> 7721693.5

Sheet floring
A1: Nos | B1: Description | C1: Qty | D1: Unit | E1: COST | F1: OHP% | G1: Rate | H1: Amount | I1: =+summary!D10 -> 0.75
B2: J - FLOORING WORK
A4: J 01 | B4: 3/4" thick D.P.C. in cement sand 1:3 finished with 2 coats of D.P.C. tar and blinded with sand. | C4: 65 | D4: Sqm | E4: =+'Rate Breakdowns'!G159 -> 670.72121 | F4: =+$I$1 -> 0.75 | G4: =ROUNDUP(E4/F4,-1) -> 900 | H4: =+G4*C4 -> 58500
A6: J 02 | B6: Gauge 750 polythene damp proof membrane with 6" laps laid under floors. | C6: 180 | D6: Sqm | E6: =+'Rate Breakdowns'!G137 -> 228.74058 | F6: =+$I$1 -> 0.75 | G6: =ROUNDUP(E6/F6,-1) -> 310 | H6: =+G6*C6 -> 55800
A8: J 03 | B8: Rendering 1/2" thick in cement sand 1:3 finished smooth with cement slurry without colour pigment and expansion joints filled with construction expansion joint sealent including the cost for cleaning the joints prior application of construction expansion joint sealent by M/s Bitumix or approved equivalent.
B9: Water tank slab/Roof Slab | C9: 35 | D9: Sqm | E9: =+'Rate Breakdowns'!G1059 -> 1219.819 | F9: =+$I$1 -> 0.75 | G9: =ROUNDUP(E9/F9,-1) -> 1630 | H9: =+G9*C9 -> 57050
B11: FLOORING WORK CARRIED TO COLLECTION | H11: =SUM(H2:H10) -> 171350

Sheet plastering
A1: Nos | B1: Description | C1: Qty | D1: Unit | E1: COST | F1: OHP% | G1: Rate | H1: Amount | I1: 0.75
B2: K - PLASTERING WORK
B3: Note:
B4: 1. The rate for plastering items includes the cost of "Febmix"as a workability enhancer.
B6: 2. For coarse textured plaster ( identified as "semi-rough") all the sand should pass through 4.0mm sieve.
B8: External Plaster
A9: K 01 | B9: 5/8" thick plastering to plinth wall in cement sand 1:3 including finishing with cement slurry floating. Rate includes cost of "Febmix" as a workability enhancer. | C9: =89*0.45 -> 40.05 | D9: S.qm | E9: =+'Rate Breakdowns'!G1024 -> 2738.1963 | F9: =+$I$1 -> 0.75 | G9: =ROUNDUP(E9/F9,-1) -> 3660 | H9: =+G9*C9 -> 146583
A11: K 02 | B11: Plastering 5/8" thick to walls in cement and sand 1:5 finished semi-rough. Rate includes cost of "Febmix"as a workability enhancer.
A12: K2.1 | B12: In Ground floor | C12: 182 | D12: S.qm | E12: =+'Rate Breakdowns'!G972 -> 1532.7348 | F12: =+$I$1 -> 0.75 | G12: =ROUNDUP(E12/F12,-1) -> 2050 | H12: =+G12*C12 -> 373100
A13: K2.2 | B13: In First floor | C13: 207 | D13: S.qm | E13: =+E12*1.02 -> 1563.3895 | F13: =+$I$1 -> 0.75 | G13: =ROUNDUP(E13/F13,-1) -> 2090 | H13: =+G13*C13 -> 432630
A14: K2.3 | B14: In Second Floor | C14: 207 | D14: S.qm | E14: =+E12*1.04 -> 1594.0442 | F14: =+$I$1 -> 0.75 | G14: =ROUNDUP(E14/F14,-1) -> 2130 | H14: =+G14*C14 -> 440910
A15: K2.4 | B15: In Terrace Floor | C15: 111 | D15: S.qm | E15: =+E12*1.06 -> 1624.6989 | F15: =+$I$1 -> 0.75 | G15: =ROUNDUP(E15/F15,-1) -> 2170 | H15: =+G15*C15 -> 240870
A17: K 03 | B17: External revels
B18: Plastering 5/8" thick to reveals in cement and sand 1:5 finished semi-rough. Rate includes cost of "Febmix"as a workability enhancer.
A19: K.3.1 | B19: In Ground floor | C19: 126 | D19: L.m | E19: =190*3.28 -> 623.2 | F19: =+$I$1 -> 0.75 | G19: =ROUNDUP(E19/F19,-1) -> 840 | H19: =+G19*C19 -> 105840
A20: K.3.2 | B20: In First floor | C20: 142 | D20: L.m | E20: =190*3.28 -> 623.2 | F20: =+$I$1 -> 0.75 | G20: =ROUNDUP(E20/F20,-1) -> 840 | H20: =+G20*C20 -> 119280
A21: K.3.3 | B21: In Second Floor | C21: 142 | D21: L.m | E21: =190*3.28 -> 623.2 | F21: =+$I$1 -> 0.75 | G21: =ROUNDUP(E21/F21,-1) -> 840 | H21: =+G21*C21 -> 119280
A22: K.3.4 | B22: In Terrace Floor | C22: 64 | D22: L.m | E22: =190*3.28 -> 623.2 | F22: =+$I$1 -> 0.75 | G22: =ROUNDUP(E22/F22,-1) -> 840 | H22: =+G22*C22 -> 53760
B24: Internal Plaster
A25: K 04 | B25: Plastering 5/8" thick to walls,columns in cement and sand 1:5 finished smooth with two coats of skim coat.
A26: K4.1 | B26: In Ground floor | C26: 329 | D26: S.qm | E26: =+'Rate Breakdowns'!G946 -> 1642.7173 | F26: =+$I$1 -> 0.75 | G26: =ROUNDUP(E26/F26,-1) -> 2200 | H26: =+G26*C26 -> 723800
A27: K4.2 | B27: In First floor | C27: 451 | D27: S.qm | E27: =+E26*1.01 -> 1659.1445 | F27: =+$I$1 -> 0.75 | G27: =ROUNDUP(E27/F27,-1) -> 2220 | H27: =+G27*C27 -> 1001220
A28: K4.3 | B28: In Second Floor | C28: 451 | D28: S.qm | E28: =+E26*1.02 -> 1675.5716 | F28: =+$I$1 -> 0.75 | G28: =ROUNDUP(E28/F28,-1) -> 2240 | H28: =+G28*C28 -> 1010240
A29: K4.4 | B29: In Terrace Floor | C29: 187 | D29: S.qm | E29: =+E26*1.03 -> 1691.9988 | F29: =+$I$1 -> 0.75 | G29: =ROUNDUP(E29/F29,-1) -> 2260 | H29: =+G29*C29 -> 422620
A32: K 05 | B32: Internal Revels
B33: Plastering 5/8" thick to reveals in cement andsand 1:5 finished smooth with two coats of skim coat in ground floor.Rate includes cost of "Febmix"as a workability enhancer.
A34: K5.1 | B34: In Ground floor | C34: 156 | D34: =D20 -> L.m | E34: =170*3.28 -> 557.6 | F34: =+$I$1 -> 0.75 | G34: =ROUNDUP(E34/F34,-1) -> 750 | H34: =+G34*C34 -> 117000
A35: K5.2 | B35: In First floor | C35: 190 | D35: =D21 -> L.m | E35: =170*3.28 -> 557.6 | F35: =+$I$1 -> 0.75 | G35: =ROUNDUP(E35/F35,-1) -> 750 | H35: =+G35*C35 -> 142500
A36: K5.3 | B36: In Second Floor | C36: 190 | D36: =D22 -> L.m | E36: =170*3.28 -> 557.6 | F36: =+$I$1 -> 0.75 | G36: =ROUNDUP(E36/F36,-1) -> 750 | H36: =+G36*C36 -> 142500
A37: K5.4 | B37: In Terrace Floor | C37: 86 | D37: =D23 -> 0 | E37: =170*3.28 -> 557.6 | F37: =+$I$1 -> 0.75 | G37: =ROUNDUP(E37/F37,-1) -> 750 | H37: =+G37*C37 -> 64500
A39: K 06 | B39: Applying two coats of skim coat ( Not exceeding 3 mm thick) to soffit of slab,beams sunshade & stair cases Inc. preparation surface.
A40: K6.1 | B40: In First floor slab | C40: 172 | D40: S.qm | E40: =+'Rate Breakdowns'!G1525 -> 590.4521 | F40: =+$I$1 -> 0.75 | G40: =ROUNDUP(E40/F40,-1) -> 790 | H40: =+G40*C40 -> 135880
A41: K6.2 | B41: In Second Floor slab | C41: 172 | D41: S.qm | E41: =+E40*1.02 -> 602.26114 | F41: =+$I$1 -> 0.75 | G41: =ROUNDUP(E41/F41,-1) -> 810 | H41: =+G41*C41 -> 139320
A42: K6.3 | B42: In Terrace Floor slab | C42: 140 | D42: S.qm | E42: =+E40*1.03 -> 608.16566 | F42: =+$I$1 -> 0.75 | G42: =ROUNDUP(E42/F42,-1) -> 820 | H42: =+G42*C42 -> 114800
A43: K6.4 | B43: Roof Flab slab | C43: 53 | D43: S.qm | E43: =+E40*1.04 -> 614.07018 | F43: =+$I$1 -> 0.75 | G43: =ROUNDUP(E43/F43,-1) -> 820 | H43: =+G43*C43 -> 43460
A46: K 07 | B46: Drip Edge
B47: Forming drip for sunshade edge cement & sand 1: 3 finished semi rough in ground floor. Rate includes cost of "Febmix"as a workability enhancer.
A48: K 07.01 | B48: In First floor slab | C48: 38 | D48: L.m | E48: =190*3.28 -> 623.2 | F48: =+$I$1 -> 0.75 | G48: =ROUNDUP(E48/F48,-1) -> 840 | H48: =+G48*C48 -> 31920
A49: K 07.02 | B49: In Second Floor slab | C49: 38 | D49: L.m | E49: =190*3.28*1.2 -> 747.84 | F49: =+$I$1 -> 0.75 | G49: =ROUNDUP(E49/F49,-1) -> 1000 | H49: =+G49*C49 -> 38000
A50: K 07.03 | B50: In Terrace Floor slab | C50: 25 | D50: L.m | E50: =190*3.28*1.4 -> 872.48 | F50: =+$I$1 -> 0.75 | G50: =ROUNDUP(E50/F50,-1) -> 1170 | H50: =+G50*C50 -> 29250
B56: PLASTERING WORK CARRIED TO COLLECTION | H56: =SUM(H4:H55) -> 6189263
H65: =#REF!+#REF!+#REF!+#REF!+#REF! -> #REF!

Sheet tile
A1: Nos | B1: Description | C1: Qty | D1: Unit | E1: COST | F1: OHP% | G1: Rate | H1: Amount | I1: =+summary!D13 -> 0.75
B2: L - TILING WORK
B3: Floor Tiling
B4: Note :
B5: Tile will be Homogenous, porcelain floor tiles of industrial grade floor tile range manufactured by Rocell , Lanka Tile or approved equivalent.
B6: Rates include the cost of 1:3 cement:sand motar leveling bed and adhesives and matching grout
B8: Copy of the first grade tile purchase bill should be produced at the time of payment.
A10: L01 | B10: Floor Finishing For Staircase
A12: L01.1 | B12: Supplying and laying of treated timber kumbuk flooring for Staircase Floor. (Rate to include to floor bed and other necessasry related work)
A14: L01.1.1 | B14: Staircase (Ground Floor to 1st Floor) | C14: 8 | D14: Sqm | E14: =(2330*10.76)+'Rate Breakdowns'!G1149 -> 26255.876 | F14: =+$I$1 -> 0.75 | G14: =ROUNDUP(E14/F14,-1) -> 35010 | H14: =+G14*C14 -> 280080
A15: L01.1.2 | B15: Staircase (1st Floor to 2nd Floor) | C15: 8 | D15: Sqm | E15: =(2330*10.76)+'Rate Breakdowns'!G1150 -> 25180.937 | F15: =+$I$1 -> 0.75 | G15: =ROUNDUP(E15/F15,-1) -> 33580 | H15: =+G15*C15 -> 268640
A16: L01.1.3 | B16: Staircase (2nd Floor to Terrace Floor) | C16: 8 | D16: Sqm | E16: =(2330*10.76)+'Rate Breakdowns'!G1151 -> 25070.8 | F16: =+$I$1 -> 0.75 | G16: =ROUNDUP(E16/F16,-1) -> 33430 | H16: =+G16*C16 -> 267440
A18: L01.2 | B18: Supply and laying of 4" high timber skirting to match the flooring
A19: L01.2.1 | B19: Staircase (Ground Floor to 1st Floor) | C19: 18 | D19: L.m | E19: =2547+450 -> 2997 | F19: =+$I$1 -> 0.75 | G19: =ROUNDUP(E19/F19,-1) -> 4000 | H19: =+G19*C19 -> 72000
A20: L01.2.2 | B20: Staircase (1st Floor to 2nd Floor) | C20: =+C19 -> 18 | D20: L.m | E20: =2547+450 -> 2997 | F20: =+$I$1 -> 0.75 | G20: =ROUNDUP(E20/F20,-1) -> 4000 | H20: =+G20*C20 -> 72000
A21: L01.2.3 | B21: Staircase (2nd Floor to Terrace Floor) | C21: =+C19 -> 18 | D21: L.m | E21: =2547+450 -> 2997 | F21: =+$I$1 -> 0.75 | G21: =ROUNDUP(E21/F21,-1) -> 4000 | H21: =+G21*C21 -> 72000
A23: L02 | B23: Tiling For Bathroom
A25: L02.1 | B25: Homogeneous Porcelain semi - glazed/matt wash room floor tile 600mm x 600mm paving on 1:3 cement & sand bedding and pointed with tile grout to match the tile. (Prime Cost of tile Rs.500.00 per sqft)
A26: L02.1.1 | B26: In Ground Floor Bathroom | C26: 4 | D26: Sqm | E26: =+'Rate Breakdowns'!G1267 -> 7973.3416 | F26: =+$I$1 -> 0.75 | G26: =ROUNDUP(E26/F26,-1) -> 10640 | H26: =+G26*C26 -> 42560
A27: L02.1.2 | B27: In 1st Floor Bathroom | C27: 13 | D27: Sqm | E27: =+E26*1.02 -> 8132.8085 | F27: =+$I$1 -> 0.75 | G27: =ROUNDUP(E27/F27,-1) -> 10850 | H27: =+G27*C27 -> 141050
A28: L02.1.3 | B28: In 2nd Floor Bathroom | C28: 13 | D28: Sqm | E28: =+E26*1.04 -> 8292.2753 | F28: =+$I$1 -> 0.75 | G28: =ROUNDUP(E28/F28,-1) -> 11060 | H28: =+G28*C28 -> 143780
A29: L02.1.4 | B29: In Terrace Floor Bathroom | C29: 4 | D29: Sqm | E29: =+E26*1.06 -> 8451.7421 | F29: =+$I$1 -> 0.75 | G29: =ROUNDUP(E29/F29,-1) -> 11270 | H29: =+G29*C29 -> 45080
A31: L02.2 | B31: Homogeneous Porcelain glazed Wall tile 300mm x 600mm paving on plaster and pointed with tile grout to match the tile. (Prime Cost of tile Rs.550.00 per sqft)
A32: L02.2.1 | B32: In Ground Floor Bathroom | C32: 17 | D32: Sqm | E32: =+'Rate Breakdowns'!G1297 -> 9307.8949 | F32: =+$I$1 -> 0.75 | G32: =ROUNDUP(E32/F32,-1) -> 12420 | H32: =+G32*C32 -> 211140
A33: L02.2.2 | B33: In 1st Floor Bathroom | C33: 51 | D33: Sqm | E33: =+E32*1.02 -> 9494.0528 | F33: =+$I$1 -> 0.75 | G33: =ROUNDUP(E33/F33,-1) -> 12660 | H33: =+G33*C33 -> 645660
A34: L02.2.3 | B34: In 2nd Floor Bathroom | C34: 51 | D34: Sqm | E34: =+E32*1.04 -> 9680.2107 | F34: =+$I$1 -> 0.75 | G34: =ROUNDUP(E34/F34,-1) -> 12910 | H34: =+G34*C34 -> 658410
A35: L02.2.4 | B35: In Terrace Floor Bathroom | C35: 20 | D35: Sqm | E35: =+E32*1.06 -> 9866.3686 | F35: =+$I$1 -> 0.75 | G35: =ROUNDUP(E35/F35,-1) -> 13160 | H35: =+G35*C35 -> 263200
A37: L03 | B37: LIVING & BEDROOM FLOOR TILE
A39: L03.1 | B39: Homogeneous Porcelain glazed floor tile 600mm x 600mm paving on 1:3 cement & sand bedding and pointed with tile grout to match the tile. (Prime Cost of tile Rs.500.00 per sqft)
A40: L03.1.1 | B40: In Ground Floor | C40: 123 | D40: Sqm | E40: =+'Rate Breakdowns'!G1267 -> 7973.3416 | F40: =+$I$1 -> 0.75 | G40: =ROUNDUP(E40/F40,-1) -> 10640 | H40: =+G40*C40 -> 1308720
A41: L03.1.2 | B41: In 1st Floor | C41: 113 | D41: Sqm | E41: =+E40*1.02 -> 8132.8085 | F41: =+$I$1 -> 0.75 | G41: =ROUNDUP(E41/F41,-1) -> 10850 | H41: =+G41*C41 -> 1226050
A42: L03.1.3 | B42: In 2nd Floor | C42: 113 | D42: Sqm | E42: =+E40*1.04 -> 8292.2753 | F42: =+$I$1 -> 0.75 | G42: =ROUNDUP(E42/F42,-1) -> 11060 | H42: =+G42*C42 -> 1249780
A43: L03.1.4 | B43: In Terrace Floor | C43: 0 | D43: Sqm | E43: =+E40*1.06 -> 8451.7421 | F43: =+$I$1 -> 0.75 | G43: =ROUNDUP(E43/F43,-1) -> 11270 | H43: =+G43*C43 -> 0
A45: L03.2 | B45: Supply and laying of 4" high skirting including tile grout to match the tile of tiling
A46: L03.2.1 | B46: In Ground Floor | C46: 96 | D46: L.m | E46: =+'Rate Breakdowns'!G1358 -> 998.104 | F46: =+$I$1 -> 0.75 | G46: =ROUNDUP(E46/F46,-1) -> 1340 | H46: =+G46*C46 -> 128640
A47: L03.2.2 | B47: In 1st Floor | C47: 106 | D47: L.m | E47: =+E46*1.02 -> 1018.0661 | F47: =+$I$1 -> 0.75 | G47: =ROUNDUP(E47/F47,-1) -> 1360 | H47: =+G47*C47 -> 144160
A48: L03.2.3 | B48: In 2nd Floor | C48: 106 | D48: L.m | E48: =+E46*1.04 -> 1038.0282 | F48: =+$I$1 -> 0.75 | G48: =ROUNDUP(E48/F48,-1) -> 1390 | H48: =+G48*C48 -> 147340
A49: L03.2.4 | B49: In Terrace Floor | C49: 80 | D49: L.m | E49: =+E46*1.06 -> 1057.9902 | F49: =+$I$1 -> 0.75 | G49: =ROUNDUP(E49/F49,-1) -> 1420 | H49: =+G49*C49 -> 113600
A52: L04 | B52: BALCONY FLOOR TILE
B78: FF2- Homogeneous Porcelain semi - glazed/matt wash room floor tile 300mm x 600mm paving on 1:3 cement & sand bedding and pointed with tile grout to match the tile.(Prime Cost of tile Rs.400.00 per sqft)
B79: In Ground floor | D79: Sqm
B80: Supplying and laying homogeneous porcelain tiles 300mm X 600mm at staircase treads including nosing type paving on 1:3 cement & sand bedding and pointed with tile grout to match the tile.(Prime Cost of tile Rs.500.00 per sqft)
B81: In Ground floor to First Floor | D81: Sqm
B83: Supply and laying of 4" high skirting including tile grout to match the tile of tiling
B84: In Ground Floor | D84: L.m
B86: Homogeneous Porcelain glazed floor tile 900mm x 900mm paving on 1:3 cement & sand bedding and pointed with tile grout to match the tile. (Prime Cost of tile Rs.500.00 per sqft)
B87: In Ground floor | D87: Sqm
A89: L04.1 | B89: Homogeneous Porcelain semi - glazed/matt Balcony floor tile 600mm x 600mm paving on 1:3 cement & sand bedding and pointed with tile grout to match the tile.(Prime Cost of tile Rs.500.00 per sqft)
A90: L04.1.1 | B90: In 1st floor | C90: 28 | D90: Sqm | E90: =+E41 -> 8132.8085 | F90: =+$I$1 -> 0.75 | G90: =ROUNDUP(E90/F90,-1) -> 10850 | H90: =+G90*C90 -> 303800
A91: L04.1.2 | B91: In 2nd floor | C91: 28 | D91: Sqm | E91: =+E42 -> 8292.2753 | F91: =+$I$1 -> 0.75 | G91: =ROUNDUP(E91/F91,-1) -> 11060 | H91: =+G91*C91 -> 309680
A92: L04.1.3 | B92: In Terrace floor | C92: 3 | D92: Sqm | E92: =+E43 -> 8451.7421 | F92: =+$I$1 -> 0.75 | G92: =ROUNDUP(E92/F92,-1) -> 11270 | H92: =+G92*C92 -> 33810
A95: L04.2 | B95: Supply and laying of 4" high skirting including tile grout to match the tile of tiling
A96: L04.2.1 | B96: In 1st floor | C96: 35 | D96: Lm | E96: =+E47 -> 1018.0661 | F96: =+$I$1 -> 0.75 | G96: =ROUNDUP(E96/F96,-1) -> 1360 | H96: =+G96*C96 -> 47600
A97: L04.2.2 | B97: In 2nd floor | C97: 35 | D97: Lm | E97: =+E48 -> 1038.0282 | F97: =+$I$1 -> 0.75 | G97: =ROUNDUP(E97/F97,-1) -> 1390 | H97: =+G97*C97 -> 48650
A98: L04.2.3 | B98: In Terrace floor | C98: 2 | D98: Lm | E98: =+E49 -> 1057.9902 | F98: =+$I$1 -> 0.75 | G98: =ROUNDUP(E98/F98,-1) -> 1420 | H98: =+G98*C98 -> 2840
A100: L05 | B100: GROUND PARKING AREA
A102: L05.1 | B102: Homogeneous Porcelain semi - glazed/matt Balcony floor tile 450mm x450mm paving on 1:3 cement & sand bedding and pointed with tile grout to match the tile.(Prime Cost of tile Rs.500.00 per sqft) | C102: 28 | D102: Sqm | E102: =+'Rate Breakdowns'!G1267 -> 7973.3416 | F102: =+$I$1 -> 0.75 | G102: =ROUNDUP(E102/F102,-1) -> 10640 | H102: =+G102*C102 -> 297920
A103: L06 | B103: TERRACE FLOOR
A105: L06.1 | B105: Homogeneous Porcelain semi - glazed/matt Balcony floor tile 450mm x450mm paving on 1:3 cement & sand bedding and pointed with tile grout to match the tile.(Prime Cost of tile Rs.500.00 per sqft) | C105: 37 | D105: Sqm | E105: =+'Rate Breakdowns'!G1267*1.06 -> 8451.7421 | F105: =+$I$1 -> 0.75 | G105: =ROUNDUP(E105/F105,-1) -> 11270 | H105: =+G105*C105 -> 416990
A107: L.07 | B107: GYM /GAMMING AREA
A108: L.07.1 | B108: Homogeneous Porcelain semi - glazed/matt Balcony floor tile 450mm x450mm paving on 1:3 cement & sand bedding and pointed with tile grout to match the tile.(Prime Cost of tile Rs.500.00 per sqft) | C108: 36 | D108: Sqm | E108: =+'Rate Breakdowns'!G1267*1.06 -> 8451.7421 | F108: =+$I$1 -> 0.75 | G108: =ROUNDUP(E108/F108,-1) -> 11270 | H108: =+G108*C108 -> 405720
B115: TILING WORK CARRIED TO COLLECTION | H115: =SUM(H3:H114) -> 9368340

Sheet paint
A1: Nos | B1: Description | C1: Qty | D1: Unit | E1: COST | F1: OHP% | G1: Rate | H1: Amount | I1: =+summary!D14 -> 0.75
B2: M - COLOUR WASHING, PAINTING & POLISHING
B3: Method of application is accordiong to the manufacturer's method specifications
B5: Internal Emultion Paint
A6: M 01 | B6: Painting walls, columns, Revels with one coat of wall primer and two coats of emulsion paint including preparing surface.
A7: M1.1 | B7: In Ground floor | C7: 329 | D7: Sqm | E7: =+'Rate Breakdowns'!G1500 -> 967.07939 | F7: =+$I$1 -> 0.75 | G7: =ROUNDUP(E7/F7,-1) -> 1290 | H7: =+G7*C7 -> 424410
A8: M1.2 | B8: In First floor | C8: 451 | D8: Sqm | E8: =+E7*1.01 -> 976.75018 | F8: =+$I$1 -> 0.75 | G8: =ROUNDUP(E8/F8,-1) -> 1310 | H8: =+G8*C8 -> 590810
A9: M1.3 | B9: In Second Floor | C9: 451 | D9: Sqm | E9: =+E7*1.02 -> 986.42097 | F9: =+$I$1 -> 0.75 | G9: =ROUNDUP(E9/F9,-1) -> 1320 | H9: =+G9*C9 -> 595320
A10: M1.4 | B10: In Terrace Floor slab | C10: 187 | D10: Sqm | E10: =+E8*1.03 -> 1006.0527 | F10: =+$I$1 -> 0.75 | G10: =ROUNDUP(E10/F10,-1) -> 1350 | H10: =+G10*C10 -> 252450
A12: M 03 | B12: Painting soffit & Beams with one coat of wall primer and two coats of emulsion paint including preparing surface.
A13: M3.2 | B13: In First floor slab | C13: 172 | D13: Sqm | E13: =+'Rate Breakdowns'!G1549 -> 741.87137 | F13: =+$I$1 -> 0.75 | G13: =ROUNDUP(E13/F13,-1) -> 990 | H13: =+G13*C13 -> 170280
A14: M3.3 | B14: In Second Floor slab | C14: 172 | D14: Sqm | E14: =+E13*1.01 -> 749.29008 | F14: =+$I$1 -> 0.75 | G14: =ROUNDUP(E14/F14,-1) -> 1000 | H14: =+G14*C14 -> 172000
A15: M3.4 | B15: In Terrace Floor slab | C15: 140 | D15: Sqm | E15: =+E14*1.02 -> 764.27588 | F15: =+$I$1 -> 0.75 | G15: =ROUNDUP(E15/F15,-1) -> 1020 | H15: =+G15*C15 -> 142800
A16: M3.5 | B16: Roof Flab slab | C16: 53 | D16: Sqm | E16: =+E15*1.03 -> 787.20416 | F16: =+$I$1 -> 0.75 | G16: =ROUNDUP(E16/F16,-1) -> 1050 | H16: =+G16*C16 -> 55650
B18: Exterior Emultion Paint
A19: M 04 | B19: Painting walls,slab and revels with one coat of Exterior wall primer and two coats of weathershield weatherproof acrylic exterior emultion paint including preparing surface. including preparing surface for exterior application before applicatin of emulsion paint.
A20: M4.1 | B20: In Ground floor | C20: 182 | D20: Sqm | E20: =+'Rate Breakdowns'!G1581 -> 1719.3864 | F20: =+$I$1 -> 0.75 | G20: =ROUNDUP(E20/F20,-1) -> 2300 | H20: =+G20*C20 -> 418600
A21: M4.2 | B21: In First floor | C21: 207 | D21: Sqm | E21: =+E20*1.02 -> 1753.7742 | F21: =+$I$1 -> 0.75 | G21: =ROUNDUP(E21/F21,-1) -> 2340 | H21: =+G21*C21 -> 484380
A22: M4.3 | B22: In Second Floor | C22: 207 | D22: Sqm | E22: =+E20*1.04 -> 1788.1619 | F22: =+$I$1 -> 0.75 | G22: =ROUNDUP(E22/F22,-1) -> 2390 | H22: =+G22*C22 -> 494730
A23: M4.4 | B23: In Terrace Floor | C23: 111 | D23: Sqm | E23: =+E20*1.06 -> 1822.5496 | F23: =+$I$1 -> 0.75 | G23: =ROUNDUP(E23/F23,-1) -> 2440 | H23: =+G23*C23 -> 270840
B26: COLOUR WASHING, PAINTING & POLISHING WORK CARRIED TO COLLECTION | H26: =SUM(H4:H25) -> 4072270

Sheet plumbing 
A1: Nos | B1: Description | C1: Qty | D1: Unit | E1: COST | F1: OHP% | G1: Rate | H1: Amount | I1: 0.75
B2: S - PLUMBING AND DRAINAGE WORK
B3: S - SANITARY FITTINGS
B6: Disable Fittings & Accessories
A7: S 01 | B7: Supply and fix ceramic wall hung wash basin for disabled of "Vitra" brand, Model No.6147 with Plush Lock waste & overflow & Bottle Trap Chrome plated or approved equivalent.(Prime cost of the wash basin is Rs.45,000.00) | D7: Nr
A9: S 02 | B9: Supply and fix Disable Water Closet "Vitra" brand-Model No.6927 with seat cover & water tank or approved equivalent complete to working order.(Prime cost of is Rs.65,000.00) | D9: Nr
A11: S 03 | B11: Supply and fix Chromium plated single level wash basin mixer tap without pop-up waste with connection flex of "cobra" brand or approved equivalent with 5 year written warranty from the authorized agent.(Prime cost of is Rs.25,000.00) | D11: Nr
A13: S 04 | B13: Supply and fix Heavy duty Straight grab bar for disabled of "J&T" brand,model "GB029" or approved equivalent.(Prime cost of is Rs.10,000.00) | D13: Nr
A16: S 01 | B16: Supply and fix white vitreous china (vc) floor standing wash basin and pedestal with overflow hole and single tap hole in center of "Rocell" brand or approved equivalent complete to working order inclusive of the 1 1/4" chromium plated waste outlet of "Rocell" brand or approved equivalent and 1 1/4" chromium plated siphon cleanable bottle trap of "Rocell" brand or approved equivalent. (Prime cost of the floor standing wash basin and pedestal is Rs.20,185.00)
B17: Ground Floor | D17: Nr
B18: Third Floor | D18: Nr
B19: Fourth Floor | D19: Nr
A21: S 01 | B21: Supply and fix white vitreous china (vc) floor standing Vanity wash basin with overflow hole and single tap hole in center of "Rocell" brand or approved equivalent complete to working order inclusive of the 1 1/4" chromium plated waste outlet of "Rocell" brand or approved equivalent and 1 1/4" chromium plated siphon cleanable bottle trap of "Rocell" brand or approved equivalent. (Prime cost of the floor standing wash basin is Rs.45,000.00)
B22: In Ground floor | C22: 1 | D22: Nr | E22: =45000+6500 -> 51500 | F22: =+$I$1 -> 0.75 | G22: =ROUNDUP(E22/F22,-1) -> 68670 | H22: =+G22*C22 -> 68670
B23: In 1st floor | C23: 3 | D23: Nr | E23: =+E22*1.02 -> 52530 | F23: =+$I$1 -> 0.75 | G23: =ROUNDUP(E23/F23,-1) -> 70040 | H23: =+G23*C23 -> 210120
B24: In 2nd Floor | C24: 3 | D24: Nr | E24: =+E22*1.04 -> 53560 | F24: =+$I$1 -> 0.75 | G24: =ROUNDUP(E24/F24,-1) -> 71420 | H24: =+G24*C24 -> 214260
B25: Terrace Floor | C25: 1 | D25: Nr | E25: =+E22*1.06 -> 54590 | F25: =+$I$1 -> 0.75 | G25: =ROUNDUP(E25/F25,-1) -> 72790 | H25: =+G25*C25 -> 72790
A27: S 02 | B27: Supply and fix white vitreous china (vc) floor standing close coupled semi . back to wall water closet suite with wash down flushing with 6/3 liters dual flushing has horizontal outlet with vario drain bend and two lateral holes for bottom water connection , P trap, cistern with water inlet from rear of "Rocell" brand or approved equivalent complete to working order inclusive of universal bend of "Rocell" brand. (Prime cost of the water closet, tank and seat cover is Rs.55,000.00)
B28: In Ground floor | C28: 1 | D28: Nr | E28: =55000+7000 -> 62000 | F28: =+$I$1 -> 0.75 | G28: =ROUNDUP(E28/F28,-1) -> 82670 | H28: =+G28*C28 -> 82670
B29: In 1st floor | C29: 3 | D29: Nr | E29: =+E28*1.02 -> 63240 | F29: =+$I$1 -> 0.75 | G29: =ROUNDUP(E29/F29,-1) -> 84320 | H29: =+G29*C29 -> 252960
B30: In 2nd Floor | C30: 3 | D30: Nr | E30: =+E28*1.04 -> 64480 | F30: =+$I$1 -> 0.75 | G30: =ROUNDUP(E30/F30,-1) -> 85980 | H30: =+G30*C30 -> 257940
B31: Terrace Floor | C31: 1 | D31: Nr | E31: =+E28*1.06 -> 65720 | F31: =+$I$1 -> 0.75 | G31: =ROUNDUP(E31/F31,-1) -> 87630 | H31: =+G31*C31 -> 87630
A33: S 06 | B33: Supply and fix Urinal with sensor type "Rocell " brand or approved equivalent complete to working order. (Prime cost of the Urinal is Rs. 77,130.00)
B34: Fouth Floor | D34: Nr
A36: S 03 | B36: Supply and fix Chromium plated 1/2" dia. angle valve of "Rocell" brand . model or approved equivalent. (Prime cost of the Chromium plated 1/2" dia. angle valve is Rs. 2,500.00)
B37: In Ground floor | C37: 1 | D37: Nr | E37: =2500+300 -> 2800 | F37: =+$I$1 -> 0.75 | G37: =ROUNDUP(E37/F37,-1) -> 3740 | H37: =+G37*C37 -> 3740
B38: In 1st floor | C38: 3 | D38: Nr | E38: =2500+300 -> 2800 | F38: =+$I$1 -> 0.75 | G38: =ROUNDUP(E38/F38,-1) -> 3740 | H38: =+G38*C38 -> 11220
B39: In 2nd Floor | C39: 3 | D39: Nr | E39: =2500+300 -> 2800 | F39: =+$I$1 -> 0.75 | G39: =ROUNDUP(E39/F39,-1) -> 3740 | H39: =+G39*C39 -> 11220
B40: Terrace Floor | C40: 1 | D40: Nr | E40: =2500+300 -> 2800 | F40: =+$I$1 -> 0.75 | G40: =ROUNDUP(E40/F40,-1) -> 3740 | H40: =+G40*C40 -> 3740
A43: S 04 | B43: Supply and fix Chromium plated 1 1/4" chromium plated push type waste outlet of "Rocell" brand or approved equivalent. (Prime cost of the Chromium plated 1 1/4" chromium plated waste outlet is Rs. 2,500.00)
B44: In Ground floor | C44: 1 | D44: Nr | E44: =2500+350 -> 2850 | F44: =+$I$1 -> 0.75 | G44: =ROUNDUP(E44/F44,-1) -> 3800 | H44: =+G44*C44 -> 3800
B45: In 1st floor | C45: 3 | D45: Nr | E45: =+E44 -> 2850 | F45: =+$I$1 -> 0.75 | G45: =ROUNDUP(E45/F45,-1) -> 3800 | H45: =+G45*C45 -> 11400
B46: In 2nd Floor | C46: 3 | D46: Nr | E46: =+E44 -> 2850 | F46: =+$I$1 -> 0.75 | G46: =ROUNDUP(E46/F46,-1) -> 3800 | H46: =+G46*C46 -> 11400
B47: Terrace Floor | C47: 1 | D47: Nr | E47: =+E44 -> 2850 | F47: =+$I$1 -> 0.75 | G47: =ROUNDUP(E47/F47,-1) -> 3800 | H47: =+G47*C47 -> 3800
A50: S 05 | B50: Supply and fix Chromium plated 1/2" dia. 36" long flexible horse of "Rocell" brand or approved equivalent. (Prime cost of the Chromium plated 1/2" dia. 18" long flexible horse is Rs. 3,000.00)
B51: In Ground floor | C51: 1 | D51: Nr | E51: =3000+350 -> 3350 | F51: =+$I$1 -> 0.75 | G51: =ROUNDUP(E51/F51,-1) -> 4470 | H51: =+G51*C51 -> 4470
B52: In 1st floor | C52: 3 | D52: Nr | E52: =+E51 -> 3350 | F52: =+$I$1 -> 0.75 | G52: =ROUNDUP(E52/F52,-1) -> 4470 | H52: =+G52*C52 -> 13410
B53: In 2nd Floor | C53: 3 | D53: Nr | E53: =+E51 -> 3350 | F53: =+$I$1 -> 0.75 | G53: =ROUNDUP(E53/F53,-1) -> 4470 | H53: =+G53*C53 -> 13410
B54: Terrace Floor | C54: 1 | D54: Nr | E54: =+E51 -> 3350 | F54: =+$I$1 -> 0.75 | G54: =ROUNDUP(E54/F54,-1) -> 4470 | H54: =+G54*C54 -> 4470
A57: S 06 | B57: Supply and fix Chromium plated 1/2" dia. 15" long flexible horse of "Rocell" brand or approved equivalent. (Prime cost of the Chromium plated 1/2" dia. 12" long flexible horse is Rs. 2,500.00)
B58: In Ground floor | C58: 1 | D58: Nr | E58: =2500+350 -> 2850 | F58: =+$I$1 -> 0.75 | G58: =ROUNDUP(E58/F58,-1) -> 3800 | H58: =+G58*C58 -> 3800
B59: In 1st floor | C59: 3 | D59: Nr | E59: =+E58 -> 2850 | F59: =+$I$1 -> 0.75 | G59: =ROUNDUP(E59/F59,-1) -> 3800 | H59: =+G59*C59 -> 11400
B60: In 2nd Floor | C60: 3 | D60: Nr | E60: =+E58 -> 2850 | F60: =+$I$1 -> 0.75 | G60: =ROUNDUP(E60/F60,-1) -> 3800 | H60: =+G60*C60 -> 11400
B61: Terrace Floor | C61: 1 | D61: Nr | E61: =+E58 -> 2850 | F61: =+$I$1 -> 0.75 | G61: =ROUNDUP(E61/F61,-1) -> 3800 | H61: =+G61*C61 -> 3800
A63: S 07 | B63: Supply and fix chromium plated Bidet Spray of "Rocell" brand or . approved equivalent. (Prime cost of the chromium plated Bidet Spray is Rs. 4,000.00)
B64: In Ground floor | C64: 1 | D64: Nr | E64: =4000+700 -> 4700 | F64: =+$I$1 -> 0.75 | G64: =ROUNDUP(E64/F64,-1) -> 6270 | H64: =+G64*C64 -> 6270
B65: In 1st floor | C65: 3 | D65: Nr | E65: =+E64 -> 4700 | F65: =+$I$1 -> 0.75 | G65: =ROUNDUP(E65/F65,-1) -> 6270 | H65: =+G65*C65 -> 18810
B66: In 2nd Floor | C66: 3 | D66: Nr | E66: =+E64 -> 4700 | F66: =+$I$1 -> 0.75 | G66: =ROUNDUP(E66/F66,-1) -> 6270 | H66: =+G66*C66 -> 18810
B67: Terrace Floor | C67: 1 | D67: Nr | E67: =+E64 -> 4700 | F67: =+$I$1 -> 0.75 | G67: =ROUNDUP(E67/F67,-1) -> 6270 | H67: =+G67*C67 -> 6270
A70: S 08 | B70: Supply and fix 5mm thick mirror of size 18" x 24" double coated with pencil edge back strecher. (Prime cost of the 5mm thick mirror of size 18" x 24" is Rs. 5,000.00)
B71: In Ground floor | C71: 1 | D71: Nr | E71: =5000+600 -> 5600 | F71: =+$I$1 -> 0.75 | G71: =ROUNDUP(E71/F71,-1) -> 7470 | H71: =+G71*C71 -> 7470
B72: In 1st floor | C72: 3 | D72: Nr | E72: =5000+600 -> 5600 | F72: =+$I$1 -> 0.75 | G72: =ROUNDUP(E72/F72,-1) -> 7470 | H72: =+G72*C72 -> 22410
B73: In 2nd Floor | C73: 3 | D73: Nr | E73: =5000+600 -> 5600 | F73: =+$I$1 -> 0.75 | G73: =ROUNDUP(E73/F73,-1) -> 7470 | H73: =+G73*C73 -> 22410
B74: Terrace Floor | C74: 1 | D74: Nr | E74: =5000+600 -> 5600 | F74: =+$I$1 -> 0.75 | G74: =ROUNDUP(E74/F74,-1) -> 7470 | H74: =+G74*C74 -> 7470
A77: S 09 | B77: Supply and fix Chromium plated pillar tap (cold water) for wash basin of "Rocell" brand or approved equivalent. (Prime cost of the Chromium plated pillar tap (cold water) for wash basin is Rs. 6,000.00)
B78: In Ground floor | C78: 1 | D78: Nr | E78: =6000+550 -> 6550 | F78: =+$I$1 -> 0.75 | G78: =ROUNDUP(E78/F78,-1) -> 8740 | H78: =+G78*C78 -> 8740
B79: In 1st floor | C79: 3 | D79: Nr | E79: =6000+550 -> 6550 | F79: =+$I$1 -> 0.75 | G79: =ROUNDUP(E79/F79,-1) -> 8740 | H79: =+G79*C79 -> 26220
B80: In 2nd Floor | C80: 3 | D80: Nr | E80: =+E78 -> 6550 | F80: =+$I$1 -> 0.75 | G80: =ROUNDUP(E80/F80,-1) -> 8740 | H80: =+G80*C80 -> 26220
B81: Terrace Floor | C81: 1 | D81: Nr | E81: =+E78 -> 6550 | F81: =+$I$1 -> 0.75 | G81: =ROUNDUP(E81/F81,-1) -> 8740 | H81: =+G81*C81 -> 8740
A83: S 10 | B83: Supply and fix Chromium plated Bip tap of of "Rocell" brand or approved equivalent. (Prime cost of the Chromium plated Bip tap is Rs. 4,000.00)
B84: In Ground floor | C84: 1 | D84: Nr | E84: =4000+500 -> 4500 | F84: =+$I$1 -> 0.75 | G84: =ROUNDUP(E84/F84,-1) -> 6000 | H84: =+G84*C84 -> 6000
B85: In 1st floor | C85: 3 | D85: Nr | E85: =+E84 -> 4500 | F85: =+$I$1 -> 0.75 | G85: =ROUNDUP(E85/F85,-1) -> 6000 | H85: =+G85*C85 -> 18000
B86: In 2nd Floor | C86: 3 | D86: Nr | E86: =+E84 -> 4500 | F86: =+$I$1 -> 0.75 | G86: =ROUNDUP(E86/F86,-1) -> 6000 | H86: =+G86*C86 -> 18000
B87: Terrace Floor | C87: 1 | D87: Nr | E87: =+E84 -> 4500 | F87: =+$I$1 -> 0.75 | G87: =ROUNDUP(E87/F87,-1) -> 6000 | H87: =+G87*C87 -> 6000
B90: Bathroom Accessories
A91: S 11 | B91: Supply and fix chromium plated Soap holder of "Rocell" brand or . approved equivalent. (Prime cost of the chromium plated Soap holder is Rs. 3,000.00)
B92: In Ground floor | C92: 1 | D92: Nr | E92: =3000+500 -> 3500 | F92: =+$I$1 -> 0.75 | G92: =ROUNDUP(E92/F92,-1) -> 4670 | H92: =+G92*C92 -> 4670
B93: In 1st floor | C93: 3 | D93: Nr | E93: =+E92 -> 3500 | F93: =+$I$1 -> 0.75 | G93: =ROUNDUP(E93/F93,-1) -> 4670 | H93: =+G93*C93 -> 14010
B94: In 2nd Floor | C94: 3 | D94: Nr | E94: =+E92 -> 3500 | F94: =+$I$1 -> 0.75 | G94: =ROUNDUP(E94/F94,-1) -> 4670 | H94: =+G94*C94 -> 14010
B95: Terrace Floor | C95: 1 | D95: Nr | E95: =+E92 -> 3500 | F95: =+$I$1 -> 0.75 | G95: =ROUNDUP(E95/F95,-1) -> 4670 | H95: =+G95*C95 -> 4670
A98: S 12 | B98: Supply and fix chromium plated Toilet Paper Holder of "Rocell" brand or . approved equivalent. (Prime cost of the chromium plated Toilet Paper Holder is Rs. 3,000.00)
B99: In Ground floor | C99: 1 | D99: Nr | E99: =3000+500 -> 3500 | F99: =+$I$1 -> 0.75 | G99: =ROUNDUP(E99/F99,-1) -> 4670 | H99: =+G99*C99 -> 4670
B100: In 1st floor | C100: 3 | D100: Nr | E100: =3000+500 -> 3500 | F100: =+$I$1 -> 0.75 | G100: =ROUNDUP(E100/F100,-1) -> 4670 | H100: =+G100*C100 -> 14010
B101: In 2nd Floor | C101: 3 | D101: Nr | E101: =3000+500 -> 3500 | F101: =+$I$1 -> 0.75 | G101: =ROUNDUP(E101/F101,-1) -> 4670 | H101: =+G101*C101 -> 14010
B102: Terrace Floor | C102: 1 | D102: Nr | E102: =3000+500 -> 3500 | F102: =+$I$1 -> 0.75 | G102: =ROUNDUP(E102/F102,-1) -> 4670 | H102: =+G102*C102 -> 4670
A105: S 13 | B105: Supply and fix Chromium plated bathroom floor gully cover square type of "Lanka Tiles Coloma " brand or approved equivalent. (Prime cost of the Chromium plated bathroom floor gully cover square type is Rs. 5,000.00)
B106: In Ground floor | C106: 1 | D106: Nr | E106: =5000+700 -> 5700 | F106: =+$I$1 -> 0.75 | G106: =ROUNDUP(E106/F106,-1) -> 7600 | H106: =+G106*C106 -> 7600
B107: In 1st floor | C107: 3 | D107: Nr | E107: =+E106 -> 5700 | F107: =+$I$1 -> 0.75 | G107: =ROUNDUP(E107/F107,-1) -> 7600 | H107: =+G107*C107 -> 22800
B108: In 2nd Floor | C108: 3 | D108: Nr | E108: =+E106 -> 5700 | F108: =+$I$1 -> 0.75 | G108: =ROUNDUP(E108/F108,-1) -> 7600 | H108: =+G108*C108 -> 22800
B109: Terrace Floor | C109: 1 | D109: Nr | E109: =+E106 -> 5700 | F109: =+$I$1 -> 0.75 | G109: =ROUNDUP(E109/F109,-1) -> 7600 | H109: =+G109*C109 -> 7600
A111: S 14 | B111: Supply and fix chromium plated Toilet Brush Holder of "Lanka Tiles Coloma - Angelo " brand or approved equivalent. (Prime cost of the chromium plated Toilet Brush Holder is Rs. 3,000.00)
B112: In Ground floor | C112: 1 | D112: Nr | E112: =3000+450 -> 3450 | F112: =+$I$1 -> 0.75 | G112: =ROUNDUP(E112/F112,-1) -> 4600 | H112: =+G112*C112 -> 4600
B113: In 1st floor | C113: 3 | D113: Nr | E113: =+E112 -> 3450 | F113: =+$I$1 -> 0.75 | G113: =ROUNDUP(E113/F113,-1) -> 4600 | H113: =+G113*C113 -> 13800
B114: In 2nd Floor | C114: 3 | D114: Nr | E114: =+E112 -> 3450 | F114: =+$I$1 -> 0.75 | G114: =ROUNDUP(E114/F114,-1) -> 4600 | H114: =+G114*C114 -> 13800
B115: Terrace Floor | C115: 1 | D115: Nr | E115: =+E112 -> 3450 | F115: =+$I$1 -> 0.75 | G115: =ROUNDUP(E115/F115,-1) -> 4600 | H115: =+G115*C115 -> 4600
A117: S 15 | B117: Supply and fix Chromium plated Sink tap (Swan neck type) of "Rocell" . brand or approved equivalent. (Prime cost of the Chromium plated Sink tap (Swan neck type) is Rs. 5,047.00) | C117: 1 | D117: Nr | E117: =5047+650 -> 5697 | F117: =+$I$1 -> 0.75 | G117: =ROUNDUP(E117/F117,-1) -> 7600 | H117: =+G117*C117 -> 7600
B120: T - PLUMBING
B121: ACCESSORIES
A122: S 22 | B122: Supply and fixing 1" dia PVC Compact Ball valve. | D122: Nr
A124: S 23 | B124: Supply and fixing 1 1/2" dia PVC Compact Ball valve. | D124: Nr
B126: Foot Valve
A127: S 24 | B127: Supply and fixing 1" dia PVC Foot valve. | D127: Nr
B129: Water Tanks
B130: Water tank should combined with three layers of high density polyethylene except 5000 Ltr. Water tank.
B132: The inner and outer layers made of 100% FDA approved virgin raw materials , ensuring non-contamination.
B134: Contractor should submit the purchasing bill and the required warranty for water tanks (10 year warranty) manufactured by "Anton , Arpico" to the Divisional Engineer.
A135: S 16 | B135: Supplying and installing of water tank 2000 ltr. Capacity rate to including the cost of transport. Hoisting in position and specials,rate to include to necessary ball valve and other related fixtures and accessories | C135: 1 | D135: Nr | E135: =95000+32000 -> 127000 | F135: =+$I$1 -> 0.75 | G135: =ROUNDUP(E135/F135,-1) -> 169340 | H135: =+G135*C135 -> 169340
B137: P.V.C. Pipes
B138: All P.V.C. pipes should confirm to S.L.S. 147. The fittings should be of the same brand as pipes.Ratt to include to necessary all required specials and fittings T, l bor, Clips,bends, etc
B140: Water Supply Pipes.
...

Sheet electicle 
A1: Nos | B1: Description | C1: Qty | D1: Unit | E1: COST | F1: OHP% | G1: Rate | H1: Amount | I1: =+summary!D16 -> 0.75
B2: V - ELECTRICAL INSTALLATION.
A4: V01 | B4: Testing
A6: V01.01 | B6: Testing of the electrical installation and submission of certificate from a chartered Electrical Engineer registered at CEB. | C6: 1 | D6: Item | E6: 30000 | F6: =+$I$1 -> 0.75 | G6: =ROUNDUP(E6/F6,-1) -> 40000 | H6: =+G6*C6 -> 40000
A8: V01.02 | B8: Charges for verifying the wiring done with meggar test & continuity test before commensing installation of Distribution Board & Electrical Fittings. | C8: 1 | D8: Item | E8: 45000 | F8: =+$I$1 -> 0.75 | G8: =ROUNDUP(E8/F8,-1) -> 60000 | H8: =+G8*C8 -> 60000
A10: V02 | B10: Main Cabling System
B12: Main cables for sub distribution boards of each floor shall be tapped from the bus bar riser
A14: V02.01 | B14: Supply, installation & termination of main cable from CEB supply to MDB | C14: 1 | D14: Item | E14: 52000 | F14: =+$I$1 -> 0.75 | G14: =ROUNDUP(E14/F14,-1) -> 69340 | H14: =+G14*C14 -> 69340
A16: V02.02 | B16: Supply, installation & termination of from MDB to DB-Lifts | D16: Item
A18: V02.03 | B18: Supply, installation & termination of from MDB to each DBs. | C18: 1 | D18: Item | E18: 43000 | F18: =+$I$1 -> 0.75 | G18: =ROUNDUP(E18/F18,-1) -> 57340 | H18: =+G18*C18 -> 57340
A20: V03 | B20: Main Distribution Board and SUB Distribution Boards and Isolators
B22: Supply and Installation of Power Distribution Panels
A23: V03.01 | B23: MDB
B24: 02 Nos 4P 63A MCCB /(10kA), 04 Nos 2P 32A MCB /(10kA),01 Nos 125A 4P Automatic Chainge over,01 Nos 40A 4P MCCB, 07 Nos 40A 4P MCCB, 07 Nos 40A 4P 30mA RCCB, 01 Nos 40A 2P 30mA RCCB,and nessasary bus bar and protective system and Cables Lugs and other suppotive meterials | C24: 3 | D24: Nos | F24: =+$I$1 -> 0.75 | G24: =ROUNDUP(E24/F24,-1) -> 0 | H24: =+G24*C24 -> 0
B25: 1 set of LED Phase indicator lamps c/w 3 x 2A fuse | F25: =+$I$1 -> 0.75 | G25: =ROUNDUP(E25/F25,-1) -> 0 | H25: =+G25*C25 -> 0
B26: Supply and mounted (LED Phase indicator lamps ) Wall/Surface mounted Powder Coated Steel Enclosure with lockable doors ,cover plate & internal wiring c/w bus bars and Accessories.(Rate to include necessary MCCB,MCB,RCCB,and other necessary fixturesand Other required supportive materials should include ) The contractor shoud take advise an electricle engineer before undataking the work. | E26: =94000+15000 -> 109000 | F26: =+$I$1 -> 0.75 | G26: =ROUNDUP(E26/F26,-1) -> 145340 | H26: =+G26*C24 -> 436020
B27: Surface mounted Powder Coated Steel Enclosure with lockable doors ,cover plate & internal wiring c/w bus bars and Accessories.
A28: V03.02 | B28: DB
B29: 01 No. 4P 63A MCCB (16kA Breaking capacity), 01 No. 4P 40A MCCB (16kA Breaking capacity),01 No. 2P 32A, MCB (16kA Breaking capacity),02 Nos. 1P 10A MCB (6kA Breaking capacity),02 Nos. 1P 20A MCB (6kA Breaking capacity),01 No. 2P 40A, 30mA RCCB, and nessasary bus bar and protective system and Cables Lugs and other suppotive meterials1 | C29: 2 | D29: Nos | F29: =+$I$1 -> 0.75 | G29: =ROUNDUP(E29/F29,-1) -> 0 | H29: =+G29*C29 -> 0
B30: Supply and mounted LED phase indicator lamps powder coated steel encloser with lockble door, Wall mounted distribution board (3 nr of DB) & internal wiring c/w bus bars and Accessories.(Rate to include necessary MCCB,MCB,RCCB,and other necessary fixturesand Other required supportive materials should include ) The contractor shoud take advise an electricle engineer before undataking the work. | E30: =60000+9000 -> 69000 | F30: =+$I$1 -> 0.75 | G30: =ROUNDUP(E30/F30,-1) -> 92000 | H30: =+G30*C29 -> 184000
B31: Surface mounted Powder Coated Steel Enclosure with lockable doors ,cover plate & internal wiring c/w bus bars and Accessories.
A33: V03.03 | B33: DB- For Lift
B34: Supply and mounted LED phase indicator lamps powder coated steel encloser with lockble door, Wall mounted distribution board & internal wiring c/w bus bars and Accessories.(Rate to include necessary MCCB,MCB,RCCB,and other necessary fixturesand Other required supportive materials should include ) The contractor shoud take advise an electricle engineer before undataking the work | D34: P.S
B35: Surface mounted Powder Coated Steel Enclosure c/w bus bars and Accessories.
A37: V03.04 | B37: DB- For bank- 4 nr of DB
B38: Supply and mounted LED phase indicator lamps powder coated steel encloser with lockble door, Wall mounted distribution board (4 nr of DB) & internal wiring c/w bus bars and Accessories.(Rate to include necessary MCCB,MCB,RCCB,and other necessary fixturesand Other required supportive materials should include ) The contractor shoud take advise an electricle engineer before undataking the work | D38: P.S
B39: Surface mounted Powder Coated Steel Enclosure with lockable doors ,cover plate & internal wiring c/w bus bars and Accessories.
A41: V03.04 | B41: DBs For Shop
B42: Supply and mounted Wall mounted distribution board( 42 nr) & internal wiring c/w bus bars and Accessories.(Rate to include necessary MCCB,MCB,RCCB,and other necessary fixturesand Other required supportive materials should include ) The contractor shoud take advise an electricle engineer before undataking the work | D42: P.S
B43: Surface mounted Powder Coated Steel Enclosure with lockable doors ,cover plate & internal wiring c/w bus bars and Accessories.
A53: V03.05 | B53: DBs For Banks
A54: V04 | B54: Wiring for light points, ceiling fans, socket outlets
B56: SUB CIRCUIT & LIGHT POINT WIRING
A58: V04.1 | B58: Point wiring for socket outlets 13A - ( 16A Circuits) Supply, Installation & wiring of 13A power Socket Outlet, by using 2x1C 2.5mm^2 Cu /PVC/PVC Cable + 1C 2.5 mm^2 Cu/PVC Earth Cable (in radial circuit) through slab & wall in PVC conduits including PVC conduits, sunk box, junction box, outlet and complete with all other relevant accessories.
B59: For Ground Floor | C59: 25 | D59: nr | E59: 9000 | F59: =+$I$1 -> 0.75 | G59: =ROUNDUP(E59/F59,-1) -> 12000 | H59: =+G59*C59 -> 300000
B60: For 1st Floor | C60: 35 | D60: nr | E60: 9000 | F60: =+$I$1 -> 0.75 | G60: =ROUNDUP(E60/F60,-1) -> 12000 | H60: =+G60*C60 -> 420000
B61: For 2nd Floor | C61: 35 | D61: nr | E61: 9000 | F61: =+$I$1 -> 0.75 | G61: =ROUNDUP(E61/F61,-1) -> 12000 | H61: =+G61*C61 -> 420000
B62: For Terrace Floor | C62: 12 | D62: nr | E62: 9000 | F62: =+$I$1 -> 0.75 | G62: =ROUNDUP(E62/F62,-1) -> 12000 | H62: =+G62*C62 -> 144000
A64: V04.2 | B64: Light Point Wiring (10A Circuits)-indoor/outdoor Supply & Installation of light Point Wiring, by using 2x1C 1.5mm^2 Cu/PVC/PVC Cable + 1C 1.5 mm^2 Cu/PVC Earth Cable through slab & wall in PVC conduits including PVC conduits, sunk box, junction box, 10A PVC Switch and complete with all other relevant accessories.
B65: For Ground Floor | C65: 22 | D65: nr | E65: 7500 | F65: =+$I$1 -> 0.75 | G65: =ROUNDUP(E65/F65,-1) -> 10000 | H65: =+G65*C65 -> 220000
B66: For 1st Floor | C66: 25 | D66: nr | E66: 7500 | F66: =+$I$1 -> 0.75 | G66: =ROUNDUP(E66/F66,-1) -> 10000 | H66: =+G66*C66 -> 250000
B67: For 2nd Floor | C67: 25 | D67: nr | E67: 7500 | F67: =+$I$1 -> 0.75 | G67: =ROUNDUP(E67/F67,-1) -> 10000 | H67: =+G67*C67 -> 250000
B68: For Terrace Floor | C68: 7 | D68: nr | E68: 7500 | F68: =+$I$1 -> 0.75 | G68: =ROUNDUP(E68/F68,-1) -> 10000 | H68: =+G68*C68 -> 70000
A70: V04.3 | B70: Two way light Point Wiring (10A Circuits) Supply & Installation of 2way light Point Wiring, by using 2x1C 1.5mm^2 Cu/PVC/PVC Cable + 1C 1.5 mm^2 Cu/PVC Earth Cable through slab & wall in PVC conduits including PVC conduits, sunk box, junction box, 10A PVC 2 way Switches and complete with all other relevant accessories.
B71: For Ground Floor | C71: 3 | D71: nr | E71: 8000 | F71: =+$I$1 -> 0.75 | G71: =ROUNDUP(E71/F71,-1) -> 10670 | H71: =+G71*C71 -> 32010
B72: For 1st Floor | C72: 3 | D72: nr | E72: 8000 | F72: =+$I$1 -> 0.75 | G72: =ROUNDUP(E72/F72,-1) -> 10670 | H72: =+G72*C72 -> 32010
B73: For 2nd Floor | C73: 3 | D73: nr | E73: 8000 | F73: =+$I$1 -> 0.75 | G73: =ROUNDUP(E73/F73,-1) -> 10670 | H73: =+G73*C73 -> 32010
B74: For Terrace Floor | C74: 1 | D74: nr | E74: 8000 | F74: =+$I$1 -> 0.75 | G74: =ROUNDUP(E74/F74,-1) -> 10670 | H74: =+G74*C74 -> 10670
A76: V04.4 | B76: Fan Point Wiring - (10A Circuits ) Supply & installation of Fan Point wiring, by using 2X1C 1.5mm^2 Cu/PVC /PVC Cable + 1C 1.5 mm^2 Cu/PVC earth Cable through slab & wall in PVC conduits including PVC conduits, junction boxes, sunk boxes, 10A PVC Switch, and complete with all other relevant accessories.
B77: For Ground Floor | C77: 6 | D77: nr | E77: 7500 | F77: =+$I$1 -> 0.75 | G77: =ROUNDUP(E77/F77,-1) -> 10000 | H77: =+G77*C77 -> 60000
B78: For 1st Floor | C78: 5 | D78: nr | E78: 7500 | F78: =+$I$1 -> 0.75 | G78: =ROUNDUP(E78/F78,-1) -> 10000 | H78: =+G78*C78 -> 50000
B79: For 2nd Floor | C79: 5 | D79: nr | E79: 7500 | F79: =+$I$1 -> 0.75 | G79: =ROUNDUP(E79/F79,-1) -> 10000 | H79: =+G79*C79 -> 50000
B80: For Terrace Floor | C80: 1 | D80: nr | E80: 7500 | F80: =+$I$1 -> 0.75 | G80: =ROUNDUP(E80/F80,-1) -> 10000 | H80: =+G80*C80 -> 10000
A82: V04.5 | B82: Supply & Installation of ceiling fans- Brand - KDK (model need to be finalized with architect) Supply & Installation of ceiling fan (Diameter-56") and speed regulator with roll plugs, screws, metal hooks (Fan hook need to be passed through the slab and properly connected) and complete with all other relevant accessories. (PC sum is Rs. 26,200.00)
B83: For Ground Floor | C83: 6 | D83: nr | E83: =26200+800+950 -> 27950 | F83: =+$I$1 -> 0.75 | G83: =ROUNDUP(E83/F83,-1) -> 37270 | H83: =+G83*C83 -> 223620
B84: For 1st Floor | C84: 5 | D84: nr | E84: =26200+800+950 -> 27950 | F84: =+$I$1 -> 0.75 | G84: =ROUNDUP(E84/F84,-1) -> 37270 | H84: =+G84*C84 -> 186350
B85: For 2nd Floor | C85: 5 | D85: nr | E85: =26200+800+950 -> 27950 | F85: =+$I$1 -> 0.75 | G85: =ROUNDUP(E85/F85,-1) -> 37270 | H85: =+G85*C85 -> 186350
B86: For Terrace Floor | C86: 1 | D86: nr | E86: =26200+800+950 -> 27950 | F86: =+$I$1 -> 0.75 | G86: =ROUNDUP(E86/F86,-1) -> 37270 | H86: =+G86*C86 -> 37270
A88: V05 | B88: Light Fittings
A89: V05.1 | B89: Installation of light fittings-indoor/outdoor Installation of light fittings including roll plugs, screws and complete with all other relevant accessories.
B90: For Ground Floor | C90: 6 | D90: nr | E90: 1350 | F90: =+$I$1 -> 0.75 | G90: =ROUNDUP(E90/F90,-1) -> 1800 | H90: =+G90*C90 -> 10800
B91: For 1st Floor | C91: 5 | D91: nr | E91: 1350 | F91: =+$I$1 -> 0.75 | G91: =ROUNDUP(E91/F91,-1) -> 1800 | H91: =+G91*C91 -> 9000 | J91: 17700
B92: For 2nd Floor | C92: 5 | D92: nr | E92: 1350 | F92: =+$I$1 -> 0.75 | G92: =ROUNDUP(E92/F92,-1) -> 1800 | H92: =+G92*C92 -> 9000 | J92: 9350
B93: For Terrace Floor | C93: 1 | D93: nr | E93: 1350 | F93: =+$I$1 -> 0.75 | G93: =ROUNDUP(E93/F93,-1) -> 1800 | H93: =+G93*C93 -> 1800 | J93: 3850
J94: =5690*3 -> 17070
A95: V05.2 | B95: Outdoor/Indoor wall mounted light fitting with 18w LED bulb. (Prime cost is Rs.4,000.00) | J95: =2100*3 -> 6300
B96: For Ground Floor | C96: 7 | D96: nr | E96: =4000+500 -> 4500 | F96: =+$I$1 -> 0.75 | G96: =ROUNDUP(E96/F96,-1) -> 6000 | H96: =+G96*C96 -> 42000 | J96: =725*36 -> 26100
B97: For 1st Floor | C97: 9 | D97: nr | E97: =4000+500 -> 4500 | F97: =+$I$1 -> 0.75 | G97: =ROUNDUP(E97/F97,-1) -> 6000 | H97: =+G97*C97 -> 54000
B98: For 2nd Floor | C98: 9 | D98: nr | E98: =4000+500 -> 4500 | F98: =+$I$1 -> 0.75 | G98: =ROUNDUP(E98/F98,-1) -> 6000 | H98: =+G98*C98 -> 54000
B99: For Terrace Floor | C99: 2 | D99: nr | E99: =4000+500 -> 4500 | F99: =+$I$1 -> 0.75 | G99: =ROUNDUP(E99/F99,-1) -> 6000 | H99: =+G99*C99 -> 12000
A102: V05.3 | B102: Inner diameter of 150mm Ceiling/slab mounted down light complete with 18w LED lamp. (Prime cost is Rs.5,000.00)
B103: For Ground Floor | C103: 45 | D103: nr | E103: =5000+700 -> 5700 | F103: =+$I$1 -> 0.75 | G103: =ROUNDUP(E103/F103,-1) -> 7600 | H103: =+G103*C103 -> 342000
B104: For 1st Floor | C104: 50 | D104: nr | E104: =5000+700 -> 5700 | F104: =+$I$1 -> 0.75 | G104: =ROUNDUP(E104/F104,-1) -> 7600 | H104: =+G104*C104 -> 380000
B105: For 2nd Floor | C105: 50 | D105: nr | E105: =5000+700 -> 5700 | F105: =+$I$1 -> 0.75 | G105: =ROUNDUP(E105/F105,-1) -> 7600 | H105: =+G105*C105 -> 380000
B106: For Terrace Floor | C106: 28 | D106: nr | E106: =5000+700 -> 5700 | F106: =+$I$1 -> 0.75 | G106: =ROUNDUP(E106/F106,-1) -> 7600 | H106: =+G106*C106 -> 212800
B109: wall mounted clear transparent glass globe light fitting and bracket with 12w LED bulb. (Prime cost is Rs.5,000.00) | D109: Nr
A111: V05.4 | B111: Supplying of pendent light (Type 01) fittings as per the proposal(Pc sum is Rs. 40,000.00)
B112: For Ground Floor | C112: 2 | D112: nr | E112: =40000+3000 -> 43000 | F112: =+$I$1 -> 0.75 | G112: =ROUNDUP(E112/F112,-1) -> 57340 | H112: =+G112*C112 -> 114680
B113: For 1st Floor | C113: 2 | D113: nr | E113: =40000+3000 -> 43000 | F113: =+$I$1 -> 0.75 | G113: =ROUNDUP(E113/F113,-1) -> 57340 | H113: =+G113*C113 -> 114680
B114: For 2nd Floor | C114: 2 | D114: nr | E114: =40000+3000 -> 43000 | F114: =+$I$1 -> 0.75 | G114: =ROUNDUP(E114/F114,-1) -> 57340 | H114: =+G114*C114 -> 114680
A116: V05.5 | B116: Supplying of pendent light (Type 03) fittings as per the proposal(Pc sum is Rs. 60,000.00)
B117: For 2nd Floor | C117: 1 | D117: nr | E117: =60000+4000 -> 64000 | F117: =+$I$1 -> 0.75 | G117: =ROUNDUP(E117/F117,-1) -> 85340 | H117: =+G117*C117 -> 85340
A119: V05.6 | B119: Supplying and install of LED 6w spot light.- (Prime cost is Rs.5,500.00)
B120: For Ground Floor | C120: 8 | D120: nr | E120: =5500+500 -> 6000 | F120: =+$I$1 -> 0.75 | G120: =ROUNDUP(E120/F120,-1) -> 8000 | H120: =+G120*C120 -> 64000
B121: For 1st Floor | C121: 8 | D121: nr | E121: =5500+500 -> 6000 | F121: =+$I$1 -> 0.75 | G121: =ROUNDUP(E121/F121,-1) -> 8000 | H121: =+G121*C121 -> 64000
B122: For 2nd Floor | C122: 8 | D122: nr | E122: =5500+500 -> 6000 | F122: =+$I$1 -> 0.75 | G122: =ROUNDUP(E122/F122,-1) -> 8000 | H122: =+G122*C122 -> 64000
B123: For Terrace Floor | C123: 3 | D123: nr | E123: =5500+500 -> 6000 | F123: =+$I$1 -> 0.75 | G123: =ROUNDUP(E123/F123,-1) -> 8000 | H123: =+G123*C123 -> 24000
A125: V05.7 | B125: Supplying and install of LED 6w down light.- (Prime cost is Rs.5,500.00)
B126: For Ground Floor | C126: 5 | D126: nr | E126: =5500+500 -> 6000 | F126: =+$I$1 -> 0.75 | G126: =ROUNDUP(E126/F126,-1) -> 8000 | H126: =+G126*C126 -> 40000
B127: For 1st Floor | C127: 2 | D127: nr | E127: =5500+500 -> 6000 | F127: =+$I$1 -> 0.75 | G127: =ROUNDUP(E127/F127,-1) -> 8000 | H127: =+G127*C127 -> 16000
B128: For 2nd Floor | C128: 2 | D128: nr | E128: =5500+500 -> 6000 | F128: =+$I$1 -> 0.75 | G128: =ROUNDUP(E128/F128,-1) -> 8000 | H128: =+G128*C128 -> 16000
B129: For Terrace Floor | C129: 6 | D129: nr | E129: =5500+500 -> 6000 | F129: =+$I$1 -> 0.75 | G129: =ROUNDUP(E129/F129,-1) -> 8000 | H129: =+G129*C129 -> 48000
A131: V05.8 | B131: Supplying and install of 3 nr of Spot light track light system as per the design (Prime cost is Rs. 42,000.00)
B132: For Ground Floor | C132: 2 | D132: nr | E132: 45000 | F132: =+$I$1 -> 0.75 | G132: =ROUNDUP(E132/F132,-1) -> 60000 | H132: =+G132*C132 -> 120000
B133: For 1st Floor | C133: 3 | D133: nr | E133: 45000 | F133: =+$I$1 -> 0.75 | G133: =ROUNDUP(E133/F133,-1) -> 60000 | H133: =+G133*C133 -> 180000
B134: For 2nd Floor | C134: 3 | D134: nr | E134: 45000 | F134: =+$I$1 -> 0.75 | G134: =ROUNDUP(E134/F134,-1) -> 60000 | H134: =+G134*C134 -> 180000
B135: For Terrace Floor | C135: 2 | D135: nr | E135: 45000 | F135: =+$I$1 -> 0.75 | G135: =ROUNDUP(E135/F135,-1) -> 60000 | H135: =+G135*C135 -> 120000
A139: V05.9 | B139: LED 6w Mirror lamp fitting.- (Prime cost is Rs.2,500.00)
B140: For Ground Floor | C140: 2 | D140: nr | E140: =2500+500 -> 3000 | F140: =+$I$1 -> 0.75 | G140: =ROUNDUP(E140/F140,-1) -> 4000 | H140: =+G140*C140 -> 8000
B141: For 1st Floor | C141: 3 | D141: nr | E141: =2500+500 -> 3000 | F141: =+$I$1 -> 0.75 | G141: =ROUNDUP(E141/F141,-1) -> 4000 | H141: =+G141*C141 -> 12000
...

Sheet metal 
A1: Nos | B1: Description | C1: Qty | D1: Unit | E1: COST | F1: OHP% | G1: Rate | H1: Amount | I1: =+summary!D17 -> 0.85
B2: U - METAL WORK
A3: 1 | B3: Metal Ceiling
A4: =A3+0.01 -> 1.01 | B4: Supplying & Installing of 600mmx 600mm non perforated white metal sheet ceiling, supported by concealed type furring suspended system installed in a flat horizontal manner using furing bars clipped on to inter locking hot dipped GI main tees with clips, ciling to be susppended using GI 04mm thick hanger rods (Prime cost of 2'-0" x 2'-0" sheet is Rs.2,640.00)
B5: Ground Floor- banak area | D5: Sqr.
B7: Aluminium Panel Ceiling
A8: =A3+0.01 -> 1.01 | B8: Supplying & installing of suspended Aluminium Panel Ceiling in 600mm x 600 grid size reveal / bevel type using hot dipped GI pre –engineered inter - locking main tees (38mm x 14mm) and cross tees (25mm x 14mm) and wall angles expose areas finished with white baked enamel finish and suspended on 4 mm dia. adjustable hanger rods with spring clips. Ceiling panels will be Compton aluminium tiles 600mm x 600mm x 0.7mm (thickness) and complete to working order as per manufacture's specifications..
B9: Ground Floor- | D9: Sqm
A11: U.1 | B11: Hand Rail
B12: G.I Tube Hand Rail
A13: U.1.1 | B13: Staircase & Balcony handrail (6mm Tempered Glass / SS Box bar etc. )as per the design | C13: =42+42+3 -> 87 | D13: m | E13: =11500*3.28 -> 37720 | F13: =+$I$1 -> 0.85 | G13: =ROUNDUP(E13/F13,-1) -> 44380 | H13: =+G13*C13 -> 3861060 | J13: =3*3*610 -> 5490
A15: =A13+0.01 -> #VALUE! | B15: Powder coated perforated mesh Hand Rail
B16: Supplying, fabricating & fixing of perforated mesh hand rail upto 1.2m height 50mm dia 2.3mm thick G.I round bar upright @ 3000mm c/c as vertical members fixed bottom end to steps with the 150mm dia 8mm thick M.S. plate connecting with 4 nos of 8mm dia.anchor bolts and work complete in order. Rate Shall include for applying one coat of etch primer (50% of etch primer base and 50% etch primer activator),one coat of anti-corrosive primer with two coats of enamel paint. (Prime cost is Rs, 1,250.00 per sqft)
A18: 3 | B18: Partitions
A20: =A18+0.01 -> 3.01 | B20: Tempored Glass Partition
B21: P1 in 37.5mm x 25mm x 1.4mm thick hairline finished stainless steel 'U' channel framed work and 12mm thick tempered glass with printed PVC stickering fixed with silicon joints as per the detailed drawing and finishes as specified as per the drawings | D21: Sqr.
A23: =A20+0.01 -> 3.02 | B23: HPL Partition
B25: First Floor | D25: Sqm
A27: =A23+0.01 -> 3.03 | B27: Tempored fixed Glass
B28: 37.5mm x 25mm x 1.4mm thick hairline finished stainless steel 'U' channel framed work and 12mm thick tempered glass with printed PVC stickering fixed with silicon joints as per the detailed drawing and finishes as specified as per the drawings
B29: Second Floor | D29: Sqr.
A31: U.2 | B31: Doors
A33: U.2.1 | B33: Door type D1 size 1500mm x 2700mm Teak Timber Framed Solid Teak Timber Double door as per the detail drawings with all necessary iron mongaries with smart lock. (Smart Lock PC - 72,000.00 per unit)
B34: In Ground Floor | C34: 1 | D34: nr | E34: =6450*5*9+72000 -> 362250 | F34: =+$I$1 -> 0.85 | G34: =ROUNDUP(E34/F34,-1) -> 426180 | H34: =+G34*C34 -> 426180
A36: U.2.2 | B36: Door type D2 size 1000mm x 2400mm Teak Timber Framed Solid Teak Timber single slash door as per the detail drawings with all necessary iron mongaries
B37: In Ground Floor | C37: 2 | D37: nr | E37: =6150*26 -> 159900 | F37: =+$I$1 -> 0.85 | G37: =ROUNDUP(E37/F37,-1) -> 188120 | H37: =+G37*C37 -> 376240
B38: In 1st Floor | C38: 4 | D38: nr | E38: =+E37*1.01 -> 161499 | F38: =+$I$1 -> 0.85 | G38: =ROUNDUP(E38/F38,-1) -> 190000 | H38: =+G38*C38 -> 760000
B39: In 2nd Floor | C39: 4 | D39: nr | E39: =+E38*1.01 -> 163113.99 | F39: =+$I$1 -> 0.85 | G39: =ROUNDUP(E39/F39,-1) -> 191900 | H39: =+G39*C39 -> 767600
A41: U.2.3 | B41: Door type D3 size 825mm x 2400mm Teak Timber Framed Solid Teak Timber single slash door as per the detail drawings with all necessary iron mongaries
B42: In Ground Floor | C42: 3 | D42: nr | E42: =6150*22 -> 135300 | F42: =+$I$1 -> 0.85 | G42: =ROUNDUP(E42/F42,-1) -> 159180 | H42: =+G42*C42 -> 477540
B43: In 1st Floor | C43: 3 | D43: nr | E43: =+E42*1.01 -> 136653 | F43: =+$I$1 -> 0.85 | G43: =ROUNDUP(E43/F43,-1) -> 160770 | H43: =+G43*C43 -> 482310
B44: In 2nd Floor | C44: 3 | D44: nr | E44: =+E42*1.02 -> 138006 | F44: =+$I$1 -> 0.85 | G44: =ROUNDUP(E44/F44,-1) -> 162360 | H44: =+G44*C44 -> 487080
B45: In Terrace Floor | C45: 1 | D45: nr | E45: =+E42*1.03 -> 139359 | F45: =+$I$1 -> 0.85 | G45: =ROUNDUP(E45/F45,-1) -> 163960 | H45: =+G45*C45 -> 163960
A47: U.2.4 | B47: Door type D4 size 1000mm x 2700mm Teak Timber Framed Solid Teak Timber single slash door as per the detail drawings with all necessary iron mongaries
B48: In Ground Floor | C48: 2 | D48: nr | E48: =6150*29 -> 178350 | F48: =+$I$1 -> 0.85 | G48: =ROUNDUP(E48/F48,-1) -> 209830 | H48: =+G48*C48 -> 419660
B49: In Terrace Floor | C49: 1 | D49: nr | E49: =+E48*1.04 -> 185484 | F49: =+$I$1 -> 0.85 | G49: =ROUNDUP(E49/F49,-1) -> 218220 | H49: =+G49*C49 -> 218220
A51: U.2.5 | B51: Door type GD size 900mm x 2700mm Teak Timber Framed Solid Teak Timber single slash door as per the detail drawings with all necessary iron mongaries
B52: In Ground Floor | C52: 2 | D52: nr | E52: =6150*27 -> 166050 | F52: =+$I$1 -> 0.85 | G52: =ROUNDUP(E52/F52,-1) -> 195360 | H52: =+G52*C52 -> 390720
A54: U.3 | B54: Windows
A56: U.3.1 | B56: Window type W1 , size 4425mm x1800mm Powder coated aluminum glazed Sliding window, complete with all necessary ironmongeries and complete as per thedetail drawings.
B57: In Ground Floor | C57: 1 | D57: nr | E57: =86*4250 -> 365500 | F57: =+$I$1 -> 0.85 | G57: =ROUNDUP(E57/F57,-1) -> 430000 | H57: =+G57*C57 -> 430000 | I57: =4.425*1.8 -> 7.965 | J57: =+I57*10.76 -> 85.7034
A59: U.3.2 | B59: Window type W2 , size 1200mm x 1650mm Powder coated aluminum glazed Sliding window, complete with all necessary ironmongeries and complete as per thedetail drawings.
B60: In Ground Floor | C60: 2 | D60: nr | E60: =21*4250 -> 89250 | F60: =+$I$1 -> 0.85 | G60: =ROUNDUP(E60/F60,-1) -> 105000 | H60: =+G60*C60 -> 210000 | I60: =1.2*1.65 -> 1.98 | J60: =+I60*10.76 -> 21.3048
A62: U.3.3 | B62: Window type SD1 , size 4425mm x 2700mm Powder coated aluminum glazed Sliding window, complete with all necessary ironmongeries and complete as per thedetail drawings.
B63: In Ground Floor | C63: 1 | D63: nr | E63: =129*4250 -> 548250 | F63: =+$I$1 -> 0.85 | G63: =ROUNDUP(E63/F63,-1) -> 645000 | H63: =+G63*C63 -> 645000 | I63: =4.425*2.7 -> 11.9475 | J63: =+I63*10.76 -> 128.5551
B64: In 1st Floor | C64: 2 | D64: nr | E64: =129*4250 -> 548250 | F64: =+$I$1 -> 0.85 | G64: =ROUNDUP(E64/F64,-1) -> 645000 | H64: =+G64*C64 -> 1290000
B65: In 2nd Floor | C65: 2 | D65: nr | E65: =129*4250 -> 548250 | F65: =+$I$1 -> 0.85 | G65: =ROUNDUP(E65/F65,-1) -> 645000 | H65: =+G65*C65 -> 1290000
A67: U.3.4 | B67: Window type SD2 , size 4350mm x 2700mm Powder coated aluminum glazed Sliding window, complete with all necessary ironmongeries and complete as per thedetail drawings.
B68: In Ground Floor | C68: 1 | D68: nr | E68: =126*4250 -> 535500 | F68: =+$I$1 -> 0.85 | G68: =ROUNDUP(E68/F68,-1) -> 630000 | H68: =+G68*C68 -> 630000 | I68: =4.35*2.7 -> 11.745 | J68: =+I68*10.76 -> 126.3762
A70: U.3.5 | B70: Window type SD3 , size 2400mm x 2700mm Powder coated aluminum glazed Sliding window, complete with all necessary ironmongeries and complete as per thedetail drawings.
B71: In Ground Floor | C71: 2 | D71: nr | E71: =70*4250 -> 297500 | F71: =+$I$1 -> 0.85 | G71: =ROUNDUP(E71/F71,-1) -> 350000 | H71: =+G71*C71 -> 700000 | I71: =2.025*2.7 -> 5.4675 | J71: =+I71*10.76 -> 58.8303
B72: In 1st Floor | C72: 4 | D72: nr | E72: =70*4250 -> 297500 | F72: =+$I$1 -> 0.85 | G72: =ROUNDUP(E72/F72,-1) -> 350000 | H72: =+G72*C72 -> 1400000
B73: In 2nd Floor | C73: 4 | D73: nr | E73: =70*4250 -> 297500 | F73: =+$I$1 -> 0.85 | G73: =ROUNDUP(E73/F73,-1) -> 350000 | H73: =+G73*C73 -> 1400000
B74: Terrace Floor | C74: 1 | D74: nr | E74: =70*4250 -> 297500 | F74: =+$I$1 -> 0.85 | G74: =ROUNDUP(E74/F74,-1) -> 350000 | H74: =+G74*C74 -> 350000
A76: U.3.6 | B76: Window type SD4 , size 3600mm x 2700mm Powder coated aluminum glazed Sliding window, complete with all necessary ironmongeries and complete as per thedetail drawings.
B77: Terrace Floor | C77: 1 | D77: nr | E77: =105*4250 -> 446250 | F77: =+$I$1 -> 0.85 | G77: =ROUNDUP(E77/F77,-1) -> 525000 | H77: =+G77*C77 -> 525000
A80: U.3.7 | B80: Window type SD5 , size 2025mm x 2700mm Powder coated aluminum glazed Sliding window, complete with all necessary ironmongeries and complete as per thedetail drawings.
B81: Terrace Floor | C81: 1 | D81: nr | E81: =59*4250 -> 250750 | F81: =+$I$1 -> 0.85 | G81: =ROUNDUP(E81/F81,-1) -> 295000 | H81: =+G81*C81 -> 295000
A83: U.3.8 | B83: Window type FG1, size 2100mm x 2400mm Powder coated aluminum Fix glazed window, complete with all necessary equipments and complete as per thedetail drawings.
B84: In Ground Floor | C84: 1 | D84: nr | E84: =55*3850 -> 211750 | F84: =+$I$1 -> 0.85 | G84: =ROUNDUP(E84/F84,-1) -> 249120 | H84: =+G84*C84 -> 249120 | I84: =2.1*2.4 -> 5.04 | J84: =+I84*10.76 -> 54.2304
B85: In 1st Floor | C85: 1 | D85: nr | E85: =+E84*1.01 -> 213867.5 | F85: =+$I$1 -> 0.85 | G85: =ROUNDUP(E85/F85,-1) -> 251610 | H85: =+G85*C85 -> 251610
B86: In 2nd Floor | C86: 1 | D86: nr | E86: =+E84*1.02 -> 215985 | F86: =+$I$1 -> 0.85 | G86: =ROUNDUP(E86/F86,-1) -> 254100 | H86: =+G86*C86 -> 254100
B87: Terrace Floor | C87: 1 | D87: nr | E87: =+E85*1.02 -> 218144.85 | F87: =+$I$1 -> 0.85 | G87: =ROUNDUP(E87/F87,-1) -> 256650 | H87: =+G87*C87 -> 256650
A90: U.3.9 | B90: Fanlight type FL1 , size 900mm x 1500mm high overall Powder Coated fanlight, complete with all necessary ironmongeries.
B91: In Ground Floor | C91: 1 | D91: nr | E91: =15*3850 -> 57750 | F91: =+$I$1 -> 0.85 | G91: =ROUNDUP(E91/F91,-1) -> 67950 | H91: =+G91*C91 -> 67950 | I91: =0.6*1.5 -> 0.9 | J91: =+I91*10.76 -> 9.684
B92: In 1st Floor | C92: 2 | D92: nr | E92: =15*3850 -> 57750 | F92: =+$I$1 -> 0.85 | G92: =ROUNDUP(E92/F92,-1) -> 67950 | H92: =+G92*C92 -> 135900
B93: In 2nd Floor | C93: 2 | D93: nr | E93: =15*3850 -> 57750 | F93: =+$I$1 -> 0.85 | G93: =ROUNDUP(E93/F93,-1) -> 67950 | H93: =+G93*C93 -> 135900
A95: U.3.10 | B95: Fanlight type F2 , size 600mm x 1500mm high overall Powder Coated fanlight, complete with all necessary ironmongeries.
B96: In Ground Floor | C96: 1 | D96: nr | E96: =10*2650 -> 26500 | F96: =+$I$1 -> 0.85 | G96: =ROUNDUP(E96/F96,-1) -> 31180 | H96: =+G96*C96 -> 31180
B97: In 1st Floor | C97: 1 | D97: nr | E97: =10*2650 -> 26500 | F97: =+$I$1 -> 0.85 | G97: =ROUNDUP(E97/F97,-1) -> 31180 | H97: =+G97*C97 -> 31180
B98: In 2nd Floor | C98: 1 | D98: nr | E98: =10*2650 -> 26500 | F98: =+$I$1 -> 0.85 | G98: =ROUNDUP(E98/F98,-1) -> 31180 | H98: =+G98*C98 -> 31180
B99: Terrace Floor | C99: 1 | D99: nr | E99: =10*2650 -> 26500 | F99: =+$I$1 -> 0.85 | G99: =ROUNDUP(E99/F99,-1) -> 31180 | H99: =+G99*C99 -> 31180
B105: METAL WORK CARRIED TO COLLECTION | H105: =SUM(H3:H104) -> 19471520

Sheet waterprof
A1: Nos | B1: Description | C1: Qty | D1: Unit | E1: COST | F1: OHP% | G1: Rate | H1: Amount | I1: 0.85
B2: R - WATER PROOFING WORK
A3: R.1 | B3: Internal Wet Areas without Exposure to Sunlight Sq.ft. (Cementitious water proofing using Barralastic or approved equivalnt)
B5: Application of cementitious water proofing using Barralastic or approved equivalnt for internal wet areas such as toilet floors and walls (Walls Up to 1.60m) where the surfaces are not directly exposed to sunlight and weathering. Rate will include to cleaning the substrate and 1:3 cement sand bedding and all other work as per manufacturer's specifications on application and shall include ponding test for a 300mm water height kept for a period of 48 hours for horizontal surfaces. | J5: WITH ANGLE FILLET
A6: R.1.1 | B6: Ground Floor | C6: =4+17 -> 21 | D6: S.qm | E6: =+J6*10.76 -> 3550.8 | F6: =+$I$1 -> 0.85 | G6: =ROUNDUP(E6/F6,-1) -> 4180 | H6: =+G6*C6 -> 87780 | J6: =275*1.2 -> 330
A7: R.1.2 | B7: First Floor | C7: =13+51 -> 64 | D7: S.qm | E7: =+E6*1.01 -> 3586.308 | F7: =+$I$1 -> 0.85 | G7: =ROUNDUP(E7/F7,-1) -> 4220 | H7: =+G7*C7 -> 270080
A8: E.1.3 | B8: 2nd Floor | C8: 64 | D8: S.qm | E8: =+E6*1.02 -> 3621.816 | F8: =+$I$1 -> 0.85 | G8: =ROUNDUP(E8/F8,-1) -> 4270 | H8: =+G8*C8 -> 273280
A9: E.1.4 | B9: Terrace Floor | C9: 22.9 | D9: S.qm | E9: =+E6*1.03 -> 3657.324 | F9: =+$I$1 -> 0.85 | G9: =ROUNDUP(E9/F9,-1) -> 4310 | H9: =+G9*C9 -> 98699
A12: R.2 | B12: Areas exposed to sunlight (Balconies, Sun-Shades Concrete Gutters , Slab Top ,etc) (Elastomeric water proofing using thoroseal or approved equivalent.)
B14: Application of two coats of elastomeric water proofing material using thoroseal or approved equivalnt capable to withstand temperature variation for wet areas exposed to sunlight and weathering. ( balconies, sun-shades, concrete gutters etc.) rate shall include for cleaning the substrate and all other work as per manufacturer's specifications on application and shall include ponding test for a 300mm water height kept for a period of 48 hours for horizontal surfaces and cement sand finished with neat finish smooth rendering
A15: R.2.1 | B15: First Floor | C15: 28 | D15: S.qm | E15: =+E6 -> 3550.8 | F15: =+$I$1 -> 0.85 | G15: =ROUNDUP(E15/F15,-1) -> 4180 | H15: =+G15*C15 -> 117040
A16: R.2.2 | B16: 2nd Floor | C16: 28 | D16: S.qm | E16: =+E7 -> 3586.308 | F16: =+$I$1 -> 0.85 | G16: =ROUNDUP(E16/F16,-1) -> 4220 | H16: =+G16*C16 -> 118160
A17: R.2.3 | B17: Terrace Floor | C17: =98+19 -> 117 | D17: S.qm | E17: =+E9 -> 3657.324 | F17: =+$I$1 -> 0.85 | G17: =ROUNDUP(E17/F17,-1) -> 4310 | H17: =+G17*C17 -> 504270
A18: R.2.4 | B18: Roof Slab | C18: 52 | D18: S.qm | E18: =+E15*1.04 -> 3692.832 | F18: =+$I$1 -> 0.85 | G18: =ROUNDUP(E18/F18,-1) -> 4350 | H18: =+G18*C18 -> 226200
B20: WATER PROOFING WORK CARRIED TO COLLECTION | H20: =SUM(H6:H19) -> 1695509

Sheet Pool
A1: Nos | B1: Description | C1: Qty | D1: Unit | E1: COST | F1: OHP% | G1: Rate | H1: Amount | I1: =+summary!D18 -> 0.75
A2: Q | B2: SWIMMING POOL (700 CUFT)
B4: CONSTRUCTION OF SWIMMING POOL (700 CUFT) AND PLANT ROOM
J5: =16.4*10.76 -> 176.464
A6: Q.1 | B6: Construction swimming pool and plant room | J6: =+J5*4 -> 705.856
A8: Q.1.1 | B8: 6" Concrete wall | C8: m³ | D8: =19.75*0.15*1.2 -> 3.555 | E8: =+'Rate Breakdowns'!G532*1.2 -> 39113.531 | F8: =+$I$1 -> 0.75 | G8: =ROUNDUP(E8/F8,-1) -> 52160 | H8: =+G8*D8 -> 185428.8
A9: Q.1.2 | B9: Staircase | C9: m³ | D9: 1.8 | E9: =+E8 -> 39113.531 | F9: =+$I$1 -> 0.75 | G9: =ROUNDUP(E9/F9,-1) -> 52160 | H9: =+G9*D9 -> 93888
A11: Q.2 | B11: Formwork
A12: Q.2.1 | B12: walls | C12: m² | D12: =19.75*2*1.2 -> 47.4 | E12: 2650 | F12: =+$I$1 -> 0.75 | G12: =ROUNDUP(E12/F12,-1) -> 3540 | H12: =+G12*D12 -> 167796
A13: Q.2.2 | B13: Staircase | C13: m² | D13: 2.5 | E13: 2650 | F13: =+$I$1 -> 0.75 | G13: =ROUNDUP(E13/F13,-1) -> 3540 | H13: =+G13*D13 -> 8850
A15: Q.3 | B15: Reinforcement
A16: Q.3.1 | B16: Walls | C16: kg | D16: =+D8*250 -> 888.75 | E16: 469.07047 | F16: =+$I$1 -> 0.75 | G16: =ROUNDUP(E16/F16,-1) -> 630 | H16: =+G16*D16 -> 559912.5
A17: Q.3.2 | B17: Staircase | C17: kg | D17: =+D9*85 -> 153 | E17: 469.07047 | F17: =+$I$1 -> 0.75 | G17: =ROUNDUP(E17/F17,-1) -> 630 | H17: =+G17*D17 -> 96390
A19: Q.4 | B19: Rendering work
A20: Q.4.1 | B20: Pool bed | C20: m² | D20: 16.04 | E20: =+'Rate Breakdowns'!H946 -> 1343.1479 | F20: =+$I$1 -> 0.75 | G20: =ROUNDUP(E20/F20,-1) -> 1800 | H20: =+G20*D20 -> 28872
A22: Q.5 | B22: Plaster work
A23: Q.5.1 | B23: Pool Internal Wall | C23: m² | D23: 16.04 | E23: =+E20 -> 1343.1479 | F23: =+$I$1 -> 0.75 | G23: =ROUNDUP(E23/F23,-1) -> 1800 | H23: =+G23*D23 -> 28872
A24: Q.5.2 | B24: Pool External Wall | C24: m² | D24: 16.04 | E24: =+E20*1.05 -> 1410.3053 | F24: =+$I$1 -> 0.75 | G24: =ROUNDUP(E24/F24,-1) -> 1890 | H24: =+G24*D24 -> 30315.6
A26: Q.6 | B26: Waterproofing work (4 coats system)
A27: Q.5.1 | B27: Pool Floor | C27: m² | D27: 16 | E27: 5800 | F27: =+$I$1 -> 0.75 | G27: =ROUNDUP(E27/F27,-1) -> 7740 | H27: =+G27*D27 -> 123840
A28: Q.5.2 | B28: Pool Wall | C28: m² | D28: 20 | E28: 5800 | F28: =+$I$1 -> 0.75 | G28: =ROUNDUP(E28/F28,-1) -> 7740 | H28: =+G28*D28 -> 154800
A30: Q.7 | B30: Pool Tiling Work
A31: Q.7.1 | B31: Pool floor tile | C31: m² | D31: 16 | E31: =+'Rate Breakdowns'!G1326 -> 14232.545 | F31: =+$I$1 -> 0.75 | G31: =ROUNDUP(E31/F31,-1) -> 18980 | H31: =+G31*D31 -> 303680
A32: Q.7.2 | B32: Pool wall tile | C32: m² | D32: 20 | E32: =+'Rate Breakdowns'!G1326 -> 14232.545 | F32: =+$I$1 -> 0.75 | G32: =ROUNDUP(E32/F32,-1) -> 18980 | H32: =+G32*D32 -> 379600
A34: Q.8 | B34: Timber plank Decking at Swimming Pool | C34: m² | D34: 24.63 | E34: 19520 | F34: =+$I$1 -> 0.75 | G34: =ROUNDUP(E34/F34,-1) -> 26030 | H34: =+G34*D34 -> 641118.9
A36: Q.9 | B36: Drain in around pool | C36: m | D36: 17 | E36: 8200 | F36: =+$I$1 -> 0.75 | G36: =ROUNDUP(E36/F36,-1) -> 10940 | H36: =+G36*D36 -> 185980
A38: Q.10 | B38: Water bar | C38: m | D38: =16.5*3 -> 49.5 | E38: 3150 | F38: =+$I$1 -> 0.75 | G38: =ROUNDUP(E38/F38,-1) -> 4200 | H38: =+G38*D38 -> 207900
A40: Q.11 | B40: Pool Equipment including Lightfittings | C40: Item | D40: 1 | E40: 285000 | F40: =+$I$1 -> 0.75 | G40: =ROUNDUP(E40/F40,-1) -> 380000 | H40: =+G40*D40 -> 380000
A42: Q.12 | B42: Testing & Commissioning | C42: Item | D42: 1 | E42: 40000 | F42: =+$I$1 -> 0.75 | G42: =ROUNDUP(E42/F42,-1) -> 53340 | H42: =+G42*D42 -> 53340
A44: Q.13 | B44: Swimming Pool Ladders | C44: Item | D44: 1 | E44: 84000 | F44: =+$I$1 -> 0.75 | G44: =ROUNDUP(E44/F44,-1) -> 112000 | H44: =+G44*D44 -> 112000
A46: Q.14 | B46: Water Sump (250cuft Capacity) | C46: Item | D46: 1 | E46: 1050000 | F46: =+$I$1 -> 0.75 | G46: =ROUNDUP(E46/F46,-1) -> 1400000 | H46: =+G46*D46 -> 1400000
A48: Q.15 | B48: Submasible Pump | C48: Nos | D48: 3 | E48: 78000 | F48: =+$I$1 -> 0.75 | G48: =ROUNDUP(E48/F48,-1) -> 104000 | H48: =+G48*D48 -> 312000
A50: Q.16 | B50: Pressure Pump | C50: Nos | D50: 2 | E50: 65000 | F50: =+$I$1 -> 0.75 | G50: =ROUNDUP(E50/F50,-1) -> 86670 | H50: =+G50*D50 -> 173340
A52: Q.17 | B52: Filter Room /Accessories and Pool pipe network | C52: Ps | D52: 1 | E52: 2200000 | F52: =+$I$1 -> 0.75 | G52: =ROUNDUP(E52/F52,-1) -> 2933340 | H52: =+G52*D52 -> 2933340
B55: V - PROVISIONAL SUM CARRIED TO GRAND SUMMARY | H55: =SUM(H5:H54) -> 8561263.8

Sheet Pantry
A1: Nos | B1: Description | C1: Unit | D1: Qty | E1: COST | F1: OHP% | G1: Rate | H1: Amount | I1: 0.85
A3: 1 | B3: PANTRY CUPBOARD
B5: Eco Board Pantry Cupboard - Bottom
A6: 1.1 | B6: U shape and I shape Bottom Pantry Cupboards with drawers/ rotating shelves (18mm Eco board with structure) With 25 Years Warranty | C6: m | D6: 12 | E6: =12000*3.28 -> 39360 | F6: =+$I$1 -> 0.85 | G6: =ROUNDUP(E6/F6,-1) -> 46310 | H6: =+G6*D6 -> 555720
B8: PANTRY TOP
A9: 1.2 | B9: Black Granite Top (Finished) | C9: Sqm | D9: =4.7*2.5 -> 11.75 | E9: =3200*10.76 -> 34432 | F9: =+$I$1 -> 0.85 | G9: =ROUNDUP(E9/F9,-1) -> 40510 | H9: =+G9*D9 -> 475992.5
A11: 1.3 | B11: Supply and Fixing Electric Hood and 4 Burner Stove. | C11: Item | D11: 1 | H11: 75000
B13: Kitchen Sink
A14: 1.4 | B14: Supply and fix stainless steel (Mat Black) 36"x 18" 0.6mm thick kitchen sink with double bowl of "Seal core" by mascons or approved equivalent with 5 year written warranty from the authorized agent. including Pullout tap and water connection with flexible hose, all complete to working order. (Swan neck tap paid separately.)(Prime cost is Rs. 34,000.00) | C14: Nos | D14: 2 | E14: 38600 | F14: =+$I$1 -> 0.85 | G14: =ROUNDUP(E14/F14,-1) -> 45420 | H14: =+G14*D14 -> 90840
B16: V - PROVISIONAL SUM CARRIED TO GRAND SUMMARY | H16: =SUM(H4:H15) -> 1197552.5

Sheet Rate Breakdowns
A2: EXCAVATION & EARTH WORK
A4: Site Clearing & Removing top soil
A5: Per 1 Sqr
B6: Decription | C6: Unit | D6: Qty | E6: Rate | F6: Amount | G6: Total
B8: Labour | F8: =D8*E8 -> 0
B9: Un/Skilled | C9: Sqr | D9: 10 | E9: 2500 | F9: =D9*E9 -> 25000
B11: Total Labour Cost | F11: =D11*E11 -> 0 | G11: =SUM(F9:F11) -> 25000
B13: Transport (Disposal of Excavated material) | C13: Day | D13: 0.2 | E13: 15000 | F13: =D13*E13 -> 3000 | G13: =+F13 -> 3000
A15: Basic Cost per 10 Sqr | G15: =SUM(G11:G14) -> 28000
A16: Basic Cost per 1 sqr | G16: =G15/10 -> 2800
A17: Basic Cost per 1m2 | G17: =G16/9.29 -> 301.39935
A20: Excavation for foundations depth not exceeding 1.5m (Manual Excavation)
A21: Per 1 Cube
B22: Decription | C22: Unit | D22: Qty | E22: Rate | F22: Amount | G22: Total
B24: Labour | F24: =D24*E24 -> 0
B25: Sub Contractor's Rate | C25: Cube | D25: 1 | E25: 6000 | F25: =D25*E25 -> 6000
B27: Total Labour Cost | F27: =D27*E27 -> 0 | G27: =SUM(F25:F27) -> 6000
A31: Basic Cost per 1 Cube | G31: =G27 -> 6000
A32: Basic Cost per 1 m3 | G32: =G31/2.83 -> 2120.1413
A35: Earth Filling (Excavated material)
A36: Per 1 Cube
B37: Decription | C37: Unit | D37: Qty | E37: Rate | F37: Amount | G37: Total
B38: Consider 12 Cubes
B40: Material
F41: =D41*E41 -> 0
F42: =D42*E42 -> 0
B43: Total Material Cost | F43: =D43*E43 -> 0 | G43: =SUM(F40:F43) -> 0
B44: Labour
B45: Un/Skilled Labour for levelling & Compaction | C45: Days | D45: 4 | E45: 2500 | F45: =D45*E45 -> 10000
B47: Total Labour Cost | F47: =D47*E47 -> 0 | G47: =SUM(F45:F47) -> 10000
B48: Plant & Machinery
B50: Jumping Compactor | C50: hr | D50: 24 | E50: 625 | F50: =D50*E50 -> 15000
B52: Total Plant & Machinery Cost | F52: =D52*E52 -> 0 | G52: =SUM(F49:F52) -> 15000
A55: Basic Cost per 12 Cube | G55: =G43+G47+G52 -> 25000
A56: Basic Cost per 1 Cube | G56: =G55/12 -> 2083.3333
A57: Basic Cost per 1 m3 | G57: =G56/2.83 -> 736.16019
A63: Imported Soil Filling
A64: Per 1 Cube
B65: Decription | C65: Unit | D65: Qty | E65: Rate | F65: Amount | G65: Total
B66: Consider 12 Cubes
B68: Material
B69: Cost of Imported Soil Transport to Site | C69: Cube | D69: 12 | E69: =Material!E23 -> 8000 | F69: =D69*E69 -> 96000
B70: 35% of Additional Soil for Compaction | F70: =F69*35% -> 33600
F71: =D71*E71 -> 0
F72: =D72*E72 -> 0
B73: Total Material Cost | F73: =D73*E73 -> 0 | G73: =SUM(F68:F73) -> 129600
B74: Labour | F74: =D74*E74 -> 0
B75: Un/Skilled Labour for levelling & Compaction | C75: Days | D75: 3 | E75: 2500 | F75: =D75*E75 -> 7500
B77: Total Labour Cost | F77: =D77*E77 -> 0 | G77: =SUM(F75:F77) -> 7500
B78: Plant & Machinery
B80: Jumping Compactor | C80: hr | D80: 24 | E80: 625 | F80: =D80*E80 -> 15000
B82: Total Plant & Machinery Cost | F82: =D82*E82 -> 0 | G82: =SUM(F79:F82) -> 15000
A85: Basic Cost per 12 Cube | G85: =G73+G77+G82 -> 152100
A86: Basic Cost per 1 Cube | G86: =G85/12 -> 12675
A87: Basic Cost per 1 m3 | G87: =G86/2.83 -> 4478.7986
A90: Qurry Dust Filling
A91: Per 1 Cube
B92: Decription | C92: Unit | D92: Qty | E92: Rate | F92: Amount | G92: Total
B93: Consider 12 Cubes
B95: Material
B96: Cost of Qurry Dust Transport to Site | C96: Cube | D96: 5 | E96: =+Material!E24 -> 17000 | F96: =D96*E96 -> 85000
B97: 10% of Additional Quarry Dust for Compaction | F97: =F96*10% -> 8500
F98: =D98*E98 -> 0
F99: =D99*E99 -> 0
B100: Total Material Cost | F100: =D100*E100 -> 0 | G100: =SUM(F95:F100) -> 93500
B101: Labour | F101: =D101*E101 -> 0
B102: Un/Skilled Labour for levelling & Compaction | C102: Days | D102: 3 | E102: 2500 | F102: =D102*E102 -> 7500
B104: Total Labour Cost | F104: =D104*E104 -> 0 | G104: =SUM(F102:F104) -> 7500
B105: Plant & Machinery
B107: JCB with Operator | C107: hr | D107: 3 | E107: 7000 | F107: =D107*E107 -> 21000
B108: Jumping Compactor | C108: hr | D108: 10 | E108: 625 | F108: =D108*E108 -> 6250
B110: Total Plant & Machinery Cost | F110: =D110*E110 -> 0 | G110: =SUM(F106:F110) -> 27250
A113: Basic Cost per 12 Cube | G113: =G100+G104+G110 -> 128250
A114: Basic Cost per 1 Cube | G114: =G113/12 -> 10687.5
A115: Basic Cost per 1 m3 | G115: =G114/2.83 -> 3776.5018
A120: Dam Proof Membrane ; Gauge 1000 Polythene
A121: Per 1 Sqr
B122: Decription | C122: Unit | D122: Qty | E122: Rate | F122: Amount | G122: Total
B124: Material
B125: Gauge 1000 polythene | C125: Kg | D125: 2.5 | E125: =Material!E63 -> 650 | F125: =D125*E125 -> 1625
F128: =D128*E128 -> 0
B129: Total Material Cost | F129: =D129*E129 -> 0 | G129: =SUM(F124:F129) -> 1625
B130: Labour | F130: =D130*E130 -> 0
B131: Laying | C131: ft2 | D131: 100 | E131: 5 | F131: =D131*E131 -> 500
B133: Total Labour Cost | F133: =D133*E133 -> 0 | G133: =SUM(F131:F133) -> 500
A136: Basic Cost per 1 Sqr | G136: =G129+G133 -> 2125
A137: Basic Cost per 1 m2 | G137: =G136/9.29 -> 228.74058
A138: Basic Cost per 1 ft2 | G138: =G137/10.76 -> 21.258418
A140: 3/4" thick D.P.C. in cement sand 1:3 finished with 2 coats of D.P.C. tar and blinded with sand.
A141: Per 1 Sqr
B142: Decription | C142: Unit | D142: Qty | E142: Rate | F142: Amount | G142: Total
B144: Material
B145: Cement | C145: Bag | D145: 0.8 | E145: =+F197 -> 2235.625 | F145: =D145*E145 -> 1788.5
B146: Sand | C146: Sand | D146: 0.03 | E146: =+Material!E13 -> 23500 | F146: =D146*E146 -> 705
B148: Bitumix (20 L 18,500 LKR) | C148: Lit | D148: 3.5 | E148: 925 | F148: =+E148*D148 -> 3237.5
B151: Total Material Cost | G151: =SUM(F144:F151) -> 5731
B152: Labour
B153: Laying | C153: ft2 | D153: 100 | E153: 5 | F153: =D153*E153 -> 500
B155: Total Labour Cost | F155: =D155*E155 -> 0 | G155: =SUM(F153:F155) -> 500
A158: Basic Cost per 1 Sqr | G158: =G151+G155 -> 6231
...

Sheet roof
A1: Item | B1: Description | C1: Qty | D1: Unit | E1: COST | F1: OHP% | G1: Rate | H1: Amount ( Rs.) | I1: =+summary!#REF! -> #REF!
A2: 1 | B2: Q - ROOFING AND CEILING
A4: =A2+0.01 -> 1.01 | B4: Supplying fabrication and erection of roof, rate to include to roof structure, roof plumbing work and roof covering work and finished as per the detail drawings and design | C4: 117 | D4: Sqm | E4: =(1300+180)*10.76 -> 15924.8 | F4: =+I1 -> #REF! | G4: =ROUNDUP(E4/F4,-1) -> #REF! | H4: =+G4*C4 -> #REF!
B7: ROOFING AND CEILING WORK CARRIED TO COLLECTION | H7: =SUM(H2:H6) -> #REF!

Sheet mis
A1: Nos | B1: Description | C1: Qty | D1: Unit | E1: COST | F1: OHP% | G1: Rate | H1: Amount | I1: =+summary!D18 -> 0.75
A2: 1 | B2: V-MISSLENIOUS WORK
A4: =A2+0.01 -> 1.01 | B4: Outdoor Flatform Work
B5: Construction of outdoor flatform work, main structure complete with 100mmx75mm sectional size I section and cladded with Treated Teak planks and applying of suitable coats of wood presavative and enemal paints and complete as per the design (item price include to stiars) | C5: 13 | D5: Sqm | E5: 40300 | F5: =+$I$1 -> 0.75 | G5: =ROUNDUP(E5/F5,-1) -> 53740 | H5: =+G5*C5 -> 698620
B7: V - MISSLENIOUS WORK CARRIED TO GRAND SUMMARY | H7: =SUM(H5:H6) -> 698620

Sheet Material
A2: BUILDING SCHEDULE OF RATES
A4: PRICES OF MATERIAL & TOOLS
K5: 719041540
A6: Item | B6: Description | C6: Unit | D6: Rate without Transport | E6: Rate with Transport | F6: Remarks | G6: Transporting Price
B8: Materials | L8: Lanwa | M8: 2100 | N8: 1920
L9: Ultratech | M9: 2200 | N9: 2050
B10: Cement ( 50 Kg ) | C10: Bags | D10: 2100 | G10: =E10-D10 -> -2100 | L10: tokyo santha | M10: 2200 | N10: 2050
G11: =E11-D11 -> 0
B12: Sand
B13: River Sand | C13: Cube | E13: 23500 | G13: =E13-D13 -> 23500 | H13: 1080 | I13: 800 | L13: 10mm | M13: 1274
B14: Sea Sand | C14: Cube | G14: =E14-D14 -> 0
B15: Wash Sand | C15: Cube | G15: =E15-D15 -> 0
M16: 6mm | N16: 10mm | O16: 12mm | P16: 16mm | Q16: 20mm | S16: =16*16 -> 256 | T16: =S16/162.162 -> 1.5786682
B17: 3/4" Metal | C17: Cube | E17: 13500 | N17: 1274 | O17: 1879 | P17: 3370
B18: 1" Metal | C18: Cube
B20: 6" x 9" Rubble | C20: Cube | E20: 14500 | L20: Binding wire | M20: 380
B21: 6" x 4" Rubble | C21: Cube
M22: 150 | N22: 17400
B23: Imported Soil | C23: Cube | E23: 8000
B24: Quarry Dust | C24: Cube | E24: 17000
B25: ABC | C25: Cube
B28: Reinforcement | S28: =20*20 -> 400 | T28: =S28/162.162 -> 2.4666691
B29: Tor Steel | L29: Lanwa | N29: 1285 | O29: 1895 | P29: 3397 | Q29: 5374
B30: Lanwa | C30: Ton | D30: 365000 | K30: =363059.05*1.15 -> 417517.91 | L30: 363059.05
B31: Melwa | C31: Ton
B32: GTB | C32: Ton | N32: 0.617 | O32: 0.888 | P32: 1.579 | Q32: 2.467
B33: RS | C33: Ton | N33: =N32*6 -> 3.702 | O33: =O32*6 -> 5.328 | P33: =P32*6 -> 9.474 | Q33: =Q32*6 -> 14.802
N35: =N29/N33 -> 347.10967 | O35: =O29/O33 -> 355.66817 | P35: =P29/P33 -> 358.56027 | Q35: =Q29/Q33 -> 363.05905
B36: 16 BWG Binding Wire | C36: Lbs | D36: 360
B39: Water Proofing | C39: Gals | E39: 10
B40: Bitumix ( 20L ) | C40: Ltr | E40: 650
B41: Finex Motar Plus (Plasticiser) | C41: Ltr | E41: =300*1.15 -> 345 | L41: 10 Litre - Rs.2350 +VAT | M41: =2350*1.15 -> 2702.5
M42: =M41/10 -> 270.25
B44: BRICKS
B46: Engineering Brick 200mm x 100mm x 50mm
B47: Engineering Brick 200mm x 150mm x 75mm (6") thk.
B50: BLOCKS
B51: Solid Block 390 x 190 x 100mm | C51: nr
B52: Solid Block 390 x 190 x 150mm | C52: nr
B53: Solid Block 390 x 190 x 120mm | C53: nr
B55: Hollow Block 390 x 190 x 100mm | C55: nr
B56: Hollow Block 390 x 190 x 150mm | C56: nr
B57: Hollow Block 390 x 190 x 120mm | C57: nr
B59: Skim Coat
B60: Sand Papers
B61: Chiken mesh ( 1 x 3.33 ) | C61: L.ft | E61: 230 | L61: =12*7 -> 84
B62: 50 x 50 GI Mesh | C62: ft²
B63: Gauge 1000 polythene | C63: Kg | E63: 650
B65: BRC mesh (12'x7')
B66: 2"x2" | C66: item | D66: 6500 | E66: 7500 | K66: 84ft2
B67: 6"x6" | C67: item | D67: 10500 | E67: 11500
B68: 8"x8" | C68: item | D68: 8500 | E68: 9500
M69: Supreme Readymix | N69: Tokyo | O69: Prema
B70: Redy Mix Concrete | L70: G.15
L71: G.20
B72: G15 | E72: 27000 | F72: Supreme Readymix
B73: G20 | E73: 28000 | F73: Supreme Readymix
B74: G25 | E74: 29000 | F74: Supreme Readymix | L74: G.25
B75: Pump Car (25m3) Additional 1m3 - Rs.1500 | E75: 45000 | F75: Supreme Readymix | L75: G.30
E77: 45000 | F77: 15000
B78: Plywood Board
B79: 15mm thk 8'x4' non-coated Plywood board | C79: Nrs | E79: 4500
B80: 15mm thk 8'x4' coated Plywood board | C80: Nrs
B81: 16mm thk 8'x4' coated Plywood board | C81: Nrs | E81: 5500
B83: Mould oil | C83: Ltrs | E83: 100
B85: Class I timber
B86: 1" Class I timber planks | C86: Sq.ft | E86: 172
B87: 1" timber base plate to props | C87: Sq.ft | E87: 150
B88: 1 1/2" Class I planks | C88: Sq.ft
B89: 1" Class II timber | C89: Sq.ft | E89: 140
B90: 6"x3/4" Lunumidella Ceiling planks | C90: Sq.ft
B91: 2"x1" Class I reepers | C91: L.ft
B92: 2"x2" Class I timber | C92: L.ft | E92: 55
B93: 4"x2" Class I timber | C93: L.ft | E93: 85
B94: 4"x3" Class I timber | C94: L.ft
B95: 2"x2" Class II timber in yokes | C95: L.ft | E95: 50
B96: 2"x1" Class II timber batterns | C96: L.ft | E96: 30
B97: 2"x2" Class II Ledges | C97: L.ft | E97: 50
B98: 4"x2" Class II bearers | C98: L.ft | E98: 85
B99: 4"x2" Class II timber props | C99: L.ft | E99: 85
B100: 2"x2" Halmilla cove moulding | C100: L.ft
B101: 1 1/2"x1 1/2" Halmilla beading | C101: L.ft
B102: Props | C102: Nrs | E102: 200
B104: Brick
B106: Wirecut Bricks | C106: Nrs
B107: Brick Size 212.5mm x 100mm x 50mm ( 9" ) | C107: Nrs | E107: 18 | F107: Hashan (Wellawaya Brick Supplier) | K107: 13
B108: Brick Size 212.5mm x 150mm x 75mm ( 6" ) | C108: Nrs | E108: 38 | K108: 30
G109: =E109-D109 -> 0 | T109: with loading & unloading (AMTRAD limited prices)
B110: Bloock | G110: =E110-D110 -> 0 | L110: Size | M110: LHP | N110: Amtrad | O110: Wapco | P110: Sachindra
B111: 390x190x100mm Solid block | C111: Nr | D111: 156 | F111: LH Piyasena | G111: =E111-D111 -> -156 | L111: 390x190x100mm Solid block | M111: 156
B112: 390x190x150mm Solid block | C112: Nr | D112: 231 | F112: LH Piyasena | G112: =E112-D112 -> -231 | L112: 390x190x150mm Solid block | M112: 231
B113: 390x190x200mm Solid block | C113: Nr | D113: 308 | F113: LH Piyasena | G113: =E113-D113 -> -308 | L113: 390x190x200mm Solid block | M113: 308
B115: 390x190x100mm Hollow block | C115: Nr | D115: 109 | F115: LH Piyasena | L115: 390x190x100mm Hollow block | M115: 109
B116: 390x190x150mm Hollow block | C116: Nr | D116: 168 | F116: LH Piyasena | G116: =E116-D116 -> -168 | L116: 390x190x150mm Hollow block | M116: 168
B117: 390x190x200mm Hollow block | C117: Nr | D117: 237 | F117: LH Piyasena | G117: =E117-D117 -> -237 | L117: 390x190x200mm Hollow block | M117: 237
B119: Tile
B120: 2x2 Glazed Floor tile | C120: Nrs
B121: 3x3 Glazed Floor tile | C121: Nrs
B122: 4x4 Glazed Floor tile | C122: Nrs
B123: 6x6 Glazed Floor tile | C123: Nrs
...

Sheet m shet Miss premila
A1: NO | B1: DESCRIPTION | C1: NOS | F1: LENGTH | G1: WIDTH | H1: HEIGHT | I1: QTY | J1: T.QTY | O1: UNIT
K2: 1.05
A3: =exca!A5 -> B 01 | B3: =exca!B5 -> Clearing site vegetation manually including removal of bushes, shurb removing rubbish. | J3: =I3 -> 0 | K3: =$K$2 -> 1.05 | L3: =K3*J3 -> 0 | M3: =ROUND(L3,1) -> 0 | N3: =ROUNDUP(M3,0) -> 0 | O3: m2 | P3: 1.1
A5: =exca!A7 -> B 02 | B5: =exca!B7 -> Removing top soil including mud, machinery to a nessasary depth and removing all debris away from site, location decided by client withing 3 km | J5: =I5 -> 0 | K5: =$K$2 -> 1.05 | L5: =K5*J5 -> 0 | M5: =ROUND(L5,1) -> 0 | N5: =ROUNDUP(M5,0) -> 0 | O5: m2
A7: =exca!A17 -> B 03 | B7: =exca!B17 -> Excavation for column, wall, staircase foundations in any material (except rock requiring blasting) up to depth (as per the drawings), part return fill in and ram and surplus depositted within site as directed. | D7: F1 | E7: 1 | F7: 0.9 | G7: 1.2 | H7: =0.75+0.75 -> 1.5 | I7: =H7*G7*F7*E7 -> 1.62 | P7: =E7*F7*G7 -> 1.08
D8: F2 | E8: 3 | F8: 1.65 | G8: 1.65 | H8: =0.75+0.75 -> 1.5 | I8: =H8*G8*F8*E8 -> 12.25125 | Q8: =SUM(E8:E17) -> 20
D9: F3 | E9: 3 | F9: 1.98 | G9: 1.98 | H9: =0.75+0.75 -> 1.5 | I9: =H9*G9*F9*E9 -> 17.6418 | Q9: =Q8*0.3*0.3*0.75 -> 1.35
D10: F4 | E10: 2 | F10: 1.1 | G10: 1.5 | H10: =0.75+0.75 -> 1.5 | I10: =H10*G10*F10*E10 -> 4.95
D11: F5 | E11: 3 | F11: 1.45 | G11: 1.45 | H11: =0.75+0.75 -> 1.5 | I11: =H11*G11*F11*E11 -> 9.46125
D12: F6 | E12: 1 | F12: 1.25 | G12: 2.3 | H12: =0.75+0.75 -> 1.5 | I12: =H12*G12*F12*E12 -> 4.3125
D13: F7 | E13: 1 | F13: 3.36 | G13: 2.16 | H13: =0.75+0.75 -> 1.5 | I13: =H13*G13*F13*E13 -> 10.8864
D14: F8 | E14: 2 | F14: 1.1 | G14: 1.1 | H14: =0.75+0.75 -> 1.5 | I14: =H14*G14*F14*E14 -> 3.63
D15: F9 | E15: 1 | F15: 1.8 | G15: 1.8 | H15: =0.75+0.75 -> 1.5 | I15: =H15*G15*F15*E15 -> 4.86
D16: 1 | E16: 2 | F16: 12.5 | G16: 0.75 | H16: =0.45+0.75 -> 1.2 | I16: =H16*G16*F16*E16 -> 22.5 | P16: =F16*E16 -> 25
E17: 2 | F17: 13.9 | G17: 0.75 | H17: =0.45+0.75 -> 1.2 | I17: =H17*G17*F17*E17 -> 25.02 | P17: =F17*E17 -> 27.8 | Q17: =P16+P17 -> 52.8 | R17: =Q17*1*0.35 -> 18.48
J18: =SUM(I7:I18) -> 117.1332 | K18: =$K$2 -> 1.05 | L18: =K18*J18 -> 122.98986 | M18: =ROUND(L18,1) -> 123 | N18: =ROUNDUP(M18,0) -> 123 | O18: m3
A21: =exca!A29 -> B 06 | B21: =exca!B28 -> Back Filling | I21: 20 | J21: =SUM(I21) -> 20 | K21: =$K$2 -> 1.05 | L21: =K21*J21 -> 21 | M21: =ROUND(L21,1) -> 21 | N21: =ROUNDUP(M21,0) -> 21 | O21: m3
A23: =exca!A34 -> 0 | B23: =exca!B33 -> Antitermite -Tretement | J23: =SUM(I23) -> 0 | K23: =$K$2 -> 1.05 | L23: =K23*J23 -> 0 | M23: =ROUND(L23,1) -> 0 | N23: =ROUNDUP(M23,0) -> 0 | O23: m2
A25: =concrete!A7 -> C 01 | B25: =concrete!B7 -> Cement concrete 1:3:6 (1") laid to a thickness of 2" in wall foundations, under column/stair footings,plinth beams including placing in position,compacting and curing.
R30: =1500-710-690 -> 100
Q38: =I38/100 -> 0
Q39: =Q38*9.29 -> 0
Q44: =SUM(I33:I36) -> 0
Q45: =SUM(I38:I47) -> 0
Q46: =Q44+Q45 -> 0
J64: =SUM(I25:I64) -> 0 | K64: =$K$2 -> 1.05 | L64: =K64*J64 -> 0 | M64: =ROUND(L64,1) -> 0 | N64: =ROUNDUP(M64,0) -> 0 | O64: m3
A66: =concrete!A15 -> C2.1 | B66: =concrete!B15 -> In column/strip footing
J77: =SUM(I66:I77) -> 0 | K77: =$K$2 -> 1.05 | L77: =K77*J77 -> 0 | M77: =ROUND(L77,1) -> 0 | N77: =ROUNDUP(M77,0) -> 0 | O77: m3
A79: =concrete!A16 -> C2.2 | B79: =concrete!B16 -> In column shaft
J96: =SUM(I79:I96) -> 0 | K96: =$K$2 -> 1.05 | L96: =K96*J96 -> 0 | M96: =ROUND(L96,1) -> 0 | N96: =ROUNDUP(M96,0) -> 0 | O96: m3
A98: =concrete!A17 -> C2.3 | B98: =concrete!B17 -> In plinth Beams
J104: =SUM(I98:I104) -> 0 | K104: =$K$2 -> 1.05 | L104: =K104*J104 -> 0 | M104: =ROUND(L104,1) -> 0 | N104: =ROUNDUP(M104,0) -> 0 | O104: m3
A106: =concrete!A22 -> C3.1 | B106: =concrete!B22 -> Ground floor concrete(75mm thick) | J106: =SUM(I106) -> 0 | K106: =$K$2 -> 1.05 | L106: =K106*J106 -> 0 | M106: =ROUND(L106,1) -> 0 | N106: =ROUNDUP(M106,0) -> 0 | O106: m3
A108: =concrete!A34 -> C4.1 | B108: =concrete!B34 -> In column shaft from ground floor level to First floor level
J125: =SUM(I108:I125) -> 0 | K125: =$K$2 -> 1.05 | L125: =K125*J125 -> 0 | M125: =ROUND(L125,1) -> 0 | N125: =ROUNDUP(M125,0) -> 0 | O125: m3
A127: =concrete!A47 -> C5.1 | B127: =concrete!B47 -> In Reinforced beam at First floor level | D127: 1B5 | E127: 1 | F127: 13.2 | G127: 0.225 | H127: 0.45 | I127: =H127*G127*F127*E127 -> 1.3365 | L127: =K127*J127 -> 0 | M127: =ROUND(L127,1) -> 0 | N127: =ROUNDUP(M127,0) -> 0
D128: 1B1 | E128: 1 | F128: 10.5 | G128: 0.225 | H128: 0.45 | I128: =H128*G128*F128*E128 -> 1.063125 | L128: =K128*J128 -> 0 | M128: =ROUND(L128,1) -> 0 | N128: =ROUNDUP(M128,0) -> 0
D129: 1B2 | E129: 1 | F129: 6.15 | G129: 0.225 | H129: 0.6 | I129: =H129*G129*F129*E129 -> 0.83025 | L129: =K129*J129 -> 0 | M129: =ROUND(L129,1) -> 0 | N129: =ROUNDUP(M129,0) -> 0
D130: 1B4 | E130: 1 | F130: 12.95 | G130: 0.225 | H130: 0.6 | I130: =H130*G130*F130*E130 -> 1.74825 | L130: =K130*J130 -> 0 | M130: =ROUND(L130,1) -> 0 | N130: =ROUNDUP(M130,0) -> 0
D131: 1B3 | E131: 1 | F131: 3.88 | G131: 0.225 | H131: 0.45 | I131: =H131*G131*F131*E131 -> 0.39285 | L131: =K131*J131 -> 0 | M131: =ROUND(L131,1) -> 0 | N131: =ROUNDUP(M131,0) -> 0
D132: 1B6 | E132: 1 | F132: 13.35 | G132: 0.225 | H132: 0.45 | I132: =H132*G132*F132*E132 -> 1.3516875 | L132: =K132*J132 -> 0 | M132: =ROUND(L132,1) -> 0 | N132: =ROUNDUP(M132,0) -> 0
D133: 1B7 | E133: 1 | F133: 8.225 | G133: 0.225 | H133: 0.45 | I133: =H133*G133*F133*E133 -> 0.83278125 | L133: =K133*J133 -> 0 | M133: =ROUND(L133,1) -> 0 | N133: =ROUNDUP(M133,0) -> 0
D134: 1B8 | E134: 1 | F134: 0.9 | G134: 0.225 | H134: 0.45 | I134: =H134*G134*F134*E134 -> 0.091125 | L134: =K134*J134 -> 0 | M134: =ROUND(L134,1) -> 0 | N134: =ROUNDUP(M134,0) -> 0
D135: 1B9 | E135: 1 | F135: 3.775 | G135: 0.225 | H135: 0.45 | I135: =H135*G135*F135*E135 -> 0.38221875 | L135: =K135*J135 -> 0 | M135: =ROUND(L135,1) -> 0 | N135: =ROUNDUP(M135,0) -> 0
D136: 1B10 | E136: 1 | F136: 4.55 | G136: 0.225 | H136: 0.3 | I136: =H136*G136*F136*E136 -> 0.307125 | L136: =K136*J136 -> 0 | M136: =ROUND(L136,1) -> 0 | N136: =ROUNDUP(M136,0) -> 0
D137: 1B11 | E137: 1 | F137: 0.9 | G137: 0.225 | H137: 0.45 | I137: =H137*G137*F137*E137 -> 0.091125 | J137: =SUM(I127:I145) -> 11.041538 | K137: =$K$2 -> 1.05 | L137: =K137*J137 -> 11.593614 | M137: =ROUND(L137,1) -> 11.6 | N137: =ROUNDUP(M137,0) -> 12 | O137: m3
D138: 1B12 | E138: 1 | F138: 10.8 | G138: 0.225 | H138: 0.45 | I138: =H138*G138*F138*E138 -> 1.0935
D139: 1B13 | E139: 1 | F139: 4.8 | G139: 0.225 | H139: 0.3 | I139: =H139*G139*F139*E139 -> 0.324
D140: 1B14 | E140: 1 | F140: 4 | G140: 0.225 | H140: 0.45 | I140: =H140*G140*F140*E140 -> 0.405
D141: 1B1a | E141: 2 | F141: 0.675 | G141: 0.225 | H141: 0.45 | I141: =H141*G141*F141*E141 -> 0.1366875
D142: Curb | E142: 3 | F142: 2.39 | G142: 0.075 | H142: 0.225 | I142: =H142*G142*F142*E142 -> 0.12099375
E143: 1 | F143: 3.45 | G143: 0.075 | H143: 0.225 | I143: =H143*G143*F143*E143 -> 0.05821875
E144: 2 | F144: 4.04 | G144: 0.15 | H144: 0.2 | I144: =H144*G144*F144*E144 -> 0.2424
E145: 2 | F145: 3.895 | G145: 0.15 | H145: 0.2 | I145: =H145*G145*F145*E145 -> 0.2337
A147: =concrete!A48 -> C5.2 | B147: =concrete!B48 -> In Reinforced beam at second floor level | D147: 2B1 | E147: 1 | F147: 10.5 | G147: 0.225 | H147: 0.3 | I147: =H147*G147*F147*E147 -> 0.70875
D148: 2B2 | E148: 1 | F148: 6.15 | G148: 0.3 | H148: 0.6 | I148: =H148*G148*F148*E148 -> 1.107
D149: 2B3 | E149: 1 | F149: 3.875 | G149: 0.3 | H149: 0.45 | I149: =H149*G149*F149*E149 -> 0.523125
D150: 2B4 | E150: 1 | F150: 10.27 | G150: 0.225 | H150: 0.6 | I150: =H150*G150*F150*E150 -> 1.38645
D151: 2B5 | E151: 1 | F151: 10.15 | G151: 0.225 | H151: 0.45 | I151: =H151*G151*F151*E151 -> 1.0276875
D152: 2B6 | E152: 1 | F152: 11.95 | G152: 0.225 | H152: 0.45 | I152: =H152*G152*F152*E152 -> 1.2099375
D153: 2B7 | E153: 1 | F153: 10.8 | G153: 0.225 | H153: 0.45 | I153: =H153*G153*F153*E153 -> 1.0935
D154: 2B8 | E154: 1 | F154: =0.9+10.8 -> 11.7 | G154: 0.225 | H154: 0.45 | I154: =H154*G154*F154*E154 -> 1.184625
D155: 2B9 | E155: 1 | F155: 10.8 | G155: 0.225 | H155: 0.3 | I155: =H155*G155*F155*E155 -> 0.729
D156: CURB | E156: 1 | F156: =4.725 -> 4.725 | G156: 0.15 | H156: 0.225 | I156: =H156*G156*F156*E156 -> 0.15946875
E157: 2 | F157: 3 | G157: 0.225 | H157: 0.1 | I157: =H157*G157*F157*E157 -> 0.135
E158: 1 | F158: 4 | G158: 0.1 | H158: 0.225 | I158: =H158*G158*F158*E158 -> 0.09 | J158: =SUM(I147:I158) -> 9.3545438 | K158: =$K$2 -> 1.05 | L158: =K158*J158 -> 9.8222709 | M158: =ROUND(L158,1) -> 9.8 | N158: =ROUNDUP(M158,0) -> 10 | O158: m3
A160: =concrete!A49 -> C5.3 | B160: =concrete!B49 -> In Reinforced beam at Terrace floor level (with Swimming Pool) | D160: 3B1 | E160: 1 | F160: 7.1 | G160: 0.225 | H160: 0.3 | I160: =H160*G160*F160*E160 -> 0.47925
D161: 3B2 | E161: 1 | F161: 5.15 | G161: 0.225 | H161: 0.45 | I161: =H161*G161*F161*E161 -> 0.5214375
D162: 3B3 | E162: 1 | F162: 3.7 | G162: 0.225 | H162: 0.45 | I162: =H162*G162*F162*E162 -> 0.374625
D163: 3B4 | E163: 1 | F163: 6.05 | G163: 0.225 | H163: 0.45 | I163: =H163*G163*F163*E163 -> 0.6125625
D164: 3B5 | E164: 1 | F164: 2.45 | G164: 0.225 | H164: 0.3 | I164: =H164*G164*F164*E164 -> 0.165375
D165: 3B6 | E165: 1 | F165: 4.9 | G165: 0.225 | H165: 0.45 | I165: =H165*G165*F165*E165 -> 0.496125
D166: 3B7 | E166: 1 | F166: 2.45 | G166: 0.225 | H166: 0.3 | I166: =H166*G166*F166*E166 -> 0.165375
D167: 3B8 | E167: 1 | F167: 3.125 | G167: 0.225 | H167: 0.3 | I167: =H167*G167*F167*E167 -> 0.2109375
D168: 3B9 | E168: 1 | F168: 3 | G168: 0.225 | H168: 0.3 | I168: =H168*G168*F168*E168 -> 0.2025
D169: 3B10 | E169: 1 | F169: 0.9 | G169: 0.225 | H169: 0.45 | I169: =H169*G169*F169*E169 -> 0.091125 | J169: =SUM(I160:I169) -> 3.3193125 | K169: =$K$2 -> 1.05 | L169: =K169*J169 -> 3.4852781 | M169: =ROUND(L169,1) -> 3.5 | N169: =ROUNDUP(M169,0) -> 4 | O169: m3
A171: =concrete!A52 -> C5.5 | B171: =concrete!B52 -> In Reinforced slab at First floor level | F171: 131 | H171: 0.125 | I171: =H171*F171 -> 16.375 | J171: =SUM(I171) -> 16.375 | K171: =$K$2 -> 1.05 | L171: =K171*J171 -> 17.19375 | M171: =ROUND(L171,1) -> 17.2 | N171: =ROUNDUP(M171,0) -> 18 | O171: m3
A173: =concrete!A53 -> C5.6 | B173: =concrete!B53 -> In Reinforced Slab at second floor level | F173: 108 | H173: 0.125 | I173: =H173*F173 -> 13.5 | J173: =SUM(I173) -> 13.5 | K173: =$K$2 -> 1.05 | L173: =K173*J173 -> 14.175 | M173: =ROUND(L173,1) -> 14.2 | N173: =ROUNDUP(M173,0) -> 15 | O173: m3
A175: =concrete!A54 -> C5.7 | B175: =concrete!B54 -> In Reinforced slab at Terrace floor level (with Swimming Pool) | F175: 32 | H175: 0.15 | I175: =H175*F175 -> 4.8 | J175: =SUM(I175) -> 4.8 | K175: =$K$2 -> 1.05 | L175: =K175*J175 -> 5.04 | M175: =ROUND(L175,1) -> 5 | N175: =ROUNDUP(M175,0) -> 5
A177: =concrete!A69 -> D 02 | B177: =concrete!B70 -> Plinth beam
J183: =SUM(I177:I183) -> 0 | K183: =$K$2 -> 1.05 | L183: =K183*J183 -> 0 | M183: =ROUND(L183,1) -> 0 | N183: =ROUNDUP(M183,0) -> 0 | O183: m2
B185: =concrete!B71 -> Column base
J196: =SUM(I185:I196) -> 0 | K196: =$K$2 -> 1.05 | L196: =K196*J196 -> 0 | M196: =ROUND(L196,1) -> 0 | N196: =ROUNDUP(M196,0) -> 0 | O196: m2
B198: =concrete!B72 -> Column Stub
J233: =SUM(I198:I233) -> 0 | K233: =$K$2 -> 1.05 | L233: =K233*J233 -> 0 | M233: =ROUND(L233,1) -> 0 | N233: =ROUNDUP(M233,0) -> 0 | O233: m2
A235: =concrete!A76 -> D 3.1 | B235: =concrete!B76 -> In column from ground floor level to First floor level
A272: =concrete!A89 -> D 4.1 | B272: =concrete!B89 -> In Slab at First floor level | F272: =F171 -> 131 | I272: =SUM(F272) -> 131 | J272: =SUM(I272) -> 131 | K272: =$K$2 -> 1.05 | L272: =K272*J272 -> 137.55 | M272: =ROUND(L272,1) -> 137.6 | N272: =ROUNDUP(M272,0) -> 138 | O272: m2
A274: =concrete!A90 -> D 4.2 | B274: =concrete!B90 -> In Slab at second floor level | F274: =F173 -> 108 | I274: =SUM(F274:H274) -> 108 | J274: =SUM(I274) -> 108 | K274: =$K$2 -> 1.05 | L274: =K274*J274 -> 113.4 | M274: =ROUND(L274,1) -> 113.4 | N274: =ROUNDUP(M274,0) -> 114 | O274: m2
A276: =concrete!A91 -> D 4.3 | B276: =concrete!B91 -> In Slab at Terrace floor level (with Swimming Pool) | F276: =F175 -> 32 | I276: =SUM(F276:H276) -> 32 | J276: =SUM(I276) -> 32 | K276: =$K$2 -> 1.05 | L276: =K276*J276 -> 33.6 | M276: =ROUND(L276,1) -> 33.6 | N276: =ROUNDUP(M276,0) -> 34 | O276: m2
A278: =concrete!A95 -> D 5.1 | B278: =concrete!B95 -> In beam at First floor level | D278: 1B5 | E278: 1 | F278: 13.2 | H278: 0.45 | I278: =F278*H278*E278 -> 5.94
E279: 2 | F279: 13.2 | H279: 0.225 | I279: =F279*H279*E279 -> 5.94
D280: 1B1 | E280: 1 | F280: 10.5 | H280: 0.45 | I280: =F280*H280*E280 -> 4.725
E281: 2 | F281: 10.5 | H281: 0.225 | I281: =F281*H281*E281 -> 4.725
D282: 1B2 | E282: 1 | F282: 6.15 | H282: 0.6 | I282: =F282*H282*E282 -> 3.69
E283: 2 | F283: 6.15 | H283: 0.225 | I283: =F283*H283*E283 -> 2.7675
D284: 1B4 | E284: 1 | F284: 12.95 | H284: 0.6 | I284: =F284*H284*E284 -> 7.77
E285: 2 | F285: 12.95 | H285: 0.225 | I285: =F285*H285*E285 -> 5.8275
D286: 1B3 | E286: 1 | F286: 3.88 | H286: 0.45 | I286: =F286*H286*E286 -> 1.746
E287: 2 | F287: 3.88 | H287: 0.225 | I287: =F287*H287*E287 -> 1.746
D288: 1B6 | E288: 1 | F288: 13.35 | H288: 0.45 | I288: =F288*H288*E288 -> 6.0075
...

Sheet Sheet7
H5: Long | J5: short
G7: anagathe vadi vei | J7: anagathedi aduvei

Sheet Sheet4

Sheet Sheet5

Sheet rf
A1: PROPSED THREE STORY LIBREARY BUILDING FOR MINUWANGODA URBAN COUNCIL MINUWANGODA.
A3: Nos | B3: Description | C3: Qty | D3: Unit | E3: Rate | F3: Amount
B4: E - REINFORCEMENT
A5: E 01 | B5: Mild steel reinforcement to slabs, beams, lintols, columns, footings & etc.. bent to shape, laid in position and tied with 16 B.W.G. Aneal binding wire up to Dpc .
A6: E1.1 | B6: In column shaft | D6: Kg | E6: 192 | F6: =+C6*E6 -> 0
A7: E1.2 | B7: In Tie Beams | D7: Kg | E7: 192 | F7: =+C7*E7 -> 0
A9: E 02 | B9: Mild steel reinforcement to slabs, beams, lintols, columns, footings & etc.. bent to shape, laid in position and tied with 16 B.W.G. Aneal binding wire in Ground floor .
A10: E2.1 | B10: In column shaft | D10: Kg | E10: 192 | F10: =+C10*E10 -> 0
A11: E2.2 | B11: In Beams | D11: Kg | E11: 192 | F11: =+C11*E11 -> 0
A13: E 03 | B13: Mild steel reinforcement to slabs, beams, lintols, columns, footings & etc.. bent to shape, laid in position and tied with 16 B.W.G. Aneal binding wire in first floor .
A14: E3.1 | B14: In column shaft | D14: Kg | E14: 198 | F14: =+C14*E14 -> 0
A15: E3.2 | B15: In Beams | D15: Kg | E15: 198 | F15: =+C15*E15 -> 0
A17: E 04 | B17: Mild steel reinforcement to slabs, beams, lintols, columns, footings & etc.. bent to shape, laid in position and tied with 16 B.W.G. Aneal binding wire in second floor .
A18: E4.1 | B18: In column shaft | D18: Kg | E18: 202 | F18: =+C18*E18 -> 0
A19: E4.2 | B19: In Beams | D19: Kg | E19: 202 | F19: =+C19*E19 -> 0
A21: E 05 | B21: Mild steel reinforcement to slabs, beams, lintols, columns, footings & etc.. bent to shape, laid in position and tied with 16 B.W.G. Aneal binding wire in Third floor .
A22: E5.1 | B22: In column shaft | D22: Kg | E22: 208 | F22: =+C22*E22 -> 0
A23: E5.2 | B23: In Beams | D23: Kg | E23: 208 | F23: =+C23*E23 -> 0
A25: E 06 | B25: Tor steel reinforcement to slabs, beams, lintols, columns, footings & etc.. bent to shape, laid in position and tied with 16 B.W.G. Aneal binding wire up to Dpc . | D25: Kg | E25: 164
A26: E6.1 | B26: In column footing | D26: Kg | E26: 204 | F26: =+C26*E26 -> 0
A27: E6.2 | B27: In column shaft | D27: Kg | E27: 204 | F27: =+C27*E27 -> 0
A28: E6.3 | B28: In Tie Beams | D28: Kg | E28: 204 | F28: =+C28*E28 -> 0
A29: E6.4 | B29: In staircases | D29: Kg | E29: 204 | F29: =+C29*E29 -> 0
A31: E 07 | B31: Tor steel reinforcement to slabs, beams, lintols, columns, footings & etc.. bent to shape, laid in position and tied with 16 B.W.G. Aneal binding wire in Ground floor.
A32: E7.1 | B32: In column shaft | D32: Kg | E32: 204 | F32: =+C32*E32 -> 0
A33: E7.2 | B33: In Beams | D33: Kg | E33: 204 | F33: =+C33*E33 -> 0
A34: E7.3 | B34: In Slab | D34: Kg | E34: 204 | F34: =+C34*E34 -> 0
A35: E7.4 | B35: In Staircase | D35: Kg | E35: 204 | F35: =+C35*E35 -> 0
A37: E 08 | B37: Tor steel reinforcement to slabs, beams, lintols, columns, footings & etc.. bent to shape, laid in position and tied with 16 B.W.G. Aneal binding wire in first floor.
A38: E8.1 | B38: In column shaft | D38: Kg | E38: 210 | F38: =+C38*E38 -> 0
A39: E8.2 | B39: In Beams | D39: Kg | E39: 210 | F39: =+C39*E39 -> 0
A40: E8.3 | B40: In Slab | D40: Kg | E40: 210 | F40: =+C40*E40 -> 0
A41: E8.4 | B41: In Staircase | D41: Kg | E41: 210 | F41: =+C41*E41 -> 0
A43: E 09 | B43: Tor steel reinforcement to slabs, beams, lintols, columns, footings & etc.. bent to shape, laid in position and tied with 16 B.W.G. Aneal binding wire in second floor.
A44: E9.1 | B44: In column shaft | D44: Kg | E44: 210 | F44: =+C44*E44 -> 0
A45: E9.2 | B45: In Beams | D45: Kg | E45: 210 | F45: =+C45*E45 -> 0
A46: E9.3 | B46: In Slab | D46: Kg | E46: 210 | F46: =+C46*E46 -> 0
A48: E 10 | B48: Tor steel reinforcement to slabs, beams, lintols, columns, footings & etc.. bent to shape, laid in position and tied with 16 B.W.G. Aneal binding wire in Third floor.
A49: E10.1 | B49: In column shaft | D49: Kg | E49: 216 | F49: =+C49*E49 -> 0
A50: E10.2 | B50: In Beams | D50: Kg | E50: 216 | F50: =+C50*E50 -> 0
A51: E10.3 | B51: In Slab | D51: Kg | E51: 216 | F51: =+C51*E51 -> 0
B55: TOTAL CARRIED TO COLLECTION | F55: =SUM(F5:F53) -> 0

Sheet Minuwangoda Final
A1: PROPSED THREE STORY LIBREARY BUILDING FOR MINUWANGODA URBAN COUNCIL MINUWANGODA.
A3: Nos | B3: Description | C3: Qty | D3: Unit | E3: Rate | F3: Amount
B4: BILL NO. 01
A5: 1/PR | B5: PRELIMINARIES
B7: Please refer Specifications & Priceing reambles
B8: This Bill Provides for the typical general items complimentary to the works wich are required to be provided by the Contractor in compliance with the Conditions of Contract and Contract Data in the execution of the works according to the Contract.
A10: 1/PR.1 | B10: Allow lump sum for providing Securtiy Bonds and Guarantees. | C10: 1 | D10: Item | E10: 685000 | F10: =C10*E10 -> 685000
A12: 1/PR.2 | B12: Allow lump sum for mobilization to site | C12: 1 | D12: Item | E12: 20000 | F12: =C12*E12 -> 20000
A14: 1/PR.3 | B14: Allow lump sum for insurance of works, plant & machinery,materials, third pary and workmen (All the insurances should be submitted for the end of defect liability period.) | C14: 1 | D14: Item | E14: 810000 | F14: =C14*E14 -> 810000
A16: 1/PR.4 | B16: Provide lump sum to construct, maintain and removal at end of contract temporary buildings for protection & storage of materials & plant and for workshops. | C16: 1 | D16: Item | E16: 30000 | F16: =C16*E16 -> 30000
A18: 1/PR.5 | B18: Provide lump sum to construct furnish, maintain and removal at end of contract contractor's office and Engineers office separately. | C18: 1 | D18: Item | E18: 160000 | F18: =C18*E18 -> 160000
A20: 1/PR.6 | B20: Allow for providing safety, Health and sanitary facilities for Contractor's Staff. | C20: 1 | D20: Item | E20: 100000 | F20: =C20*E20 -> 100000
A22: 1/PR.7 | B22: Provide lump sum for electronic equipment and setting out of the works. | C22: 1 | D22: Item | E22: 15000 | F22: =C22*E22 -> 15000
A24: 1/PR.8 | B24: Allow for supplying temperory electricity for the work including connections, distribution system for the work internal arrangements and for all payments to the authorities for consumption during construction. | D24: Item | F24: By Owner
A26: 1/PR.9 | B26: Allow for supplying water for use during the construction including supplying, storing internal arrangements and payment to local authorities for consumption. | D26: Item | F26: By Owner
A28: 1/PR.10 | B28: Provide lump sum for providing temporary water supply for the use of works. | C28: 1 | D28: Item | E28: 50000 | F28: =C28*E28 -> 50000
A30: 1/PR.11 | B30: Provide lump sum for temporary electricity services for the use of works | C30: 1 | D30: Item | E30: 60000 | F30: =C30*E30 -> 60000
A32: 1/PR.12 | B32: Provide lump sum for necessary protective fencing, hoarding and temporary dust screen, to fully cover from dust and particles etc. around buildings due to construction activities as directed by the Engineer | C32: 1 | D32: Item | E32: 150000 | F32: =C32*E32 -> 150000
A34: 1/PR.13 | B34: Provide lump sum for necessary warning notices, adequate night lighting etc. | C34: 1 | D34: Item | E34: 50000 | F34: =C34*E34 -> 50000
A36: 1/PR.14 | B36: Provide lump sum for providing security and safeguarding the works, material & plant against damage, vandalism and trespass. | C36: 1 | D36: Item | E36: 300000 | F36: =C36*E36 -> 300000
A38: 1/PR.16 | B38: Provide lump sum for demobilization, removal of all rubbish & debris and clearing up site on completion, leaving all in good order and handing over. | C38: 1 | D38: Item | E38: 200000 | F38: =C38*E38 -> 200000
A40: 1/PR.17 | B40: Allow lum sum for obtaining all necessary approvals from local authorities for proper execution and completion of works. | C40: 1 | D40: Item | E40: 100000 | F40: =C40*E40 -> 100000
A42: 1/PR.18 | B42: Allow lump sum for obtaining test reports including lab reports for structural works and Chartered electrical Engineer's cerfificate for Electrical installation works. | C42: 1 | D42: Item | E42: 75000 | F42: =C42*E42 -> 75000
A44: 1/PR.19 | B44: Allow lump sum for providing approved samples at site. | C44: 1 | D44: Item | E44: 30000 | F44: =C44*E44 -> 30000
A46: 1/PR.20 | B46: Allow lump sum for providing progress charts, Construction Programs, Progrress photos (minimum 5 photos every month) bar schedules, shop/working drawings etc. | C46: 1 | D46: Item | E46: 20000 | F46: =C46*E46 -> 20000
A48: 1/PR.21 | B48: Allow lump sum for providing three(03) copies of " As Built" drawing with Operation manual. | C48: 1 | D48: Item | E48: 15000 | F48: =C48*E48 -> 15000
B55: TOTAL CARRIED TO GRAND SUMMARY | F55: =SUM(F10:F54) -> 2870000
B57: B - EXCAVATION & EARTH WORK
B58: Excavation
A59: B 01 | B59: Site preparation, Clearing site vegetation, removing bushes, shrubs & top soil to a depth not exceeding 6" and removing all debris away from site. | C59: 43.63 | D59: Sqr. | E59: 1640 | F59: =+C59*E59 -> 71553.2 | H59: =95/10.76 -> 8.8289963
B61: Shoring, dewatering and rock blasting if necessary for the excavation, shall be paid for separately for item B04 - B06
A62: B 02 | B62: Manual Excavation for column, wall, staircase foundations in any material (except rock requiring blasting) up to 5'-0" depth, part return fill in and ram and surplus depositted within site as directed. | C62: 18.2 | D62: Cube | E62: 3450 | F62: =+C62*E62 -> 62790
B64: Filling & Compaction
B65: Note:-
B66: Approved earth shall mean filling materials that comply to the following :
A67: ( a ) | B67: The earth shall be free of vegetation, roots, boulders, easily decomposable materials, chemicals, industrial waste, plastic etc.
A68: ( b ) | B68: The maximum size of particle shall not exceed 75mm.
A69: ( c ) | B69: The earth shall be well graded and the silt and clay (fines) content shall not be more than 25%
A70: ( d ) | B70: The Standerd proctor density shall be grater than 1.70g/cm3
A71: B 03 | B71: Approved earth supplying and piled at site (measured at piled volume) | C71: 21.3 | D71: Cube | E71: 3570 | F71: =+C71*E71 -> 76041 | H71: =8.9+21.3 -> 30.2
A72: B 04 | B72: Transport of Bulk material (Earth, Graded quarry dust, ABC mix) per Km per cube. | D72: 1 km | E72: 157
A73: B 05 | B73: Compaction of Earth including watering in 225mm thick layers (measured on piled volume) using machine Rammer. Rate include hire charges of the machine rammer. This rate is applicable for building construction with earth work not exceeding 50 cubes. (earth available at site). | C73: 30.2 | D73: Cube | E73: 1470 | F73: =+C73*E73 -> 44394
B75: Test
A76: B 06 | B76: Conducting a proctor density check on sample fill matearial. | D76: Per Test | E76: 3000
A77: B 07 | B77: Field density testing of the compacted earth fill using Sand cone method. | D77: Per Test | E77: 4000
B78: Antitermite -Tretement
A79: B 08 | B79: Antitermite-treatement for the new construction with applying Biflexthrine 10Tc (Biflex ) or approved equivelant , Dialuted chemicals 1:200 ratio with water after supplying the sealed bottle with lables to the site and should be followed the manufacture standards of application including horizontal & vertical barriers. It should be 10 years warranty on application. | C79: 4363 | D79: Sq.ft. | E79: 32 | F79: =+C79*E79 -> 139616
B82: TOTAL CARRIED TO COLLECTION | F82: =SUM(F59:F80) -> 394394.2
B83: C - CONCRETE
B84: Note:
B85: The Quality of the concrete should confirm to the relevant B.S., S.L.S. and ICTAD specification for Building works.
B86: UP TO DPC LEVEL
B87: IN - SITU PLAIN CONCRETE
A88: C 01 | B88: Cement concrete 1:3:6 (1") laid to a thickness of 2" in wall foundations, under column/stair footings, including placing in position,compacting and curing. | C88: 3.81 | D88: Sqr. | E88: 6235 | F88: =+C88*E88 -> 23755.35 | H88: =14292*2.83 -> 40446.36
B90: IN - SITU REINFORCED CONCRETE
A92: C 02 | B92: Volume Batched Grade 25 concrete prepared at site using mixer and vibrator in ground floor. Rate shall include the cost of curing continously for 7 days.
A93: C2.1 | B93: In column footing | C93: 13.86 | D93: Cube | E93: 46030 | F93: =C93*E93 -> 637975.8 | H93: =+C93/2.83 -> 4.8975265 | I93: 4.8975265
A94: C2.2 | B94: In column shaft | C94: 1.77 | D94: Cube | E94: 46030 | F94: =C94*E94 -> 81473.1 | H94: =+C94/2.83 -> 0.6254417 | I94: 0.6254417
A95: C2.3 | B95: In Tie Beams | C95: 17.63 | D95: Cube | E95: 46030 | F95: =C95*E95 -> 811508.9 | H95: =+C95/2.83 -> 6.229682 | I95: 6.229682
A96: C2.4 | B96: In staircases | C96: 1.07 | D96: Cube | E96: 46030 | F96: =C96*E96 -> 49252.1 | H96: =+C96/2.83 -> 0.37809187 | I96: 0.37809187
A98: C 03 | B98: Volume Batched Grade 20 concrete prepaired at site for reinforced and unreinforced concrete floors laid on ground. Rate shall include the cost of curing continously for 5 days. | H98: =18.76/2.83 -> 6.6289753
A99: C3.1 | B99: Groung floor concrete | C99: 6.63 | D99: Cube | E99: 37095 | F99: =+C99*E99 -> 245939.85 | H99: 2.5 | I99: =+H99/2.83 -> 0.88339223
A100: C3.2 | B100: steps at ground floor entrance area | C100: 0.88 | D100: Cube | E100: 37095 | F100: =+C100*E100 -> 32643.6
A101: C3.3 | B101: Ramp at entrance | C101: 0.23 | D101: Cube | E101: 37095 | F101: =+C101*E101 -> 8531.85 | H101: 0.65 | I101: =+H101/2.83 -> 0.22968198
B103: SUPER STRUCTURE
A105: C 04 | B105: Volume Batched Grade 25 concrete prepared at site using mixer and vibrator in ground floor. Rate shall include the cost of curing continously for 7 days.
A106: C4.1 | B106: In column shaft from ground floor level to First floor level | C106: 2.31 | D106: Cube | E106: 46030 | F106: =C106*E106 -> 106329.3
A107: C4.2 | B107: In column shaft from First floor level to Second floor level | C107: 1.83 | D107: Cube | E107: 47410 | F107: =C107*E107 -> 86760.3
A108: C4.3 | B108: In column shaft from Second floor level to Lift machinary level | C108: 1.3 | D108: Cube | E108: 48330 | F108: =C108*E108 -> 62829
A109: C4.4 | B109: In column shaft from Lift machinary level to water tank level | C109: 0.8 | D109: Cube | E109: 49250 | F109: =C109*E109 -> 39400
B112: READY MIX CONCRETE
A113: C 05 | B113: Ready mix concrete of grade 25(25 N/mm2) confirming to SLS 1144- 1997, transport 20km from batching plant. Rate shall inclue for placing, levelling, vibrating & curing the concrete & pump car cost | E113: 14690
A114: C5.1 | B114: In Reinforced beam at First floor level | C114: 15.33 | D114: Cu.m | E114: 14690 | F114: =C114*E114 -> 225197.7 | H114: =+C114+C119+C124 -> 50.44 | I114: =+H114*E113+H114*500+21750+725*20.44 -> 802752.6 | J114: =236.65*5.25 -> 1242.4125 | K114: =SUM(I114:J114) -> 803995.01 | L114: =+K114/H114 -> 15939.631
A115: C5.2 | B115: In Reinforced beam at second floor level | C115: 13.83 | D115: Cu.m | E115: 14690 | F115: =C115*E115 -> 203162.7 | H115: =+C115+C120+C125 -> 48.94 | I115: =+H115*E113+H115*500+21750+725*18.94 -> 778880.1 | J115: =236.65*5.25 -> 1242.4125 | K115: =SUM(I115:J115) -> 780122.51 | L115: =+K115/H115 -> 15940.386
A116: C5.3 | B116: In Reinforced beam at roof & lift machinary level | C116: 7.35 | D116: Cu.m | E116: 14690 | F116: =C116*E116 -> 107971.5 | H116: =+C116+C121 -> 11.71
A117: C5.4 | B117: In Reinforced beam at water tank level | C117: 2.67 | D117: Cu.m | E117: 14690 | F117: =C117*E117 -> 39222.3 | H117: =+C117+C122 -> 7.03
A119: C5.5 | B119: In Reinforced slab at First floor level | C119: 30.91 | D119: Cu.m | E119: 14690 | F119: =C119*E119 -> 454067.9 | H119: =SUM(H114:H115) -> 99.38
A120: C5.6 | B120: In Reinforced Slab at second floor level | C120: 30.91 | D120: Cu.m | E120: 14690 | F120: =C120*E120 -> 454067.9
A121: C5.7 | B121: In Reinforced slab at lift machinary level | C121: 4.36 | D121: Cu.m | E121: 14690 | F121: =C121*E121 -> 64048.4
A122: C5.8 | B122: In Reinforced Slab at water tank level | C122: 4.36 | D122: Cu.m | E122: 14690 | F122: =C122*E122 -> 64048.4
A124: C5.9 | B124: In staircase from ground floor level to First floor level | C124: 4.2 | D124: Cu.m | E124: 14690 | F124: =C124*E124 -> 61698 | J124: =C116+C117+C121+C122+C124+C125 -> 27.14
A125: C5.10 | B125: In staircase from First floor level to Second floor level | C125: 4.2 | D125: Cu.m | E125: 14690 | F125: =C125*E125 -> 61698
A127: C5.11 | B127: Transport charges per Km per m3 for over and above 20 km. | D127: Km | E127: 325
A128: C5.12 | B128: Placing , levelling , vibrating the concrete. | C128: 118.12 | D128: Cu.m | E128: 500 | F128: =C128*E128 -> 59060 | H128: =C114+C115+C116+C117+C119+C120+C121+C122+C124+C125 -> 118.12
A129: C5.13 | B129: Pumping charge for quantites up to 30 m3 by pump car | C129: 4 | D129: Nr | E129: 21750 | F129: =C129*E129 -> 87000 | H129: =H128/5 -> 23.624 | I129: =H129*3 -> 70.872
A130: C5.14 | B130: For more than 30 m3 additional pumping charges. (Rate for every m3 over and above 30 m3) | C130: 39.38 | D130: Cu.m | E130: 725 | F130: =C130*E130 -> 28550.5
A131: C5.15 | B131: Curing of Concrete slabs with ponding water or covering with polythene sheets and continuous wetting for 7 days. | C131: =532*10.76 -> 5724.32 | D131: Sq.ft | E131: 5.25 | F131: =C131*E131 -> 30052.68
A132: C5.16 | B132: Casting of 6" x 6" x 6" concrete cubes on a steel mould, curing for 7 days and testing for compressive strength at an approved laboratory (rate includes transport of cubes from site to laboratory ). | C132: 72 | D132: Nr | E132: 1155 | F132: =C132*E132 -> 83160
B135: TOTAL CARRIED TO COLLECTION | F135: =SUM(F88:F133) -> 4209405.1
B136: D - FORM WORK
B137: Note:
A138: (a) | B138: The rates given for items D 02, D 03 to D 08 herein are applicable for plywood sheets of 15 mm thick. Hence the rate is valid only if the shuttering / formwork for footing , column , beams , lintel, walls, slabs are of 15 mm thick ply boards.
A139: (b) | B139: Any deviation from the specified materials, specified thickness and the arrangement of formwork given in this document should require the written approval of the Divisional Engineer. Rate for such deviation from the item description will be decided by the D(B/SW)
A140: (c) | B140: For ordinary plywood of 15 mm thick boarding as shuttering, (Even for WBP sheets the same rate shall be applicable).
A141: D 01 | B141: Shuttering for sides of foundation with 1" thick rubber planking including dismantling | H141: =35.04*10.76 -> 377.0304
A142: D 1.1 | B142: In column footing | C142: 3.77 | D142: Sqr. | E142: 3725 | F142: =C142*E142 -> 14043.25
A143: D 1.2 | B143: steps at ground floor entrance area | C143: 0.61 | D143: Sqr. | E143: 3725 | F143: =C143*E143 -> 2272.25 | H143: =+C143*10.76 -> 6.5636
A144: D 1.3 | B144: Ramp at rentrance | C144: 0.12 | D144: Sqr. | E144: 3725 | F144: =C144*E144 -> 447 | H144: =+C144*10.76 -> 1.2912
A146: D 02 | B146: Shuttering for sides and bottom of plinth beams, ground beams including dismantling in 15mm thick plywood board. | C146: 11.35 | D146: Sqr. | E146: 13385 | F146: =C146*E146 -> 151919.75 | H146: =105.5*10.76 -> 1135.18
A148: D 03 | B148: Shuttering for columns including dismantling in 15mm thick Plywood board.
...

Sheet Timber doors
A1: Nos | B1: Description | C1: Qty | D1: Unit | E1: Rate | F1: Amount
B2: N - TIMBER DOORS
B3: Timber :
B4: 1. Refer preamble note for approved timber species for Doors & Windows.
B6: 2 All timber for doors & windows should be well drying subjected to pressure impregnation treatment using chemical of copper sulphate pentahydrate, Sodium dichromate dihydrate and Boric acid to reduce the moisture level up to 8%- 10% ( Final moisture level should be maintain 12% to 15% after Stabilize with the Environment.)
B8: 3. Glass thickness to be 5mm.
B10: 4. Following Brass or stainless steel furniture are recommended for timber Doors/ Windows/ Fan lights. Rate with out following heavy duty brass furniture.
B11: (a)Doors :- 4 no. 5"x 3" Solid brass hinges
B12: (b)Doors :- 2 no. 6" Solid brass barrel bolts
B13: (c)Windows of 4'-0" height :- 2 no. 4"x 2" Solid brass hinges
B14: (d)Windows above 4'-0" height :- 3 no. 4"x 2" Solid brass hinges
B15: (e)Windows :- 1 no. 2" Solid brass ring
B16: (f)Windows :- 1 no. 10" Solid brass Casement Stay
B17: (g)Windows :- 1 no. Solid brass Casement Fastener
A19: N 01 | B19: Door (D6) paneled (Class I teak or eq treated timber) 1 1/8" thick double sash hung on 3/4" x 2 3/4" frame. Rate without brass furniture, painting and lock. | C19: ='m shet Miss premila'!#REF! -> #REF! | D19: Sq.ft. | E19: 2359 | F19: =E19*C19 -> #REF! | G19: =(1.4*2.7)+(1.05*2.7) -> 6.615 | H19: =G19*4 -> 26.46 | I19: =H19*10.76 -> 284.7096
K20: =2700/300 -> 9
A21: N 02 | B21: Door frame in approved timber supplying & fixing in position.(Class I teak or eq treated timber) | C21: ='m shet Miss premila'!#REF! -> #REF! | D21: l.ft. | E21: 779 | F21: =E21*C21 -> #REF!
A23: N 03 | B23: Door (D7) paneled (Class I teak or eq treated timber) 1 1/8" thick double sash hung on 3/4" x 2 3/4" frame. Rate without brass furniture, painting and lock. | C23: ='m shet Miss premila'!#REF! -> #REF! | D23: Sq.ft. | E23: =E19 -> 2359 | F23: =E23*C23 -> #REF!
A25: N 04 | B25: Door frame in approved timber supplying & fixing in position.(Class I teak or eq treated timber) | C25: ='m shet Miss premila'!#REF! -> #REF! | D25: l.ft. | E25: =E21 -> 779 | F25: =E25*C25 -> #REF!
B28: P - IRON MONGARY
B29: Note:
B30: All Iron mongary shall be heavy duty and samples should be approved by the D.E. Prior to installation.
B32: 1. In view of the variety of door locks available in the market, it has become necessary to prescribe the exact quality requirements in terms of performance and durability aspects. The "Union" brand and respective model numbers have been chosen as a bench mark to establish the said requirements.
B34: 2. The brand name and model number appearing in the respective BSR items are purely meant to describe the performance standard of the said fitting/item and does not imply in any manner that only the "Union" brand is recommended or considered to be restricted to the "Union" brand.
B35: Any other make/brand that has equivalent performance characteristics are considered as equivalent provided such fittings met with following criteria.
B36: (a) has an authorized local agent in Sri Lanka
B37: (b) The local agent has been in the trade of the offered make for not less than 5 years.
B38: (c) The fittings are manufactured in conformity to BS, JIS, ASTM, AS or SLS standards.
B39: (d) The dimensions and performance characteristics are in par with the stated model.
B41: The brands that may be considered as equivalent are "Miva" of Japan "Whitco" of Australian make or "Dorma" of European make or any other approved make which prior approval to be obtained from Deputy Chief Secretary(Engineering), Director(Building) or Director(Engineering) after producing necessary catalogues and documents.
A43: N 02 | B43: Supplying and fixing two lever Mortice door lock for D6 double sash of Union Brand or approved equivalent. (Prime cost is Rs.25,000.00) | C43: 4 | D43: Nr | E43: =25000*1.25 -> 31250 | F43: =E43*C43 -> 125000
A45: N 03 | B45: Supplying and fixing 5" x 3" x 3mm thick solid brass hinges for D6 inclusive of brass screws marketed by M.M.Noorbhoy & company or approved equivalent. | C45: 32 | D45: Nr. | E45: 2702 | F45: =E45*C45 -> 86464 | I45: =4*8 -> 32
A47: N 04 | B47: Supplying and fixing 8" long heavy duty solid brass tower bolt for D6 inclusive of brass screws marketed by M.M.Noorbhoy & company or approved equivalent. | C47: 8 | D47: Nr. | E47: 3108 | F47: =E47*C47 -> 24864
A49: N 05 | B49: Supplying and fixing Handle Pair I type "Magnum" Brand & model no "2512I" handle 900 mm long stainless steel door pull handle fixed complete to working order. | C49: 8 | D49: Nr | E49: =8614*4 -> 34456 | F49: =E49*C49 -> 275648
A51: N 06 | B51: Supplying & fixing surface mounted door closer of "Union Brand" & Model no. - N8803 or approved equivalent. In second Floor | C51: 8 | D51: Nr. | E51: 9953 | F51: =E51*C51 -> 79624
A53: N 07 | B53: Supplying and fixing two lever Mortice door lock for D7 single sash of Union Brand or approved equivalent. (Prime cost is Rs.15,000.00) | C53: 4 | D53: Nr | E53: =15000*1.25 -> 18750 | F53: =E53*C53 -> 75000
A55: N 08 | B55: Supplying and fixing 5" long heavy duty solid brass tower bolt for D7 inclusive of brass screws marketed by M.M.Noorbhoy & company or approved equivalent. | C55: 4 | D55: Nr. | E55: =E47/8*5 -> 1942.5 | F55: =E55*C55 -> 7770
A57: N 09 | B57: Supplying & fixing surface mounted door closer of "Union Brand" & Model no. - N8803 or approved equivalent. In Ground Floor D7 | C57: 4 | D57: Nr. | E57: 9953 | F57: =E57*C57 -> 39812
B60: Water Based Application
B61: All water base products are none toxic and conform to EN 71 standards. | L61: =K62*2 -> 7.56
A62: N 04 | B62: Preparing and application two coats of water based stain and two coats of water based top coat to new wood work. Rate shall include for preparing the surface and sanding with sand paper 80, 120, 180 and 320 or 400 . (Prime cost of "JAT - Sayerlack Brand" is water base stain - 4 L is Rs.8916.00.00 & water base top coat - 5L is Rs.16887.00 with 5 year product warranty) for D6 | C62: ='m shet Miss premila'!#REF!+'m shet Miss premila'!#REF! -> #REF! | D62: Sqr | E62: 23446 | F62: =E62*C62 -> #REF! | G62: =SUM(F6:F63) -> #REF! | J62: =G62/37 -> #REF! | K62: =2.7*1.4 -> 3.78 | L62: =L61*10.76 -> 81.3456
L63: =L62/100 -> 0.813456
B64: DOORS & WINDOWS WORK CARRIED TO COLLECTION | F64: =SUM(F2:F63) -> #REF! | H64: =F64/I19 -> #REF! | I64: =H64/4 -> #REF!

Sheet steel work
A1: Item | B1: Description | C1: Qty | D1: Unit | E1: Rate ( Rs.) | F1: Amount ( Rs.) | G1: RATE
A2: 1 | B2: P - STEEL STRUCTURAL WORK
B4: Notes:
B5: in this Bill and with accordance to Drawings, Specifications
B6: and to the approval of the Engineer.
B8: Contractor shall carry out and complete the Works described
B9: in this Bill and with accordance to Drawings, Specifications
B10: and to the approval of the Engineer.
B12: All steel used in the work shall comply with the relevent british standerds and to the specifications
B14: All steel shall be new and each, member shall be free from any built weld or other forms of splice for the full strength between joints shown in or indicated in the drawings unless such spelice shall have been shown in the approved drawings
B16: the bidder shall submit the specification for the steel which he proposed to use and obtain prior approval from the engineer before commencemnt of ordering of steel and fabrications
B18: Drawings
B19: Before any steel work is fabricated the contractor shall obtain the engineers approval of the proposed details of fabrications. For this purpose, two copies of each drawings shall be submitted to the engineer not less than 14 days before commencemnt of fabrication
B21: Inspections
... B45: c) Aginst excessive colour fading and chalking - 10 yrs
A47: P 01 | B47: Steel Column Work
A49: P 01.1 | B49: Supply and fabrication and erection of IC1 250X125 29.6kg/m I column including fixing and connection to concrete shaft, rate to include to gusset plates,sole plated,base plates,cleats and nuts bolts, j bolts, plates, welding & applying one coat of Zn/phosphate paint and two coats of enamal and nesessary other work, complete to working order as per the detail drawings and specification | C49: ='m shet Miss premila'!#REF! -> #REF! | D49: ton | E49: =#REF! -> #REF! | F49: =E49*C49 -> #REF!
A51: P 02 | B51: Roof Beam Work
A53: P 02.1 | B53: Supply and fabrication and erection of IRB1 250X125 29.6kg/m I roof beam including fixing and connection to concrete beam and I column, rate to include to gusset plates,sole plated,base plates,cleats and nuts bolts, j bolts, plates, welding & applying one coat of Zn/phosphate paint and two coats of enamal and nesessary other work, complete to working order as per the detail drawings and specification | C53: ='m shet Miss premila'!#REF! -> #REF! | D53: ton | E53: =E49 -> #REF! | F53: =E53*C53 -> #REF!
A55: P 02.2 | B55: Supply and fabrication and erection of ITB1 150X75 14kg/m I roof beam including fixing and connection to concrete beam and I column, rate to include to gusset plates,sole plated,base plates,cleats and nuts bolts, j bolts, plates, welding & applying one coat of Zn/phosphate paint and two coats of enamal and nesessary other work, complete to working order as per the detail drawings and specification | C55: ='m shet Miss premila'!#REF! -> #REF! | D55: ton | E55: =#REF! -> #REF! | F55: =E55*C55 -> #REF!
B57: STEEL STRUCTURAL WORK CARRIED TO COLLECTION | F57: =SUM(F43:F56) -> #REF! | H57: =F57/#REF! -> #REF!
F60: =F57 -> #REF!
F63: =#REF!+#REF! -> #REF!
F64: =F63*10.76 -> #REF!
F66: =#REF!/F64 -> #REF!

Sheet Sheet6

Sheet BOQ-Electrical System
A1: Supply, Installation, Testing and Commissioning of Electrical Distribution System.
A2: Proposed Building For Mr. Hiroshan Hettiarachchi at Maharagama.
A3: BoQ and Specifications for Electrical System.
A5: NO | B5: DESCRIPTION | C5: QTY | D5: UNIT | E5: RATE (LKR) | F5: AMOUNT (LKR)
B7: Specifications & General Notes For Electrical Installation | D7: Note
A9: 1. | B9: All related work to the above installation shall meet the requirements of BS 7671:2018;Requirments for Electrical Installations (IET Wiring Regulations;18th Edition)
A11: 2. | B11: The Electrical Installation is designed for 400/230 volts, 3 phase 50Hz with earthed neutral.
A13: 3. | B13: All items shall be quoted and Contract is Measure and pay Basis. It is possible to increase or decrease number of quantities of items and total removal of items also can occur, depend on the site conditions and requirements.
A15: 4. | B15: Cable terminations shall be carried out using correct accessories such as lugs, brass glands, bushes, lock nuts etc.
A17: 5. | B17: Installation work shall be carried out by experienced electrical contractors who has had previous experience in similar capacity projects and shall have proper standard tools, equipment and experienced and competent staff for electrical installation and commissioning and testing.
A19: 6. | B19: Contractor must check actual cable lengths at site before purchasing and start laying/implementation hence avoid cable joints.
A21: 7. | B21: The contractor shall provide a minimum one year warranty period for the distribution panels and its accessories / components. In addition contractor shall provide manufactures’ warranty (if more than one year) for accessories and components that are used.
A23: 8. | B23: Door earthing link to be provided for metal power distribution boards.
A25: 9. | B25: keep 10% Additional Space within the Power Distribution Boards (this includes din rails & front cover plate space and front covers to be cut to the 10 % space and to be closed with blank plates.
A27: 10. | B27: Proper size of earth CU bus bars to be provided for Power Distribution Boards.
A29: 11. | B29: Proper durable metal type door locks with metal keys to be used for metal Distribution Boards
A31: 12. | B31: Samples and technical details need to be provided for all the accessories, when request by consultant without claiming any charge.
... A35: 14. | B35: After completion of the installation, the Contractor shall submit Inspection and test certificates for electrical installation( Including all tests) from a Chartered Electrical Engineer before energizing the system.
A37: 15 | B37: Contractor must perform site visits & check for practical & feasible conditions/options of the given designs based on practical site conditions & submit quotations accordingly.
A39: 16 | B39: Identification tags to be pasted at Distribution boards, sub Circuits etc.
A41: 17 | B41: Single line diagram and load description details (laminated color copies) to be kept inside the Distribution board (Those to be kept in a Proper polythene cover pasting to the back side of the front door.)
A43: 18 | B43: Proper Rubber/PVC beading to be fixed for cable entering points of Power Distribution Boards and Metal Trunking.
A45: 19 | B45: It is contractor’s responsibility to remove all the debris own/ happened due to contractor’s work.
A47: 20 | B47: Installation heights of switches, socket outlets and other items will be given by architect/consultant/client.
A49: 21 | B49: Contractor shall give item schedule (that mentioned all brands going to be used), for consultant’s approval before purchasing and starting the work.
A51: 22 | B51: Contractor shall submit shop drawings for consultant's approval before start site works.
B53: Equipment Specifications | D53: Note
A55: 1. | B55: Wall Mounted and Floor Mounted Distribution Boards,
B56: All Floor mounted and wall mounted distribution boards are complied for IP 55 and be fabricated with 2.0 mm thickness mild steel sheet metal and painted with powdered epoxy paint.
A58: 2. | B58: Electrical Cable Trays, Ladders Trunkings
B59: Cable ladder system and cable tray system should be complied with BS EN61537 :2007 & IEC 61537: 2006 .Cable management, Cable Tray system and Cable Ladder system
B61: These items shall be complied with mentioned standards. Mild steel: BS EN 10149-3, Stainless steel BS 1449: Part 2, Surface coating BS EN ISO 1461:2009
A63: 3. | B63: Molded Case Circuit Breaker
B64: (MCCB) shall have breaking capacity of more than 25 kA or as indicated in drawings; and shall conform to BS 4752. Current transformer shall conform to BS 3938. The bus bars shall be copper conforming to BS 159 and covered with heat shrink insulation and colour coded. All the bus bars and cables from bus bars to MCCB and MCB shall be adequately rated so that the temperature in those are not more than 50 deg C at full load current.
B66: All MCCB’s and switch boards shall be labelled to indicate area it feeds.
A68: 4. | B68: MCB (Miniature Circuit Breakers)
B69: MCB shall be comply with BS 3871 and breaking capacity shall be more than 5kA; type 2 used for lighting and socket outlets whereas type 3 is used for AC circuits.
A71: 5. | B71: RCCB ( Residual Current Circuit Breaker)
B72: RCCB shall be comply with BS 4293 and sensitivity has been mentioned in the BoQ and Single line diagrams.
A74: 6. | B74: 20A Double Pole (2pole) Switches
B75: Above Switches shall be comply with BS 3676
A77: 7. | B77: 13A Switched Socket Outlets (Square Pin)
B78: Above socket outlets shall be comply with BS 546
B80: Recommended brands of Item | D80: Note
B82: Note: Bidder shall mention their consent for below brands, if not mention alternative brands.
B84: Panel Board Power Analyzer / Digital kWh Meter - Schneider (France),Circutor (Spain),Merlin Gerin or equivalent (need consultant's approval)
B86: MCCB - Schneider (France),Hager(France), Terasaki(Japan), Moeller(German),Siemens(German) (need consultant's approval)
B88: MCB-Schneider(France),Hager(France),Moeller(German), Siemens(German) or equivalent (need consultant's approval)
B90: RCCB-Schneider(France),Hager(France),Moeller(German), Siemens(German) or equivalent (need consultant's approval)
B92: Power/Telephone Outlets – Orange or equivalent (need consultant's approval)
B93: Switches – Orange or equivalent (need consultant's approval)
B95: Power Cables - ACL, Kelani
B97: Fire resistant cables – ACL, Kelani, Wilson (complying with BS7629/BS6387 Cat: CWZ )
B99: PVC Conduits and junction Boxes, Sunk Boxes – National, Slon, Polychrome or equivalent (need consultant's approval)
B101: ELR - Merlin Gerin(France), Moeller(German),Delab,Micro or equivalent (need consultant's approval)
B103: PFR - Merlin Gerin(France), Moeller(German) or equivalent (need consultant's approval)
... B113: Cable Trays, Trunking and Ladders- PUBUDU, EMP or equivalent. ( need consultants approval)
B115: This is Measure and pay Contract. All items should be checked, measured and verified with relevant drawings. | D115: Note
B117: Contractor must check the actual cable length @ site, before purchasing and start cable laying/implementation. | D117: Note
B119: Contractor must read the specifications, General notes given and submit the quotation accordingly. | D119: Note
B121: As this is Measure and pay contract, Bidders are advised to carefully refer and understand all drawings, specifications and general notes before submission of their quotation and proposal. | D121: Note
B123: Contractor must submit shop drawing and get approval before start fabrication and installation. | D123: Note
B125: Contractor must submit brands and specifications of all items and get approval before start fabrication and installation | D125: Note
B127: It’s bidders’ responsibility to refer Drawings, relevant specifications and general notes thereby check and verify quantities. | D127: Note
B129: If any discrepancy identified, bidder should clarify the same with client/consultant engineer before submission of final quotation and proposal. | D129: Note
B131: Supply and Installation of Power Distribution Panels
A133: =IF(C133>0,COUNT(C$132:C133),"") -> 1 | B133: ATS WITH MDB | C133: 1 | D133: nr | E133: 3500000 | F133: =E133*C133 -> 3500000
A134: =IF(C134>0,COUNT(C$132:C134),"") | B134: 03 Nos. 100A 4P MCCB
A135: =IF(C135>0,COUNT(C$132:C135),"") | B135: 01 No. 32A 4P Isolator
A136: =IF(C136>0,COUNT(C$132:C136),"") | B136: 01 No. 32A 4P MCCB
A137: =IF(C137>0,COUNT(C$132:C137),"") | B137: 01 No. 63A 4P MCB
A138: =IF(C138>0,COUNT(C$132:C138),"") | B138: 04 Nos. 32A 4P MCB
A139: =IF(C139>0,COUNT(C$132:C139),"") | B139: 02 Nos. 32A 2P MCB
A140: =IF(C140>0,COUNT(C$132:C140),"") | B140: 04 Nos. 20A 4P MCB
A141: =IF(C141>0,COUNT(C$132:C141),"") | B141: 01 No. 20A 2P MCB
A142: =IF(C142>0,COUNT(C$132:C142),"") | B142: 01 No. 16A 4P MCB
A143: =IF(C143>0,COUNT(C$132:C143),"") | B143: 01 No. power analyzer with all other relevant accessories.
A144: =IF(C144>0,COUNT(C$132:C144),"") | B144: 01 Set of SPD - Surge Protection Devices ( 3 Nos 50kA & 1 Nos. 120kA) with 4 Nos 100A HRC fuses
A145: =IF(C145>0,COUNT(C$132:C145),"") | B145: 01 No. 100A ATS arrangement with electrical & mechanical interlock, all controlling and complete with all other relevant accessories.
... A151: =IF(C151>0,COUNT(C$132:C151),"") | B151: 01 No. Free Standing type, Powder coated metal Enclosure with front doors, metal locks & front cover plate
A152: =IF(C152>0,COUNT(C$132:C152),"")
A153: =IF(C153>0,COUNT(C$132:C153),"") -> 2 | B153: DB-GF | C153: 1 | D153: nr | E153: 500000 | F153: =E153*C153 -> 500000
A154: =IF(C154>0,COUNT(C$132:C154),"") | B154: 01 No. 20A 4P MCB
A155: =IF(C155>0,COUNT(C$132:C155),"") | B155: 05 Nos. 40A 30mA 2P RCCB
A156: =IF(C156>0,COUNT(C$132:C156),"") | B156: 09 Nos. 6A SP MCB
A157: =IF(C157>0,COUNT(C$132:C157),"") | B157: 08 Nos. 10A SP MCB
A158: =IF(C158>0,COUNT(C$132:C158),"") | B158: 05 Nos. 16A SP MCB
A159: =IF(C159>0,COUNT(C$132:C159),"") | B159: 01 Set of Cu Bus bars for R,Y,B,N,E
A160: =IF(C160>0,COUNT(C$132:C160),"") | B160: 01 Set (R,Y,B) LED type phase indicators with fuses.
A161: =IF(C161>0,COUNT(C$132:C161),"") | B161: 01 No. Wall mounted Type, Powder coated metal Enclosure with front door, metal locks & front cover plate.
A162: =IF(C162>0,COUNT(C$132:C162),"")
A163: =IF(C163>0,COUNT(C$132:C163),"") -> 3 | B163: DB-1F-RAW | C163: 1 | D163: nr | E163: 500000 | F163: =E163*C163 -> 500000
A164: =IF(C164>0,COUNT(C$132:C164),"") | B164: 01 No. 20A 4P MCB
A165: =IF(C165>0,COUNT(C$132:C165),"") | B165: 03 Nos. 40A 30mA 2P RCCB
A166: =IF(C166>0,COUNT(C$132:C166),"") | B166: 07 Nos. 6A SP MCB
A167: =IF(C167>0,COUNT(C$132:C167),"") | B167: 09 Nos. 10A SP MCB
A168: =IF(C168>0,COUNT(C$132:C168),"") | B168: 02 No. 16A SP MCB
A169: =IF(C169>0,COUNT(C$132:C169),"") | B169: 01 Set of Cu Bus bars for R,Y,B,N,E
A170: =IF(C170>0,COUNT(C$132:C170),"") | B170: 01 Set (R,Y,B) LED type phase indicators with fuses.
A171: =IF(C171>0,COUNT(C$132:C171),"") | B171: 01 No. Wall mounted Type, Powder coated metal Enclosure with front door, metal locks & front cover plate.
...

Sheet electicle
A1: Nos | B1: Description | C1: Qty | D1: Unit | E1: Rate | F1: Amount
B2: V - ELECTRICAL INSTALLATION.
B3: Note:
B4: Work shall be done in accordance with specifications for electrical and mechanical works - ICTAD Publication No.SCA/8 of Aug.2000(2nd Edition -Revised)
B6: Internal light wiring shall comply with the drawings and shall be in 230/440 volt PVC insulated copper cables
B8: All switches and socket outlets shall be plated type make"Clipsal", " Orange X5", "Krypton" or any other approved equivalent complying to SLS1000:1993 for switches & SLS 1998 : 1991 for soket outlets .
B10: Rate to include switch boxes, Rowl plugs, square pin plug base, Chromium plated M.S. chains, brass hooks, ceiling roses, holders and any other item necessary.
B12: All distribution boards should be incorporated with multi 9, Orange Industrial, Merlin Gerin, , Hager, LS, Moeller/EATON, clipsal,SIEMENS make MCB's (Miniature circuit Breaker ) and cabtree, Clipsal ,Orange Industrial 10 kA, LS , Merlin Gerin,Schinieider make R.C.C.B.'s (Residual Current circuit Breaker) and Schinieider, Merlin Gerin, LS, Dormans Smith ,Orange Industrial (10K), Biticano , Clockner moeller make M.C.C.B.'s (Moulded Case Circuit Breakers)
B14: The whole installation shall be carried out according to CEB/IEE wiring regulations.
B16: All the M.C.C.B.'s, MCB's and RCCB's for the distribution boards should be purchased from the following authorized agents or from heir dealers and a certificate or invoice along with their Company seal and Part No., numbers and warranty should be produced at the time of payment.
B17: a). All MCB, RCCB, shall have 20 Years warranty and hence products which comes with 20 years warranty are permitted.
B18: b). All MCCB shall have 2 Years warranty and hence products which comes with 2 years warranty are permitted.
B19: e). All socket and switches shall have 20 Years warranty and hence products which comes with 20 years warranty are permitted.
... B51: Breaker's - European Brand
A53: V01 | B53: Submittal of As Built drawings
A55: V01.01 | B55: Submittal of As Built drawings c/w set of AutoCAD drawings in a CD and three hard copies size in A1 sheet and submittal of 3 sets of document files all the items listed in this BOQ. Eg: Product broachers for MCCB , MCB, Lightd, Fans,Socket outlets , cables, Medical grade isolation transformers etc. | C55: 1 | D55: Item | E55: 35000 | F55: =E55*C55 -> 35000
B58: Inspection and testing
A60: V01.02 | B60: Testing of the electrical installation and submission of certificate from a chartered Electrical Engineer registered at CEB. | C60: 1 | D60: Item | E60: 68250 | F60: =E60*C60 -> 68250
A62: V01.03 | B62: Charges for verifying the wiring done with meggar test & continuity test before commensing installation of Distribution Board & Electrical Fittings | C62: 1 | D62: Item | E62: 50000 | F62: =E62*C62 -> 50000
A64: V02 | B64: Main Cabling System
B66: All the Cables quoted below shall be on measure and pay basis.
B68: Rates should include for all necessary cable accessories such as cable ties, Cable Lugs, Glands, identification tags, and all accessories for complete installation
B70: Rate shall include for supply and installation of following cables including cable trays, ladders and trunking, conduits,Underground Installments incuding sand beddings ,concrete tiles warning tapes etc. including termination.
B72: All horizontal and vertical Cable trays , trunking , conduits & ladders should be adequately sized to provide 25% spare space. Installation method shall be according to BS 7671
B74: Contractor shall investigate the site conditions and include all the cost involved in point rates given below.
B76: All wiring shall be in securely fixed conduits /trunkig above the ceiling
B78: Main cables for sub distribution boards of each floor shall be tapped from the bus bar riser
A80: V02.01 | B80: Supply, installation & termination of main cable from CEB supply to MDB | C80: 50 | D80: m | E80: 6500 | F80: =E80*C80 -> 325000
A82: V02.02 | B82: Supply, installation & termination of from MDB to DB-Lift | D82: m | E82: 4500
A84: V02.02 | B84: Supply, installation & termination of from Gf Dbs to Banks DB | D84: m | E84: 2500
A86: V02.03 | B86: Supply, installation & termination of from MDB to each floor DBs. | C86: 75 | D86: m | E86: 3900 | F86: =E86*C86 -> 292500
A88: V02.04 | B88: Supply, installation & termination cable from corresponding meter to each DB at shops | D88: m | E88: 2500 | F88: =E88*C88 -> 0
A89: V03 | B89: Main Distribution Board and SUB Distribution Boards and Isolators
B91: All the Distribution Boards shall be surface/flush mounted type Distribution Boards complete with powder coated steel enclosure with lockable doors.
B93: The panel board should have wire numbering and a laminated circuit diagram pasted on the inside surface of the door.
B95: Distribution Boards shall be completed with necessary protection
B97: Make of MCCBs and MCBs, etc shall be Schnider / ABB / Terasaki or equivalent make, approved by the Consultant.
B99: Manufactures shop drawings should be submitted and approved by the Consultant before fabrication
B101: All switches and socket outlets shall be plated type make"Clipsal", " Orange X5", "Krypton" or any other approved equivalent complying to SLS1000:1993 for switches & SLS 1998 : 1991 for soket outlets .
B103: Rate to include switch boxes, Rowl plugs, square pin plug base, Chromium plated M.S. chains, brass hooks, ceiling roses, holders and any other item necessary.
B105: All distribution boards should be incorporated with multi 9, Orange Industrial, Merlin Gerin, , Hager, LS, Moeller/EATON, clipsal, SIEMENS make MCB's (Miniature circuit Breaker ) and cabtree, Clipsal ,Orange Industrial 10 kA, LS , Merlin Gerin,Schinieider make R.C.C.B.'s (Residual Current circuit Breaker) and Schinieider, Merlin Gerin, LS, Dormans Smith ,Orange Industrial (10K), Biticano , Clockner moeller make M.C.C.B.'s (Moulded Case Circuit Breakers)
B107: The whole installation shall be carried out according to CEB/IEE wiring regulations.
B109: All the M.C.C.B.'s, MCB's and RCCB's for the distribution boards should be purchased from the following authorized agents or from their dealers and a certificate or invoice along with their Company seal and Part No., numbers and warranty should be produced at the time of payment.
B111: a). All MCB, RCCB, shall have 20 Years warranty and hence products which comes with 20 years warranty are permitted.
B113: b). All MCCB shall have 2 Years warranty and hence products which comes with 2 years warranty are permitted.
... B129: Point wiring only with and including Socket (Rate includes wiring from MCB to the Socket, socket box, and conduit)
A131: V03.01 | B131: MDB
B132: 02 Nos 4P 63A MCCB /(10kA), 04 Nos 2P 32A MCB /(10kA),01 Nos 125A 4P Automatic Chainge over,01 Nos 40A 4P MCCB, 07 Nos 40A 4P MCCB, 07 Nos 40A 4P 30mA RCCB, 01 Nos 40A 2P 30mA RCCB,and nessasary bus bar and protective system and Cables Lugs and other suppotive meterials | D132: P.S | E132: 275000 | F132: =E132 -> 275000
B133: 1 set of LED Phase indicator lamps c/w 3 x 2A fuse
B134: Supply and mounted (LED Phase indicator lamps ) Wall/Surface mounted Powder Coated Steel Enclosure with lockable doors ,cover plate & internal wiring c/w bus bars and Accessories.(Rate to include necessary MCCB,MCB,RCCB,and other necessary fixturesand Other required supportive materials should include ) The contractor shoud take advise an electricle engineer before undataking the work and
B135: Surface mounted Powder Coated Steel Enclosure with lockable doors ,cover plate & internal wiring c/w bus bars and Accessories.
A137: V03.02 | B137: DB
B138: Ground Floor,First Floor
B139: 01 No. 4P 63A MCCB (16kA Breaking capacity), 01 No. 4P 40A MCCB (16kA Breaking capacity),01 No. 2P 32A, MCB (16kA Breaking capacity),02 Nos. 1P 10A MCB (6kA Breaking capacity),02 Nos. 1P 20A MCB (6kA Breaking capacity),01 No. 2P 40A, 30mA RCCB, and nessasary bus bar and protective system and Cables Lugs and other suppotive meterials1 | D139: P.S | E139: =150000*2 -> 300000 | F139: =E139 -> 300000 | G139: 9900
B140: Supply and mounted LED phase indicator lamps powder coated steel encloser with lockble door, Wall mounted distribution board (3 nr of DB) & internal wiring c/w bus bars and Accessories.(Rate to include necessary MCCB,MCB,RCCB,and other necessary fixturesand Other required supportive materials should include ) The contractor shoud take advise an electricle engineer before undataking the work | G140: 25000 | H140: =SUM(G139:G140) -> 34900 | I140: =H140+15000 -> 49900
B141: Surface mounted Powder Coated Steel Enclosure with lockable doors ,cover plate & internal wiring c/w bus bars and Accessories.
A143: V03.03 | B143: DB- For Lift
B144: Supply and mounted LED phase indicator lamps powder coated steel encloser with lockble door, Wall mounted distribution board & internal wiring c/w bus bars and Accessories.(Rate to include necessary MCCB,MCB,RCCB,and other necessary fixturesand Other required supportive materials should include ) The contractor shoud take advise an electricle engineer before undataking the work | D144: P.S | E144: =100000 -> 100000
B145: Surface mounted Powder Coated Steel Enclosure c/w bus bars and Accessories.
A147: V03.04 | B147: DB- For bank- 4 nr of DB
B148: Supply and mounted LED phase indicator lamps powder coated steel encloser with lockble door, Wall mounted distribution board (4 nr of DB) & internal wiring c/w bus bars and Accessories.(Rate to include necessary MCCB,MCB,RCCB,and other necessary fixturesand Other required supportive materials should include ) The contractor shoud take advise an electricle engineer before undataking the work | D148: P.S | E148: =75000*4 -> 300000
B149: Surface mounted Powder Coated Steel Enclosure with lockable doors ,cover plate & internal wiring c/w bus bars and Accessories.
A151: V03.04 | B151: DBs For Shop
B152: Supply and mounted Wall mounted distribution board( 42 nr) & internal wiring c/w bus bars and Accessories.(Rate to include necessary MCCB,MCB,RCCB,and other necessary fixturesand Other required supportive materials should include ) The contractor shoud take advise an electricle engineer before undataking the work | D152: P.S | E152: =50500*42 -> 2121000
B153: Surface mounted Powder Coated Steel Enclosure with lockable doors ,cover plate & internal wiring c/w bus bars and Accessories.
A163: V03.05 | B163: DBs For Banks
B164: Supply and mounted LED phase indicator lamps powder coated steel encloser with lockble door, Wall mounted distribution board) & internal wiring c/w bus bars and Accessories.(Rate to include necessary MCCB,MCB,RCCB,and other necessary fixturesand Other required supportive materials should include ) The contractor shoud take advise an electricle engineer before undataking the work | C164: 4 | D164: nr | E164: 85000
B165: Surface mounted Powder Coated Steel Enclosure with lockable doors ,cover plate & internal wiring c/w bus bars and Accessories.
A167: V04 | B167: Wiring for light points, ceiling fans, socket outlets
B169: Rate for point wiring shall include for all the cables trays/ladders,conduits, conduit fittings, casings,surface cable trunks, fixing material, switches, wiring and terminations, holders for light fittings and socket outlets for power points. Contractor shall obtain approvals from the Consultant/CEE for above items
B171: As a standard of quality for switches and socket outlets, the contractor may use 'ML/Legrand /ACL or approved equal'.
B173: Light Point Wiring
B174: Point Wiring With Earthwire.
B176: GROUND FLOOR
A177: V04.01 | B177: Light point wired through a 10Amp one gang one way plate switch using 2x1/1.13mm(2x1/.044) P.V.C. insulated copper wire & 1x7/0.67mm P.V.C. insulated copper earth wire in fully concealed/surface P.V.C. conduits. (For a switch circuit) | D177: Nr | E177: 3364 | F177: =E177*C177 -> 0
A179: V04.02 | B179: Light point wired through a 10Amp two gang one way plate switch using 2x1/1.13mm(2x1/.044) P.V.C. insulated copper wire & 1x7/0.67mm P.V.C. insulated copper earth wire in fully concealed/surface P.V.C. conduits. (For a switch circuit) | D179: Nr | E179: 4373 | F179: =E179*C179 -> 0
A181: V04.03 | B181: Light point wired through a 10 Amp two gang one way plate switch using 2x1/1.13mm(2x1/.044) P.V.C. insulated copper wire & 1x7/0.67mm P.V.C. insulated copper earth wire in fully concealed/surface P.V.C. conduits. (For a switch circuit) | D181: Nr | E181: 8577 | F181: =E181*C181 -> 0
A183: V04.04 | B183: Light point wired through a 10 Amp one gang two way plate switch using 2x1/1.13mm(2x1/.044) P.V.C. insulated copper wire & 1x7/0.67mm P.V.C. insulated copper earth wire in fully concealed/surface P.V.C.conduits. (For a switch circuit) | D183: Nr | E183: 7500 | F183: =E183*C183 -> 0
A185: V04.04 | B185: Light point wired through a 10 Amp one gang four way plate switch using 2x1/1.13mm(2x1/.044) P.V.C. insulated copper wire & 1x7/0.67mm P.V.C. insulated copper earth wire in fully concealed/surface P.V.C.conduits. (For a switch circuit) | D185: Nr | E185: 12100 | F185: =E185*C185 -> 0
B187: FIRST FLOOR
A188: V04.05 | B188: Light point wired through a 10Amp one gang one way plate switch using 2x1/1.13mm(2x1/.044) P.V.C. insulated copper wire & 1x7/0.67mm P.V.C. insulated copper earth wire in fully concealed/surface P.V.C. conduits. (For a switch circuit) | D188: Nr | E188: 3364 | F188: =E188*C188 -> 0
A190: V04.06 | B190: Light point wired through a 10Amp two gang one way plate switch using 2x1/1.13mm(2x1/.044) P.V.C. insulated copper wire & 1x7/0.67mm P.V.C. insulated copper earth wire in fully concealed/surface P.V.C. conduits. (For a switch circuit) | D190: Nr | E190: =E181 -> 8577 | F190: =E190*C190 -> 0
A192: V04.07 | B192: Light point wired through a 10 Amp one gang four way plate switch using 2x1/1.13mm(2x1/.044) P.V.C. insulated copper wire & 1x7/0.67mm P.V.C. insulated copper earth wire in fully concealed/surface P.V.C.conduits. (For a switch circuit) | D192: Nr | E192: 12100 | F192: =E192*C192 -> 0
A194: V04.08 | B194: Light point wired through a 10 Amp one gang two way plate switch using 2x1/1.13mm(2x1/.044) P.V.C. insulated copper wire & 1x7/0.67mm P.V.C. insulated copper earth wire in fully concealed/surface P.V.C. conduits. (For a switch circuit) | D194: Nr | E194: =E183 -> 7500 | F194: =E194*C194 -> 0
B196: SECOND FLOOR
A197: V04.09 | B197: Light point wired through a 10Amp one gang one way plate switch using 2x1/1.13mm(2x1/.044) P.V.C. insulated copper wire & 1x7/0.67mm P.V.C. insulated copper earth wire in fully concealed/surface P.V.C. conduits. (For a switch circuit) | D197: Nr | E197: 3364 | F197: =E197*C197 -> 0
A199: V04.10 | B199: Light point wired through a 10Amp two gang one way plate switch using 2x1/1.13mm(2x1/.044) P.V.C. insulated copper wire & 1x7/0.67mm P.V.C. insulated copper earth wire in fully concealed/surface P.V.C. conduits. (For a switch circuit) | D199: Nr | E199: 4373 | F199: =E199*C199 -> 0
A201: V04.11 | B201: Light point wired through a 10 Amp three gang one way plate switch using 2x1/1.13mm(2x1/.044) P.V.C. insulated copper wire & 1x7/0.67mm P.V.C. insulated copper earth wire in fully concealed/surface P.V.C. conduits. (For a switch circuit) | D201: Nr | E201: =E190 -> 8577 | F201: =E201*C201 -> 0
A203: V04.12 | B203: Light point wired through a 10 Amp one gang two way plate switch using 2x1/1.13mm(2x1/.044) P.V.C. insulated copper wire & 1x7/0.67mm P.V.C. insulated copper earth wire in fully concealed/surface P.V.C.conduits. (For a switch circuit) | D203: Nr | E203: =E194 -> 7500 | F203: =E203*C203 -> 0
B211: Switch Socket Wiring
B212: Point wiring for socket outlets 13A - ( 16A Circuits)
A214: V04.13 | B214: Supply , Installation & wiring of power Socket Outlet Flush mounted 13 Amp switch socket outlet wired using 2x7/0.67(2x7/.029) insulated copper wire & 1x7/0.67(7/.029) copper earth wire in fully concealed/surface P.V.C. conduits (in radial circuit) through the ceiling , wall / partition up to the point including PVC trucking , outlet and other accessories up to the point in ground floor | D214: Nr | E214: 9500 | F214: =E214*C214 -> 0
A216: V04.14 | B216: Supply , Installation & wiring of power Socket Outlet Flush mounted 13 Amp switch socket outlet wired using 2x7/0.67(2x7/.029) insulated copper wire & 1x7/0.67(7/.029) copper earth wire in fully concealed/surface P.V.C. conduits (in radial circuit) through the ceiling , wall / partition up to the point including PVC trucking , outlet and other accessories up to the point in first floor | D216: Nr | E216: =E214 -> 9500 | F216: =E216*C216 -> 0
A218: V04.15 | B218: Supply , Installation & wiring of power Socket Outlet Flush mounted 13 Amp switch socket outlet wired using 2x7/0.67(2x7/.029) insulated copper wire & 1x7/0.67(7/.029) copper earth wire in fully concealed/surface P.V.C. conduits (in radial circuit) through the ceiling , wall / partition up to the point including PVC trucking , outlet and other accessories up to the point in second floor | D218: Nr | E218: =E216 -> 9500 | F218: =E218*C218 -> 0
B220: Fan Regulator
B222: cost of wiring, regulator, fan hook & other accessories. For regulator shall be a three star energy.
A223: V04.16 | B223: Fan regulator wired without a switch using 2x1/1.13 mm P.V.C. insulated copper wire & 1x7/0.67mm P.V.C. insulated copper earth wire in fully concealed/surface P.V.C. conduits. Ground Floor | D223: Nr | E223: 5429 | F223: =E223*C223 -> 0
A225: V04.17 | B225: Fan regulator wired without a switch using 2x1/1.13 mm P.V.C. insulated copper wire & 1x7/0.67mm P.V.C. insulated copper earth wire in fully concealed/surface P.V.C. conduits. First Floor | D225: Nr | E225: =E223 -> 5429 | F225: =E225*C225 -> 0
A227: V04.18 | B227: Fan regulator wired with a switch using 2x1/1.13 mm P.V.C. insulated copper wire & 1x7/0.67mm P.V.C. insulated copper earth wire in fully concealed/surface P.V.C. conduits. second Floor | D227: Nr | E227: =E225 -> 5429 | F227: =E227*C227 -> 0
B228: Telephone Socket Wiring ( Direct & intercom)
...

Sheet Wattala - (6)
A1: PROPSED THREE STORY LIBREARY BUILDING FOR MINUWANGODA URBAN COUNCIL MINUWANGODA.
A3: Nos | B3: Description | C3: Qty | D3: Unit | E3: Rate | F3: Amount
B4: BILL NO. 01
A5: 1/PR | B5: PRELIMINARIES
B7: Please refer Specifications & Priceing reambles | K7: 60000000
B8: This Bill Provides for the typical general items complimentary to the works wich are required to be provided by the Contractor in compliance with the Conditions of Contract and Contract Data in the execution of the works according to the Contract. | K8: =K7*1.44% -> 864000
L9: =K8*0.23 -> 198720
A10: 1/PR.1 | B10: Allow lump sum for providing Securtiy Bonds and Guarantees. | C10: 1 | D10: Item | E10: 685000 | F10: =C10*E10 -> 685000 | L10: =K8*0.18 -> 155520
L11: =K8*0.22 -> 190080 | M11: =L11+L10 -> 345600
A12: 1/PR.2 | B12: Allow lump sum for mobilization to site | C12: 1 | D12: Item | E12: 20000 | F12: =C12*E12 -> 20000
M13: =K8*0.1 -> 86400
A14: 1/PR.3 | B14: Allow lump sum for insurance of works, plant & machinery,materials, third pary and workmen (All the insurances should be submitted for the end of defect liability period.) | C14: 1 | D14: Item | E14: 810000 | F14: =C14*E14 -> 810000 | M14: =K8*0.12 -> 103680
A16: 1/PR.4 | B16: Provide lump sum to construct, maintain and removal at end of contract temporary buildings for protection & storage of materials & plant and for workshops. | C16: 1 | D16: Item | E16: 30000 | F16: =C16*E16 -> 30000
A18: 1/PR.5 | B18: Provide lump sum to construct furnish, maintain and removal at end of contract contractor's office and Engineers office separately. | C18: 1 | D18: Item | E18: 160000 | F18: =C18*E18 -> 160000
A20: 1/PR.6 | B20: Allow for providing safety, Health and sanitary facilities for Contractor's Staff. | C20: 1 | D20: Item | E20: 100000 | F20: =C20*E20 -> 100000
A22: 1/PR.7 | B22: Provide lump sum for electronic equipment and setting out of the works. | C22: 1 | D22: Item | E22: 15000 | F22: =C22*E22 -> 15000
A24: 1/PR.8 | B24: Allow for supplying temperory electricity for the work including connections, distribution system for the work internal arrangements and for all payments to the authorities for consumption during construction. | D24: Item | F24: By Owner
A26: 1/PR.9 | B26: Allow for supplying water for use during the construction including supplying, storing internal arrangements and payment to local authorities for consumption. | D26: Item | F26: By Owner
A28: 1/PR.10 | B28: Provide lump sum for providing temporary water supply for the use of works. | C28: 1 | D28: Item | E28: 50000 | F28: =C28*E28 -> 50000
A30: 1/PR.11 | B30: Provide lump sum for temporary electricity services for the use of works | C30: 1 | D30: Item | E30: 60000 | F30: =C30*E30 -> 60000
A32: 1/PR.12 | B32: Provide lump sum for necessary protective fencing, hoarding and temporary dust screen, to fully cover from dust and particles etc. around buildings due to construction activities as directed by the Engineer | C32: 1 | D32: Item | E32: 150000 | F32: =C32*E32 -> 150000
A34: 1/PR.13 | B34: Provide lump sum for necessary warning notices, adequate night lighting etc. | C34: 1 | D34: Item | E34: 50000 | F34: =C34*E34 -> 50000
A36: 1/PR.14 | B36: Provide lump sum for providing security and safeguarding the works, material & plant against damage, vandalism and trespass. | C36: 1 | D36: Item | E36: 300000 | F36: =C36*E36 -> 300000
A38: 1/PR.16 | B38: Provide lump sum for demobilization, removal of all rubbish & debris and clearing up site on completion, leaving all in good order and handing over. | C38: 1 | D38: Item | E38: 200000 | F38: =C38*E38 -> 200000
A40: 1/PR.17 | B40: Allow lum sum for obtaining all necessary approvals from local authorities for proper execution and completion of works. | C40: 1 | D40: Item | E40: 100000 | F40: =C40*E40 -> 100000
A42: 1/PR.18 | B42: Allow lump sum for obtaining test reports including lab reports for structural works and Chartered electrical Engineer's cerfificate for Electrical installation works. | C42: 1 | D42: Item | E42: 75000 | F42: =C42*E42 -> 75000
A44: 1/PR.19 | B44: Allow lump sum for providing approved samples at site. | C44: 1 | D44: Item | E44: 30000 | F44: =C44*E44 -> 30000
A46: 1/PR.20 | B46: Allow lump sum for providing progress charts, Construction Programs, Progrress photos (minimum 5 photos every month) bar schedules, shop/working drawings etc. | C46: 1 | D46: Item | E46: 20000 | F46: =C46*E46 -> 20000
A48: 1/PR.21 | B48: Allow lump sum for providing three(03) copies of " As Built" drawing with Operation manual. | C48: 1 | D48: Item | E48: 15000 | F48: =C48*E48 -> 15000
B55: TOTAL CARRIED TO GRAND SUMMARY | F55: =SUM(F10:F54) -> 2870000
B57: B - EXCAVATION & EARTH WORK
B58: Excavation
A59: B 01 | B59: Site preparation, Clearing site vegetation, removing bushes, shrubs & top soil to a depth not exceeding 6" and removing all debris away from site. | D59: Sqr. | E59: 1640 | F59: =+C59*E59 -> 0 | H59: =95/10.76 -> 8.8289963
B61: Shoring, dewatering and rock blasting if necessary for the excavation, shall be paid for separately for item B04 - B06
A62: B 02 | B62: Manual Excavation for column, wall, staircase foundations in any material (except rock requiring blasting) up to 5'-0" depth, part return fill in and ram and surplus depositted within site as directed. | D62: Cube | E62: 3450 | F62: =+C62*E62 -> 0
B64: Filling & Compaction
B65: Note:-
B66: Approved earth shall mean filling materials that comply to the following :
A67: ( a ) | B67: The earth shall be free of vegetation, roots, boulders, easily decomposable materials, chemicals, industrial waste, plastic etc.
A68: ( b ) | B68: The maximum size of particle shall not exceed 75mm.
A69: ( c ) | B69: The earth shall be well graded and the silt and clay (fines) content shall not be more than 25%
A70: ( d ) | B70: The Standerd proctor density shall be grater than 1.70g/cm3
A71: B 03 | B71: Approved earth supplying and piled at site (measured at piled volume) | D71: Cube | E71: 3570 | F71: =+C71*E71 -> 0 | H71: =8.9+21.3 -> 30.2
A72: B 04 | B72: Transport of Bulk material (Earth, Graded quarry dust, ABC mix) per Km per cube. | D72: 1 km | E72: 157
A73: B 05 | B73: Compaction of Earth including watering in 225mm thick layers (measured on piled volume) using machine Rammer. Rate include hire charges of the machine rammer. This rate is applicable for building construction with earth work not exceeding 50 cubes. (earth available at site). | D73: Cube | E73: 1470 | F73: =+C73*E73 -> 0
B75: Test
A76: B 06 | B76: Conducting a proctor density check on sample fill matearial. | D76: Per Test | E76: 3000
A77: B 07 | B77: Field density testing of the compacted earth fill using Sand cone method. | D77: Per Test | E77: 4000
B78: Antitermite -Tretement
